Workbook

Sheet 2020.07
A1: 到课情况 | D1: 咨询回访 （写内容） | E1: 是否成功 | F1: 分组 | G1: 学号 | H1: 学生姓名 | J1: jiaofei | K1: 试读日期 | L1: 年龄 | M1: 家长联系方式 | N1: 校区 | O1: 市场 | P1: 区域国家 | Q1: 在读状态 | R1: 课程顾问 | S1: 学科 | T1: 课程情况 | U1: 在读课堂 | V1: 授课老师 | W1: 每周课时情况 | X1: 收费标准 | Z1: 优惠活动 | AB1: 课时情况 | AE1: 收费员 | AF1: 付费方式 | AG1: 习惯付款方式 | AH1: 最后缴费日期 | AI1: 计费日期 | AK1: 最后收费金额 | AL1: 请假情况 | AN1: 到期日期 | AO1: 备注
D2: 1 | E2: 1 | F2: 4 | G2: 20WA00236 | H2: 叶丹尼 | I2: 叶丹尼 | J2: =IFERROR(VLOOKUP(I2,Sheet1!A:C,3,FALSE),"zhoanudao") -> 是 | K2: 44013 | M2: angelicaye | P2: 西班牙 | S2: 中文 | U2: 四十三课堂 第九节 | X2: 660 | AH2: 44019 | AI2: 44018 | AJ2: 44048 | AK2: 660 | AN2: 44048
D3: 1 | E3: 1 | F3: 3 | G3: 20WC00351 | H3: 陈雅婷1（数） | I3: 陈雅婷1 | J3: =IFERROR(VLOOKUP(I3,Sheet1!A:C,3,FALSE),"zhoanudao") -> 是 | K3: 44013 | M3: simonechen170 | P3: 意大利 | S3: 数学 | U3: 十一课堂 第二节 | X3: 660 | AH3: 44014 | AI3: 44016 | AJ3: 44046 | AK3: 660 | AN3: 44046
D4: 1 | E4: 1 | F4: 兼职 | G4: 20WA00237 | H4: 潘佳慧（英） | I4: 潘佳慧 | J4: =IFERROR(VLOOKUP(I4,Sheet1!A:C,3,FALSE),"zhoanudao") -> zhoanudao | K4: 44013 | M4: xia618388632 | P4: 西班牙 | S4: 英文 | U4: 二十课堂 第三节 | X4: 660 | AH4: 44018 | AI4: 44018 | AJ4: 44079 | AK4: 1320 | AN4: 44079
D5: 语言听不懂 | E5: 0 | F5: 3 | G5: 20WC00352 | H5: kevinwang王柏皓（数） | I5: 王柏皓 | J5: =IFERROR(VLOOKUP(I5,Sheet1!A:C,3,FALSE),"zhoanudao") -> zhoanudao | K5: 44013 | M5: h1443638 | P5: 意大利 | S5: 数学 | U5: 一课堂 第二节
E6: 1 | F6: 3 | G6: 20WK0010 | H6: 姜希雅（数） | I6: 姜希雅 | J6: =IFERROR(VLOOKUP(I6,Sheet1!A:C,3,FALSE),"zhoanudao") -> zhoanudao | K6: 44013 | M6: huan8878216 | P6: 希腊 | S6: 数学 | U6: 十一课堂 第二节
D7: 1 | E7: 1 | F7: 1 | G7: 20WC00353 | H7: 虞可可 | I7: 虞可可 | J7: =IFERROR(VLOOKUP(I7,Sheet1!A:C,3,FALSE),"zhoanudao") -> 是 | K7: 44013 | M7: a3398259751 | P7: 意大利 | S7: 中文 | U7: 三十课堂 第四节 | X7: 660 | AH7: 44020 | AI7: 44018 | AJ7: 44048 | AK7: 660 | AN7: 44048
D8: 1 | E8: 1 | F8: 3 | G8: 20WC00354 | H8: 虞可可（英） | I8: 虞可可 | J8: =IFERROR(VLOOKUP(I8,Sheet1!A:C,3,FALSE),"zhoanudao") -> 是 | K8: 44013 | M8: a3398259752 | P8: 意大利 | S8: 英文 | U8: 五十八课堂 第五节 | X8: 660 | AH8: 44020 | AI8: 44016 | AJ8: 44046 | AK8: 660 | AN8: 44046
D9: 1 | E9: 1 | F9: 2 | G9: 20WA00238 | H9: 单梓嫣（英） | I9: 单梓嫣 | J9: =IFERROR(VLOOKUP(I9,Sheet1!A:C,3,FALSE),"zhoanudao") -> zhoanudao | K9: 44013 | M9: jing774435 | P9: 西班牙 | S9: 英文 | U9: 十四课堂 第三节 | X9: 660 | AH9: 44019 | AI9: 44018 | AJ9: 44109 | AK9: 1980 | AN9: 44109
D10: 1（7.8缴费） | E10: 1 | F10: 1 | G10: 20WA00239 | H10: 陈洋1 | I10: 陈洋1 | J10: =IFERROR(VLOOKUP(I10,Sheet1!A:C,3,FALSE),"zhoanudao") -> 是 | K10: 44013 | M10: linlanpin | P10: 西班牙 | S10: 中文 | U10: 二十二课堂 第八节 | X10: 660 | AH10: 44020 | AI10: 44018 | AJ10: 44048 | AK10: 660 | AN10: 44048
D11: 1 | E11: 1 | F11: 1 | G11: 20WA00240 | H11: 李林家俊 | I11: 李林家俊 | J11: =IFERROR(VLOOKUP(I11,Sheet1!A:C,3,FALSE),"zhoanudao") -> 是 | K11: 44013 | M11: linye821123 | P11: 西班牙 | S11: 中文 | U11: 三十六课堂 第四节 | X11: 660 | AH11: 44019 | AI11: 44018 | AJ11: 44048 | AK11: 660 | AN11: 44048
D12: 去代理那边报名，只上周末班或者兼职班 | E12: 1 | F12: 1 | G12: 20WA00241 | H12: 黄思睿 | I12: 黄思睿 | J12: =IFERROR(VLOOKUP(I12,Sheet1!A:C,3,FALSE),"zhoanudao") -> zhoanudao | K12: 44013 | M12: wxid_6rwnklpow3c511 | P12: 西班牙 | S12: 中文 | U12: 三十六课堂 第八节
E13: 1 | F13: 4 | G13: 20WD0066 | H13: 倪星哲 | I13: 倪星哲 | J13: =IFERROR(VLOOKUP(I13,Sheet1!A:C,3,FALSE),"zhoanudao") -> 是 | K13: 44013 | M13: xiulinfu | O13: 新 | P13: 巴西 | S13: 中文 | U13: 三课堂 6：30-7：00
F14: 1 | G14: 20WI0036 | H14: 陈冠燊 | I14: 陈冠燊 | J14: =IFERROR(VLOOKUP(I14,Sheet1!A:C,3,FALSE),"zhoanudao") -> zhoanudao | K14: 44013 | M14: winnie12345 | P14: 美国 | S14: 中文 | U14: 三十九课堂 第二节 | AO14: 运营部新生
D15: 1 | E15: 1 | F15: 3 | G15: 20WC00355 | H15: 陈亭妤 | I15: 陈亭妤 | J15: =IFERROR(VLOOKUP(I15,Sheet1!A:C,3,FALSE),"zhoanudao") -> zhoanudao | K15: 44014 | M15: zhang_xjin | P15: 意大利 | S15: 中文 | U15: 四十二课堂 第六节
D16: 1（妈妈很少看微信） | E16: 1 | F16: 1 | G16: 20WC00356 | H16: 张晓丹 | I16: 张晓丹 | J16: =IFERROR(VLOOKUP(I16,Sheet1!A:C,3,FALSE),"zhoanudao") -> 是 | K16: 44014 | M16: wxid_n9m9yp0ue2y422 | P16: 意大利 | S16: 中文 | U16: 三十九课堂 第二节 | X16: 660 | AH16: 44022 | AI16: 44025 | AJ16: 44117 | AK16: 1980 | AN16: 44117
D17: 暑假班冲突 | E17: 0 | F17: 2 | G17: 20WK031 | H17: 吴露娜 | I17: 吴露娜 | J17: =IFERROR(VLOOKUP(I17,Sheet1!A:C,3,FALSE),"zhoanudao") -> zhoanudao | K17: 44014 | M17: Qunyu_Vienna | P17: 奥地利 | S17: 中文 | U17: 五十五课堂 第五节
D18: 以前上学的地方开网课了 | E18: 0 | F18: 1 | H18: 章侨偌 | I18: 章侨偌 | J18: =IFERROR(VLOOKUP(I18,Sheet1!A:C,3,FALSE),"zhoanudao") -> zhoanudao | K18: 44014 | M18: zuiaidexiaozhi | P18: 意大利 | S18: 中文 | U18: 五十课堂 第三节
D19: 1（跟哥哥林泽锴1一起付） | F19: 3 | G19: 20WA00242 | H19: 林炜真（数） | I19: 林炜真 | J19: =IFERROR(VLOOKUP(I19,Sheet1!A:C,3,FALSE),"zhoanudao") -> zhoanudao | K19: 44014 | M19: ibai2012 | P19: 西班牙 | S19: 数学 | U19: 一课堂 第四节
D20: 家长觉得教的太慢了作业也少 | E20: 0 | F20: 3 | G20: 20WC00358 | H20: 王家轩（数） | I20: 王家轩 | J20: =IFERROR(VLOOKUP(I20,Sheet1!A:C,3,FALSE),"zhoanudao") -> zhoanudao | K20: 44014 | M20: xunzhao1023 | P20: 意大利 | S20: 数学 | U20: 四十四课堂 第六节
D21: 第二天转28课堂，后转回52课堂 | F21: 4 | G21: 20WA00243 | H21: 麻雅妮 | I21: 麻雅妮 | J21: =IFERROR(VLOOKUP(I21,Sheet1!A:C,3,FALSE),"zhoanudao") -> zhoanudao | K21: 44014 | M21: qingqing127214 | P21: 西班牙 | S21: 中文 | U21: 五十二课堂 第四节
D22: 第三天转52课堂 | F22: 4 | G22: 20WA00244 | H22: 麻安妮 | I22: 麻安妮 | J22: =IFERROR(VLOOKUP(I22,Sheet1!A:C,3,FALSE),"zhoanudao") -> zhoanudao | K22: 44014 | M22: qingqing127215 | P22: 西班牙 | S22: 中文 | U22: 三十一课堂 第五节
E23: 1 | F23: 2 | G23: 20WC00359 | H23: 任鹏铄 | I23: 任鹏铄 | J23: =IFERROR(VLOOKUP(I23,Sheet1!A:C,3,FALSE),"zhoanudao") -> 是 | K23: 44014 | M23: xie3272841959 | P23: 意大利 | S23: 中文 | U23: 二十六课堂 第四节 | X23: 660 | AH23: 44019 | AI23: 44018 | AJ23: 44048 | AK23: 660 | AN23: 44048
D24: 1 | F24: 2 | G24: 20WA00245 | H24: 杨雨宸 | I24: 杨雨宸 | J24: =IFERROR(VLOOKUP(I24,Sheet1!A:C,3,FALSE),"zhoanudao") -> zhoanudao | K24: 44014 | M24: xiaoqing8618 | P24: 西班牙 | S24: 中文 | U24: 五十五课堂 第五节
D25: 报了别的平台一对一 | E25: 0 | F25: 4 | G25: 20WI0037 | H25: 牛小凯 | I25: 牛小凯 | J25: =IFERROR(VLOOKUP(I25,Sheet1!A:C,3,FALSE),"zhoanudao") -> zhoanudao | K25: 44014 | M25: IvyNiu | P25: 美国 | S25: 中文 | U25: 四十三课堂 5:30-6:00
E26: 1 | F26: 4 | G26: 20WA00246 | H26: 潘昊泉 | I26: 潘昊泉 | J26: =IFERROR(VLOOKUP(I26,Sheet1!A:C,3,FALSE),"zhoanudao") -> 是 | K26: 44014 | M26: Z139017555 | P26: 西班牙 | S26: 中文 | U26: 五十三课堂 第十节 | AO26: 运营部新生
E27: 1 | F27: 3 | G27: 20WK032 | H27: 姜欢欣（数） | I27: 姜欢欣 | J27: =IFERROR(VLOOKUP(I27,Sheet1!A:C,3,FALSE),"zhoanudao") -> 是 | K27: 44015 | M27: huan8878216 | P27: 希腊 | S27: 数学 | U27: 一课堂 第九节 | AH27: 44015 | AI27: 44018 | AJ27: 44109 | AK27: 1854元 | AN27: 44109
D28: 1 | E28: 1 | F28: 2 | G28: 20WA00247 | H28: 叶豪 | I28: 叶豪 | J28: =IFERROR(VLOOKUP(I28,Sheet1!A:C,3,FALSE),"zhoanudao") -> 是 | K28: 44015 | M28: peifen8216 | P28: 西班牙 | S28: 中文 | U28: 五十五课堂 第五节 | X28: 620 | AH28: 44021 | AI28: 44019 | AJ28: 44112 | AK28: 1860 | AN28: 44112
D29: 1（7.8转四十九课堂） | E29: 1 | F29: 3 | G29: 20WA00248 | H29: 徐俏俏（数） | I29: 徐俏俏 | J29: =IFERROR(VLOOKUP(I29,Sheet1!A:C,3,FALSE),"zhoanudao") -> 是 | K29: 44015 | M29: q597037537 | P29: 西班牙 | S29: 数学 | U29: 三十二课堂 第二节 | X29: 660 | AH29: 44019 | AI29: 44021 | AJ29: 44051 | AK29: 660 | AN29: 44051
D30: 1 | E30: 1 | F30: 3 | G30: 20WA00249 | H30: 黄薏卉 | I30: 黄薏卉 | J30: =IFERROR(VLOOKUP(I30,Sheet1!A:C,3,FALSE),"zhoanudao") -> 是 | K30: 44015 | M30: HZY1314258 | P30: 西班牙 | S30: 中文 | U30: 四十二课堂 第二节 | X30: 660 | AH30: 44019 | AI30: 44021 | AJ30: 44051 | AK30: 660 | AN30: 44051
D31: 1 | E31: 1 | F31: 4 | G31: 20WA00250 | H31: 黄梓烨 | I31: 黄梓烨 | J31: =IFERROR(VLOOKUP(I31,Sheet1!A:C,3,FALSE),"zhoanudao") -> 是 | K31: 44015 | M31: HZY1314259 | P31: 西班牙 | S31: 中文 | U31: 五十三课堂 第十节 | X31: 660 | AH31: 44019 | AI31: 44021 | AJ31: 44051 | AK31: 660 | AN31: 44051
D32: 1 | E32: 1 | F32: 3 | G32: 20WA00251 | H32: 张智轩（数） | I32: 张智轩 | J32: =IFERROR(VLOOKUP(I32,Sheet1!A:C,3,FALSE),"zhoanudao") -> zhoanudao | K32: 44015 | M32: QT656866634 | P32: 西班牙 | S32: 数学 | U32: 六课堂 第六节
D33: 1 | E33: 1 | F33: 4 | G33: 20WA00252 | H33: 叶欣 | I33: 叶欣 | J33: =IFERROR(VLOOKUP(I33,Sheet1!A:C,3,FALSE),"zhoanudao") -> 是 | K33: 44015 | M33: peifen8216 | P33: 西班牙 | S33: 中文 | U33: 二十七课堂 第四节 | X33: 620 | AH33: 44021 | AI33: 44019 | AJ33: 44112 | AK33: 1860 | AN33: 44112
D34: 1 | F34: 金华 | G34: 20WC00360 | H34: 陈泉铕 | I34: 陈泉铕 | J34: =IFERROR(VLOOKUP(I34,Sheet1!A:C,3,FALSE),"zhoanudao") -> zhoanudao | K34: 44015 | M34: zhongyan027588 | P34: 意大利 | S34: 中文 | U34: 阳光第七课堂 第三节
E35: 1 | F35: 金华 | G35: 20WI0038 | H35: 王佳怡3 | I35: 王佳怡3 | J35: =IFERROR(VLOOKUP(I35,Sheet1!A:C,3,FALSE),"zhoanudao") -> 是 | K35: 44015 | M35: w9177168661 | P35: 美国 | S35: 中文 | U35: 阳光第七课堂 第三节 | X35: 660 | AH35: 44020 | AI35: 44021 | AJ35: 44051 | AK35: 660 | AN35: 44051
D36: 1 | E36: 1 | F36: 金华 | G36: 20WA00253 | H36: 叶婷2 | I36: 叶婷2 | J36: =IFERROR(VLOOKUP(I36,Sheet1!A:C,3,FALSE),"zhoanudao") -> 是 | K36: 44015 | M36: peifen8216 | P36: 西班牙 | S36: 中文 | U36: 阳光第七课堂 第三节 | X36: 620 | AH36: 44021 | AI36: 44019 | AJ36: 44112 | AK36: 1860 | AN36: 44112
D37: 1 | F37: 金华 | G37: 20WC00361 | H37: 林慧 | I37: 林慧 | J37: =IFERROR(VLOOKUP(I37,Sheet1!A:C,3,FALSE),"zhoanudao") -> zhoanudao | K37: 44015 | M37: wang605705793 | P37: 意大利 | S37: 中文 | U37: 阳光第七课堂 第三节
D38: 1 | E38: 1 | F38: 金华 | G38: 20WI0039 | H38: 王昕宇1 | I38: 王昕宇1 | J38: =IFERROR(VLOOKUP(I38,Sheet1!A:C,3,FALSE),"zhoanudao") -> zhoanudao | K38: 44015 | M38: wang112423 | P38: 美国 | S38: 中文 | U38: 阳光第七课堂 第三节
D39: 1 | F39: 3 | G39: 20WA00382 | H39: 单陈依 | I39: 单陈依 | J39: =IFERROR(VLOOKUP(I39,Sheet1!A:C,3,FALSE),"zhoanudao") -> zhoanudao | K39: 44018 | M39: Mm553173 | P39: 西班牙 | S39: 中文 | U39: 二十八课堂 第七节
D40: 1 | F40: 3 | G40: 20WC00362 | H40: 林子腾（数） | I40: 林子腾 | J40: =IFERROR(VLOOKUP(I40,Sheet1!A:C,3,FALSE),"zhoanudao") -> zhoanudao | K40: 44018 | M40: linjunleo | P40: 意大利 | S40: 数学 | U40: 六课堂 第七节
E41: 1 | F41: 2 | G41: 20WA00383 | H41: 陈思彤 | I41: 陈思彤 | J41: =IFERROR(VLOOKUP(I41,Sheet1!A:C,3,FALSE),"zhoanudao") -> 是 | K41: 44018 | M41: lingjiao72 | P41: 西班牙 | S41: 中文 | U41: 二十三课堂 第二节 | X41: 660 | AH41: 44022 | AI41: 44021 | AJ41: 44051 | AK41: 660 | AN41: 44051
D42: 1 | E42: 1 | F42: 3 | G42: 20WC00363 | H42: 林乐欣（英） | I42: 林乐欣 | J42: =IFERROR(VLOOKUP(I42,Sheet1!A:C,3,FALSE),"zhoanudao") -> zhoanudao | K42: 44018 | M42: ERICA52038 | P42: 意大利 | S42: 英文 | U42: 四十五课堂 第十节 | X42: 660 | AH42: 44021 | AI42: 44021 | AJ42: 44051 | AK42: 660 | AN42: 44049
D43: 1 | E43: 1 | F43: 金华 | G43: 20WA00384 | H43: 李林欣怡 | I43: 李林欣怡 | J43: =IFERROR(VLOOKUP(I43,Sheet1!A:C,3,FALSE),"zhoanudao") -> 是 | K43: 44018 | M43: linye821123 | P43: 西班牙 | S43: 中文 | U43: 阳光第七课堂 第三节 | AH43: 44021
D44: 1 | F44: 金华 | G44: 20WA00385 | H44: 胡欣妍 | I44: 胡欣妍 | J44: =IFERROR(VLOOKUP(I44,Sheet1!A:C,3,FALSE),"zhoanudao") -> 是 | K44: 44018 | M44: haixiao1235678 | P44: 西班牙 | S44: 中文 | U44: 阳光第八课堂 第一节
D45: 1 | E45: 0 | F45: 金华 | G45: 20WA00386 | H45: 卢卡斯1 | I45: 卢卡斯1 | J45: =IFERROR(VLOOKUP(I45,Sheet1!A:C,3,FALSE),"zhoanudao") -> zhoanudao | K45: 44018 | M45: martalc | P45: 西班牙 | S45: 中文 | U45: 阳光第八课堂 第一节
D46: 1 | F46: 金华 | G46: 20WA00387 | H46: 杨雨泽 | I46: 杨雨泽 | J46: =IFERROR(VLOOKUP(I46,Sheet1!A:C,3,FALSE),"zhoanudao") -> zhoanudao | K46: 44018 | M46: xiaoqing8618 | P46: 西班牙 | S46: 中文 | U46: 阳光第八课堂 第一节
D47: 1 | F47: 4 | G47: 20WA00388 | H47: 陈杨昕 | I47: 陈杨昕 | J47: =IFERROR(VLOOKUP(I47,Sheet1!A:C,3,FALSE),"zhoanudao") -> zhoanudao | K47: 44018 | M47: wxid_4kquy12sibx412 | P47: 西班牙 | S47: 中文 | U47: 五十六课堂 第八节
E48: 1 | F48: 3 | G48: 20WC00364 | H48: 周素丽 | I48: 周素丽 | J48: =IFERROR(VLOOKUP(I48,Sheet1!A:C,3,FALSE),"zhoanudao") -> 是 | K48: 44018 | M48: HUHAIXlA369 | P48: 意大利 | S48: 中文 | U48: 五十七课堂 第三节 | X48: 660 | AH48: 44019 | AI48: 44021 | AJ48: 44112 | AK48: 1980 | AN48: 44112 | AO48: 运营部新生
E49: 1 | F49: 3 | G49: 20WC00365 | H49: 周熠 | I49: 周熠 | J49: =IFERROR(VLOOKUP(I49,Sheet1!A:C,3,FALSE),"zhoanudao") -> 是 | K49: 44018 | M49: HUHAIXlA370 | P49: 意大利 | S49: 中文 | U49: 五十七课堂 第三节 | X49: 660 | AH49: 44019 | AI49: 44021 | AJ49: 44112 | AK49: 1980 | AN49: 44112 | AO49: 运营部新生
D50: 觉得人太多，孩子年龄相差太大 | E50: 0 | F50: 3 | G50: 20WA00389 | H50: 杨嘉颖 | I50: 杨嘉颖 | J50: =IFERROR(VLOOKUP(I50,Sheet1!A:C,3,FALSE),"zhoanudao") -> zhoanudao | K50: 44019 | M50: luna12588 | P50: 西班牙 | S50: 中文 | U50: 五十七课堂 第三节
D51: 1 | E51: 1 | F51: 4 | G51: 20WG0009 | H51: 张雨涵2 | I51: 张雨涵2 | J51: =IFERROR(VLOOKUP(I51,Sheet1!A:C,3,FALSE),"zhoanudao") -> zhoanudao | K51: 44019 | M51: weixiaoli886 | P51: 捷克 | S51: 中文 | U51: 二十七课堂 第五节
F52: 2 | G52: 20WI0040 | H52: 倪际娜 | I52: 倪际娜 | J52: =IFERROR(VLOOKUP(I52,Sheet1!A:C,3,FALSE),"zhoanudao") -> zhoanudao | K52: 44019 | L52: 14 | M52: nity5611 | P52: 美国 | S52: 中文 | U52: 八课堂 第十一节 | X52: 660
F53: 2 | G53: 20WI0041 | H53: 倪际垚 | I53: 倪际垚 | J53: =IFERROR(VLOOKUP(I53,Sheet1!A:C,3,FALSE),"zhoanudao") -> zhoanudao | K53: 44019 | L53: 15 | M53: nity5614 | P53: 美国 | S53: 中文 | U53: 八课堂 第十一节 | X53: 660
E54: 1 | F54: 1 | G54: 20WC00366 | H54: 叶伟 | I54: 叶伟 | J54: =IFERROR(VLOOKUP(I54,Sheet1!A:C,3,FALSE),"zhoanudao") -> 是 | K54: 44019 | L54: 11 | M54: wxid_dcv3a0pp0k2i22 | P54: 意大利 | S54: 中文 | U54: 十二课堂 第三节 | X54: 660 | AH54: 44022 | AI54: 44025 | AJ54: 44055 | AK54: 660 | AN54: 44055
F55: 2 | G55: 20WI0042 | H55: 王柯云 | I55: 王柯云 | J55: =IFERROR(VLOOKUP(I55,Sheet1!A:C,3,FALSE),"zhoanudao") -> zhoanudao | K55: 44019 | L55: 9 | M55: jingping_zhang | P55: 美国 | S55: 中文 | U55: 十课堂 第十节 | X55: 660
F56: 3 | G56: 20WA00390 | H56: 程盈杰（数） | I56: 程盈杰 | J56: =IFERROR(VLOOKUP(I56,Sheet1!A:C,3,FALSE),"zhoanudao") -> zhoanudao | K56: 44019 | M56: zhuxu88828 | P56: 西班牙 | S56: 数学 | U56: 四十四课堂 第七节
F57: 1 | G57: 20WA00391 | H57: 陈雨晨 | I57: 陈雨晨 | J57: =IFERROR(VLOOKUP(I57,Sheet1!A:C,3,FALSE),"zhoanudao") -> zhoanudao | K57: 44019 | L57: 7 | M57: phiihp | P57: 西班牙 | S57: 中文 | U57: 二十二课堂 第三节
D58: 1 | E58: 1 | F58: 4 | G58: 20WB0040 | H58: 蒋静瑄 | I58: 蒋静瑄 | J58: =IFERROR(VLOOKUP(I58,Sheet1!A:C,3,FALSE),"zhoanudao") -> 是 | K58: 44019 | L58: 12 | M58: wang967231606 | P58: 葡萄牙 | S58: 中文 | U58: 二十九课堂 第四节 | X58: 660 | AH58: 44021 | AI58: 44025 | AJ58: 44055 | AK58: 660 | AN58: 44055
F59: 4 | G59: 20WB0041 | H59: 叶琪琪 | I59: 叶琪琪 | J59: =IFERROR(VLOOKUP(I59,Sheet1!A:C,3,FALSE),"zhoanudao") -> 是 | K59: 44019 | L59: 12 | M59: Ye19781105 | P59: 葡萄牙 | S59: 中文 | U59: 五十三课堂 第十节 | X59: 660 | AH59: 44022 | AI59: 44025 | AJ59: 44055 | AK59: 660 | AN59: 44055
F60: 4 | G60: 20WB0042 | H60: 吴雅琪 | I60: 吴雅琪 | J60: =IFERROR(VLOOKUP(I60,Sheet1!A:C,3,FALSE),"zhoanudao") -> zhoanudao | K60: 44019 | L60: 10 | M60: cpandwgs | P60: 葡萄牙 | S60: 中文 | U60: 五十二课堂 第四节
F61: 3 | G61: 20WC00367 | H61: 林欣怡（数） | I61: 林欣怡 | J61: =IFERROR(VLOOKUP(I61,Sheet1!A:C,3,FALSE),"zhoanudao") -> 是 | K61: 44019 | M61: italia2005 | P61: 意大利 | S61: 数学 | U61: 四十四课堂 第九节
F62: 金华 | G62: 20WC00369 | H62: 林欣怡 | I62: 林欣怡 | J62: =IFERROR(VLOOKUP(I62,Sheet1!A:C,3,FALSE),"zhoanudao") -> 是 | K62: 44019 | L62: 7 | M62: huiarianna | P62: 意大利 | S62: 中文 | U62: 阳光第九课堂 第七节
D63: 1 | E63: 1 | F63: 金华 | G63: 20WG00010 | H63: 魏子墨 | I63: 魏子墨 | J63: =IFERROR(VLOOKUP(I63,Sheet1!A:C,3,FALSE),"zhoanudao") -> zhoanudao | K63: 44019 | L63: 7.5 | M63: weixiaoli886 | P63: 捷克 | S63: 中文 | U63: 阳光第九课堂 第七节
F64: 金华 | G64: 20WA00392 | H64: 徐拉拉 | I64: 徐拉拉 | J64: =IFERROR(VLOOKUP(I64,Sheet1!A:C,3,FALSE),"zhoanudao") -> zhoanudao | K64: 44019 | L64: 6 | M64: sofia-zheng815 | P64: 西班牙 | S64: 中文 | U64: 阳光第九课堂 第七节
F65: 金华 | G65: 20WA00393 | H65: 罗雨欣 | I65: 罗雨欣 | J65: =IFERROR(VLOOKUP(I65,Sheet1!A:C,3,FALSE),"zhoanudao") -> zhoanudao | K65: 44019 | L65: 8 | M65: wxid_21052s847svi22 | P65: 西班牙 | S65: 中文 | U65: 阳光第九课堂 第七节
F66: 金华 | G66: 20WA00394 | H66: 陈雅琪 | I66: 陈雅琪 | J66: =IFERROR(VLOOKUP(I66,Sheet1!A:C,3,FALSE),"zhoanudao") -> zhoanudao | K66: 44019 | L66: 5.5 | M66: simonechen169 | P66: 西班牙 | S66: 中文 | U66: 阳光第九课堂 第七节
F67: 金华 | G67: 20WA00395 | H67: 徐浩 | I67: 徐浩 | J67: =IFERROR(VLOOKUP(I67,Sheet1!A:C,3,FALSE),"zhoanudao") -> zhoanudao | K67: 44019 | M67: sofia-zheng815 | P67: 西班牙 | S67: 中文 | U67: 阳光第八课堂 第一节
F68: 金华 | G68: 20WA00396 | H68: 杨嘉翔 | I68: 杨嘉翔 | J68: =IFERROR(VLOOKUP(I68,Sheet1!A:C,3,FALSE),"zhoanudao") -> zhoanudao | K68: 44019 | L68: 17 | M68: hongli626134827 | P68: 西班牙 | S68: 中文 | U68: 阳光第八课堂 第一节
F69: 金华 | G69: 20WC00370 | H69: 胡嘉莹1 | I69: 胡嘉莹1 | J69: =IFERROR(VLOOKUP(I69,Sheet1!A:C,3,FALSE),"zhoanudao") -> zhoanudao | K69: 44019 | L69: 20 | M69: wxid_uycqx528j3e112 | P69: 意大利 | S69: 中文 | U69: 阳光第八课堂 第一节
F70: 3 | G70: 20WC00371 | H70: 诸启湖 | I70: 诸启湖 | J70: =IFERROR(VLOOKUP(I70,Sheet1!A:C,3,FALSE),"zhoanudao") -> 是 | K70: 44019 | M70: fabiomarco | P70: 意大利 | S70: 中文 | U70: 二十八课堂 第十一节 | AO70: 运营部新生
F71: 2 | G71: 20WC00372 | H71: 诸启翔 | I71: 诸启翔 | J71: =IFERROR(VLOOKUP(I71,Sheet1!A:C,3,FALSE),"zhoanudao") -> 是 | K71: 44019 | M71: fabiomarco | P71: 意大利 | S71: 中文 | U71: 五十五课堂 第十一节 | AO71: 运营部新生
F72: 1 | G72: 20WC00373 | H72: 章艳慧 | I72: 章艳慧 | J72: =IFERROR(VLOOKUP(I72,Sheet1!A:C,3,FALSE),"zhoanudao") -> zhoanudao | K72: 44020 | L72: 12 | M72: zhang638023 | P72: 意大利 | S72: 中文 | U72: 十二课堂 第二节
F73: 1 | G73: 20WC00374 | H73: 章艳亮 | I73: 章艳亮 | J73: =IFERROR(VLOOKUP(I73,Sheet1!A:C,3,FALSE),"zhoanudao") -> zhoanudao | K73: 44020 | L73: 10 | M73: zhang638024 | P73: 意大利 | S73: 中文 | U73: 三十一课堂 第五节
F74: 2 | G74: 20WA00397 | H74: 游皓 | I74: 游皓 | J74: =IFERROR(VLOOKUP(I74,Sheet1!A:C,3,FALSE),"zhoanudao") -> zhoanudao | K74: 44020 | L74: 11 | M74: Li952883629 | P74: 西班牙 | S74: 中文 | U74: 二十六课堂 第四节
F75: 金华 | G75: 20WA00398 | H75: 游恒 | I75: 游恒 | J75: =IFERROR(VLOOKUP(I75,Sheet1!A:C,3,FALSE),"zhoanudao") -> zhoanudao | K75: 44020 | M75: Li952883630 | P75: 西班牙 | S75: 中文 | U75: 阳光第八课堂 第八节
F76: 2 | G76: 20WA00399 | H76: 叶晨阳 | I76: 叶晨阳 | J76: =IFERROR(VLOOKUP(I76,Sheet1!A:C,3,FALSE),"zhoanudao") -> zhoanudao | K76: 44020 | M76: sunlishuang1128 | P76: 西班牙 | S76: 中文 | U76: 五十五课堂 第七节
F77: 3 | G77: 20WC00375 | H77: 郑雅稀（数） | I77: 郑雅稀 | J77: =IFERROR(VLOOKUP(I77,Sheet1!A:C,3,FALSE),"zhoanudao") -> zhoanudao | K77: 44020 | M77: taotao99309786 | P77: 意大利 | S77: 数学 | U77: 四十四课堂 第七节
F78: 4 | G78: 20WB0043 | H78: 留雨珂 | I78: 留雨珂 | J78: =IFERROR(VLOOKUP(I78,Sheet1!A:C,3,FALSE),"zhoanudao") -> zhoanudao | K78: 44020 | M78: wxid_82wfjo85b1ka11 | P78: 葡萄牙 | S78: 中文 | U78: 五十六课堂 第七节
F79: 金华 | G79: 20WB0044 | H79: 留瑞翔 | I79: 留瑞翔 | J79: =IFERROR(VLOOKUP(I79,Sheet1!A:C,3,FALSE),"zhoanudao") -> zhoanudao | K79: 44020 | M79: wxid_82wfjo85b1ka11 | P79: 葡萄牙 | S79: 中文 | U79: 阳光第八课堂 第八节
E80: 1 | F80: 4 | G80: 20WB0045 | H80: 尹可乐 | I80: 尹可乐 | J80: =IFERROR(VLOOKUP(I80,Sheet1!A:C,3,FALSE),"zhoanudao") -> 是 | K80: 44020 | L80: 13 | M80: yfq6731107 | P80: 葡萄牙 | S80: 中文 | U80: 二十九课堂 第四节 | AH80: 44021 | AI80: 44026 | AJ80: 44056 | AK80: 660 | AN80: 44056
E81: 1 | F81: 3 | G81: 20WB0046 | H81: 尹可欣 | I81: 尹可欣 | J81: =IFERROR(VLOOKUP(I81,Sheet1!A:C,3,FALSE),"zhoanudao") -> 是 | K81: 44020 | L81: 14 | M81: yfq6731107 | P81: 葡萄牙 | S81: 中文 | U81: 五十七课堂 第九节 | AH81: 44021 | AI81: 44026 | AJ81: 44056 | AK81: 660 | AN81: 44056
E82: 1 | F82: 金华 | G82: 20WB0047 | H82: 尹佳乐 | I82: 尹佳乐 | J82: =IFERROR(VLOOKUP(I82,Sheet1!A:C,3,FALSE),"zhoanudao") -> 是 | K82: 44020 | L82: 7 | M82: yfq6731107 | P82: 葡萄牙 | S82: 中文 | U82: 阳光第七课堂 第七节 | AH82: 44021 | AI82: 44026 | AJ82: 44056 | AK82: 660 | AN82: 44056
F83: 金华 | G83: 20WI0043 | H83: 陈智宇 | I83: 陈智宇 | J83: =IFERROR(VLOOKUP(I83,Sheet1!A:C,3,FALSE),"zhoanudao") -> 是 | K83: 44020 | L83: 7 | M83: crazy2016again | P83: 美国 | S83: 中文 | U83: 阳光第七课堂 第七节 | AH83: 44021 | AI83: 44026 | AJ83: 44056 | AK83: 660 | AN83: 44056
F84: 金华 | G84: 20WB0048 | H84: 吴桠宣 | I84: 吴桠宣 | J84: =IFERROR(VLOOKUP(I84,Sheet1!A:C,3,FALSE),"zhoanudao") -> zhoanudao | K84: 44020 | L84: 8 | M84: cpandwgs | P84: 葡萄牙 | S84: 中文 | U84: 阳光第七课堂 第七节
F85: 金华 | G85: 20WB0049 | H85: 蒋静怡 | I85: 蒋静怡 | J85: =IFERROR(VLOOKUP(I85,Sheet1!A:C,3,FALSE),"zhoanudao") -> zhoanudao | K85: 44020 | L85: 7 | M85: wang967231606 | P85: 葡萄牙 | S85: 中文 | U85: 阳光第七课堂 第七节
F86: 金华 | G86: 20WA00400 | H86: 蒋雨璇 | I86: 蒋雨璇 | J86: =IFERROR(VLOOKUP(I86,Sheet1!A:C,3,FALSE),"zhoanudao") -> zhoanudao | K86: 44020 | L86: 11 | M86: wxid_a9g4r8of5z3e22 | P86: 西班牙 | S86: 中文 | U86: 阳光第七课堂 第七节
F87: 金华 | G87: 20WE0004 | H87: 梁景涵 | I87: 梁景涵 | J87: =IFERROR(VLOOKUP(I87,Sheet1!A:C,3,FALSE),"zhoanudao") -> zhoanudao | K87: 44020 | L87: 11 | M87: afenlondon | P87: 英国 | S87: 中文 | U87: 阳光第七课堂 第七节
F88: 1 | G88: 20WA00401 | H88: 邱若涵 | I88: 邱若涵 | J88: =IFERROR(VLOOKUP(I88,Sheet1!A:C,3,FALSE),"zhoanudao") -> zhoanudao | K88: 44021 | L88: 12 | M88: ONYU478 | P88: 西班牙 | S88: 中文 | U88: 五十课堂 第三节
F89: 4 | G89: 20WC00378 | H89: 吴倩文 | I89: 吴倩文 | J89: =IFERROR(VLOOKUP(I89,Sheet1!A:C,3,FALSE),"zhoanudao") -> zhoanudao | K89: 44021 | L89: 11 | M89: aaa577588588 | P89: 意大利 | S89: 中文 | U89: 十五课堂 第三节
F90: 3 | G90: 20WB0050 | H90: 蒋静瑄（数） | I90: 蒋静瑄 | J90: =IFERROR(VLOOKUP(I90,Sheet1!A:C,3,FALSE),"zhoanudao") -> 是 | K90: 44021 | M90: wang967231606 | P90: 葡萄牙 | S90: 数学 | U90: 四十四课堂 第六节
F91: 3 | G91: 20WB0051 | H91: 蒋静怡（数） | I91: 蒋静怡 | J91: =IFERROR(VLOOKUP(I91,Sheet1!A:C,3,FALSE),"zhoanudao") -> zhoanudao | K91: 44021 | M91: wang967231607 | P91: 葡萄牙 | S91: 数学 | U91: 四十四课堂 第九节
F92: 3 | G92: 20WC00379 | H92: 瞿文熙（英） | I92: 瞿文熙 | J92: =IFERROR(VLOOKUP(I92,Sheet1!A:C,3,FALSE),"zhoanudao") -> zhoanudao | K92: 44021 | M92: chicken090 | P92: 意大利 | S92: 英文 | U92: 四十五课堂 第二节 | AH92: 44021 | AI92: 44026 | AJ92: 44117 | AK92: 1854 | AN92: 44117
F93: 4 | G93: 20WA00402 | H93: 陈思含 | I93: 陈思含 | J93: =IFERROR(VLOOKUP(I93,Sheet1!A:C,3,FALSE),"zhoanudao") -> zhoanudao | K93: 44021 | L93: 13 | M93: lingjiao72 | P93: 西班牙 | S93: 中文 | U93: 五十二课堂 第七节
F94: 1 | G94: 20WC00380 | H94: 董欣 | I94: 董欣 | J94: =IFERROR(VLOOKUP(I94,Sheet1!A:C,3,FALSE),"zhoanudao") -> zhoanudao | K94: 44021 | M94: dongwenqiang1974 | P94: 意大利 | S94: 中文 | U94: 五课堂 第一节 | AO94: 运营部新生
F95: 1 | G95: 20WI0044 | H95: 王诗涵 | I95: 王诗涵 | J95: =IFERROR(VLOOKUP(I95,Sheet1!A:C,3,FALSE),"zhoanudao") -> zhoanudao | K95: 44021 | M95: wld469191788 | P95: 美国 | S95: 中文 | U95: 二十二课堂 7:30-8:00 | X95: 一对三 | AO95: 运营部新生
F96: 1 | G96: 20WI0045 | H96: 王诗杰 | I96: 王诗杰 | J96: =IFERROR(VLOOKUP(I96,Sheet1!A:C,3,FALSE),"zhoanudao") -> zhoanudao | K96: 44021 | M96: wld469191789 | P96: 美国 | S96: 中文 | U96: 二十二课堂 7:30-8:00 | X96: 一对三 | AO96: 运营部新生
F97: 1 | G97: 20WI0046 | H97: 王姝慈 | I97: 王姝慈 | J97: =IFERROR(VLOOKUP(I97,Sheet1!A:C,3,FALSE),"zhoanudao") -> 是 | K97: 44021 | M97: Jingly104 | P97: 美国 | S97: 中文 | U97: 二十二课堂 7:30-8:00 | X97: 一对三 | AO97: 运营部新生
F98: 1 | G98: 20WI0047 | H98: 王灿宇 | I98: 王灿宇 | J98: =IFERROR(VLOOKUP(I98,Sheet1!A:C,3,FALSE),"zhoanudao") -> zhoanudao | K98: 44021 | M98: Ting_Duo1314 | P98: 美国 | S98: 中文 | U98: 二十二课堂 6:50-7:20 | X98: 一对一 | AO98: 运营部新生
F99: 4 | G99: 20WI0048 | H99: 王灿宇（数） | I99: 王灿宇 | J99: =IFERROR(VLOOKUP(I99,Sheet1!A:C,3,FALSE),"zhoanudao") -> zhoanudao | K99: 44021 | M99: Ting_Duo1314 | P99: 美国 | S99: 数学 | U99: 六十六课堂 5:00－5:30 | X99: 一对一 | AO99: 运营部新生
F100: 金华 | G100: 20WA00403 | H100: 张俊熙（数） | I100: 张俊熙 | J100: =IFERROR(VLOOKUP(I100,Sheet1!A:C,3,FALSE),"zhoanudao") -> zhoanudao | K100: 44021 | M100: he2012312 | P100: 西班牙海岛 | S100: 数学 | U100: 阳光第一课堂 第八节 | AO100: 运营部新生
...

Sheet Sheet1
A1: 叶文浩1 | B1: 叶文浩1 | C1: 是
A2: 叶鋆睿 | B2: 叶鋆睿 | C2: 是
A3: 何子恒（数） | B3: 何子恒 | C3: 是
A4: 吉娜 | B4: 吉娜 | C4: 是
A5: 宋崇铭 | B5: 宋崇铭 | C5: 是
A6: 吴楚惟 | B6: 吴楚惟 | C6: 是
A7: 吕泽歆 | B7: 吕泽歆 | C7: 是
A8: 小恩 | B8: 小恩 | C8: 是
A9: 吴炳铨（数） | B9: 吴炳铨 | C9: 是
A10: 林泽锴1 | B10: 林泽锴1 | C10: 是
A11: 胡昊阳 | B11: 胡昊阳 | C11: 是
A12: 胡昊阳（数） | B12: 胡昊阳 | C12: 是
... A253: 郑安俊郑俊杰郑迪纪柯艳 | B253: 郑安俊 | C253: 是
B254: 柯艳 | C254: 是
B255: 郑迪纪 | C255: 是
B256: 郑俊杰 | C256: 是
A257: 金喜1（数） | B257: 金喜1 | C257: 是
A258: 金娜娜1 | B258: 金娜娜1 | C258: 是
A259: 陈帅 | B259: 陈帅 | C259: 是
A260: 陈诺1 | B260: 陈诺1 | C260: 是
A261: 袁乐琛（数） | B261: 袁乐琛 | C261: 是
A262: 王新迪 | B262: 王新迪 | C262: 是
A263: 倪瑞璇 | B263: 倪瑞璇 | C263: 是
A264: 周素丽 | B264: 周素丽 | C264: 是
A265: 周熠 | B265: 周熠 | C265: 是
A266: 李浩然1 | B266: 李浩然1 | C266: 是
A267: 陈奕嘉 | B267: 陈奕嘉 | C267: 是
A268: 龚炫瑞 | B268: 龚炫瑞 | C268: 是
... A363: Huana wang, haoda wang,xunda wang | B363: Huana wang | C363: 是
B364: xunda wang | C364: 是
B365: haoda wang | C365: 是
A366: 张欣悦 | B366: 张欣悦 | C366: 是
A367: 朱佳慧 | B367: 朱佳慧 | C367: 是
A368: 朱凯文 | B368: 朱凯文 | C368: 是
A369: 陈明雪 | B369: 陈明雪 | C369: 是
A370: 杨欣蕊 | B370: 杨欣蕊 | C370: 是
A371: 叶欣茹前几天付了一个月 84现在在付一个月84。 叶思雅付两个月168 | B371: 叶欣茹 | C371: 是
B372: 叶思雅 | C372: 是
A373: 胡思光 | B373: 胡思光 | C373: 是
A374: 张晓丹 | B374: 张晓丹 | C374: 是
A375: zhao lina | B375: zhao lina | C375: 是
A376: 李林欣怡 | B376: 李林欣怡 | C376: 是
A377: 潘恩义 | B377: 潘恩义 | C377: 是
A378: 叶子晴 | B378: 叶子晴 | C378: 是
A379: 郑国豪 | B379: 郑国豪 | C379: 是
A380: 林雷腾 | B380: 林雷腾 | C380: 是
A381: 陶子璐 | B381: 陶子璐 | C381: 是
A382: 邱露茜娅 | B382: 邱露茜娅 | C382: 是
A383: 朱俊豪1 | B383: 朱俊豪1 | C383: 是
A384: 陈思彤 | B384: 陈思彤 | C384: 是
... A422: 邹欣颖 | B422: 邹欣颖 | C422: 是

Sheet 2020.06
A1: 到课情况 | D1: 咨询回访 （写内容） | E1: 是否成功 | F1: 分组 | G1: 学号 | H1: 学生姓名 | I1: 年龄 | J1: 家长联系方式 | K1: 校区 | L1: 市场 | M1: 区域国家 | N1: 在读状态 | O1: 课程顾问 | P1: 学科 | Q1: 课程情况 | R1: 在读课堂 | S1: 授课老师 | T1: 每周课时情况 | U1: 收费标准 | W1: 优惠活动 | Y1: 课时情况 | AB1: 收费员 | AC1: 付费方式 | AD1: 习惯付款方式 | AE1: 最后缴费时间 | AF1: 计费日期 | AH1: 最后收费金额 | AI1: 请假情况 | AK1: 到期时间 | AL1: 试读日期 | AM1: 备注
U2: 按月收费 | V2: 按节收费 | W2: 送课时 | X2: 优惠金额 | Y2: 总课时 | Z2: 当月消耗课时 | AA2: 剩余课时 | AF2: 起始日期 | AG2: 截止日期 | AH2: 人民币 | AI2: 开始请假日期 | AJ2: 截止请假日期
A3: 1 | B3: 1 | C3: 1 | D3: 1 | E3: 1 | F3: 2 | G3: 20WC00234 | H3: 叶毅晨 | J3: xunzhen158491543 | K3: 堂堂行 | L3: 老 | M3: 意大利 | P3: 中文 | Q3: 一对六 | R3: 五十五课堂 第四节 | T3: 一周五天 | U3: 660元/月 | AE3: 43983 | AF3: 43984 | AG3: 44014 | AH3: 660元 | AK3: 44014 | AL3: 6.01
A4: 1 | B4: 1 | C4: 1 | D4: 1 | E4: 1 | F4: 1 | G4: 20WC00233 | H4: 叶晨星 | J4: xunzhen158491544 | K4: 堂堂行 | L4: 老 | M4: 意大利 | P4: 中文 | Q4: 一对六 | R4: 三十课堂 第七节 | T4: 一周五天 | U4: 660元/月 | AE4: 43983 | AF4: 43984 | AG4: 44014 | AH4: 660元 | AK4: 44014 | AL4: 6.01
A5: 1 | B5: 1 | C5: 1 | D5: 1 | E5: 1 | F5: 4 | G5: 20WB0021 | H5: 陈毅轩 | J5: dong19791014 | K5: 堂堂行 | L5: 老 | M5: 葡萄牙 | O5: 陈雨2妈妈 | P5: 中文 | Q5: 一对六 | R5: 四十三课堂 第四节 | T5: 一周五天 | U5: 660元/月 | AE5: 43983 | AF5: 43984 | AG5: 44014 | AH5: 660元 | AK5: 44014 | AL5: 6.01
A6: 1 | B6: 1 | C6: 1 | D6: 1 | E6: 1 | F6: 4 | G6: 20WD0056 | H6: 胡智豪 | J6: huyou2009 | K6: 堂堂行 | L6: 老 | M6: 巴西 | P6: 中文 | Q6: 一对六 | R6: 五十六课堂 第十二节 | T6: 一周五天 | U6: 660元/月 | AE6: 43983 | AF6: 43984 | AG6: 44014 | AH6: 660元 | AK6: 44014 | AL6: 6.01
A7: 1 | B7: 1 | C7: 1 | D7: 1 | E7: 1 | F7: 2 | G7: 20WD0057 | H7: 胡子怡 | J7: huyou2009 | K7: 堂堂行 | L7: 老 | M7: 巴西 | P7: 中文 | Q7: 一对六 | R7: 三十八课堂 第六节 | T7: 一周五天 | U7: 660元/月 | AE7: 43983 | AF7: 43984 | AG7: 44014 | AH7: 660元 | AK7: 44014 | AL7: 6.01
A8: 1 | B8: 1 | C8: 1 | D8: 1 | E8: 1 | F8: 3 | G8: 20WC00235 | H8: 樊益洁（数） | J8: yjqsnyeq | K8: 堂堂行 | L8: 老 | M8: 意大利 | P8: 数学 | Q8: 一对六 | R8: 六课堂 第五节 | T8: 一周五天 | U8: 79元/节 | AE8: 43983 | AF8: 43994 | AG8: 44023 | AH8: 660元 | AK8: 44023 | AL8: 6.01 | AM8: 短期
A9: 1 | B9: 1 | C9: 1 | D9: 1 | E9: 1 | F9: 3 | G9: 20WC00236 | H9: 樊益欣（数） | J9: yjqsnyeq | K9: 堂堂行 | L9: 老 | M9: 意大利 | P9: 数学 | Q9: 一对六 | R9: 六课堂 第五节 | T9: 一周五天 | U9: 79元/节 | AE9: 43983 | AF9: 43994 | AG9: 44023 | AH9: 660元 | AK9: 44023 | AL9: 6.01 | AM9: 短期
A10: 1 | B10: 1 | C10: 1 | D10: 1 | E10: 1 | F10: 3 | G10: 20WA00175 | H10: 朱晞欧（数） | J10: Azul651420220 | K10: 堂堂行 | L10: 老 | M10: 西班牙 | P10: 数学 | Q10: 一对六 | R10: 四十四课堂 第八节 | T10: 一周五天 | U10: 660元/月 | AE10: 43983 | AF10: 43984 | AG10: 44014 | AH10: 660元 | AK10: 44014 | AL10: 6.01
A11: 1 | B11: 1 | C11: 1 | D11: 1 | E11: 1 | F11: 2 | G11: 20WC00237 | H11: 胡欢胜 | J11: michela001 | K11: 堂堂行 | L11: 老 | M11: 意大利 | P11: 中文 | Q11: 一对六 | R11: 四十八课堂 第二节 | T11: 一周五天 | U11: 660元/月 | AE11: 43983 | AF11: 43984 | AG11: 44014 | AH11: 660元 | AK11: 44014 | AL11: 6.01
A12: 1 | B12: 1 | C12: 1 | D12: 孩子不喜欢 | E12: 0 | F12: 3 | H12: 历暄妍（数） | J12: S123456789y2006 | K12: 堂堂行 | L12: 老 | M12: 意大利 | P12: 数学 | Q12: 一对六 | R12: 三十二课堂 第六节 | T12: 一周五天 | U12: 660元/月 | AL12: 6.01
A13: 1 | B13: 1 | C13: 1 | D13: 1 | E13: 1 | F13: 1 | G13: 20WA00176 | H13: 章鑫彦 | J13: ZYF301411 | K13: 堂堂行 | L13: 老 | M13: 西班牙 | P13: 中文 | Q13: 一对六 | R13: 三十七课堂 第九节 | T13: 一周五天 | U13: 660元/月 | AE13: 2020.6.19 | AF13: 43986 | AG13: 44104 | AH13: 2427元 | AK13: 44104 | AL13: 6.01
A14: 1 | B14: 1 | C14: 1 | D14: 1 | E14: 1 | F14: 2 | G14: 20WC00239 | H14: 虞咏凯 | J14: chen1534779756 | K14: 堂堂行 | L14: 老 | M14: 意大利 | O14: 徐熙桐妈妈 | P14: 中文 | Q14: 一对六 | R14: 三十三课堂 第八节 | T14: 一周五天 | U14: 660元/月 | AE14: 43983 | AF14: 43987 | AG14: 44016 | AH14: 660元 | AK14: 44016 | AL14: 6.01
A15: 1 | B15: 1 | C15: 1 | D15: 1 | E15: 1 | F15: 3 | G15: 20WC00240 | H15: 葛子涵 | J15: geyun221 | K15: 堂堂行 | L15: 老 | M15: 意大利 | P15: 中文 | Q15: 一对六 | R15: 五十七课堂 第十节 | T15: 一周五天 | U15: 660元/月 | AE15: 43984 | AF15: 43986 | AG15: 44015 | AH15: 660元 | AK15: 44015 | AL15: 6.01
A16: 1 | B16: 1 | C16: 1 | D16: 1 | E16: 1 | F16: 1 | G16: 20WC00241 | H16: 叶培熙 | J16: qq546245075 | K16: 堂堂行 | L16: 老 | M16: 意大利 | P16: 中文 | Q16: 一对六 | R16: 三十课堂 第七节 | T16: 一周五天 | U16: 660元/月 | AE16: 43988 | AF16: 43986 | AG16: 44015 | AH16: 660元 | AK16: 44015 | AL16: 6.01
A17: 1 | E17: 0 | F17: 3 | G17: 20WA00177 | H17: 张家盛(数） | J17: hongli1688 | K17: 堂堂行 | L17: 新 | M17: 西班牙 | P17: 数学 | Q17: 一对六 | R17: 十一课堂 第十二节 | T17: 一周五天 | U17: 660元/月 | AL17: 6.01 | AM17: 运营部老生重读
A18: 1 | B18: 1 | C18: 1 | D18: 1 | E18: 1 | F18: 2 | G18: 20WC00242 | H18: 周嘉欣 | J18: tina19861120 | K18: 堂堂行 | L18: 老 | M18: 意大利 | P18: 中文 | Q18: 一对六 | R18: 十三课堂 第二节 | T18: 一周五天 | U18: 660元/月 | AL18: 6.02
A19: 1 | B19: 1 | C19: 1 | D19: 1 | E19: 1 | F19: 3 | G19: 20WC00243 | H19: 朱浩钰（数） | J19: wxid_to3k0bbkljeh11 | K19: 堂堂行 | L19: 老 | M19: 意大利 | P19: 数学 | Q19: 一对六 | R19: 三十二课堂 第八节 | T19: 一周五天 | U19: 660元/月 | AE19: 43990 | AF19: 43990 | AG19: 44020 | AH19: 660元 | AK19: 44020 | AL19: 6.02
A20: 1 | B20: 1 | C20: 1 | D20: 学美术，没时间 | E20: 0 | F20: 1 | H20: 留诗雅 | J20: Sara__26 | K20: 堂堂行 | L20: 老 | M20: 意大利 | P20: 中文 | Q20: 一对六 | R20: 三十课堂 第七节 | T20: 一周五天 | U20: 660元/月 | AL20: 6.02
A21: 1 | B21: 1 | C21: 1 | D21: 1 | E21: 1 | F21: 2 | G21: 20WC00245 | H21: 庄嘉宁 | J21: lin697403 | K21: 堂堂行 | L21: 老 | M21: 意大利 | P21: 中文 | Q21: 一对六 | R21: 五十四课堂 第二节 | T21: 一周五天 | U21: 660元/月 | AE21: 43998 | AF21: 43988 | AG21: 44079 | AH21: 1980元 | AK21: 44079 | AL21: 6.02
A22: 1 | B22: 1 | C22: 1 | D22: 1 | E22: 1 | F22: 3 | G22: 20WC00246 | H22: 林轩玮（英） | J22: yaoyao369815226 | K22: 堂堂行 | L22: 老 | M22: 意大利 | P22: 英文 | Q22: 一对六 | R22: 四十五课堂 第八节 | T22: 一周五天 | U22: 660元/月 | AE22: 43990 | AF22: 43990 | AG22: 44019 | AH22: 660元 | AK22: 44019 | AL22: 6.02
A23: 1 | B23: 1 | C23: 1 | D23: 1 | E23: 1 | F23: 2 | G23: 20WC00247 | H23: 杜王洲 | J23: caihq1210 | K23: 堂堂行 | L23: 老 | M23: 意大利 | P23: 中文 | Q23: 一对六 | R23: 四十八课堂 第十节 | T23: 一周五天 | U23: 660元/月 | AE23: 43988 | AF23: 43988 | AG23: 44079 | AH23: 1980元 | AK23: 44079 | AL23: 6.02
A24: 1 | D24: 没有时间陪孩子 | E24: 0 | F24: 2 | H24: 张灵萱 | J24: Evaluky | K24: 堂堂行 | L24: 老 | M24: 意大利 | P24: 中文 | Q24: 一对六 | R24: 四十八课堂 第十节 | T24: 一周五天 | U24: 660元/月 | AL24: 6.02
A25: 1 | D25: 1 | E25: 1 | F25: 2 | G25: 20WC00249 | H25: 林晶茹 | J25: paola123 | K25: 堂堂行 | L25: 老 | M25: 意大利 | P25: 中文 | Q25: 一对六 | R25: 四十八课堂 第十节 | T25: 一周五天 | U25: 660元/月 | AE25: 2020.6.18 | AF25: 43987 | AG25: 44078 | AH25: 1980元 | AK25: 44078 | AL25: 6.02
A26: 1 | D26: 1 | E26: 1 | F26: 2 | G26: 20WB0023 | H26: 陈洛彬 | J26: Chloe130708 | K26: 堂堂行 | L26: 老 | M26: 葡萄牙 | P26: 中文 | Q26: 一对六 | R26: 四十八课堂 第十节 | T26: 一周五天 | U26: 660元/月 | AE26: 43990 | AF26: 43990 | AG26: 44020 | AH26: 660元 | AK26: 44020 | AL26: 6.02
A27: 1 | D27: 1 | E27: 1 | F27: 3 | G27: 20WB0024 | H27: 李世龙1（英） | J27: L571638321 | K27: 堂堂行 | L27: 老 | M27: 葡萄牙海岛 | P27: 英文 | Q27: 一对六 | R27: 四十五课堂 第十节 | T27: 一周五天 | U27: 660元/月 | AE27: 43990 | AF27: 43990 | AG27: 44020 | AH27: 660元 | AK27: 44020 | AL27: 6.02
A28: 1 | D28: 1 | E28: 1 | F28: 3 | G28: 20WA00178 | H28: 陈知奕（数） | J28: helena331835 | K28: 堂堂行 | L28: 老 | M28: 西班牙 | P28: 数学 | Q28: 一对六 | R28: 三十二课堂 第八节 | T28: 一周五天 | U28: 660元/月 | AE28: 43988 | AF28: 43988 | AG28: 44079 | AH28: 1980元 | AK28: 44079 | AL28: 6.02
A29: 1 | D29: 1 | E29: 1 | F29: 3 | G29: 20WA00179 | H29: 唐惠怡（数） | J29: twjw32 | K29: 堂堂行 | L29: 老 | M29: 西班牙 | P29: 数学 | Q29: 一对六 | R29: 三十二课堂 第八节 | T29: 一周五天 | U29: 660元/月 | AE29: 43999 | AF29: 43987 | AG29: 44016 | AH29: 660元 | AK29: 44016 | AL29: 6.02
A30: 1 | E30: 1 | F30: 4 | G30: 20WA00180 | H30: 王天缘 | J30: wangzhaonihao | K30: 堂堂行 | L30: 新 | M30: 西班牙 | P30: 中文 | Q30: 一对六 | R30: 四十三课堂 第五节 | T30: 一周五天 | U30: 660元/月 | AB30: 运营部新生 | AE30: 44008 | AF30: 43987 | AG30: 44078 | AH30: 1980元 | AK30: 44078 | AL30: 6.02 | AM30: 运营部新生
A31: 1 | D31: 1 | E31: 1 | F31: 3 | G31: 20WC00250 | H31: 包瑞莹（英） | J31: bao19831012 | K31: 堂堂行 | L31: 老 | M31: 意大利 | P31: 英文 | Q31: 一对六 | R31: 四十五课堂 第三节 | T31: 一周五天 | U31: 640元/月 | AE31: 43991 | AF31: 43991 | AG31: 44082 | AH31: 1920元 | AK31: 44082 | AL31: 6.03
A32: 1 | D32: 1 | E32: 1 | F32: 3 | G32: 20WA00181 | H32: 叶晨欣(英） | J32: liushuangmei1982 | K32: 堂堂行 | L32: 老 | M32: 西班牙 | P32: 英文 | Q32: 一对六 | R32: 四十五课堂 第三节 | T32: 一周五天 | U32: 660元/月 | Y32: 1 | AL32: 6.03
A33: 1 | D33: 1 | E33: 1 | F33: 3 | G33: 20WB0025 | H33: 李子涵1（英） | J33: L571638321 | K33: 堂堂行 | L33: 老 | M33: 葡萄牙海岛 | P33: 英文 | Q33: 一对六 | R33: 四十五课堂 第三节 | T33: 一周五天 | U33: 660元/月 | AE33: 43990 | AF33: 43990 | AG33: 44020 | AH33: 660元 | AK33: 44020 | AL33: 6.03
A34: 1 | D34: 1 | E34: 1 | F34: 3 | G34: 20WC00251 | H34: 叶昊铭（英） | J34: zjpdxyx | K34: 堂堂行 | L34: 老 | M34: 意大利 | P34: 英文 | Q34: 一对六 | R34: 四十五课堂 第三节 | T34: 一周五天 | U34: 660元/月 | AE34: 20/6/08 | AF34: 44019 | AG34: 44019 | AH34: 610元 | AK34: 44019 | AL34: 6.03
A35: 1 | D35: 1 | E35: 1 | F35: 2 | G35: 20WD0058 | H35: yuranran(余冉冉) | J35: one138138 | K35: 堂堂行 | L35: 老 | M35: 巴西 | P35: 中文 | Q35: 一对六 | R35: 四十八课堂 第十节 | T35: 一周五天 | U35: 660元/月 | AE35: 20.6.23 | AF35: 43990 | AG35: 44081 | AH35: 1860元 | AK35: 44081 | AL35: 6.03
A36: 1 | D36: 1 | E36: 1 | F36: 1 | G36: 20WC00252 | H36: 黄可馨 | J36: Jie2782286 | K36: 堂堂行 | L36: 老 | M36: 意大利 | P36: 中文 | Q36: 一对六 | R36: 十二课堂 第五节 | T36: 一周五天 | U36: 660元/月 | AE36: 43998 | AF36: 43991 | AG36: 44020 | AH36: 660元 | AK36: 44020 | AL36: 6.03
A37: 1 | D37: 1 | E37: 1 | F37: 3 | G37: 20WA00182 | H37: 庞梦洁 | J37: xiping_1111 | K37: 堂堂行 | L37: 老 | M37: 西班牙 | P37: 中文 | Q37: 一对六 | R37: 二十八课堂 第十节 | T37: 一周五天 | U37: 660元/月 | AE37: 44016 | AF37: 43991 | AG37: 44020 | AH37: 660元 | AK37: 44020 | AL37: 6.03
A38: 1 | D38: 1 | E38: 1 | F38: 2 | G38: 20WB0026 | H38: 叶君泽 | J38: Zeng963739528 | K38: 堂堂行 | L38: 老 | M38: 葡萄牙 | P38: 中文 | Q38: 一对六 | R38: 四十八课堂 第十节 | T38: 一周五天 | U38: 660元/月 | Y38: 1 | AE38: 44000 | AF38: 43990 | AG38: 44019 | AH38: 660元 | AK38: 44019 | AL38: 6.04
A39: 1 | D39: 1 | E39: 1 | F39: 3 | G39: 20WC00253 | H39: 胡梦蕾（英） | J39: chichichiting | K39: 堂堂行 | L39: 老 | M39: 意大利 | P39: 英文 | Q39: 一对六 | R39: 四十五课堂 第三节 | T39: 一周五天 | U39: 660元/月 | Y39: 1 | AE39: 20/6/11 | AF39: 43990 | AG39: 44081 | AH39: 1980元 | AK39: 44081 | AL39: 6.04
A40: 1 | D40: 追女孩学英文 | E40: 0 | F40: 3 | H40: 周炀（英） | J40: a719465208 | K40: 堂堂行 | L40: 老 | M40: 意大利 | P40: 英文 | Q40: 一对六 | R40: 十四课堂 第五节 | T40: 一周五天 | U40: 660元/月 | X40: 试读失败 | AL40: 6.04
A41: 1 | D41: 更喜欢其他平台的老师 | E41: 0 | F41: 2 | G41: 20WC00255 | H41: 赵芊雅 | J41: mony85 | K41: 堂堂行 | L41: 老 | M41: 意大利 | P41: 中文 | Q41: 一对六 | R41: 四十八课堂 第十节 | T41: 一周五天 | U41: 660元/月 | X41: 试读失败 | AL41: 6.04
A42: 1 | D42: 1 | E42: 1 | F42: 1 | G42: 20WC00256 | H42: 朱浩锦 | J42: zhu3778211745 | K42: 堂堂行 | L42: 老 | M42: 意大利 | P42: 中文 | Q42: 一对六 | R42: 三十九课堂 | T42: 一周五天 | U42: 660元/月 | AE42: 44014 | AF42: 43993 | AG42: 44022 | AH42: 660元 | AK42: 44022 | AL42: 6.05 | AM42: 转39课堂
A43: 1 | D43: 孩子有安排，太忙 | E43: 0 | F43: 3 | H43: 杜乐督 | J43: jiyiyin001 | K43: 堂堂行 | L43: 老 | M43: 巴西 | P43: 中文 | Q43: 一对六 | R43: 一课堂 第一节 | T43: 一周五天 | U43: 660元/月 | X43: 试读失败 | AL43: 6.05
A44: 1 | D44: 孩子有安排，太忙 | E44: 0 | F44: 2 | H44: 杜乐柔 | J44: jiyiyin001 | K44: 堂堂行 | L44: 老 | M44: 巴西 | P44: 中文 | Q44: 一对六 | R44: 三十三课堂 第二节 | T44: 一周五天 | U44: 660元/月 | X44: 试读失败 | AL44: 6.05
A45: 1 | D45: 换时间没合适的课程，先学中文 | E45: 0 | F45: 3 | G45: 20WC00257 | H45: 叶培熙（数） | J45: qq546245075 | K45: 堂堂行 | L45: 老 | M45: 意大利 | P45: 数学 | Q45: 一对六 | R45: 三十二课堂 第八节 | T45: 一周五天 | U45: 660元/月 | X45: 试读失败 | AE45: 1 | AL45: 6.05
A46: 1 | D46: 1 | E46: 1 | F46: 4 | G46: 20WC00258 | H46: 叶乔 | J46: Axiaofl | K46: 堂堂行 | L46: 老 | M46: 意大利 | P46: 中文 | Q46: 一对六 | R46: 五十六课堂 第一节 | T46: 一周五天 | U46: 660元/月 | AE46: 2020.6.19 | AF46: 43993 | AG46: 44022 | AH46: 660元 | AK46: 44022 | AL46: 6.05
A47: 1 | B47: 1 | C47: 1 | D47: 1 | E47: 1 | F47: 1 | G47: 20WH0006 | H47: 韩子嫣 | J47: w11800228 | K47: 堂堂行 | L47: 老 | M47: 德国 | P47: 中文 | Q47: 一对六 | R47: 三十课堂 第七节 | T47: 一周五天 | U47: 660元/月 | AE47: 2020.6.19 | AF47: 43993 | AG47: 44022 | AH47: 660元 | AK47: 44022 | AL47: 6.05
A48: 1 | D48: 1 | E48: 1 | F48: 2 | G48: 20WC00259 | H48: 朱安琪 | J48: qiu3388400374 | K48: 堂堂行 | L48: 老 | M48: 意大利 | P48: 中文 | Q48: 一对六 | R48: 二十六课堂 第十节 | T48: 一周五天 | U48: 660元/月 | AE48: 43994 | AF48: 43993 | AG48: 44084 | AH48: 1860元 | AK48: 44084 | AL48: 6.05
A49: 1 | D49: 1 | E49: 1 | F49: 3 | G49: 20WC00260 | H49: 吴诗涵1 | J49: sussi666666 | K49: 堂堂行 | L49: 老 | M49: 意大利 | P49: 英文 | Q49: 一对六 | R49: 四十五课堂 第三节 | T49: 一周五天 | U49: 660元/月 | AL49: 6.08
A50: 1 | D50: 家长未回复 | E50: 0 | F50: 3 | G50: 20WC00261 | H50: 杨珍祯（数） | J50: dongbiao012077 | K50: 堂堂行 | L50: 老 | M50: 意大利 | P50: 数学 | Q50: 一对六 | R50: 四十四课堂 第五节 | T50: 一周五天 | U50: 660元/月 | AL50: 6.08
A51: 1 | E51: 1 | F51: 1 | G51: 20WC00262 | H51: 陳鑫隆彥 | J51: J315905293 | K51: 堂堂行 | L51: 老 | M51: 意大利 | P51: 中文 | Q51: 一对六 | R51: 十二课堂 第六节 | T51: 一周五天 | U51: 660元/月 | AE51: 43998 | AF51: 43994 | AG51: 44085 | AH51: 1980元 | AK51: 44085 | AL51: 6.08
A52: 1 | D52: 1 | E52: 1 | F52: 4 | G52: 20WC00263 | H52: 胡雅歆 | J52: hcyyy29 | K52: 堂堂行 | L52: 老 | M52: 意大利 | P52: 中文 | Q52: 一对六 | R52: 五十二课堂 20:20-20:50 | T52: 一周五天 | U52: 660元/月 | AE52: 43990 | AF52: 43994 | AG52: 44023 | AH52: 660元 | AK52: 44023 | AL52: 6.08
A53: 1 | E53: 1 | F53: 4 | G53: 20WC00264 | H53: 郑毅翔 | J53: hucongyao90 | K53: 堂堂行 | L53: 老 | M53: 意大利 | P53: 中文 | Q53: 一对六 | R53: 五十二课堂 20:20-20:50 | T53: 一周五天 | U53: 660元/月 | AE53: 43990 | AF53: 43994 | AG53: 44023 | AH53: 660元 | AK53: 44023 | AL53: 6.08
A54: 1 | D54: 1 | E54: 1 | F54: 1 | G54: 20WC00265 | H54: 胡舒涵 | J54: hcyyy29 | K54: 堂堂行 | L54: 老 | M54: 意大利 | P54: 中文 | Q54: 一对六 | R54: 三十七课堂 第八节 | T54: 一周五天 | U54: 660元/月 | AE54: 43990 | AF54: 43994 | AG54: 44023 | AH54: 660元 | AK54: 44023 | AL54: 6.08
A55: 1 | D55: 后来没回复老师了，大概是价格与上课时长不搭 | E55: 0 | F55: 2 | G55: 20WC00266 | H55: 严嘉鹏 | J55: FENGYAQIN2008 | K55: 堂堂行 | L55: 老 | M55: 意大利 | P55: 中文 | Q55: 一对六 | R55: 十四课堂 第八节 | T55: 一周五天 | U55: 660元/月 | AL55: 6.08
A56: 1 | D56: 试读3天，课程不大适合 | E56: 0 | F56: 2 | G56: 20WC00267 | H56: 黄仲谦 | J56: Ating3344 | K56: 堂堂行 | L56: 老 | M56: 意大利 | P56: 中文 | Q56: 一对六 | R56: 四十八课堂 第十节 | T56: 一周五天 | U56: 660元/月 | AL56: 6.08
A57: 1 | D57: 1 | E57: 1 | F57: 2 | G57: 20WD0059 | H57: 叶金豪 | J57: aiwu780313 | K57: 堂堂行 | L57: 老 | M57: 巴西 | P57: 中文 | Q57: 一对六 | R57: 二十六课堂20:20-20:50 | T57: 一周五天 | U57: 620元/月 | AE57: 20.6.24 | AF57: 43994 | AG57: 44069 | AH57: 1860元 | AK57: 44069 | AL57: 6.08
A58: 1 | D58: 上了一节课 | E58: 0 | F58: 4 | G58: 20WC00268 | H58: 戴恩琦 | J58: linjianyao02 | K58: 堂堂行 | L58: 老 | M58: 意大利 | P58: 中文 | Q58: 一对六 | R58: 五十六课堂 第七节 | T58: 一周五天 | U58: 660元/月 | AL58: 6.09
A59: 1 | D59: 1 | E59: 1 | F59: 4 | G59: 20WA00183 | H59: 雪怡 | J59: xiaohua20190801 | K59: 堂堂行 | L59: 老 | M59: 西班牙 | P59: 中文 | Q59: 一对六 | R59: 五十六课堂 第七节 | T59: 一周五天 | U59: 660元/月 | AE59: 20.6.23 | AF59: 43997 | AG59: 44057 | AH59: 1854元 | AK59: 44057 | AL59: 6.09
A60: 1 | D60: 1 | E60: 1 | F60: 4 | G60: 20WC00269 | H60: 叶子豪 | J60: wange996578188 | K60: 堂堂行 | L60: 老 | M60: 意大利 | P60: 中文 | Q60: 一对六 | R60: 五十六课堂 第七节 | T60: 一周五天 | U60: 660元/月 | AE60: 20.6.21 | AF60: 43997 | AG60: 44104 | AH60: 2163元 | AK60: 44104 | AL60: 6.09
A61: 1 | D61: 1 | E61: 1 | F61: 4 | G61: 20WC00270 | H61: 徐欣怡 | J61: Giovanni2581314 | K61: 堂堂行 | L61: 老 | M61: 意大利 | P61: 中文 | Q61: 一对六 | R61: 五十六课堂 第七节 | T61: 一周五天 | U61: 660元/月 | AE61: 20.6.20 | AF61: 43994 | AG61: 44104 | AH61: 2232元 | AK61: 44104 | AL61: 6.09
A62: 1 | D62: 1 | E62: 1 | F62: 4 | G62: 20WC00271 | H62: 王妤心 | J62: shanshanita | K62: 堂堂行 | L62: 老 | M62: 意大利 | P62: 中文 | Q62: 一对六 | R62: 五十六课堂 第七节 | T62: 一周五天 | U62: 660元/月 | AL62: 6.09
A63: 1 | D63: 中文转数学 | E63: 0 | F63: 4 | G63: 20WC00272 | H63: 刘妤可 | J63: Elisa19890712 | K63: 堂堂行 | L63: 老 | M63: 意大利 | P63: 中文 | Q63: 一对六 | R63: 五十六课堂 第七节 | T63: 一周五天 | U63: 660元/月 | AL63: 6.09
A64: 1 | D64: 1 | E64: 1 | F64: 4 | G64: 20WC00273 | H64: 陈奕贝 | J64: luisa119411814 | K64: 堂堂行 | L64: 老 | M64: 意大利 | P64: 中文 | Q64: 一对六 | R64: 五十六课堂 第三节 | T64: 一周五天 | U64: 660元/月 | AE64: 20.6.16 | AF64: 43995 | AG64: 44024 | AH64: 660元 | AK64: 44024 | AL64: 6.09
A65: 1 | D65: 1 | E65: 1 | F65: 4 | G65: 20WC00274 | H65: 王子昊 | J65: minixin1234567 | K65: 堂堂行 | L65: 老 | M65: 意大利 | P65: 中文 | Q65: 一对六 | R65: 六十六课堂 第六节 | T65: 一周五天 | U65: 660元/月 | AE65: 43998 | AF65: 43995 | AG65: 44024 | AH65: 660元 | AK65: 44024 | AL65: 6.09
A66: 1 | D66: 1 | E66: 1 | F66: 4 | G66: 20WC00275 | H66: 王子业 | J66: minixin1234567 | K66: 堂堂行 | L66: 老 | M66: 意大利 | P66: 中文 | Q66: 一对六 | R66: 六十六课堂 第六节 | T66: 一周五天 | U66: 660元/月 | AE66: 43998 | AF66: 43995 | AG66: 44024 | AH66: 660元 | AK66: 44024 | AL66: 6.09
A67: 1 | E67: 1 | F67: 4 | G67: 20WC00276 | H67: 周振皓 | J67: caiwenjing1985 | K67: 堂堂行 | L67: 老 | M67: 意大利 | P67: 中文 | Q67: 一对六 | R67: 六十六课堂 第七节 | T67: 一周五天 | U67: 660元/月 | AE67: 43991 | AF67: 43994 | AG67: 44024 | AH67: 660元 | AK67: 44024 | AL67: 6.09
A68: 1 | D68: 1 | E68: 1 | F68: 4 | G68: 20WC00277 | H68: 陈奕向 | J68: luisa119411814 | K68: 堂堂行 | L68: 老 | M68: 意大利 | P68: 中文 | Q68: 一对六 | R68: 六十六课堂 第七节 | T68: 一周五天 | U68: 660元/月 | AE68: 20.6.16 | AF68: 43995 | AG68: 44024 | AH68: 660元 | AK68: 44024 | AL68: 6.09
A69: 1 | D69: 1 | E69: 1 | F69: 4 | G69: 20WC00278 | H69: 李绍祺 | J69: shuli12345chen | K69: 堂堂行 | L69: 老 | M69: 意大利 | P69: 中文 | Q69: 一对六 | R69: 六十六课堂 第七节 | T69: 一周五天 | U69: 660元/月 | AE69: 43991 | AF69: 43994 | AG69: 44024 | AH69: 660元 | AK69: 44024 | AL69: 6.09
A70: 1 | D70: 1 | E70: 1 | F70: 4 | G70: 20WC00279 | H70: 杨镇旭 | J70: meimeixiang168 | K70: 堂堂行 | L70: 老 | M70: 意大利 | P70: 中文 | Q70: 一对六 | R70: 六十六课堂 第七节 | T70: 一周五天 | U70: 660元/月 | AE70: 43991 | AF70: 43994 | AG70: 44024 | AH70: 660元 | AK70: 44024 | AL70: 6.09
A71: 1 | D71: 1 | E71: 1 | F71: 4 | G71: 20WA00184 | H71: 林辰浩 | J71: meimeixiang168 | K71: 堂堂行 | L71: 老 | M71: 西班牙 | P71: 中文 | Q71: 一对六 | R71: 六十六课堂 第七节 | T71: 一周五天 | U71: 660元/月 | AE71: 43995 | AF71: 43994 | AG71: 44024 | AH71: 660元 | AK71: 44024 | AL71: 6.09
A72: 1 | E72: 1 | F72: 4 | G72: 20WC00280 | H72: 徐芷其 | J72: xujianyong0929 | K72: 堂堂行 | L72: 老 | M72: 意大利 | P72: 中文 | Q72: 一对六 | R72: 六十六课堂 第六节 | T72: 一周五天 | U72: 660元/月 | AE72: 43991 | AF72: 43994 | AG72: 44024 | AH72: 660元 | AK72: 44024 | AL72: 6.09
A73: 1 | E73: 1 | F73: 4 | G73: 20WC00281 | H73: 徐芷洋 | J73: xujianyong0930 | K73: 堂堂行 | L73: 老 | M73: 意大利 | P73: 中文 | Q73: 一对六 | R73: 六十六课堂 第六节 | T73: 一周五天 | U73: 660元/月 | AE73: 43991 | AF73: 43994 | AG73: 44024 | AH73: 660元 | AK73: 44024 | AL73: 6.09
A74: 1 | E74: 1 | F74: 3 | G74: 20WA00185 | H74: 郭朱璇（数） | J74: chunmei685820950 | K74: 堂堂行 | L74: 老 | M74: 西班牙 | P74: 数学 | Q74: 一对六 | R74: 一课堂 第十节 | T74: 一周五天 | U74: 620元/月 | AE74: 43997 | AF74: 43997 | AG74: 44057 | AH74: 1240元 | AK74: 44057 | AL74: 6.09
A75: 1 | D75: 半小时时间少，不合适 | E75: 0 | F75: 3 | G75: 20WC00282 | H75: 赵冰冰 | J75: susannaj | K75: 堂堂行 | L75: 老 | M75: 意大利 | P75: 中文 | Q75: 一对六 | R75: 四十课堂 第四节 | T75: 一周五天 | U75: 660元/月 | AL75: 6.09
A76: 1 | D76: 18岁 觉得课程不合适 | E76: 0 | F76: 4 | G76: 20WD0059 | H76: 吴威杰 | J76: weijiejosue | K76: 堂堂行 | L76: 老 | M76: 巴西 | P76: 中文 | Q76: 一对六 | R76: 三十四课堂 第九节 | T76: 一周五天 | U76: 660元/月 | AL76: 6.09
A77: 1 | D77: 1 | E77: 1 | F77: 3 | G77: 20WC00283 | H77: 林俊杰（英） | J77: ERICA52038 | K77: 堂堂行 | L77: 老 | M77: 意大利 | P77: 英文 | Q77: 一对六 | R77: 四十五课堂 第十节 | T77: 一周五天 | U77: 660元/月 | AE77: 44001 | AF77: 43994 | AG77: 44023 | AH77: 660元 | AK77: 44023 | AL77: 6.09
A78: 1 | E78: 1 | F78: 1 | G78: 20WA00186 | H78: 吴雨晨1 | J78: wuxijie002 | K78: 堂堂行 | L78: 老 | M78: 西班牙 | P78: 中文 | Q78: 一对六 | R78: 三十七课堂 第四节 | T78: 一周五天 | U78: 660元/月 | AE78: 43997 | AF78: 43997 | AG78: 44027 | AH78: 660元 | AK78: 44027 | AL78: 6.1
D79: 1 | E79: 1 | F79: 1 | G79: 20WC00284 | H79: 林乐欣 | J79: ERICA52038 | K79: 堂堂行 | L79: 老 | M79: 意大利 | P79: 中文 | Q79: 一对六 | R79: 五课堂 20:00-20:30 | T79: 一周五天 | U79: 660元/月 | AE79: 44001 | AF79: 43994 | AG79: 44023 | AH79: 660元 | AK79: 44023 | AL79: 6.1
E80: 1 | F80: 2 | G80: 20WC00285 | H80: 林蜜雪 | J80: monica517LI | K80: 堂堂行 | L80: 老 | M80: 意大利 | P80: 中文 | Q80: 一对六 | R80: 二十三课堂 第四节 | T80: 一周五天 | U80: 660元/月 | AE80: 43999 | AF80: 43998 | AG80: 44027 | AH80: 660元 | AK80: 44027 | AL80: 6.1
D81: 1 | E81: 1 | F81: 3 | G81: 20WB0028 | H81: 裘宸懿（数） | J81: qxozl320 | K81: 堂堂行 | L81: 老 | M81: 葡萄牙 | P81: 数学 | Q81: 一对六 | R81: 十一课堂 第八节 | T81: 一周五天 | U81: 660元/月 | AL81: 6.1
E82: 1 | F82: 4 | G82: 20WA00187 | H82: 何家乐 | J82: oscartiaoyuan | K82: 堂堂行 | L82: 老 | M82: 西班牙 | P82: 中文 | Q82: 一对六 | R82: 五十二课堂 第三节 | T82: 一周五天 | U82: 660元/月 | AE82: 44002 | AF82: 43997 | AG82: 44088 | AH82: 1980元 | AK82: 44088 | AL82: 6.1
D83: 家长没回消息 | E83: 0 | F83: 4 | G83: 20WC00286 | H83: 胡紫怡 | J83: a3778401702 | K83: 堂堂行 | L83: 老 | M83: 意大利 | P83: 中文 | Q83: 一对六 | R83: 五十六课堂 第七节 | T83: 一周五天 | U83: 660元/月 | AL83: 6.1
D84: 想和表哥一起，但是学费太贵 | E84: 0 | F84: 3 | G84: 20WD0060 | H84: 赵梦颖 | J84: yuxiao-zhaowei | K84: 堂堂行 | L84: 老 | M84: 巴西 | P84: 中文 | Q84: 一对六 | R84: 五十七课堂 6:00-6：30 | T84: 一周五天 | U84: 660元/月 | AL84: 6.1
E85: 1 | F85: 1 | G85: 20WI0024 | H85: 张妍茜 | J85: lin20110111 | K85: 堂堂行 | L85: 老 | M85: 美国 | P85: 中文 | Q85: 一对六 | R85: 二十二课堂 5:30-6:00 | T85: 一周五天 | U85: 660元/月 | AE85: 43995 | AF85: 43997 | AG85: 44027 | AH85: 660元 | AK85: 44027 | AL85: 6.1
E86: 1 | F86: 2 | G86: 20WC00287 | H86: 邱烁颖（英） | J86: qiu3388400374 | K86: 堂堂行 | L86: 老 | M86: 意大利 | P86: 英文 | Q86: 一对六 | R86: 十四课堂 第六节 | T86: 一周五天 | U86: 660元/月 | AE86: 43995 | AF86: 43997 | AG86: 44027 | AH86: 660元 | AK86: 44027 | AL86: 6.11
E87: 1 | F87: 3 | G87: 20WC00288 | H87: 邱琪深（英） | J87: qiu3388400375 | K87: 堂堂行 | L87: 老 | M87: 意大利 | P87: 英文 | Q87: 一对六 | R87: 五十八课堂 第一节 | T87: 一周五天 | U87: 660元/月 | AE87: 43995 | AF87: 43997 | AG87: 44027 | AH87: 660元 | AK87: 44027 | AL87: 6.11
E88: 1 | F88: 1 | G88: 20WC00289 | H88: 胡紫瑶 | J88: a3778401702 | K88: 堂堂行 | L88: 老 | M88: 意大利 | P88: 中文 | Q88: 一对六 | R88: 二十四课堂 第八节 | T88: 一周五天 | U88: 660元/月 | AE88: 43999 | AF88: 43999 | AG88: 2020/9.16 | AH88: 660元 | AK88: 44090 | AL88: 6.11
E89: 1 | F89: 1 | G89: 20WI0025 | H89: 张语茜 | J89: lin20110111 | K89: 堂堂行 | L89: 老 | M89: 美国 | P89: 中文 | Q89: 一对六 | R89: 二十四课堂 第八节 | T89: 一周五天 | U89: 660元/月 | AE89: 43995 | AF89: 43997 | AG89: 44027 | AH89: 660元 | AK89: 44027 | AL89: 6.11
E90: 1 | F90: 3 | G90: 20WC00290 | H90: 徐瓅湉（数） | J90: A3396987803 | K90: 堂堂行 | L90: 老 | M90: 意大利 | P90: 数学 | Q90: 一对六 | R90: 十一课堂 第六节 | T90: 一周五天 | U90: 660元/月 | AE90: 44012 | AF90: 43999 | AG90: 44028 | AH90: 660元 | AK90: 44028 | AL90: 6.11
D91: 线下大学生家教到家里辅导 | E91: 0 | F91: 1 | G91: 20WC00291 | H91: 郑恩祺 | J91: f20121029 | K91: 堂堂行 | L91: 老 | M91: 意大利 | P91: 中文 | Q91: 一对六 | R91: 三十一课堂 第五节 | T91: 一周五天 | U91: 660元/月 | AL91: 6.11
D92: 孩子跟不上进度，觉得太难了，劝过之后就没回复了 | E92: 0 | F92: 1 | G92: 20WN0001 | H92: 张睿2 | J92: jullie81 | K92: 堂堂行 | L92: 老 | M92: 墨西哥 | P92: 中文 | Q92: 一对六 | R92: 二十二课堂 5:30-6:00 | T92: 一周五天 | U92: 660元/月 | AL92: 6.11
E93: 1 | F93: 1 | G93: 20WK023 | H93: 叶晏成 | J93: xiaofen1977 | K93: 堂堂行 | L93: 老 | M93: 奥地利 | P93: 中文 | Q93: 一对六 | R93: 五十五课堂 第十二节 | T93: 一周五天 | U93: 660元/月 | AE93: 44014 | AF93: 44014 | AG93: 44105 | AH93: 1854元 | AK93: 44105 | AL93: 6.11
E94: 1 | F94: 1 | G94: 20WK024 | H94: 厉晏绮 | J94: xuefen304394275 | K94: 堂堂行 | L94: 老 | M94: 奥地利 | P94: 中文 | Q94: 一对六 | R94: 五十五课堂 第十二节 | T94: 一周五天 | U94: 660元/月 | AE94: 44014 | AF94: 44014 | AG94: 44105 | AH94: 1854元 | AK94: 44105 | AL94: 6.11
D95: 1 | E95: 1 | F95: 3 | G95: 20WC00292 | H95: 王翔4（英） | J95: wxid_rjlw0p2ximn412 | K95: 堂堂行 | L95: 老 | M95: 意大利 | P95: 英文 | Q95: 一对六 | R95: 五十八课堂 第九节 | T95: 一周五天 | U95: 660元/月 | AE95: 44014 | AF95: 43999 | AG95: 44028 | AH95: 660元 | AK95: 44028 | AL95: 6.11
E96: 1 | F96: 4 | G96: 20WA00188 | H96: 张淑慧 | J96: zhangyi781184554 | K96: 堂堂行 | L96: 老 | M96: 西班牙 | P96: 中文 | Q96: 一对六 | R96: 四十三课堂 第二节 | T96: 一周五天 | U96: 660元/月 | AE96: 43999 | AF96: 43999 | AG96: 44028 | AH96: 660元 | AK96: 44028 | AL96: 6.12
E97: 1 | F97: 1 | G97: 20WC00310 | H97: 金如意 | J97: xv3319093812 | K97: 堂堂行 | L97: 老 | M97: 意大利 | P97: 中文 | Q97: 一对六 | R97: 二十二课堂 第一节 | T97: 一周五天 | U97: 660元/月 | AE97: 43999 | AF97: 43999 | AG97: 44090 | AH97: 1860元 | AK97: 44090 | AL97: 6.12
E98: 1 | F98: 3 | G98: 20WC00311 | H98: 刘妤可（数） | J98: Elisa19890712 | K98: 堂堂行 | L98: 老 | M98: 意大利 | P98: 数学 | Q98: 一对六 | R98: 四十四课堂 第九节 | T98: 一周五天 | U98: 660元/月 | AE98: 43999 | AL98: 6.12
E99: 1 | F99: 3 | G99: 20WA00199 | H99: 林伟宸（数） | J99: m106871746 | K99: 堂堂行 | L99: 老 | M99: 西班牙 | P99: 数学 | Q99: 一对六 | R99: 四十四课堂 第九节 | T99: 一周五天 | U99: 660元/月 | AE99: 44007 | AF99: 44000 | AG99: 2020/7.17 | AH99: 660元 | AK99: 44029 | AL99: 6.12
D100: 1 | E100: 1 | F100: 1 | G100: 20WC00312 | H100: 程卡咪 | J100: wxid_odrv8kut6g2552 | K100: 堂堂行 | L100: 老 | M100: 意大利 | P100: 中文 | Q100: 一对六 | R100: 十二课堂 第八节 | T100: 一周五天 | U100: 660元/月 | AE100: 43999 | AF100: 43999 | AG100: 44090 | AH100: 1860元 | AK100: 44090 | AL100: 6.12
...

Sheet 2020.05
A1: 国家 | B1: 科目 | C1: 学生 | D1: 课程安排 | E1: 试读日期 | G1: 新生到课情况 | J1: 是否回访 | L1: 是否缴费 | N1: 备注
A2: 葡萄牙 | B2: 中文 | C2: 陈锦汝 | D2: 八课堂 第七节 | E2: 5.04 | F2: 2 | G2: 1 | M2: 5.11
A3: 意大利 | B3: 中文 | C3: 陈梦琪 | D3: 八课堂 第七节 | E3: 5.04 | F3: 2 | G3: 1 | M3: 5.15
A4: 荷兰 | B4: 中文 | C4: 潘书雅 | D4: 八课堂 第七节 | E4: 5.04 | F4: 2 | G4: 1 | M4: 5.15
A5: 意大利 | B5: 中文 | C5: 焦梓 | D5: 八课堂 第七节 | E5: 5.04 | F5: 2 | G5: 1 | M5: 5.15
A6: 西班牙 | B6: 中文 | C6: 蒋俊豪 | D6: 八课堂 第七节 | E6: 5.04 | F6: 2 | G6: 1 | M6: 5.19
A7: 意大利 | B7: 中文 | C7: 温杰利 | D7: 四课堂 第八节 | E7: 5.04 | F7: 4 | M7: 5.07
A8: 西班牙 | B8: 中文 | C8: 叶竞骏 | D8: 五十三课堂 第二节 | E8: 5.05 | F8: 4 | M8: 5.18
A9: 意大利 | B9: 数学 | C9: 虞冠中（数） | D9: 十一课堂 第六节 | E9: 5.05 | F9: 4 | M9: 5.18
A10: 意大利 | B10: 中文 | C10: 郑语涵 | D10: 三十课堂 第八节 | E10: 5.05 | F10: 1 | G10: 1 | H10: 1 | M10: 5.06
A11: 西班牙 | B11: 中文 | C11: 潘若茜 | D11: 十课堂 第七节 | E11: 5.05 | F11: 2 | M11: 5.09
A12: 西班牙 | B12: 英文 | C12: 潘若茜 | D12: 五十八课堂 第十节 | E12: 5.05 | F12: 3 | J12: 试读失败
A13: 意大利 | B13: 中文 | C13: 叶新裕 | D13: 十课堂 第七节 | E13: 5.05 | F13: 2 | M13: 5.15
A14: 葡萄牙 | B14: 中文 | C14: 叶铭哲 | D14: 三十八课堂 第十节 | E14: 5.05 | F14: 2 | G14: 1 | H14: 1 | I14: 1 | J14: 试读失败
A15: 巴西 | B15: 数学 | C15: 朱家豪2 | D15: 四十九课堂 6:00-6:30 | E15: 5.05 | F15: 3 | M15: 5.18
A16: 意大利 | B16: 中文 | C16: 焦心蕾 | D16: 四课堂第五节 | E16: 5.06 | F16: 4 | M16: 5.15
A17: 巴西 | B17: 中文 | C17: 叶奕辰 | D17: 四十一课堂第二节 | E17: 5.06 | F17: 2 | K17: 1 | L17: 1 | M17: 6.09 | N17: 19岁
A18: 巴西 | B18: 中文 | C18: 叶欣佁 | D18: 四十一课堂第二节 | E18: 5.06 | F18: 2 | J18: 试读失败
A19: 西班牙 | B19: 数学 | C19: 潘若茜（数） | D19: 一课堂 第六节 | E19: 5.06 | F19: 3 | M19: 5.09
A20: 奥地利 | B20: 中文 | C20: 刘懿暄 | D20: 三十八课堂 第五节 | E20: 5.06 | F20: 2 | M20: 5.15
A21: 巴西 | B21: 中文 | C21: 陈墨轩 | D21: 十课堂 第五节 | E21: 5.06 | F21: 2 | M21: 5.15
A22: 西班牙 | B22: 中文 | C22: 郭可欣 | D22: 十课堂 第五节 | E22: 5.06 | F22: 2 | M22: 转白班在读
A23: 西班牙 | B23: 中文 | C23: 郭欣得 | D23: 八课堂 第七节 | E23: 5.06 | F23: 2 | M23: 转白班在读
A24: 西班牙 | B24: 中文 | C24: 邹雨欣 | D24: 五十二课堂 第十二节 | E24: 5.06 | F24: 2 | M24: 5.19
A25: 西班牙 | B25: 中文 | C25: 邹博宇 | D25: 二十二课堂 第六节 | E25: 5.06 | F25: 1 | G25: 1 | H25: 试读失败
A26: 西班牙 | B26: 中文 | C26: 张婕 | D26: 五十六课堂 第十二节 | E26: 5.06 | F26: 4 | M26: 5.22
A27: 意大利 | B27: 英文 | C27: 虞冠中（英） | D27: 十四课堂 第三节 | E27: 5.06 | F27: 2 | M27: 5.18
A28: 西班牙 | B28: 英文 | C28: 桑德拉（英） | D28: 十四课堂 第三节 | E28: 5.06 | F28: 2 | M28: 5.27
A29: 西班牙 | B29: 中文 | C29: 朱语欣 | D29: 五十六课堂 第三节 | E29: 5.06 | F29: 4 | J29: 试读失败
A30: 意大利 | B30: 中文 | C30: 张安娜 | D30: 二十六课堂 第七节 | E30: 5.06 | F30: 2 | M30: 5.28
A31: 西班牙 | B31: 中文 | C31: 张浩宇 | D31: 三十八课堂 第八节 | E31: 5.06 | F31: 2 | M31: 5.09
A32: 意大利 | B32: 中文 | C32: 曦曦 | D32: 十课堂 第五节 | E32: 5.06 | F32: 2 | J32: 试读失败
A33: 意大利 | B33: 中文 | C33: 黄衍凯 | D33: 十课堂 第九节 | E33: 5.06 | F33: 2 | L33: 1 | M33: 5.19
A34: 希腊 | B34: 数学 | C34: 黄浩然（数） | D34: 四十四课堂 第五节 | E34: 5.06 | F34: 3 | M34: 5.09
A35: 巴西 | B35: 数学 | C35: 李煜（数） | D35: 四十九课堂 第九节 | E35: 5.06 | F35: 3 | M35: 5.25
A36: 西班牙 | B36: 中文 | C36: 彭宇航 | D36: 五十六课堂第十一节 | E36: 5.06 | F36: 4 | M36: 5.15 | N36: 老生重读
A37: 美国 | B37: 双语中文 | C37: 发发1 | D37: 十八课堂 第一节 | E37: 5.06 | F37: 兼职 | J37: 试读失败
A38: 美国 | B38: 双语中文 | C38: 宝宝1 | D38: 十八课堂 第一节 | E38: 5.06 | F38: 兼职 | J38: 试读失败
A39: 西班牙 | B39: 中文 | C39: 陈亚楠 | D39: 五十三课堂 第七节 | E39: 5.07 | F39: 4 | M39: 5.15
A40: 西班牙 | B40: 中文 | C40: 程金雅萱 | D40: 十课堂 第五节 | E40: 5.07 | F40: 2 | K40: 1
A41: 意大利 | B41: 中文 | C41: 张文俊1 | D41: 三十九课堂 第三节 | E41: 5.07 | F41: 1 | L41: 1 | M41: 5.26
A42: 意大利 | B42: 数学 | C42: 曦曦（数） | D42: 四十四课堂 第一节 | E42: 5.07 | F42: 3 | J42: 试读失败
A43: 意大利 | B43: 中文 | C43: 石昊然 | D43: 十三课堂 第二节 | E43: 5.07 | F43: 2 | L43: 1 | M43: 5.26
A44: 意大利 | B44: 中文 | C44: 王宇喆 | D44: 八课堂 第二节 | E44: 5.07 | F44: 2 | L44: 1 | M44: 5.26
A45: 西班牙 | B45: 中文 | C45: 郑贵洋 | D45: 五十三课堂 第十节 | E45: 5.07 | F45: 4 | L45: 1 | M45: 6.1
A46: 挪威 | B46: 中文 | C46: 周欣1 | D46: 十课堂 第五节 | E46: 5.07 | F46: 2 | L46: 1 | M46: 5.15
A47: 西班牙 | B47: 英文 | C47: 陈欣然 | D47: 十四课堂 第七节 | E47: 5.07 | F47: 2 | L47: 1 | M47: 5.15
A48: 西班牙 | B48: 中文 | C48: 郑赵德瑞 | D48: 二十三课堂 第十节 | E48: 5.07 | F48: 2 | L48: 1 | M48: 6.1
A49: 西班牙 | B49: 中文 | C49: 郑赵居安 | D49: 五十三课堂 第十节 | E49: 5.07 | F49: 4 | L49: 1 | M49: 6.1
A50: 意大利 | B50: 中文 | C50: 徐睿璇 | D50: 二十六课堂 第十节 | E50: 5.07 | F50: 2 | N50: 运营部新生
A51: 意大利 | B51: 中文 | C51: 徐宸皞 | D51: 四十课堂 第八节 | E51: 5.07 | F51: 3 | N51: 运营部新生
A52: 西班牙 | B52: 数学 | C52: 陈杨杨一 | D52: 四十九课堂 第十节 | E52: 5.07 | F52: 3 | L52: 1 | M52: 5.18 | N52: 运营部新生
A53: 西班牙 | B53: 中文 | C53: 陈琦睿 | D53: 五课堂 第三节 | E53: 5.08 | F53: 1 | K53: 1
A54: 西班牙 | B54: 中文 | C54: 王叶温俊 | D54: 五十二课堂 20:20-20:50 | E54: 5.08 | F54: 4 | L54: 1 | M54: 5.18
A55: 西班牙 | B55: 数学 | C55: 陈欣然（数） | D55: 三十二课堂 第二节 | E55: 5.08 | F55: 3 | L55: 1 | M55: 5.15
A56: 西班牙 | B56: 中文 | C56: 郑赵奇德 | D56: 四十三课堂 第四节 | E56: 5.08 | F56: 4 | J56: 试读失败
A57: 巴西 | B57: 数学 | C57: 周照祥（数） | D57: 四十四课堂 第一节 | E57: 5.08 | F57: 3 | L57: 1
A58: 意大利 | B58: 中文 | C58: 徐卓浠 | D58: 五十三课堂 第七节 | E58: 5.08 | F58: 4 | L58: 1 | M58: 5.13
A59: 意大利 | B59: 中文 | C59: 黄璟雯 | D59: 三课堂 第四节 | E59: 5.08 | F59: 4 | L59: 1 | M59: 6.5
A60: 意大利 | B60: 中文 | C60: 黄璟涵 | D60: 二十七课堂 第八节 | E60: 5.08 | F60: 4 | L60: 1 | M60: 6.5
A61: 意大利 | B61: 中文 | C61: 黄良昊 | D61: 三十八课堂 第十节 | E61: 5.08 | F61: 2 | L61: 1 | M61: 6.5
A62: 意大利 | B62: 中文 | C62: 黄毅 | D62: 八课堂 第九节 | E62: 5.08 | F62: 2 | L62: 1 | M62: 5.15
A63: 意大利 | B63: 中文 | C63: 郑仕钦 | D63: 八课堂 第九节（换启蒙课） | E63: 5.08 | F63: 2 | L63: 1
A64: 意大利 | B64: 中文 | C64: 金莉雅 | D64: 八课堂 第九节（换启蒙课） | E64: 5.08 | F64: 2
A65: 意大利 | B65: 中文 | C65: 郑婷婷 | D65: 十课堂 第五节 | E65: 5.08 | F65: 2 | L65: 1 | M65: 5.13
A66: 意大利 | B66: 中文 | C66: 余忠磊 | D66: 五十课堂 第五节 | E66: 5.08 | F66: 1 | L66: 1 | M66: 5.13
A67: 巴西 | B67: 中文 | C67: 李学东 | D67: 八课堂 第七节 | E67: 5.08 | F67: 2 | L67: 1 | M67: 5.13
A68: 法国 | B68: 中文 | C68: 姜金利 | D68: 三十一课堂 第六节 | E68: 5.08 | F68: 1 | L68: 1 | M68: 5.14
A69: 法国 | B69: 中文 | C69: 姜金瑞 | D69: 七课堂 第九节 | E69: 5.08 | F69: 1 | L69: 1 | M69: 5.14
A70: 西班牙 | B70: 数学 | C70: 张懿文（数） | D70: 周末班 一课堂 23:40-0:40 | E70: 5.09 | F70: 3 | L70: 1 | M70: 5.15
A71: 西班牙 | B71: 中文 | C71: 郑昕悦 | D71: 三十八课堂第一节 | E71: 5.11 | F71: 2 | L71: 1 | M71: 5.13
A72: 意大利 | B72: 中文 | C72: 廖晨晨 | D72: 八课堂 第九节 | E72: 5.11 | F72: 2 | L72: 1 | M72: 5.14
A73: 意大利 | B73: 中文 | C73: 徐熙桐 | D73: 八课堂 第九节 | E73: 5.11 | F73: 2 | L73: 1 | M73: 5.14
A74: 意大利 | B74: 中文 | C74: 徐立威 | D74: 三十一课堂 第四节 | E74: 5.11 | F74: 1 | L74: 1 | M74: 5.14
A75: 西班牙 | B75: 中文 | C75: 林盛达 | D75: 三十八课堂 第七节 | E75: 5.11 | F75: 2 | J75: 试读失败
A76: 意大利 | B76: 中文 | C76: 夏涵 | D76: 二十四课堂 第六节 | E76: 5.11 | F76: 1 | L76: 1 | M76: 5.14
A77: 西班牙 | B77: 中文 | C77: 陈家宝 | D77: 三十八课堂 第七节 | E77: 5.11 | F77: 2 | L77: 1 | M77: 5.25
A78: 西班牙 | B78: 中文 | C78: 张素茜 | D78: 二十八课堂 第二节 | E78: 5.11 | F78: 3 | L78: 1 | M78: 5.15
A79: 西班牙 | B79: 中文 | C79: 张君浩 | D79: 五十一课堂 第二节 | E79: 5.11 | F79: 1 | L79: 1 | M79: 5.15
A80: 西班牙 | B80: 数学 | C80: 郭朱煜（数） | D80: 四十九课堂 第五节 | E80: 5.11 | F80: 3 | L80: 1
A81: 西班牙 | B81: 中文 | C81: 陈杨杨一 | D81: 五十三课堂 第七节 | E81: 5.11 | F81: 4 | L81: 1 | M81: 5.21 | N81: 运营部新生
A82: 加拿大 | B82: 中文 | C82: 陈艾迪 | D82: 十课堂 5:20-5:50 | E82: 5.12 | F82: 2 | N82: 运营部新生
A83: 加拿大 | B83: 中文 | C83: 陈俊名 | D83: 七课堂 5:20-5:50 | E83: 5.12 | F83: 1 | N83: 运营部新生
A84: 意大利 | B84: 中文 | C84: 叶以琳 | D84: 三十六课堂 第二节 | E84: 5.12 | F84: 1 | L84: 1 | M84: 5.20 | N84: 运营部新生
A85: 意大利 | B85: 数学 | C85: 郑婷婷（数） | D85: 三十二课堂第三节 | E85: 5.12 | F85: 3 | L85: 1 | M85: 5.21
A86: 西班牙 | B86: 中文 | C86: 郭朱煜 | D86: 五课堂第七节 | E86: 5.12 | F86: 1 | L86: 1
A87: 意大利 | B87: 中文 | C87: 金雅悯 | D87: 五十三课堂 第七节 | E87: 5.12 | F87: 4 | L87: 1 | M87: 5.27
A88: 西班牙 | B88: 中文 | C88: 徐瑞希 | D88: 五课堂 第七节 | E88: 5.12 | F88: 1 | L88: 1 | M88: 5.15
A89: 意大利 | B89: 中文 | C89: 项光军 | D89: 三十六课堂 第七节 | E89: 5.12 | F89: 1 | K89: 1 | L89: 1 | M89: 6.09
A90: 西班牙 | B90: 中文 | C90: 黄子轩1 | D90: 四课堂 第五节 | E90: 5.12 | F90: 4 | J90: 试读失败 | K90: 1
A91: 意大利 | B91: 中文 | C91: 项冰冰 | D91: 三十九课堂 第六节 | E91: 5.12 | F91: 1 | K91: 1 | L91: 1 | M91: 6.09
A92: 意大利 | B92: 中文 | C92: 黄乐彤 | D92: 五课堂 第七节 | E92: 5.12 | F92: 1 | L92: 1 | M92: 5.15
A93: 巴西 | B93: 数学 | C93: 袁乐昕（数） | D93: 一课堂 第七节 | E93: 5.12 | F93: 1 | L93: 1 | M93: 5.14
A94: 意大利 | B94: 中文 | C94: 羽翔 | D94: 五十六课堂 第十一节 | E94: 5.12 | F94: 4 | J94: 试读失败
A95: 斯洛文尼亚 | B95: 中文 | C95: 唐杰1 | D95: 五十六课堂 第十一节 | E95: 5.12 | F95: 4 | L95: 1 | M95: 5.18
A96: 加拿大 | B96: 数学 | C96: 曾美杰 | D96: 十一课堂6:35-7:05 | E96: 5.13 | F96: 4 | N96: 运营部老生
A97: 意大利 | B97: 中文 | C97: 叶以诺 | D97: 五十五课堂 第五节 | E97: 5.13 | F97: 4 | L97: 1 | M97: 5.20 | N97: 运营部新生
A98: 智利 | B98: 中文 | C98: 胡鑫城 | D98: 十课堂 第五节 | E98: 5.13 | F98: 2 | K98: 1 | N98: 运营部新生
A99: 巴西 | B99: 数学 | C99: 郭朱晨 | D99: 十一课堂 第二节 | E99: 5.13 | F99: 4 | L99: 1
A100: 巴西 | B100: 数学 | C100: 肖笑 | D100: 六课堂 第五节 | E100: 5.13 | F100: 3 | L100: 1 | M100: 5.29
...

Sheet 2020.04
A1: 国家 | B1: 科目 | C1: 学生 | D1: 课程安排 | E1: 试读日期 | G1: 新生到课情况 | J1: 是否回访 | L1: 是否缴费 | M1: 缴费日期 | N1: 备注
A2: 巴西 | B2: 中文 | C2: 郭畅 | D2: 五课堂6:30 | E2: 4.01 | F2: 1 | G2: 1 | H2: 1 | I2: 1 | M2: 4.03
A3: 巴西 | B3: 中文 | C3: 郭好 | D3: 十课堂5:20 | E3: 4.01 | F3: 2 | G3: 1 | M3: 4.03
A4: 巴西 | B4: 中文 | C4: 郭阳 | D4: 五课堂6:30 | E4: 4.01 | F4: 1 | G4: 1 | H4: 1 | I4: 1 | M4: 4.03
A5: 西班牙 | B5: 中文 | C5: 章宇婧 | D5: 三十八课堂第一节课 | E5: 4.02 | F5: 2 | G5: 1 | H5: 1 | I5: 1 | M5: 5.07
A6: 意大利 | B6: 中文 | C6: 叶昕阳 | D6: 五十二课堂第一节课 | E6: 4.02 | F6: 4 | G6: 1
A7: 希腊 | B7: 中文 | C7: 叶米娜 | D7: 三十八课堂第三节课 | E7: 4.02 | F7: 2 | G7: 1 | H7: 1 | M7: 从叶安娜2处分八个月
A8: 西班牙 | B8: 中文 | C8: 朱逸晨 | D8: 三十八课堂第三节课 | E8: 4.02 | F8: 2 | G8: 1 | H8: 1 | I8: 试读失败 | N8: 试读失败
A9: 西班牙海岛 | B9: 中文 | C9: 陈起锐 | D9: 二十七课堂第四节课 | E9: 4.02 | F9: 4 | G9: 1 | N9: 4.8试读失败
A10: 西班牙海岛 | B10: 中文 | C10: 王战鑫 | D10: 三十八课堂第三节课 | E10: 4.02 | F10: 2 | G10: 1 | H10: 1 | I10: 0
A11: 西班牙 | B11: 中文 | C11: 周凯文 | D11: 三十八课堂第三节课 | E11: 4.02 | F11: 2 | G11: 1 | H11: 1 | I11: 1
A12: 西班牙 | B12: 中文 | C12: 徐佳儿 | D12: 五十四课堂第二节课 | E12: 4.02 | F12: 3 | G12: 1 | H12: 1 | I12: 1 | M12: 5.13
A13: 西班牙 | B13: 中文 | C13: 徐嘉诚 | D13: 三十八课堂第三节课 | E13: 4.02 | F13: 2 | G13: 1 | H13: 1 | M13: 5.13
A14: 西班牙 | B14: 中文 | C14: 林文轩 | D14: 三十八课堂第二节课 | E14: 4.02 | F14: 2 | G14: 1 | H14: 1 | I14: 1 | M14: 5.20
A15: 西班牙海岛 | B15: 中文 | C15: 陈佳瑜 | D15: 三十八课堂第三节课 | E15: 4.02 | F15: 2 | G15: 1 | H15: 1 | I15: 试读失败 | N15: 试读失败
A16: 希腊 | B16: 中文 | C16: 胡雅晗 | D16: 十三课堂第十节课 | E16: 4.02 | F16: 3 | G16: 1 | H16: 1 | I16: 1 | J16: 1 | M16: 5.18
A17: 希腊 | B17: 中文 | C17: 胡浩元1 | D17: 十三课堂第十节课 | E17: 4.02 | F17: 3 | G17: 1 | H17: 1 | I17: 1 | J17: 1 | M17: 5.18
A18: 捷克 | B18: 数学 | C18: 胡立源 | D18: 十一课堂第七节课 | E18: 4.02 | F18: 4 | G18: 1 | M18: 4.03
A19: 意大利 | B19: 中文 | C19: 陈莉莎 | D19: 三十八课堂第四节课 | E19: 4.02 | F19: 2 | G19: 1 | H19: 1 | I19: 1 | M19: 5.09
A20: 意大利 | B20: 中文 | C20: 黄铭翔 | D20: 五十八课堂第四节课 | E20: 4.02 | F20: 4 | G20: 1 | M20: 4.25
A21: 巴西 | B21: 中文 | C21: 袁乐琛 | D21: 四十一课堂第三节课 | E21: 4.02 | F21: 2 | G21: 1 | H21: 1 | I21: 1
A22: 巴西 | B22: 数学 | C22: 袁乐琛 | D22: 十一课堂5:00 | E22: 4.02 | F22: 4 | G22: 1 | M22: 5.06
A23: 意大利 | B23: 中文 | C23: 柳程怡 | D23: 十三课堂第四节课 | E23: 4.02 | F23: 3 | G23: 1 | H23: 1 | I23: 1 | J23: 1 | M23: 4.05
A24: 葡萄牙海岛 | B24: 中文 | C24: 柳怡 | D24: 三十八课堂第四节课 | E24: 4.02 | F24: 2 | G24: 1 | H24: 1 | I24: 1 | M24: 4.26
A25: 葡萄牙海岛 | B25: 中文 | C25: 柳彦1 | D25: 三十八课堂第四节课 | E25: 4.02 | F25: 2 | G25: 1 | H25: 1 | I25: 1 | M25: 4.26
A26: 西班牙 | B26: 中文 | C26: 朱雨昕 | D26: 三十八课堂第四节课 | E26: 4.02 | F26: 2 | G26: 1 | H26: 1 | I26: 1 | M26: 5.11
A27: 美国 | B27: 中文 | C27: 赵艾米 | D27: 五十六课堂第十一节课 | E27: 4.02 | F27: 4 | G27: 1 | M27: 4.03
A28: 西班牙 | B28: 中文 | C28: 王理轩 | D28: 三十八课堂第二节课 | E28: 4.03 | F28: 2 | G28: 1 | H28: 1 | I28: 1 | N28: 运营部新生
A29: 西班牙 | B29: 中文 | C29: 翁佳慧 | D29: 十三课堂第一节课 | E29: 4.03 | F29: 3 | G29: 1 | H29: 试读失败 | N29: 运营部新生
A30: 巴西 | B30: 中文 | C30: 黄俊皓 | D30: 三十八课堂第四节课 | E30: 4.03 | F30: 2 | G30: 1 | H30: 1 | M30: 4.27
A31: 葡萄牙海岛 | B31: 数学 | C31: 柳彦1 | D31: 十一课堂第三节课 | E31: 4.03 | F31: 4 | G31: 1 | M31: 4.26
A32: 葡萄牙海岛 | B32: 数学 | C32: 柳怡 | D32: 四十九课堂第五节课 | E32: 4.03 | F32: 3 | G32: 1 | H32: 1 | I32: 1 | M32: 4.26
A33: 西班牙 | B33: 数学 | C33: 徐均盛 | D33: 十一课堂第七节课 | E33: 4.03 | F33: 4 | G33: 1 | M33: 5.14
A34: 巴西 | B34: 中文 | C34: 方浩轩 | D34: 三十九课堂第三节课 | E34: 4.03 | F34: 1 | G34: 1 | H34: 1 | M34: 4.09
A35: 巴西 | B35: 数学 | C35: 方浩轩 | D35: 十一课堂第五节课 | E35: 4.03 | F35: 4 | G35: 1 | M35: 4.09
A36: 西班牙海岛 | B36: 中文 | C36: 许泽凯 | D36: 十九课堂第六节课 | E36: 4.03 | F36: 2 | G36: 1
A37: 西班牙海岛 | B37: 中文 | C37: 许吴菲 | D37: 二十七课堂第七节课 | E37: 4.03 | F37: 4 | G37: 1
A38: 意大利 | B38: 中文 | C38: 纪柯艳 | D38: 三十八课堂第一节课 | E38: 4.03 | F38: 2 | G38: 1 | H38: 1 | M38: 4.7
A39: 西班牙 | B39: 中文 | C39: 徐宇浩 | D39: 十三课堂第三节课 | E39: 4.03 | F39: 3 | G39: 1 | H39: 1 | I39: 1 | J39: 1 | M39: 5.08
A40: 西班牙 | B40: 中文 | C40: 徐宇芯 | D40: 三十八课堂第四节课 | E40: 4.03 | F40: 2 | G40: 1 | M40: 5.08
A41: 意大利 | B41: 英语 | C41: 吴梓涵 | D41: 四十课堂第六节课 | E41: 4.03 | F41: 3 | G41: 1 | H41: 1 | I41: 试读失败
A42: 意大利 | B42: 中文 | C42: 陈孝贤 | D42: 十三课堂第一节课 | E42: 4.03 | F42: 3 | G42: 1 | H42: 1 | I42: 1 | J42: 1 | M42: 4.29
A43: 西班牙 | B43: 中文 | C43: Maria1 | D43: 十八课堂第二节课 | E43: 4.03 | F43: 兼职 | G43: 1
A44: 意大利 | B44: 中文 | C44: 张韵瑶 | D44: 十三课堂第一节课 | E44: 4.03 | F44: 3 | G44: 1 | H44: 试读失败
A45: 意大利 | B45: 中文 | C45: 杨子萱 | D45: 十二课堂第五节课 | E45: 4.03 | F45: 4 | G45: 1
A46: 意大利 | B46: 中文 | C46: 王华3 | D46: 七课堂第五节课 | E46: 4.03 | F46: 1 | G46: 1 | H46: 0 | M46: 5.08
A47: 意大利 | B47: 中文 | C47: 杨美娇 | D47: 十课堂第八节课 | E47: 4.03 | F47: 2 | G47: 1 | H47: 1
A48: 意大利 | B48: 中文 | C48: 杨子豪 | D48: 三十八课堂第九节课 | E48: 4.03 | F48: 2 | G48: 1 | H48: 试读失败
A49: 意大利 | B49: 中文 | C49: 杨子俊 | D49: 三十八课堂第九节课 | E49: 4.03 | F49: 2 | G49: 1 | H49: 试读失败
A50: 巴西 | B50: 美术 | C50: 朱婷婷1 | D50: 九课堂23:00 | E50: 4.04 | F50: 兼职
A51: 西班牙 | B51: 美术 | C51: 徐华均 | D51: 九课堂17:00 | E51: 4.04 | F51: 兼职
A52: 意大利 | B52: 中文 | C52: 廖银宣 | D52: 十三课堂第一节课 | E52: 4.07 | F52: 3 | G52: 1 | H52: 1 | I52: 1 | J52: 1 | M52: 4.13
A53: 意大利 | B53: 中文 | C53: 廖凯文 | D53: 三十八课堂第二节课 | E53: 4.07 | F53: 2 | G53: 1 | H53: 1 | M53: 4.13
A54: 葡萄牙 | B54: 中文 | C54: 郭子龙 | D54: 五十六课堂第一节课 | E54: 4.07 | F54: 4 | G54: 1 | M54: 5.21
A55: 葡萄牙 | B55: 数学 | C55: 郭子龙 | D55: 四十九课堂第五节课 | E55: 4.07 | F55: 3 | G55: 1 | H55: 1 | I55: 1 | N55: 试读失败5.21
A56: 葡萄牙 | B56: 中文 | C56: 李瑞贤 | D56: 十三课堂第一节课 | E56: 4.07 | F56: 3 | G56: 1 | H56: 1 | I56: 1 | J56: 1 | M56: 5.09
A57: 西班牙 | B57: 中文 | C57: 林安琪 | D57: 一课堂第八节课 | E57: 4.07 | F57: 3 | G57: 1 | H57: 1 | I57: 1 | M57: 4.10
A58: 意大利 | B58: 中文 | C58: 郭浩翔 | D58: 三十九课堂第三节课 | E58: 4.07 | F58: 1 | G58: 1 | H58: 1 | M58: 4.15
A59: 意大利 | B59: 中文 | C59: 周慧淋 | D59: 二十七课堂第四节课 | E59: 4.07 | F59: 4 | G59: 1 | N59: 不读，不记流失
A60: 意大利 | B60: 中文 | C60: 余欣可 | D60: 十二课堂第五节课 | E60: 4.07 | F60: 4 | G60: 1 | M60: 4.20
A61: 意大利 | B61: 中文 | C61: 王奕轩 | D61: 三十九课堂第三节课 | E61: 4.07 | F61: 1 | G61: 1 | H61: 1 | M61: 4.13
A62: 意大利 | B62: 中文 | C62: 王奕昂 | D62: 三十九课堂第三节课 | E62: 4.07 | F62: 1 | G62: 1 | H62: 1 | M62: 4.13
A63: 西班牙 | B63: 中文 | C63: 郑妮可 | D63: 十课堂第十节课 | E63: 4.07 | F63: 2 | G63: 1 | H63: 1 | I63: 1 | M63: 4.10
A64: 西班牙 | B64: 中文 | C64: 詹嘉文 | D64: 三十课堂第八节课 | E64: 4.07 | F64: 1 | G64: 1
A65: 意大利 | B65: 中文 | C65: 陈林勇 | D65: 十二课堂第八节课 | E65: 4.07 | F65: 4 | G65: 1 | M65: 4.10
A66: 意大利 | B66: 英语 | C66: 季奇璋 | D66: 五十八课堂第十节课 | E66: 4.07 | F66: 4 | G66: 1 | M66: 4.24
A67: 西班牙 | B67: 中文 | C67: 胡力奥 | D67: 五课堂第二节课 | E67: 4.08 | F67: 1 | G67: 1 | H67: 1 | M67: 4.06 | N67: 运营部新生
A68: 美国 | B68: 中文 | C68: 侯懿芮 | D68: 八课堂6:00 | E68: 4.08 | F68: 1 | G68: 1 | H68: 0 | N68: 运营部新生
A69: 西班牙 | B69: 中文 | C69: 翁多豪 | D69: 十三课堂第三节课 | E69: 4.08 | F69: 3 | G69: 1 | H69: 1 | I69: 1 | J69: 1 | M69: 5.13 | N69: 运营部新生
A70: 加拿大 | B70: 中文 | C70: 李嘉文 | D70: 三十六课堂6:00 | E70: 4.08 | F70: 1 | G70: 1 | H70: 1 | M70: 4.02 | N70: 运营部新生
A71: 加拿大 | B71: 中文 | C71: Eddie | D71: 七课堂5:20 | E71: 4.08 | F71: 1 | G71: 1 | H71: 1 | N71: 运营部新生
A72: 加拿大 | B72: 中文 | C72: Leo | D72: 十二课堂5:50 | E72: 4.08 | F72: 4 | G72: 1 | M72: 5.26 | N72: 运营部新生
A73: 西班牙 | B73: 中文 | C73: 林振 | D73: 八课堂第二节课 | E73: 4.08 | F73: 1 | G73: 1 | H73: 1 | M73: 5.18
A74: 意大利 | B74: 中文 | C74: 吴彦旭 | D74: 八课堂第二节课 | E74: 4.08 | F74: 1 | G74: 1 | H74: 1 | M74: 4.23
A75: 西班牙 | B75: 中文 | C75: 潘恩义 | D75: 八课堂第二节课 | E75: 4.08 | F75: 1 | G75: 1 | H75: 1 | M75: 4.28
A76: 意大利 | B76: 中文 | C76: 王子赫1 | D76: 八课堂第二节课 | E76: 4.08 | F76: 1 | G76: 1 | H76: 1
A77: 意大利 | B77: 中文 | C77: 王子昂 | D77: 八课堂第二节课 | E77: 4.08 | F77: 1 | G77: 1 | H77: 1
A78: 英国 | B78: 中文 | C78: 周海恩 | D78: 八课堂第二节课 | E78: 4.08 | F78: 1 | G78: 1 | H78: 0 | M78: 5.20
A79: 西班牙 | B79: 中文 | C79: 徐浩榆 | D79: 三十一课堂第一节课 | E79: 4.08 | F79: 3 | G79: 1 | H79: 1 | I79: 1 | J79: 1 | M79: 4.16
A80: 西班牙 | B80: 中文 | C80: 徐浩倬 | D80: 三十一课堂第一节课 | E80: 4.08 | F80: 3 | G80: 1 | H80: 1 | I80: 1 | J80: 1 | M80: 4.16
A81: 意大利 | B81: 中文 | C81: 卢佳琪1 | D81: 三十一课堂第六节课 | E81: 4.08 | F81: 3 | G81: 1 | H81: 1 | I81: 1 | J81: 1 | M81: 5.13
A82: 西班牙 | B82: 中文 | C82: 徐若欣 | D82: 十三课堂第三节课 | E82: 4.08 | F82: 3 | G82: 1 | H82: 1 | I82: 1 | M82: 4.16
A83: 意大利 | B83: 中文 | C83: 卢继涛 | D83: 十三课堂第三节课 | E83: 4.08 | F83: 3 | G83: 1 | H83: 1 | I83: 1 | M83: 5.13
A84: 英国 | B84: 中文 | C84: 周海粟 | D84: 三十九课堂第三节课 | E84: 4.08 | F84: 1 | G84: 1 | H84: 1 | M84: 5.25
A85: 意大利 | B85: 中文 | C85: 王梓渲 | D85: 四十五课堂第二节课 | E85: 4.08 | F85: 4 | G85: 1
A86: 西班牙 | B86: 中文 | C86: 苏文博 | D86: 一课堂第五节课 | E86: 4.08 | F86: 3 | G86: 1 | H86: 1 | I86: 1 | M86: 4.15
A87: 意大利 | B87: 数学 | C87: 任煜熙 | D87: 一课堂第五节课 | E87: 4.08 | F87: 3 | G87: 1 | H87: 1 | I87: 1 | M87: 4.29 | N87: 转至十一课堂
A88: 意大利 | B88: 数学 | C88: 卢继涛 | D88: 一课堂第五节课 | E88: 4.08 | F88: 3 | G88: 1 | H88: 1 | I88: 1 | M88: 5.13
A89: 荷兰 | B89: 中文 | C89: 周律兆 | D89: 三十八课堂第三节课 | E89: 4.08 | F89: 2 | G89: 1 | H89: 试读失败
A90: 意大利 | B90: 英语 | C90: 卢佳琪1 | D90: 四十二课堂第一节课 | E90: 4.08 | F90: 3 | G90: 1 | H90: 1 | I90: 1 | M90: 5.13
A91: 意大利 | B91: 数学 | C91: 吴彦旭 | D91: 五十八课堂第四节课 | E91: 4.08 | F91: 4 | G91: 1
A92: 意大利 | B92: 英语 | C92: 卢继涛 | D92: 五十八课堂第六节课 | E92: 4.08 | F92: 4 | G92: 1 | M92: 5.13
A93: 意大利 | B93: 英语 | C93: 卢熙蕾 | D93: 二十八课堂第三节课 | E93: 4.08 | F93: 3 | G93: 1 | H93: 1 | I93: 失败
A94: 意大利 | B94: 中文 | C94: 卢熙蕾 | D94: 七课堂第八节课 | E94: 4.08 | F94: 1 | G94: 1 | H94: 1
A95: 意大利 | B95: 数学 | C95: 任钰瞳 | D95: 十一课堂第六节课 | E95: 4.08 | F95: 4 | G95: 1 | M95: 4.29
A96: 西班牙 | B96: 中文 | C96: 阮森雅 | D96: 三十课堂第八节课 | E96: 4.08 | F96: 1 | G96: 1 | H96: 1
A97: 美国 | B97: 中文 | C97: 陈智灵 | D97: 二十七课堂第七节课 | E97: 4.09 | F97: 4 | N97: 运营部新生
A98: 巴西 | B98: 中文 | C98: 陈凯文01 | D98: 二十二课堂第二节课 | E98: 4.09 | F98: 1 | G98: 1 | M98: 5.26
A99: 意大利 | B99: 中文 | C99: 木安娜 | D99: 十三课堂第一节课 | E99: 4.09 | F99: 3 | G99: 1 | H99: 1 | M99: 5.11
A100: 波兰 | B100: 中文 | C100: 叶珈语 | D100: 十三课堂第一节课 | E100: 4.09 | F100: 3 | G100: 1 | H100: 1 | M100: 4.24
...

Sheet 2020.03
A1: 国家 | B1: 科目 | C1: 学生 | D1: 课堂 | E1: 试读日期 | F1: 组别 | G1: 新生到课情况 | J1: 是否回访 | L1: 是否缴费 | M1: 缴费日期 | N1: 备注
A2: 意大利 | B2: 中文 | C2: 魏铭轩 | D2: 二十七课堂第七节 | E2: 3.2 | F2: 4 | G2: 1 | H2: 1 | I2: 1
A3: 意大利 | B3: 中文 | C3: 柯睿媛 | D3: 六课堂第八节 | E3: 3.2 | F3: 4 | G3: 1 | H3: 1 | I3: 1
A4: 意大利 | B4: 中文 | C4: 潘佳琦 | D4: 二十七课堂第八节 | E4: 3.2 | F4: 4 | G4: 1 | H4: 1 | I4: 1
A5: 意大利 | B5: 中文 | C5: 邱叶旋 | D5: 三十九课堂第四节 | E5: 3.2 | F5: 2
A6: 意大利 | B6: 中文 | C6: 邱琪深 | D6: 四十七课堂第八节 | E6: 3.2 | F6: 4
A7: 意大利 | B7: 中文 | C7: 邱烁颖 | D7: 四十七课堂第八节 | E7: 3.2 | F7: 4
A8: 西班牙 | B8: 数学 | C8: 杨昕蕊 | D8: 二十一课堂第三节 | E8: 3.2 | F8: 1 | G8: 1 | H8: 1 | I8: 1
A9: 西班牙 | B9: 英语 | C9: 杨昕蕊 | D9: 六课堂第六节 | E9: 3.2 | F9: 4 | G9: 1 | H9: 1 | I9: 1 | L9: 1 | M9: 3.2
A10: 意大利 | B10: 中文 | C10: 洪佳乐 | D10: 三十六课堂第五节 | E10: 3.2 | F10: 1 | G10: 1 | H10: 1 | I10: 1
A11: 意大利 | B11: 英语 | C11: 洪佳乐 | D11: 四十八课堂第六节 | E11: 3.2 | F11: 1 | G11: 1 | H11: 1 | I11: 1
A12: 意大利 | B12: 中文 | C12: 洪杉杉 | D12: 七课堂第二节 | E12: 3.2 | F12: 1 | G12: 1 | H12: 1 | I12: 1
A13: 意大利 | B13: 英语 | C13: 洪杉杉 | D13: 二课堂第三节 | E13: 3.2 | F13: 1 | G13: 1 | H13: 1 | I13: 1
A14: 意大利 | B14: 英语 | C14: 洪晨燚 | D14: 六课堂第九节 | E14: 3.3 | F14: 4 | G14: 1 | H14: 1 | I14: 1
A15: 意大利 | B15: 中文 | C15: 洪晨燚 | D15: 三十六课堂第三节 | E15: 3.3 | F15: 1 | G15: 1 | H15: 1 | I15: 1
A16: 葡萄牙 | B16: 中文 | C16: 彭雅琦 | D16: 三十一课堂第十一节 | E16: 3.3 | F16: 3 | G16: 1 | H16: 1 | I16: 1
A17: 葡萄牙 | B17: 中文 | C17: 彭雅琰 | D17: 五十六课堂第九节 | E17: 3.4 | F17: 4 | G17: 1 | H17: 1 | I17: 1
A18: 美国 | B18: 中文 | C18: 辰辰 | D18: 二十二课堂6:30 | E18: 3.4 | F18: 1 | G18: 1 | H18: 1 | I18: 1
A19: 西班牙 | B19: 中文 | C19: 何矜矜 | D19: 五十五课堂第十节 | E19: 3.5 | F19: 3 | G19: 1 | H19: 1 | I19: 1
A20: 意大利 | B20: 中文 | C20: 杨承智 | D20: 六课堂第八节 | F20: 4 | G20: 1 | H20: 1 | I20: 1
A21: 意大利 | B21: 中文 | C21: 杨承栋 | D21: 五十六课堂第八节 | E21: 3.4 | F21: 4 | G21: 1 | H21: 1 | I21: 1
A22: 意大利 | B22: 中文 | C22: 王宇智 | D22: 六课堂第八节 | F22: 4 | G22: 1 | H22: 1 | I22: 1
A23: 意大利 | B23: 中文 | C23: 叶琦娇 | D23: 五十四课堂第十节 | E23: 3.4 | F23: 3 | G23: 1 | H23: 1 | I23: 1
A24: 意大利 | B24: 中文 | C24: 丹尼 | D24: 二十八课堂 | F24: 3 | G24: 未到课堂
A25: 意大利 | B25: 中文 | C25: 陈洁妮 | D25: 二十八课堂 | E25: 3.7 | F25: 3 | G25: 1 | H25: 1 | I25: 1
A26: 西班牙 | B26: 中文 | C26: 傅双俊 | D26: 五十四课堂第九节 | F26: 3 | G26: 1 | H26: 1 | I26: 1
A27: 西班牙 | B27: 中文 | C27: 傅俊羽 | D27: 五十六课堂第八节 | F27: 4 | G27: 1 | H27: 1 | I27: 1
A28: 意大利 | B28: 数学 | C28: 蒋俊哲 | D28: 十一课堂 | E28: 3.3 | F28: 4 | G28: 1 | H28: 1 | I28: 1 | J28: 1
A29: 意大利 | B29: 数学 | C29: 林静怡 | D29: 十一课堂 | E29: 3.3 | F29: 4 | G29: 1 | H29: 1 | I29: 1
A30: 意大利 | B30: 中文 | C30: 梅子1 | D30: 四十课堂第七节 | E30: 3.4 | F30: 3 | G30: 1 | H30: 1 | I30: 1
A31: 西班牙 | B31: 中文 | C31: 爱琳 | D31: 三十四课堂第四节 | E31: 3.7 | F31: 3 | G31: 1 | H31: 1 | I31: 1
A32: 西班牙 | B32: 中文 | C32: 索菲 | D32: 四十三课堂第五节 | E32: 3.7 | F32: 3 | G32: 1 | H32: 1 | I32: 1
A33: 意大利 | B33: 数学 | C33: 金依涟 | D33: 二十一课堂第八节 | F33: 1 | G33: 1 | H33: 1
A34: 意大利 | B34: 英语 | C34: 张郡雪 | D34: 四十二课堂第十节 | E34: 3.5 | F34: 3 | G34: 1 | H34: 1 | I34: 1
A35: 意大利 | B35: 中文 | C35: 吴梦冉 | D35: 五十五课堂第四节 | E35: 3.5 | F35: 3 | G35: 1 | H35: 1 | I35: 1
A36: 意大利 | B36: 中文 | C36: 何金诺 | D36: 六课堂第四节 | E36: 3.5 | F36: 4 | G36: 1 | H36: 1 | I36: 1
A37: 意大利 | B37: 数学 | C37: 何金诺 | D37: 十一课堂第三节 | E37: 3.5 | F37: 4 | G37: 1 | H37: 1 | I37: 1
A38: 意大利 | B38: 中文 | C38: 朱俊豪1 | D38: 三十四课堂第二节 | E38: 3.5 | F38: 3 | G38: 1 | H38: 1 | I38: 1
A39: 巴西 | B39: 中文 | C39: 王卓颖 | D39: 二十二课堂6:30 | E39: 3.5 | F39: 1 | G39: 1 | H39: 需要专业老师 | L39: （老生重读）
A40: 意大利 | B40: 中文 | C40: 何睿毅 | D40: 三十六课堂第一节 | E40: 3.5 | F40: 1 | G40: 1
A41: 意大利 | B41: 中文 | C41: 李梓赫 | D41: 五十五课堂第四节 | E41: 3.5 | F41: 3 | G41: 试读失败
A42: 巴西 | B42: 中文 | C42: Gustavo | D42: 新生接待课堂 | E42: 3.5 | F42: 0 | G42: 1 | H42: 觉得学费贵
A43: 西班牙 | B43: 中文 | C43: 毛菲雪 | D43: 一课堂周末班1:00 | E43: 3.5 | F43: 3 | G43: 1 | H43: 1 | I43: 1
A44: 西班牙 | B44: 中文 | C44: 毛飞阳 | D44: 二十八课堂23:35 | E44: 3.5 | F44: 3 | G44: 1 | H44: 1 | I44: 1
A45: 意大利 | B45: 中文 | C45: 胡祥源 | D45: 二十七课堂第十节 | E45: 3.6 | F45: 4 | G45: 1 | H45: 1 | I45: 1
A46: 意大利 | B46: 数学 | C46: 胡祥源 | D46: 四十九课堂第十一节 | E46: 3.6 | F46: 2
A47: 意大利 | B47: 中文 | C47: 胡希雅 | D47: 五十六课堂第九节课 | E47: 3.6 | F47: 4 | G47: 1 | H47: 1 | I47: 1
A48: 意大利 | B48: 数学 | C48: 胡希雅 | D48: 四十九课堂第十一节 | E48: 3.6 | F48: 2
A49: 美国 | B49: 中文 | C49: 李悦天 | D49: 二十二课堂6:30 | E49: 3.6 | F49: 1
A50: 西班牙 | B50: 中文 | C50: 柳星岚 | D50: 五十六课堂第二节 | E50: 3.6 | F50: 4 | G50: 1 | H50: 1 | I50: 1
A51: 意大利 | B51: 中文 | C51: 吴晨浩 | D51: 五十六课堂第二节 | E51: 3.6 | F51: 4 | G51: 1 | H51: 1 | I51: 1
A52: 葡萄牙 | B52: 中文 | C52: 刘志远1 | D52: 五十七课堂第十节 | E52: 3.9 | F52: 1 | L52: （暑假学生，重读）
A53: 葡萄牙 | B53: 中文 | C53: 刘可欣 | D53: 二十七课堂第十二节 | E53: 3.9 | F53: 4 | G53: 1 | H53: 1 | I53: 1 | L53: （暑假学生，重读）
A54: 意大利 | B54: 数学 | C54: 金洛安 | D54: 二十一课堂第三节 | E54: 3.9 | F54: 1
A55: 意大利 | B55: 中文 | C55: 金洛安 | D55: 四十五课堂第五节 | E55: 3.9 | F55: 4 | G55: 1 | H55: 1 | I55: 1 | J55: 1
A56: 意大利 | B56: 英语 | C56: 金洛安 | D56: 六课堂第七节 | E56: 3.9 | F56: 4 | G56: 1 | H56: 1 | I56: 1
A57: 意大利 | B57: 中文 | C57: 金子颜 | D57: 三十一课堂第四节 | E57: 3.9 | F57: 3 | G57: 1 | H57: 1 | I57: 1
A58: 意大利 | B58: 英语 | C58: 金子颜 | D58: 六课堂第七节 | E58: 3.9 | F58: 4 | G58: 1 | H58: 1 | I58: 1
A59: 意大利 | B59: 数学 | C59: 金子颜 | D59: 一课堂第五节 | E59: 3.9 | F59: 3 | G59: 1 | H59: 1 | I59: 1
A60: 捷克 | B60: 中文 | C60: 陈升 | D60: 三课堂第七节 | E60: 3.9 | F60: 1
A61: 葡萄牙 | B61: 中文 | C61: 孙语淇 | D61: 二十七课堂第十二节 | E61: 3.9 | F61: 4 | G61: 1 | H61: 1 | I61: 1 | L61: （暑假学生，重读）
A62: 意大利 | B62: 中文 | C62: 单以琳 | D62: 十课堂第三节 | E62: 3.9 | F62: 1
A63: 西班牙 | B63: 中文 | C63: 夏梓涵 | D63: 五十六课堂第二节 | E63: 3.9 | F63: 3 | G63: 1 | H63: 1 | I63: 1
A64: 意大利 | B64: 中文 | C64: 赵鑫1 | D64: 四十课堂第二节 | E64: 3.9 | F64: 1
A65: 意大利 | B65: 中文 | C65: 季宇浩 | D65: 五课堂第五节 | E65: 3.9 | F65: 1
A66: 意大利 | B66: 中文 | C66: 张亦欣 | D66: 四十五课堂第一节 | E66: 3.9 | F66: 3 | G66: 1 | H66: 1 | I66: 1
A67: 西班牙 | B67: 中文 | C67: 叶乐涛 | D67: 五十五课堂第十节 | E67: 3.1
A68: 西班牙 | B68: 中文 | C68: 叶乐琦 | D68: 三课堂第一节 | E68: 3.1 | F68: 1
A69: 意大利 | B69: 数学 | C69: 孙莹颖 | D69: 二十一课堂第三节 | E69: 3.1 | F69: 1
A70: 意大利 | B70: 数学 | C70: 孙俊豪 | D70: 十一课堂第五节 | E70: 3.1 | F70: 3 | G70: 1 | H70: 1 | I70: 1
A71: 西班牙 | B71: 中文 | C71: 南陈昊宇 | D71: 三十二课堂第九节 | E71: 3.1 | F71: 3 | G71: 1 | H71: 1 | I71: 1
A72: 西班牙 | B72: 中文 | C72: 南陈浩哲 | D72: 待定 | E72: 3.1 | F72: 0
A73: 意大利 | B73: 英语 | C73: 廖紫瑄 | D73: 五十八课堂第十节 | E73: 3.1 | F73: 4 | G73: 1 | H73: 1 | I73: 1
A74: 西班牙 | B74: 英语 | C74: 应卓凯 | D74: 五十八课堂第十节 | E74: 3.1 | F74: 4 | G74: 1 | H74: 1 | I74: 1
A75: 意大利 | B75: 英语 | C75: 何林轩 | D75: 四十八课堂第六节 | E75: 3.1 | F75: 1
A76: 意大利 | B76: 英语 | C76: 洪倩1 | D76: 二课堂第九节 | E76: 3.1 | F76: 1
A77: 希腊 | B77: 中文 | C77: 王艺霖1 | D77: 二十二课堂第一节 | E77: 3.1 | F77: 1
A78: 意大利 | B78: 英语 | C78: 金凯利 | D78: ChineseonlineF杨老师 | E78: 3.11 | F78: 兼职
A79: 巴西 | B79: 中文 | C79: 吴涵悦 | D79: 五课堂7:05 | E79: 3.1 | F79: 1
A80: 西班牙海岛 | B80: 中文 | C80: 李蒋俊辰 | D80: 五十五课堂第十节 | E80: 3.11 | F80: 兼职
A81: 美国 | B81: 中文 | C81: 马琳妤 | D81: 二十二课堂6:30 | E81: 3.11 | F81: 1
A82: 意大利 | B82: 中文 | C82: 周郑昊 | D82: 五十六课堂第二节 | E82: 3.11 | F82: 4 | G82: 1 | H82: 1 | I82: 1
A83: 意大利 | B83: 数学 | C83: 郑培熙 | D83: 十一课堂第十节 | E83: 3.11 | F83: 4 | G83: 1 | H83: 1 | I83: 1
A84: 意大利 | B84: 数学 | C84: 郑可馨 | D84: 十一课堂第十节 | E84: 3.11 | F84: 4 | G84: 1 | H84: 1 | I84: 1
A85: 意大利 | B85: 中文 | C85: 黄莘茹 | D85: 四十课堂第四节 | E85: 3.11 | F85: 3 | G85: 1 | H85: 1 | I85: 1
A86: 意大利 | B86: 中文 | C86: 吴浩维 | D86: 二十七课堂第六节 | E86: 3.11 | F86: 4 | G86: 1 | H86: 1 | I86: 1
A87: 意大利 | B87: 中文 | C87: 吴昱莹 | D87: 四十八课堂第二节 | E87: 3.11 | F87: 1
A88: 西班牙 | B88: 中文 | C88: 陈诺1 | D88: 三十一课堂第八节 | E88: 3.11 | F88: 3 | G88: 1 | H88: 1 | I88: 1
A89: 西班牙 | B89: 中文 | C89: 陈帅 | D89: 三十六课堂第九节 | E89: 3.11 | F89: 1
A90: 西班牙 | B90: 英语 | C90: 张淼琦 | D90: 二课堂第三节 | E90: 3.12 | F90: 1
A91: 西班牙 | B91: 数学 | C91: 张淼琦 | D91: 一课堂第四节 | E91: 3.12 | F91: 3 | G91: 1 | H91: 1 | I91: 1
A92: 西班牙 | B92: 中文 | C92: 张淼琦 | D92: 十七课堂第一节 | E92: 3.12 | F92: 2
A93: 保加利亚 | B93: 数学 | C93: 陈恩昊 | D93: 二十一课堂第八节 | E93: 3.12 | F93: 1
A94: 意大利 | B94: 英语 | C94: 陈张安生 | D94: 二十八课堂第三节 | E94: 3.12 | F94: 3 | G94: 1 | H94: 1 | I94: 1
A95: 意大利 | B95: 英语 | C95: 陈晨晨 | D95: 四十二课堂第十节 | E95: 3.12 | F95: 3 | G95: 1 | H95: 1 | I95: 1
A96: 意大利 | B96: 英语 | C96: 陈宝生 | D96: 二课堂第九节 | E96: 3.12 | F96: 1
A97: 西班牙 | B97: 中文 | C97: 尹芷馨 | D97: 五十五课堂第五节 | E97: 3.12 | F97: 3 | G97: 1 | H97: 1 | I97: 1
A98: 西班牙 | B98: 数学 | C98: 叶乐琦 | D98: 十一课堂第九节 | E98: 3.12 | F98: 4 | G98: 1 | H98: 1 | I98: 1
A99: 西班牙 | B99: 英语 | C99: 叶乐琦 | D99: 四十八课堂第六节 | E99: 3.12 | F99: 1
A100: 意大利 | B100: 数学 | C100: 吴佳佳 | D100: 十一课堂第三节 | E100: 3.12 | F100: 4 | G100: 1 | H100: 1 | I100: 1
...

Sheet 2020.01
A1: 国家 | B1: 学生 | C1: 课堂 | D1: 试读日期 | F1: 新生到课情况 | I1: 是否回访 | K1: 是否缴费 | L1: 缴费日期 | M1: 备注
E2: 组别 | F2: 第1天 | G2: 第2天 | H2: 第3天 | I2: 老师回访 | J2: 咨询回访
A3: 西班牙 | B3: 吴旭霞 | C3: 三课堂二上第一节 | D3: 43831 | E3: 1 | F3: 1 | G3: 1 | H3: 1 | M3: 1.8开始第二节
A4: 西班牙 | B4: 吴崇硕 | C4: 一上第八节 | D4: 43831 | E4: 3 | F4: 1 | G4: 1 | H4: 1 | M4: 1.8开始第二节
A5: 西班牙 | B5: 詹欣怡 | C5: 一课堂第五节 | D5: 43832 | E5: 3 | F5: 1 | G5: 1 | H5: 1
A6: 西班牙 | B6: 詹可怡 | C6: 二十一课堂第三节 | D6: 43832 | E6: 1 | F6: 1 | G6: 1 | H6: 1
A7: 意大利 | B7: 陈凯 | C7: 二十二课堂第二节 | D7: 43831 | E7: 1 | F7: 1 | G7: 1 | H7: 1
A8: 德国 | B8: 陈洁2 | C8: 新生接待课堂 | D8: 43832 | F8: 1 | M8: 放假结束再来
A9: 德国 | B9: 陈佳1 | C9: 新生接待课堂 | D9: 43832 | F9: 1 | M9: 放假结束再来
A10: 意大利 | B10: 胡玲玮 | C10: 七课堂第五节 | D10: 43832 | E10: 1 | F10: 1 | G10: 1 | H10: 1
A11: 意大利 | B11: 胡玲玮 | C11: 六课堂第七节 | D11: 43832 | E11: 4 | F11: 意大利 | G11: 胡玲玮 | H11: 六课堂第七节
A12: 意大利 | B12: 项婷婷 | C12: 四十五课堂第十节 | D12: 43832 | E12: 4 | F12: 意大利 | G12: 项婷婷 | H12: 四十五课堂第十节
A13: 意大利 | B13: 项智豪 | C13: 四十五课堂第十节 | D13: 43832 | E13: 4 | F13: 意大利 | G13: 项智豪 | H13: 四十五课堂第十节
A14: 西班牙 | B14: 叶子阳 | C14: 四十课堂第五节 | D14: 43833 | E14: 3 | F14: 1 | G14: 1 | H14: 1 | I14: 1
A15: 奥地利 | B15: 吴雨森 | C15: 四十五课堂第二节 | D15: 43833 | E15: 4 | F15: 西班牙 | G15: 罗俊浩 | H15: 六课堂第三节
A16: 西班牙 | B16: 罗俊浩 | C16: 六课堂第三节 | D16: 43833 | E16: 4 | F16: 意大利 | G16: 程贤之 | H16: 二十七课堂第十节
A17: 意大利 | B17: 程贤之 | C17: 二十七课堂第十节 | D17: 43833 | E17: 4 | F17: 西班牙 | G17: 陈梓豪 | H17: 五十六课堂第九节
A18: 西班牙 | B18: 杨嘉怡 | C18: 四十四课堂第二节 | D18: 43833 | G18: 1 | H18: 1 | M18: 转周末班
A19: 西班牙 | B19: 杨嘉心 | C19: 四十四课堂第二节 | D19: 43833 | G19: 1 | H19: 1
A20: 意大利 | B20: 晟璐 | C20: 三十一课堂第七节 | D20: 43833 | E20: 3 | F20: 1 | G20: 1 | H20: 1 | I20: 是
A21: 意大利 | B21: 源涛 | C21: 三十一课堂第四节 | D21: 43833 | E21: 3 | F21: 1 | G21: 1 | H21: 1 | I21: 是
A22: 西班牙 | B22: 徐馨怡 | C22: 三十四课堂周末00:30 | D22: 43833 | E22: 1 | F22: 1 | G22: 1
A23: 西班牙 | B23: 徐奕豪 | C23: 三十四课堂周末00:30 | D23: 43833 | E23: 1 | F23: 1 | G23: 1
A24: 意大利 | B24: 徐逸飞 | C24: 五十五课堂第四节 | D24: 43833 | E24: 3 | F24: 1 | G24: 1 | H24: 1
A25: 意大利 | B25: 吴若煦 | C25: 数学课堂03周日17:00 | D25: 43835
A26: 西班牙 | B26: 陈嘉豪 | C26: 五十五第八节 | D26: 43836 | E26: 3 | F26: 1 | G26: 1 | H26: 1
A27: 西班牙 | B27: 陈梓豪 | C27: 五十六课堂第九节 | D27: 43836 | E27: 4 | F27: 西班牙 | G27: 叶逸欧 | H27: 六课堂第三节
A28: 葡萄牙 | B28: 翁烁 | C28: 三十课堂第六节 | D28: 43836 | E28: 3 | G28: 1 | H28: 1 | I28: 是
A29: 葡萄牙 | B29: 翁航 | C29: 五课堂A第七节 | D29: 43836 | E29: 1 | F29: 1 | G29: 1
A30: 意大利 | B30: 戴百嘉 | C30: 六课堂第七节 | D30: 43836 | E30: 4 | F30: 希腊 | G30: 陈泽屹 | H30: 四十五课堂第五节
A31: 西班牙 | B31: 金以瑞 | C31: 五十五课堂第四节 | D31: 43837 | E31: 3 | F31: 1 | G31: 1 | H31: 1
A32: 西班牙 | B32: 戴澄 | C32: 二十六课堂第一节 | D32: 43837 | E32: 1 | F32: 1 | G32: 1 | H32: 1
A33: 德国 | B33: 郑鑫 | C33: 五十五课堂第四节 | D33: 43837 | E33: 3 | F33: 1 | G33: 0 | H33: 0 | M33: 试读失败
A34: 法国 | B34: 陈宣羽 | C34: ChineseonlineN课堂8:00 | D34: 43781 | F34: 1 | M34: 补登记
A35: 意大利 | B35: 陈慧淋 | C35: 三十六课堂第五节 | D35: 43837 | E35: 1 | F35: 1 | G35: 1 | H35: 1
A36: 美国 | B36: 里恩 | C36: 新生接待课堂 | D36: 43837 | F36: 1
A37: 西班牙 | B37: 周祺恩 | C37: 新生接待课堂 | D37: 43838 | F37: 1
A38: 西班牙 | B38: 夏谨睿 | C38: 五十六课堂第十节 | D38: 43838 | E38: 4 | F38: 西班牙 | G38: 朱雅琦 | H38: 二十七课堂18:00
A39: 西班牙 | B39: 蒋雨琪 | C39: 二十七课堂第十节 | D39: 43838 | E39: 4 | F39: 西班牙海岛 | G39: 林思翰 | H39: 二十七课堂第十节
A40: 法国 | B40: 吴米娜 | C40: 四课堂第九节 | D40: 1.03 | E40: 1 | F40: 1 | G40: 1 | H40: 1
A41: 美国 | B41: Jack1 | C41: 三十六课堂第一节 | D41: 1.03 | E41: 1 | F41: 1 | G41: 0 | H41: 0
A42: 法国 | B42: 叶芷欣 | C42: 五十六课堂第九节 | D42: 1.06 | E42: 4 | F42: 捷克 | G42: 叶雨祈 | H42: 六课堂第四节
A43: 德国 | B43: 陈星伊 | C43: 四十二课堂第七节 | D43: 1.09 | E43: 3 | F43: 1 | G43: 1 | H43: 1
A44: 德国 | B44: 王浩然2 | C44: 二十二课堂第二节 | D44: 1.09 | E44: 1 | F44: 1 | G44: 1 | H44: 1
A45: 德国 | B45: 王浩文 | C45: 五课堂第二节 | D45: 1.09 | E45: 1 | F45: 1 | G45: 1 | H45: 1
A46: 西班牙 | B46: 林文涛 | C46: 四十三课堂第七节 | D46: 1.09 | E46: 3 | F46: 1 | G46: 1 | H46: 1
A47: 意大利 | B47: 张佳懿 | C47: 四十五课堂第三节 | D47: 1.09 | E47: 4 | F47: 西班牙 | G47: 董陈欣宇 | H47: 二十七课堂第七节
A48: 意大利 | B48: 叶梦琪 | C48: 五十六课堂第九节 | D48: 43840 | E48: 4 | F48: 意大利 | G48: 郑涛1 | H48: 二十七课堂第十节
A49: 意大利 | B49: 王萧童 | C49: 六课堂第一节 | D49: 43840 | E49: 4 | F49: 西班牙 | G49: 郭炫宇 | H49: 五十六课堂第十节
A50: 西班牙 | B50: 林博涵 | C50: 六课堂第一节 | D50: 43840 | E50: 4 | F50: 葡萄牙 | G50: 孙妍1 | H50: 五十六课堂第十节
A51: 西班牙 | B51: 叶逸娇 | C51: 四十五课堂第一节 | D51: 43840 | E51: 4 | F51: 西班牙 | G51: 董陈炜柏 | H51: 五十六课堂第十节
A52: 西班牙 | B52: 叶逸欧 | C52: 六课堂第三节 | D52: 43840 | E52: 4 | F52: 西班牙 | G52: 王思琪 | H52: 六课堂第七节
A53: 巴西 | B53: 金娜娜1 | C53: 四十五课堂6:30 | D53: 43840 | F53: 1 | G53: 1
A54: 意大利 | B54: 胡欣荣 | C54: 六课堂第九节 | D54: 43840 | E54: 4
A55: 西班牙 | B55: 单陈霄冉 | C55: 十一课堂第十节 | D55: 43840 | E55: 4
A56: 意大利 | B56: 陈金鹏 | C56: 四十课堂第一节 | D56: 43840 | E56: 3 | F56: 0 | G56: 1 | H56: 1
A57: 希腊 | B57: 陈泽屹 | C57: 四十五课堂第五节 | D57: 43840 | E57: 4
A58: 西班牙 | B58: 林熠 | C58: 五十六课堂第九节 | D58: 43843 | E58: 4
A59: 美国 | B59: 杨楠 | C59: 美术课堂 | D59: 43841
A60: 西班牙 | B60: 陈嘉浩1 | C60: 三课堂第七节 | D60: 43843 | E60: 1 | F60: 1 | G60: 1 | H60: 1
A61: 西班牙 | B61: 黄浩博 | C61: 十课堂第六节 | D61: 43843 | E61: 1 | F61: 1 | G61: 1 | H61: 1
A62: 意大利 | B62: 吴明昊 | C62: 四课堂第七节 | D62: 43843 | E62: 1 | F62: 1 | G62: 1 | H62: 1 | K62: 1 | L62: 3.28
A63: 意大利 | B63: 吴佳慧2 | C63: 十二课堂第九节 | D63: 43843 | E63: 1 | F63: 1 | G63: 平台进不了 | H63: 1
A64: 巴西 | B64: 王瑞凯 | C64: 一课堂7:00 | D64: 43843 | E64: 3 | F64: 1 | G64: 1 | H64: 1
A65: 捷克 | B65: 郭智翔 | C65: 一课堂第六节 | D65: 43843 | E65: 3 | F65: 1 | G65: 1 | H65: 1
A66: 意大利 | B66: 郑瑞祥 | C66: 周末四课堂23:00 | D66: 43842 | E66: 1 | F66: 1 | G66: 1 | H66: 1
A67: 意大利 | B67: 赵欣怡 | C67: 天娃课堂03 21:00 | D67: 43848 | E67: 兼职
A68: 巴西 | B68: VITORIA | C68: 二十课堂6：30 | D68: 43844 | E68: 兼职
A69: 意大利 | B69: 严心妤 | C69: 五课堂第一节 | D69: 43844 | E69: 1 | F69: 1 | G69: 1
A70: 西班牙 | B70: 留雨晨 | C70: 二十七课堂第七节 | D70: 43844 | E70: 4
A71: 西班牙 | B71: 留裕涵 | C71: 五十六课堂第八节 | D71: 43844 | E71: 4
A72: 西班牙 | B72: 可可2 | C72: 四十二课堂第六节 | D72: 43844 | E72: 3 | F72: 1 | G72: 1 | H72: 1
A73: 西班牙 | B73: 宇宙1 | C73: 五十五课堂第八节 | D73: 43844 | E73: 3 | F73: 1 | G73: 0 | H73: 0 | M73: 试读失败
A74: 荷兰 | B74: 蒋懿涵 | C74: 三十一课堂第八节 | D74: 43845 | E74: 3 | F74: 1 | G74: 1 | H74: 1 | I74: 是
A75: 法国 | B75: 蔡恩佐 | C75: 三十一课堂第四节 | D75: 43845 | E75: 3 | F75: 1 | G75: 1 | H75: 1 | I75: 是 | K75: 是
A76: 西班牙 | B76: 陈昊轩2 | C76: 五十六课堂第九节 | D76: 43845 | E76: 4
A77: 西班牙 | B77: 杨昕蕊 | C77: 二十七课堂第七节 | D77: 43845 | E77: 4
A78: 西班牙 | B78: 商嘉祥 | C78: 五十六课堂第九节 | D78: 43845 | E78: 4
A79: 西班牙 | B79: 商嘉慧 | C79: 五十六课堂第八节 | D79: 43845 | E79: 4
A80: 意大利 | B80: 高翔宇 | C80: 三十七课堂第七节 | D80: 43845
A81: 意大利 | B81: 赵欣怡 | C81: 天娃课堂03 21:00 | D81: 43848
A82: 西班牙 | B82: 朱雅琦 | C82: 二十七课堂18:00 | D82: 43848 | E82: 4
A83: 西班牙 | B83: 叶秋 | C83: 三十八课堂第二节 | D83: 43846 | E83: 2
A84: 西班牙海岛 | B84: 林思翰 | C84: 二十七课堂第十节 | D84: 43846 | E84: 4
A85: 西班牙 | B85: 黄子晨 | C85: 二十七课堂第九节 | D85: 43846 | E85: 4
A86: 西班牙 | B86: 王佐伊 | C86: 四十五课堂第十节 | D86: 43846 | E86: 4
A87: 西班牙 | B87: 黄立雯 | C87: 家长没安排好时间 | D87: 43846
A88: 西班牙 | B88: 黄立霆 | C88: 家长没安排好时间 | D88: 43846
A89: 捷克 | B89: 叶雨祈 | C89: 六课堂第四节 | D89: 43847 | E89: 4
A90: 捷克 | B90: 叶雨馨1 | C90: 四十五课堂第五节 | D90: 43847 | E90: 4
A91: 西班牙 | B91: 黄泽豪 | C91: 六课堂第四节 | D91: 43847 | E91: 4
A92: 西班牙 | B92: 林子奕 | C92: 六课堂第四节 | D92: 43847 | E92: 4
A93: 西班牙 | B93: 乔嘉 | C93: 五课堂第四节 | D93: 43847 | E93: 1 | F93: 1 | G93: 1 | H93: 1
A94: 西班牙 | B94: 陈佳豪 | C94: 二十七课堂第七节 | D94: 43847 | E94: 4
A95: 西班牙 | B95: 陈佳亮 | C95: 三十二课堂第十节 | D95: 43847 | E95: 3 | F95: 1 | G95: 1 | H95: 1
A96: 西班牙 | B96: 陈佳德 | C96: 八课堂第十节 | D96: 43847 | E96: 1 | F96: 1 | G96: 1 | H96: 1
A97: 西班牙 | B97: 董陈欣宇 | C97: 二十七课堂第七节 | D97: 43850 | E97: 4
A98: 意大利 | B98: 郑涛1 | C98: 二十七课堂第十节 | D98: 43850 | E98: 4
A99: 意大利 | B99: 郑浩1 | C99: 三十一课堂第九节 | D99: 43850 | E99: 3 | F99: 1 | G99: 1 | H99: 1
A100: 西班牙 | B100: 林哲毅 | C100: 四十三课堂第十一节 | D100: 43850 | E100: 3 | F100: 1 | G100: 1 | H100: 0 | M100: 试读失败
...

Sheet 2019.11
A1: 国家 | B1: 学生 | C1: 课堂 | D1: 试读日期 | E1: 新生到课情况 | L1: 是否回访 | N1: 是否缴费 | O1: 缴费日期 | P1: 备注
E2: 第1天 | F2: 第2天 | G2: 第3天 | H2: 第4天 | I2: 第5天 | J2: 第6天 | K2: 第7天 | L2: 老师回访 | M2: 咨询回访
A3: 意大利 | B3: 虞潇 | C3: 二十八课堂第五节 | D3: 11.01 | N3: 是
A4: 西班牙海岛 | B4: 陈彩洁 | C4: 四十五课堂第五节 | D4: 11.01 | E4: 1 | F4: 1 | G4: 1 | H4: 1 | I4: 0 | J4: 0 | M4: 是 | P4: 孩子不愿意学了，家长说不来上课了
A5: 意大利 | B5: 毛铼熠 | C5: 四十五课堂第十节 | D5: 11.01 | E5: 1 | F5: 1 | G5: 1 | H5: 1 | I5: 1 | J5: 0 | N5: 是 | P5: 目前家长想要从aoe开始学，没有合适的时间和课
A6: 意大利 | B6: 吴雨静 | C6: 四十五课堂第六节 | D6: 11.01 | E6: 1 | F6: 1 | G6: 1 | H6: 1 | I6: 1 | J6: 1 | K6: 1 | M6: 是 | N6: 是
A7: 葡萄牙 | B7: 留佳 | C7: 四十二课堂第六节 | D7: 11.01 | M7: 是 | N7: 是
A8: 西班牙 | B8: 虞珊 | C8: 十三课堂第十一节 | D8: 11.01 | E8: 1 | F8: 0 | G8: 0 | H8: 0 | I8: 0 | M8: 是
A9: 挪威 | B9: 周佳欣3 | C9: 三十一课堂第四节 | D9: 11.01 | E9: 1 | F9: 1 | G9: 1 | H9: 1 | I9: 1 | M9: 是 | P9: 学生刚到挪威，家长希望孩子先学好挪威当地的语言
A10: 西班牙 | B10: 朱芳仪 | C10: 九课堂上课20:30 | D10: 11.02 | M10: 是 | N10: 是
A11: 西班牙海岛 | B11: 蔡铭瑜 | C11: 到十三课堂A 24:00 | D11: 11.02
A12: 西班牙海岛 | B12: 陈铭杰 | C12: 十三课堂A 24:00 | D12: 11.02
A13: 西班牙 | B13: 姚心一 | C13: 美术课堂21:00 | D13: 11.02 | M13: 是 | N13: 是
A14: 西班牙 | B14: 朱俊豪 | C14: 数学课堂18:20 | D14: 11.02
A15: 西班牙 | B15: 朱俊毅 | C15: 数学课堂19:20 | D15: 11.02
A16: 西班牙 | B16: 陈捷琪 | C16: 十九课堂第十节 | D16: 11.04 | E16: 1 | F16: 1 | G16: 0 | P16: 孩子觉得班级枯燥，不读了，调整班级回绝了
A17: 西班牙 | B17: 朱捷妮 | C17: 三十八课堂第八节 | D17: 11.04 | E17: 1 | F17: 1 | G17: 1 | P17: 试读失败
A18: 西班牙 | B18: 陈航勇 | C18: 四课堂第十一节 | D18: 11.04 | E18: 1 | F18: 1 | G18: 1 | H18: 1 | I18: 1 | J18: 0 | L18: 是 | M18: 是
A19: 西班牙 | B19: 陈馨妍 | C19: 四十一课堂第三节 | D19: 11.04 | E19: 1 | F19: 1 | G19: 1 | H19: 1 | I19: 1 | J19: 0 | M19: 是
A20: 西班牙 | B20: 陈航峻 | C20: 三十六课堂第一节 | D20: 11.04 | E20: 1 | F20: 1 | G20: 1 | H20: 1 | I20: 1 | J20: 0 | L20: 是 | M20: 是
A21: 西班牙 | B21: 黄函艺 | C21: 十三课堂第八节 | D21: 11.04 | M21: 是 | N21: 是
A22: 西班牙 | B22: 李炫 | C22: 十一课堂第八节 | D22: 11.04 | E22: 1 | F22: 1 | M22: 否
A23: 意大利 | B23: 朱安娜3 | C23: 四十五课堂第七节 | D23: 11.04 | E23: 1 | F23: 1 | G23: 1 | H23: 1 | I23: 1 | J23: 1 | M23: 是
A24: 西班牙 | B24: 叶雨俊 | C24: 四十五课堂第六节 | D24: 11.04 | E24: 0 | F24: 0 | M24: 是
A25: 意大利 | B25: 陈芊妤 | C25: 七课堂第二节 | D25: 11.04 | E25: 1 | F25: 1 | G25: 0 | M25: 是
A26: 意大利 | B26: 黄泽宇 | C26: 四十五课堂第五节 | D26: 11.04 | E26: 1 | F26: 1 | G26: 1 | H26: 1 | I26: 1 | J26: 1 | K26: 1 | M26: 是 | N26: 是
A27: 葡萄牙 | B27: 王碧瑶 | C27: 十六课堂第六节 | D27: 11.04 | E27: 1 | F27: 1 | G27: 1 | H27: 1 | I27: 1 | J27: 1 | K27: 1 | M27: 是 | N27: 是
A28: 西班牙 | B28: 叶璋涵 | C28: 三十八课堂第八节 | D28: 11.04 | E28: 1 | F28: 1 | G28: 1 | H28: 1 | I28: 1 | J28: 1 | K28: 1 | M28: 是 | N28: 是
A29: 西班牙 | B29: 厉韵涵 | C29: 四课堂第八节 | D29: 11.04 | E29: 0 | F29: 1 | G29: 1 | H29: 1 | I29: 1 | J29: 1 | K29: 1 | L29: 是 | M29: 是 | N29: 是
A30: 西班牙 | B30: 厉徐涵 | C30: 二十八课堂第十节 | D30: 11.04 | M30: 是 | N30: 是
A31: 意大利 | B31: 吴佳佳 | C31: 四十五课堂第五节 | D31: 11.05 | E31: 1 | F31: 1 | G31: 1 | H31: 1 | I31: 1 | J31: 1 | M31: 否 | N31: 是
A32: 西班牙 | B32: 李诺琳1 | C32: 三十三课堂第八节 | D32: 11.05 | E32: 0 | F32: 0 | G32: 1 | H32: 1 | I32: 1 | J32: 1 | K32: 1 | M32: 是 | N32: 是
A33: 西班牙 | B33: 叶湘怡 | C33: 二十三课堂第六节 | D33: 11.05 | E33: 1 | F33: 1 | G33: 1 | H33: 1 | I33: 1 | J33: 1 | K33: 1 | M33: 是 | N33: 是
A34: 西班牙 | B34: 李炫 | C34: 十三课堂第十一节 | D34: 11.05 | E34: 1 | F34: 1 | M34: 否 | N34: 是
A35: 西班牙 | B35: 朱歆妤 | C35: 四十六课堂第十一节 | D35: 11.05 | N35: 是
A36: 意大利 | B36: 晨曦 | C36: 二十二课堂第十一节 | D36: 11.05 | E36: 1 | F36: 1 | G36: 1 | H36: 0
A37: 美国 | B37: 潘尚恩 | C37: 四十三课堂7:30 | D37: 11.06 | E37: 1 | F37: 1
A38: 德国 | B38: 李凯诺 | C38: 四十五课堂第七节 | D38: 11.06 | E38: 1 | F38: 1 | G38: 1 | H38: 1 | I38: 1 | O38: 11.08
A39: 西班牙 | B39: 朱玮弘 | C39: 第十三课堂第八节 | D39: 11.06 | E39: 1 | F39: 1 | G39: 1
A40: 西班牙 | B40: 朱玮杰 | C40: 第三十七课堂第九节 | D40: 11.06 | E40: 1 | F40: 1 | G40: 1
A41: 西班牙 | B41: 张康毅 | C41: 四十五课堂第七节 | D41: 11.06 | E41: 1 | F41: 1 | G41: 1 | H41: 1 | I41: 1 | N41: 是
A42: 巴西 | B42: 林瀚 | C42: 三十课堂6:20 | D42: 11.06
A43: 意大利 | B43: 索菲亚 | C43: 三十八课堂第九节 | D43: 11.06 | E43: 1 | F43: 1 | G43: 1 | H43: 1 | I43: 1 | J43: 1 | K43: 1 | L43: 是 | N43: 是
A44: 意大利 | B44: 吴明昊 | C44: 四十七课堂第四节 | D44: 11.06
A45: 西班牙 | B45: 张若雅 | C45: 四十七课堂第二节 | D45: 11.06 | N45: 是
A46: 西班牙 | B46: 李嫒宁 | C46: 三十五课堂第五节 | D46: 11.06 | N46: 是
A47: 西班牙 | B47: 林子涵1 | C47: 二十二课堂第三节 | D47: 11.06 | E47: 1 | F47: 1 | G47: 1 | H47: 1 | I47: 1 | J47: 1 | K47: 1 | L47: 是 | N47: 是
A48: 法国 | B48: 王露西 | C48: 十课堂第六节 | D48: 11.07 | E48: 1 | F48: 1 | G48: 1 | H48: 1 | I48: 0
A49: 西班牙 | B49: 吴米娅 | C49: 四十五课堂第六节 | D49: 11.07 | E49: 1 | F49: 0 | G49: 0 | P49: 转去第八课堂了
A50: 西班牙 | B50: 杨季靖帆 | C50: 三十七课堂第六节 | D50: 11.07 | E50: 1 | F50: 1 | G50: 1 | H50: 1 | I50: 1 | J50: 1 | K50: 1 | L50: 是 | N50: 是
A51: 西班牙 | B51: 杨季伊琳 | C51: 二十二课堂第五节 | D51: 11.07 | E51: 1 | F51: 1 | G51: 1 | H51: 1 | I51: 1 | J51: 1 | K51: 1 | L51: 是 | N51: 是
A52: 比利时 | B52: 王子晟 | C52: 四十五课堂第五节 | D52: 11.07 | E52: 0 | F52: 0
A53: 比利时 | B53: 王子炫 | C53: 四十五课堂第五节 | D53: 11.07 | E53: 1 | F53: 1 | G53: 0 | H53: 0 | I53: 0
A54: 希腊 | B54: 叶伟泽 | C54: 一课堂第三节 | D54: 11.8
A55: 希腊 | B55: tony1 | C55: 一课堂第五节 | D55: 11.8
A56: 西班牙 | B56: 俞钧仪 | C56: 十七课堂第十二节 | D56: 11.8 | E56: 1 | F56: 1 | G56: 1 | H56: 1 | I56: 1 | J56: 1 | K56: 1
A57: 西班牙 | B57: 俞钧澜 | C57: 四十五课堂第十二节 | D57: 11.8 | E57: 1 | F57: 1 | G57: 1 | H57: 1 | I57: 1 | J57: 1 | K57: 0
A58: 法国 | B58: 章乐乐 | C58: 十课堂第四节 | D58: 11.8 | E58: 0 | F58: 0 | P58: 家长微信一直不回复
A59: 法国 | B59: 章小杰 | C59: 四十五课堂第十节 | D59: 11.8 | E59: 0 | F59: 0 | G59: 0 | H59: 0 | I59: 0 | J59: 0 | K59: 0 | P59: 家长微信一直不回复
A60: 法国 | B60: 章伟杰 | C60: 四十五课堂第六节 | D60: 11.8 | E60: 0 | F60: 0 | G60: 0 | H60: 0 | I60: 0 | J60: 0 | K60: 0 | P60: 家长微信一直不回复
A61: 意大利 | B61: 白永银 | C61: 第一课堂第四节课 | D61: 11.11 | E61: 1 | F61: 1 | N61: 是 | O61: 11.13
A62: 西班牙 | B62: 周露晞 | C62: 第四十四课堂第二节课 | D62: 11.11 | E62: 1 | F62: 1
A63: 西班牙 | B63: 周露娜 | C63: 第四十四课堂第二节课 | D63: 11.11 | E63: 1 | F63: 1
A64: 德国 | B64: 李睿希 | C64: 第三十一课堂第六节课 | D64: 11.11 | E64: 1 | F64: 1 | G64: 1 | H64: 1 | I64: 1 | J64: 1 | K64: 1 | L64: 是 | N64: 是
A65: 澳大利亚 | B65: 刘文竣 | C65: ChineseonlineE课堂17:20 | D65: 11.11 | N65: 是
A66: 法国 | B66: 陈彦宏 | C66: 三十六课堂7:00 | D66: 11.11 | E66: 1 | F66: 1 | G66: 1 | H66: 1 | I66: 1 | J66: 1 | K66: 1 | L66: 是 | N66: 是
A67: 意大利 | B67: 陈浩宇3 | C67: 二十八课堂第九节 | D67: 11.12 | N67: 是
A68: 西班牙 | B68: 陈欣雅 | C68: 十六课堂第一节 | D68: 11.12 | E68: 1 | F68: 1 | G68: 1 | H68: 1 | I68: 1 | J68: 1 | K68: 1 | L68: 是
A69: 西班牙 | B69: 魏家亿 | C69: 二十八课堂第五节 | D69: 11.12
A70: 意大利 | B70: 留欣怡2 | C70: 二课堂第五节 | D70: 11.12 | E70: 1 | F70: 1 | G70: 1 | H70: 1 | I70: 1 | J70: 1 | K70: 1 | L70: 是 | N70: 是
A71: 多伦多 | B71: 卓贝拉 | C71: 四十五课堂第十二节 | D71: 11.12 | E71: 1 | F71: 1 | G71: 1 | H71: 1 | I71: 1 | N71: 是
A72: 意大利 | B72: 陈倩璐 | C72: 四十七课堂第九节 | D72: 11.12 | N72: 是
A73: 多伦多 | B73: 卓安娜 | C73: 明天上二十二课堂6:00 | D73: 11.12 | E73: 1 | F73: 1 | G73: 1 | H73: 1 | I73: 1 | J73: 1 | K73: 1 | L73: 是
A74: 意大利 | B74: 包瑞莹 | C74: 四十五课堂第六节 | D74: 11.12 | E74: 1 | F74: 1 | G74: 1 | H74: 1 | I74: 1 | J74: 1 | K74: 1 | L74: 1
A75: 西班牙 | B75: 吴芯妍 | C75: 七课堂第六节 | D75: 11.12 | E75: 1很卡 | F75: 1 | G75: 1 | H75: 1 | I75: 1 | J75: 1 | K75: 1 | L75: 是 | M75: 是 | N75: 是
A76: 意大利 | B76: 张凯卫 | C76: 第八课堂第四节 | D76: 11.13 | E76: 1 | F76: 1 | G76: 1 | H76: 1 | I76: 1 | J76: 1 | K76: 1 | L76: 是 | N76: 是
A77: 瑞士 | B77: 刘天骄 | C77: 四十五课堂第六节 | D77: 11.13 | E77: 1 | F77: 1 | G77: 0 | H77: 0 | P77: 孩子不太愿意上课，一直闹情绪，家访家长没回复
A78: 西班牙 | B78: 林诗怡 | C78: 三十九课堂第二节 | D78: 11.13 | E78: 1
A79: 巴西 | B79: 郑雯月 | C79: 一课堂第十二节 | D79: 11.14 | N79: 是
A80: 意大利 | B80: 胡佳怡 | C80: 三十二课堂第五节 | D80: 11.14
A81: 意大利 | B81: 胡佳怡 | C81: 四十八课堂第六节 | D81: 11.14 | E81: 1 | F81: 1 | G81: 1 | H81: 1 | I81: 1 | J81: 1 | K81: 1 | L81: 是
A82: 意大利 | B82: 胡立材 | C82: 三十三课堂第七节 | D82: 11.14
A83: 意大利 | B83: 朱佳烨 | C83: 十一课堂第十节 | D83: 11.14 | N83: 是 | O83: 3.2
A84: 意大利 | B84: Elena | C84: 二十八课堂第三节 | D84: 11.15
A85: 捷克 | B85: 郑佩龙 | C85: 四十五课堂第五节 | D85: 11.15 | E85: 1 | F85: 1 | G85: 1 | H85: 1 | I85: 1 | J85: 1 | N85: 是
A86: 西班牙 | B86: 曾晨 | C86: 四十五课堂第五节 | D86: 11.15 | E86: 0 | F86: 1 | G86: 1 | H86: 1 | I86: 1 | J86: 0
A87: 意大利 | B87: 陈铭泽 | C87: 四十五课堂第五节 | D87: 11.15 | E87: 1 | F87: 1 | G87: 1 | H87: 1 | I87: 1 | J87: 1
A88: 西班牙 | B88: 林婷婷 | C88: 十七课堂第一节 | D88: 11.15 | N88: 是 | P88: 老生重读
A89: 西班牙 | B89: 玛莉亚 | C89: 十八课堂每周五16:00 | D89: 11.15
A90: 意大利 | B90: 林依柔 | C90: 三十一课堂第七节 | D90: 11.15 | E90: 1 | F90: 1 | G90: 1 | H90: 1 | I90: 1 | J90: 0 | K90: 1 | L90: 是 | N90: 是
A91: 西班牙 | B91: 高兴 | C91: 四十六课堂第八节 | D91: 11.15 | E91: 1
A92: 西班牙 | B92: Ryan | C92: 四十六课堂第八节 | D92: 11.15 | E92: 1
A93: 德国 | B93: 蔡黛咪 | C93: 四十六课堂第八节课 | D93: 11.18 | E93: 1 | N93: 是
A94: 西班牙 | B94: 夏柏舒 | C94: 七课堂第六节课 | D94: 11.18 | E94: 1 | F94: 1 | G94: 1 | H94: 1 | I94: 1 | J94: 1 | K94: 1 | L94: 是 | N94: 是
A95: 法国 | B95: 汪凯洲 | C95: 四十五课堂第十节课 | D95: 11.18 | E95: 1 | F95: 0 | P95: 试读失败，想给孩子调整到双语课，但是家长拒绝了，表示不学了
A96: 意大利 | B96: 方立磊 | C96: 三课堂第六节课 | D96: 11.18 | E96: 1 | F96: 1 | G96: 1 | H96: 1 | I96: 1 | J96: 1 | K96: 1 | L96: 是 | N96: 是
A97: 意大利 | B97: 杨煜婷 | C97: 一课堂2:10 | D97: 11.16
A98: 意大利 | B98: 杨珍祯 | C98: 数学课堂20:00 | D98: 11.16
A99: 意大利 | B99: Simona | C99: 十八课堂第十节 | D99: 11.18 | E99: 1 | N99: 是 | O99: 5.28
A100: 西班牙 | B100: 周心盈 | C100: 三十八课堂第六节 | D100: 11.18 | E100: 1 | F100: 1 | G100: 1 | H100: 1 | I100: 1
...

Sheet 2019.12
A1: 国家 | B1: 学生 | C1: 课堂 | D1: 试读日期 | E1: 新生到课情况 | H1: 是否回访 | J1: 是否缴费 | K1: 缴费日期 | L1: 备注
E2: 第1天 | F2: 第2天 | G2: 第3天 | H2: 老师回访 | I2: 咨询回访
A3: 巴西 | B3: 徐喆 | C3: 七课堂第十二节 | D3: 12.02 | E3: 1 | F3: 1 | G3: 1 | H3: 是 | J3: 是
A4: 巴西 | B4: 梁锡康 | C4: ChineseonlineQ课堂8:40 | D4: 12.02 | E4: 1 | J4: 是
A5: 巴西 | B5: 梁锡健 | C5: ChineseonlineQ课堂8:40 | D5: 12.02 | E5: 1 | J5: 是
A6: 西班牙 | B6: 程迪文 | C6: 新生接待课堂 | D6: 12.02 | E6: 1 | F6: 1 | G6: 1 | H6: 是 | J6: 是
A7: 西班牙 | B7: 西西 | C7: 新生接待课堂 | D7: 12.02 | E7: 1 | F7: 1 | G7: 1 | H7: 是 | J7: 是
A8: 西班牙 | B8: 陈诗晴 | C8: 新生接待课堂 | D8: 12.02 | E8: 1 | F8: 1 | G8: 1 | H8: 是 | J8: 是 | K8: 12.07
A9: 西班牙 | B9: 陈媛馨 | C9: 新生接待课堂 | D9: 12.02 | E9: 1 | F9: 1 | G9: 1 | H9: 是 | J9: 是
A10: 巴西 | B10: 叶瑜繁 | C10: 十一课堂第十二节 | D10: 12.03 | E10: 1 | J10: 是
A11: 意大利 | B11: 朱宏瑞 | C11: 十一课堂第八节 | D11: 12.03 | E11: 1 | J11: 是
A12: 西班牙 | B12: 倪晨菲 | C12: 新生接待课堂 | D12: 12.03 | E12: 1 | L12: 已试读一节课，1月搬完家入学
A13: 西班牙 | B13: 倪晨翔 | C13: 新生接待课堂 | D13: 12.03 | E13: 1 | L13: 已试读一节课，1月搬完家入学
A14: 西班牙 | B14: 倪晨睿 | C14: 新生接待课堂 | D14: 12.03 | E14: 1 | L14: 已试读一节课，1月搬完家入学
A15: 巴西 | B15: 叶妤希 | C15: 十六课堂6:20 | D15: 12.04 | E15: 1 | J15: 是
A16: 西班牙 | B16: 胡朱锦梁 | C16: 五十一课堂第五节 | D16: 12.04 | E16: 1 | F16: 1 | J16: 是
A17: 巴西 | B17: 杨心圣 | C17: 新生接待课堂 | D17: 12.04 | E17: 1 | F17: 1 | G17: 1 | J17: 是
A18: 巴西 | B18: 杨心龙 | C18: 新生接待课堂 | D18: 12.04 | E18: 1 | F18: 1 | G18: 1 | J18: 是
A19: 意大利 | B19: 朱洪涛 | C19: 五十三课堂第六节 | D19: 12.04 | E19: 1 | F19: 1 | J19: 是
A20: 意大利 | B20: 朱洪涛 | C20: 一课堂第十节 | D20: 12.05 | E20: 1 | J20: 是
A21: 西班牙 | B21: 单陈霄冉 | C21: 三十八课堂第八节 | D21: 12.05 | E21: 1 | F21: 1 | G21: 1 | J21: 是
A22: 巴西 | B22: 陈映霖 | C22: 新生接待课堂 | D22: 12.05 | E22: 1 | J22: 是
A23: 意大利 | B23: 程优璇 | C23: 新生接待课堂 | D23: 12.05 | E23: 1 | F23: 1 | G23: 1 | H23: 是 | J23: 是
A24: 意大利 | B24: 林小雨 | C24: 二十二课堂第一节 | D24: 12.05 | E24: 1 | F24: 1 | G24: 1 | H24: 是 | J24: 是
A25: 西班牙 | B25: 陈艺 | C25: 五十一课堂第五节 | D25: 12.06 | E25: 1 | F25: 1 | J25: 是
A26: 西班牙海岛 | B26: 安琳 | C26: 三十四课堂第六节 | D26: 12.06 | E26: 1 | F26: 1 | G26: 1 | H26: 是 | J26: 是
A27: 巴西 | B27: 徐喆 | C27: 黄老师的课堂18:30 | D27: 12.06 | E27: 1
A28: 西班牙 | B28: 金佳鑫 | C28: 四十二课堂第二节 | D28: 12.06 | E28: 1 | F28: 1 | G28: 1
A29: 意大利 | B29: 管似幸 | C29: 新生接待课堂 | D29: 12.09 | E29: 1（12.09） | F29: 1（12.12） | G29: 1 | J29: 是
A30: 捷克 | B30: 郭鑫睿 | C30: Chineseonline课堂13:30 滕老师 | D30: 12.08 | E30: 1 | F30: 1 | G30: 0 | L30: 试读失败，第二节课后没有联系上
A31: 捷克 | B31: 季施宇 | C31: 三十三课堂第七节 | D31: 12.1 | E31: 1 | F31: 1 | G31: 1 | J31: 是
A32: 意大利 | B32: 詹晨鑫 | C32: 四十三课堂第九节 | D32: 12.1 | E32: 1 | F32: 1 | J32: 是
A33: 西班牙 | B33: 林佳宁 | C33: 四课堂第九节 | D33: 12.1 | E33: 1 | F33: 1 | G33: 1 | H33: 是 | J33: 是
A34: 西班牙 | B34: 陈柯冉 | C34: 二课堂第七节 | D34: 12.1 | E34: 1 | F34: 1 | G34: 1 | J34: 是
A35: 葡萄牙 | B35: 程新洋 | D35: 12.11 | E35: 1 | F35: 1 | G35: 1 | J35: 是
A36: 西班牙 | B36: 梁天麟 | C36: 四课堂第九节 | D36: 12.11 | E36: 1 | F36: 1 | G36: 1 | H36: 是
A37: 西班牙 | B37: 梁天乐 | C37: 四十五课堂第二节 | D37: 12.11 | E37: 1 | F37: 1
A38: 西班牙 | B38: 张贝赟 | C38: 四课堂第九节 | D38: 12.13 | E38: 1 | F38: 1 | G38: 1 | H38: 是 | J38: 是
A39: 美国 | B39: 陈雨昕 | C39: 四十九课堂第十一节 | D39: 12.13 | E39: 1 | F39: 1 | G39: 0
A40: 美国 | B40: 陈起翔 | C40: 三十一课堂第十二节 | D40: 12.17 | E40: 1 | F40: 1 | G40: 1 | H40: 是
A41: 美国 | B41: 朱孝杰 | C41: 三十一课堂第十二节 | D41: 12.17 | E41: 1 | F41: 1 | H41: 是
A42: 西班牙 | B42: 杜铭轩 | C42: 四十九课堂第十一节 | D42: 12.16 | F42: 1 | G42: 1
A43: 西班牙 | B43: 叶欣甜 | C43: 二十二课堂第九节 | D43: 12.16 | E43: 1 | F43: 1 | G43: 1 | H43: 是
A44: 意大利 | B44: michele君豪 | C44: 四课堂第九节 | D44: 12.17 | E44: 1 | F44: 1 | G44: 1 | H44: 是 | J44: 是
A45: 西班牙 | B45: 陈佳俊 | C45: 新生接待课堂 | D45: 12.17
A46: 葡萄牙 | B46: 孙妍1 | C46: 新生接待课堂 | D46: 12.17
A47: 西班牙 | B47: 梁语嫣 | C47: 四十五课堂第二节 | D47: 12.18 | E47: 1 | F47: 1 | G47: 1
A48: 西班牙 | B48: 刘佳鑫 | C48: 二十六课堂第三节 | D48: 12.18 | E48: 0 | F48: 1 | G48: 0 | H48: 是
A49: 意大利 | B49: 张诚1 | C49: 四课堂第九节 | D49: 12.18 | E49: 1 | F49: 0 | G49: 0
A50: 西班牙 | B50: 陈语馨1 | C50: 四十五课堂第二节 | D50: 12.19 | E50: 0 | F50: 0 | G50: 0 | L50: 一天没来过，家长说不读了
A51: 意大利 | B51: 张李娜 | C51: 十七课堂第一节 | D51: 12.19 | E51: 1 | F51: 1 | G51: 1 | H51: 是 | J51: 是
A52: 巴西 | B52: 谭健宁 | C52: 四十五课堂第二节 | D52: 12.19 | E52: 1 | F52: 1 | G52: 1
A53: 西班牙 | B53: 叶俊韩 | C53: 五十四课堂第五节 | D53: 12.19
A54: 西班牙 | B54: 何子恒 | C54: 三十六课堂第一节 | D54: 12.19 | E54: 1 | F54: 1 | G54: 1
A55: 西班牙 | B55: 陈康淇 | C55: 四十五课堂第六节 | D55: 12.2 | E55: 1 | F55: 1 | G55: 1 | J55: 是
A56: 西班牙 | B56: 陈豪康 | C56: 五十六课堂A | D56: 12.2 | J56: 是
A57: 西班牙 | B57: 张叶媛 | C57: 新生接待课堂 | D57: 12.2 | E57: 1 | F57: 0 | G57: 失败 | L57: 要补西班牙语
A58: 西班牙 | B58: 姚祺 | C58: 新生接待课堂 | D58: 12.2 | E58: 1 | L58: 2月开始
A59: 西班牙 | B59: 詹佳茜 | C59: 新生接待课堂 | D59: 12.23 | L59: 1月开始
A60: 意大利 | B60: 厉馨洁 | C60: 六课堂第六节 | D60: 12.23
A61: 意大利 | B61: 吴康宇 | C61: 二十六课堂第七节 | D61: 12.23 | E61: 1 | F61: 1 | G61: 1 | H61: 是 | J61: 是
A62: 西班牙 | B62: 金明扬 | C62: 新生接待课堂 | D62: 12.23 | E62: 1 | L62: 妈妈不在家，教会孩子自己用
A63: 意大利 | B63: 胡立壹 | C63: 新生接待课堂 | D63: 12.24 | E63: 1
A64: 巴西 | B64: 陈柏宇 | C64: 十五课堂第十节 | D64: 12.24
A65: 巴西 | B65: 陈星宇2 | C65: 三课堂7:30 | D65: 12.24 | E65: 1 | F65: 1 | G65: 1 | H65: 是
A66: 巴西 | B66: 陈洪宇 | C66: 二十九课堂十二节 | D66: 12.24 | E66: 1 | F66: 1 | G66: 1 | H66: 是
A67: 意大利 | B67: 胡立壹 | C67: 五十六课堂第六节 | D67: 12.24 | J67: 是
A68: 西班牙 | B68: 何毅龙 | C68: 三十五课堂第六节 | D68: 12.27 | E68: 1 | F68: 0 | G68: 1 | H68: 是
A69: 西班牙 | B69: 何毅翔 | C69: 三十五课堂第六节 | D69: 12.27 | E69: 1 | F69: 0 | G69: 1 | H69: 是
A70: 意大利 | B70: 留鑫浩 | C70: 十课堂第十节 | D70: 12.27 | E70: 1 | F70: 1 | G70: 1
A71: 西班牙 | B71: 倪晨菲 | C71: 四十五课堂第十节 | D71: 12.27 | E71: 1 | F71: 1
A72: 巴西 | B72: 金喜1 | C72: ChineseonlineC课堂8:00 | D72: 12.27
A73: 意大利 | B73: 张凤俊 | C73: 十一课堂第八节 | D73: 12.3 | E73: 1 | J73: 是
A74: 意大利 | B74: 刘赟 | C74: 四十三课堂第一节 | D74: 12.3 | E74: 1 | F74: 1 | G74: 1 | J74: 是
A75: 意大利 | B75: 刘晟 | C75: 四十三课堂第二节 | D75: 12.3 | E75: 1 | F75: 1 | G75: 1 | J75: 是
A76: 西班牙 | B76: 季昕怡 | C76: 四十三课堂第九节 | D76: 12.31 | E76: 1 | F76: 1 | G76: 1 | J76: 是

Sheet 2020.02
A1: 巴西 | B1: 中文 | C1: 李煜 | D1: 二十九课堂6:30 | E1: 2.10 | F1: 1 | G1: 1 | H1: 1 | I1: 1
A2: 西班牙海岛 | B2: 中文 | C2: 徐子芯 | D2: 三十六课堂第二节 | E2: 2.10 | F2: 1 | G2: 1 | H2: 1 | I2: 1 | N2: 老生重读
A3: 巴西 | B3: 中文 | C3: 陶康帅 | D3: 三十五课堂第五节 | E3: 2.10 | F3: 3 | G3: 1 | H3: 1 | I3: 1
A4: 巴西 | B4: 英语 | C4: 季莎莎 | D4: 六课堂第六节 | E4: 2.10 | F4: 4 | G4: 1 | H4: 1 | I4: 1
A5: 西班牙 | B5: 中文 | C5: 蒋硕 | D5: 五十六课堂第十节 | E5: 2.10 | F5: 4 | G5: 1 | H5: 1 | I5: 1
A6: 西班牙 | B6: 中文 | C6: 蒋智 | D6: 五十六课堂第十一节 | E6: 2.10 | F6: 4 | G6: 1 | H6: 1 | I6: 1
A7: 巴西 | B7: 中文 | C7: 季莎莎 | D7: 十九课堂6：30 | E7: 2.10 | F7: 2
A8: 巴西 | B8: 中文 | C8: 季靖浩 | D8: 十七课堂第十节 | E8: 2.10 | F8: 2 | H8: 1 | I8: 1
A9: 巴西 | B9: 英语 | C9: 季靖浩 | D9: 二十九课堂7:00 | E9: 2.10 | F9: 1 | G9: 1 | H9: 1 | I9: 1
A10: 意大利 | B10: 中文 | C10: 付雨宣 | D10: 四十二课堂第七节 | E10: 2.10 | F10: 3 | G10: 1 | H10: 1 | I10: 1
A11: 意大利 | B11: 中文 | C11: 林静怡 | D11: 十四课堂第九节 | E11: 2.11 | F11: 2 | H11: 1 | I11: 1 | J11: 是
A12: 西班牙新生 | B12: 中文 | C12: 叶雨婷 | D12: 三课堂第一节 | E12: 2.11 | F12: 1 | G12: 1 | H12: 1 | I12: 1
A13: 意大利 | B13: 中文 | C13: 吴芷伊 | D13: 三课堂课堂第二节 | E13: 2.11 | F13: 1 | G13: 1 | H13: 1 | I13: 1
A14: 西班牙 | B14: 英语 | C14: 黄慧敏 | D14: 四十二课堂第十节 | E14: 2.11 | F14: 3 | G14: 1 | H14: 1 | I14: 1
A15: 西班牙 | B15: 中文 | C15: 吴烁 | D15: 新生接待课堂第九节 | E15: 2.11 | F15: 3 | G15: 1 | H15: 1 | I15: 1
A16: 意大利 | B16: 中文 | C16: 夏凯文 | D16: 新生接待课堂第九节 | E16: 2.11 | G16: 1
A17: 意大利 | B17: 中文 | C17: 何黄彼得 | D17: 新生接待课堂第九节 | E17: 2.11 | G17: 1
A18: 意大利 | B18: 中文 | C18: 罗伊佳 | D18: 五十六课堂第三节 | E18: 2.11 | F18: 4 | G18: 1
A19: 波兰 | B19: 中文 | C19: 傅陈好 | D19: 六课堂第三节 | E19: 2.11 | F19: 4 | G19: 1 | H19: 1 | I19: 1
A20: 意大利 | B20: 中文 | C20: 吴俊泽 | D20: 新生接待课堂第十节 | E20: 2.11
A21: 意大利 | B21: 中文 | C21: 何家慧 | D21: 十二课堂第六节 | E21: 2.12 | F21: 1 | G21: 1 | H21: 1 | I21: 1 | N21: 老生重读
A22: 意大利 | B22: 英语 | C22: 罗伊佳 | D22: 六课堂第一节 | E22: 2.12 | F22: 4 | G22: 1 | H22: 0
A23: 希腊 | B23: 数学 | C23: 张子轩 | D23: 二十一课堂第八节 | E23: 2.12
A24: 波兰 | B24: 中文 | C24: 傅福煜 | D24: 二十八课堂第十一节 | E24: 2.13 | F24: 3 | G24: 1 | H24: 1 | I24: 1
A25: 巴西 | B25: 数学 | C25: 金喾 | D25: 一课堂第六节 | E25: 2.14 | F25: 3 | G25: 1 | H25: 0 | I25: 0 | J25: 缴费成功后，3.2号继续上课
A26: 德国 | B26: 中文 | C26: 冯子涵 | D26: 三十一课堂17:00 | E26: 2.16 | F26: 3 | G26: 1 | H26: 1 | I26: 1
A27: 德国 | B27: 中文 | C27: 冯子萱 | D27: 三十一课堂17:00 | E27: 2.16 | F27: 3 | G27: 1 | H27: 1 | I27: 1
A28: 巴西 | B28: 中文 | C28: 吴喜乐 | D28: 四十五课堂6:30 | E28: 2.13 | F28: 4 | G28: 1
A29: 巴西 | B29: 中文 | C29: 吴喜悦 | D29: 三课堂7:30 | E29: 2.13 | F29: 1 | G29: 1 | H29: 1 | I29: 1
A30: 西班牙海岛 | B30: 美术 | C30: 陈昊轩2 | D30: 美术课堂17:00张纯纯 | E30: 2.8 | G30: 1 | H30: 1
A31: 西班牙 | B31: 美术 | C31: 魏雨萱 | D31: 美术课堂17:00张纯纯 | E31: 2.9 | G31: 1
A32: 西班牙 | B32: 美术 | C32: 张家盛 | D32: 美术课堂23:00叶老师 | E32: 2.15 | G32: 1 | H32: 0
A33: 西班牙 | B33: 美术 | C33: 刘博轩 | D33: 美术课堂17:00张纯纯 | E33: 2.15
A34: 西班牙 | B34: 美术 | C34: 陈嘉乐2 | D34: 美术课堂17:00张乙格 | E34: 2.8 | G34: 1 | H34: 1
A35: 希腊 | B35: 美术 | C35: 蒋博宇 | D35: 美术课堂17:00张纯纯 | E35: 2.15
A36: 西班牙 | B36: 中文 | C36: Erika | D36: ChineseonlineT10 | E36: 2,15
A37: 德国 | B37: 中文 | C37: 孙浚轩 | D37: 三十八课堂第七节 | E37: 2.17
A38: 西班牙 | B38: 中文 | C38: 罗超颖 | D38: 五十四课堂第十节 | E38: 2.17 | F38: 3 | G38: 1 | H38: 1 | I38: 1
A39: 西班牙 | B39: 中文 | C39: 罗超贤1 | D39: 三十一课堂第五节 | E39: 2.17 | F39: 3 | G39: 1 | H39: 1 | I39: 1
A40: 西班牙 | B40: 数学 | C40: 孙颖1 | D40: 一课堂第十节 | E40: 2.17 | F40: 3 | G40: 1 | H40: 1 | I40: 1
A41: 葡萄牙 | B41: 中文 | C41: 周慧杰 | D41: 二十七课堂第七节 | E41: 2.17 | F41: 4
A42: 意大利 | B42: 中文 | C42: 林馨悦 | D42: 二十七课堂第九节 | E42: 2.17 | F42: 4
A43: 意大利 | B43: 中文 | C43: 郭静瑾 | D43: 二十二课堂第九节 | E43: 2.17 | F43: 1 | G43: 1 | H43: 1 | I43: 1
A44: 波兰 | B44: 中文 | C44: 潘翊航 | D44: 二十七课堂第七节 | E44: 2.17 | F44: 4
A45: 奥地利 | B45: 中文 | C45: 戴子越 | D45: 四十二 课堂第六节 | E45: 2.17 | F45: 3 | G45: 1 | H45: 1 | I45: 1
A46: 意大利 | B46: 中文 | C46: 王瑶2 | D46: 六课堂第四节 | E46: 2.18 | F46: 4 | G46: 1 | H46: 1
A47: 西班牙 | B47: 中文 | C47: 留睿轩1 | D47: 六课堂第四节 | E47: 2.18 | F47: 4 | G47: 1 | H47: 1
A48: 西班牙 | B48: 中文 | C48: lili2 | D48: 五十五课堂第二节 | E48: 2.18 | F48: 3 | G48: 1 | H48: 1 | I48: 1
A49: 意大利 | B49: 中文 | C49: 裘俊凯 | D49: 五十五课堂第二节 | E49: 2.18 | F49: 3 | G49: 1 | H49: 1 | I49: 1
A50: 西班牙 | B50: 中文 | C50: 何语芯 | D50: 五十五课堂第二节 | E50: 2.18 | F50: 3 | G50: 1 | H50: 1 | I50: 1
A51: 意大利 | B51: 中文 | C51: 郭紫晔 | D51: 九课堂第七节 | E51: 2.18 | F51: 4 | G51: 1 | H51: 1 | I51: 1
A52: 日本 | B52: 中文 | C52: 小妤 | D52: 白班新生接待课堂 | E52: 2.18
A53: 意大利 | B53: 英文 | C53: 黄莘茹 | D53: 英语课堂 16:00 | E53: 2.08
A54: 意大利 | B54: 中文 | C54: 黄敬博 | D54: 天娃课堂01 17：00 | E54: 2.08
A55: 葡萄牙 | B55: 中文 | C55: 林佳怡2 | D55: 二十八课堂23：40 | E55: 2.16 | F55: 3 | G55: 1 | H55: 1 | I55: 1
A56: 美国 | B56: 中文 | C56: 周弋雯 | D56: 待定
A57: 意大利 | B57: 中文 | C57: 赵语晨 | D57: 三十一课堂第九节 | E57: 2.19 | F57: 3 | G57: 1 | H57: 1 | I57: 1
A58: 西班牙海岛 | B58: 中文 | C58: 欧馨怡 | D58: 二十四课堂 | E58: 2.20 | F58: 3 | G58: 1 | H58: 2.21未到
A59: 西班牙海岛 | B59: 中文 | C59: 欧馨俊 | D59: 五十五课堂第二节 | E59: 2.20 | F59: 3 | G59: 1 | H59: 试读失败
A60: 西班牙 | B60: 中文 | C60: 梁绚超 | D60: 十七课堂第十节 | E60: 2.19 | F60: 2 | H60: 1
A61: 西班牙 | B61: 中文 | C61: 梁硕迪 | D61: 七课堂第十一节 | E61: 2.19 | F61: 1 | G61: 1 | H61: 1 | I61: 1
A62: 巴西 | B62: 中文 | C62: 项诗媛 | D62: 三十七课堂6:00 | E62: 2.18 | F62: 2
A63: 西班牙 | B63: 中文 | C63: 戴雅欣 | D63: 二十六课堂第六节 | E63: 2.19 | F63: 1 | G63: 1 | H63: 1 | I63: 1
A64: 意大利 | B64: 中文 | C64: 王凯2 | D64: 三十三课堂第八节 | E64: 2.20 | F64: 2
A65: 意大利 | B65: 中文 | C65: 王怡璐 | D65: 十五课堂第七节 | E65: 2.20 | F65: 4
A66: 意大利 | B66: 数学 | C66: 王紫欣 | D66: 二十一课堂第八节 | E66: 2.18 | F66: 1 | G66: 1 | H66: 1 | I66: 1
A67: 意大利 | B67: 中文 | C67: 王紫欣 | D67: 四十一课堂第二节 | E67: 2.19 | F67: 2
A68: 意大利 | B68: 英语 | C68: 王紫欣 | D68: 六课堂第九节 | E68: 2.18 | F68: 4
A69: 意大利 | B69: 中文 | C69: 柳宗豪 | D69: 五十六课堂第八节 | E69: 2.20 | F69: 4 | G69: 1 | H69: 1 | I69: 1 | J69: 转到六课堂
A70: 意大利 | B70: 中文 | C70: 何婉怡 | D70: 四十课堂第七节 | E70: 2.20 | F70: 3 | G70: 1 | H70: 1 | I70: 1
A71: 意大利 | B71: 中文 | C71: 何晨曦 | D71: 三十七课堂第八节 | E71: 2.20 | F71: 2 | G71: 1 | H71: 1 | I71: 1
A72: 意大利 | B72: 数学 | C72: 陈依芯 | D72: 十一课堂第三节 | E72: 2.20 | F72: 4
A73: 西班牙 | B73: 中文 | C73: 吴逸浩 | D73: 二十七课堂第十二节 | E73: 2.20 | F73: 4 | G73: 1 | H73: 1 | I73: 1
A74: 西班牙 | B74: 中文 | C74: 吴逸雯 | D74: 八课堂第二节 | E74: 2.21 | F74: 1 | G74: 1 | H74: 1 | I74: 转38课堂
A75: 希腊 | B75: 中文 | C75: 张子轩 | D75: 二十七课堂第六节 | E75: 2.21 | F75: 4
A76: 意大利 | B76: 中文 | C76: 郑乐茹 | D76: 二十七课堂第六节 | E76: 2.21 | F76: 4
A77: 意大利 | B77: 英语 | C77: 郑乐茹 | D77: 二课堂第三节 | E77: 2.21 | F77: 1 | G77: 1 | H77: 1 | I77: 1
A78: 西班牙 | B78: 中文 | C78: 哈维 | D78: 五十六课堂第十节 | E78: 2.21 | F78: 4
A79: 西班牙 | B79: 中文 | C79: Amelie | D79: 星天娃课堂01 | E79: 2.21
A80: 巴西 | B80: 数学 | C80: 杨可心 | D80: ChineseonlineF20:00 | E80: 2.22
A81: 巴西 | B81: 中文 | C81: 杨可心 | D81: 二十八课堂1:00 | E81: 2.22 | F81: 3 | G81: 1 | H81: 1 | I81: 1
A82: 西班牙 | B82: 美术 | C82: 留欣怡 | D82: 美术课堂23:00 | E82: 2.22
A83: 西班牙 | B83: 中文 | C83: 郑金德 | D83: 待定周末班
A84: 西班牙 | B84: 中文 | C84: 郑梦晨 | D84: 待定周末班
A85: 西班牙 | B85: 中文 | C85: 周祺恩 | D85: 六课堂第四节 | E85: 2.24 | F85: 4 | G85: 1 | H85: 1 | I85: 1
A86: 意大利 | B86: 中文 | C86: 林洋德 | D86: 五十五课堂第二节 | E86: 2.24 | F86: 3 | G86: 1 | H86: 试读失败
A87: 意大利 | B87: 中文 | C87: 陈雨春 | D87: 二十五课堂第五节 | E87: 2.24 | F87: 2 | G87: 0 | H87: 0 | I87: 0
A88: 希腊 | B88: 西班牙语 | C88: 林莉娜 | D88: 星天娃课堂01 | E88: 2.23
A89: 希腊 | B89: 中文 | C89: 滕娅茹 | D89: 待定 | E89: 2.23测试
A90: 意大利 | B90: 中文 | C90: 朱瑞洋 | D90: 四十一课堂第二节 | E90: 2.24 | F90: 2 | G90: 1 | H90: 1 | I90: 1
A91: 意大利 | B91: 中文 | C91: 朱瑞康 | D91: 三十四课堂第二节 | E91: 2.24 | F91: 1 | G91: 1 | H91: 1 | I91: 1
A92: 意大利 | B92: 中文 | C92: 林昀圢 | D92: 五十五课堂第二节 | E92: 2.25 | F92: 3 | G92: 1 | H92: 1 | I92: 1
A93: 葡萄牙 | B93: 中文 | C93: 单甜贻 | D93: 三十七课堂第七节 | E93: 2.25 | F93: 2 | G93: 1 | H93: 1 | I93: 1
A94: 意大利 | B94: 中文 | C94: 张郡雪 | D94: 五十七课堂第九节 | E94: 2.25 | F94: 3 | G94: 1 | H94: 1 | I94: 1
A95: 德国 | B95: 中文 | C95: 饶德侁 | D95: 三十六课堂第十二节 | E95: 2.25 | F95: 1 | G95: 1 | H95: 1 | I95: 1
A96: 葡萄牙 | B96: 中文 | C96: 叶露希 | D96: 二十七课堂第六节 | E96: 2.25 | F96: 4
A97: 巴西 | B97: 数学 | C97: 周露西 | D97: 一课堂7:00 | E97: 2.25 | F97: 3 | G97: 试读失败
A98: 葡萄牙 | B98: 中文 | C98: 林亚晨 | D98: 五十六课堂第十节 | E98: 2.25 | F98: 4 | G98: 1 | H98: 1 | I98: 1
A99: 西班牙 | B99: 中文 | C99: 叶辰轩 | D99: 二十二课堂第九节 | E99: 2.26 | F99: 1 | G99: 1 | H99: 1 | I99: 1
A100: 德国 | B100: 中文 | C100: 马叶洁 | D100: 三十八课堂第二节 | E100: 2.26 | F100: 2 | G100: 1 | H100: 1 | I100: 1
...

Sheet 2019.10
A1: 国家 | B1: 学生 | C1: 课堂 | D1: 试读日期 | E1: 新生到课情况 | L1: 是否回访 | N1: 是否缴费 | O1: 缴费日期 | P1: 备注 | Q1: 批注：完成1，未完成0
E2: 第1天 | F2: 第2天 | G2: 第3天 | H2: 第4天 | I2: 第5天 | J2: 第6天 | K2: 第7天 | L2: 老师回访 | M2: 咨询回访
A3: 葡萄牙 | B3: 赵宇诺 | C3: 三十六课堂第六节 | D3: 10.8
A4: 巴西 | B4: 潘雨晴 | C4: 三十六课堂6:00 | D4: 10.8
A5: 西班牙 | B5: 林策 | C5: 三十课堂第二节 | D5: 10.8 | P5: 流失
A6: 西班牙 | B6: 林君 | C6: 三十课堂第二节 | D6: 10.8 | N6: 是
A7: 西班牙 | B7: 林家豪 | C7: 四十七课堂第二节 | D7: 10.8 | N7: 是
A8: 西班牙 | B8: 林家俊 | C8: 三十一课堂第七节 | D8: 10.8 | N8: 是
A9: 西班牙 | B9: 林家麒 | C9: 三十一课堂第七节 | D9: 10.8 | N9: 是
A10: 西班牙 | B10: 黄胜昔 | C10: 四十八课堂第八节 | D10: 10.8 | N10: 是
A11: 西班牙 | B11: 黄胜毅 | C11: 十三课堂第七节 | D11: 10.8 | N11: 是
A12: 西班牙 | B12: 林安娜1 | C12: 三十六课堂第十二节 | D12: 10.8 | N12: 是
A13: 西班牙 | B13: 潘凯涵 | C13: 四十六课堂第十节 | D13: 10.8 | N13: 是
A14: 西班牙 | B14: 潘凯祥 | C14: 四十八课堂第九节 | D14: 10.8 | N14: 是
A15: 西班牙 | B15: 阮卓正 | C15: 四十七课堂第八节 | D15: 10.8 | P15: 流失
A16: 西班牙 | B16: 阮卓莹 | C16: 四十七课堂第八节 | D16: 10.8 | P16: 流失
A17: 西班牙 | B17: 陈骏 | C17: 二十二课堂第十节 | D17: 10.8 | N17: 是
A18: 西班牙 | B18: 陈依诺 | C18: 十课堂第十节 | D18: 10.8 | N18: 是
A19: 巴西 | B19: 陈骏禹 | C19: 三十六课堂6:00 | D19: 10.8
A20: 西班牙 | B20: 朱文浩 | C20: 三十课堂第三节 | D20: 10.8 | N20: 是
A21: 西班牙 | B21: 刘恩泽 | C21: 三十一课堂第七节 | D21: 10.8 | N21: 是
A22: 西班牙 | B22: 刘翔泽 | C22: 三十一课堂第七节 | D22: 10.8 | P22: 流失
A23: 西班牙 | B23: 程新泽 | C23: 三十一课堂第八节 | D23: 10.8 | N23: 是
A24: 西班牙 | B24: 陈轩 | C24: 四十六课堂第十节 | D24: 10.9 | N24: 是
A25: 西班牙 | B25: 朱雨霜 | C25: 二十二课堂第六节 | D25: 10.9 | N25: 是
A26: 西班牙 | B26: 李淑晴 | C26: 二课堂第一节 | D26: 10.9 | E26: 1 | F26: 1 | G26: 1 | H26: 1 | I26: 1 | J26: 1 | K26: 1
A27: 西班牙 | B27: 朱锌锌 | C27: 二十三课堂第一节 | D27: 10.9 | E27: 1 | F27: 1 | G27: 1 | H27: 1 | I27: 1 | J27: 1 | K27: 1 | N27: 是
A28: 葡萄牙 | B28: 麻佳瑶 | C28: 四十六课堂第八节 | D28: 10.9 | N28: 是
A29: 西班牙 | B29: 诸心茹 | C29: 三十六课堂第十二节 | D29: 10.9
A30: 西班牙 | B30: 林馨1 | C30: 十七课堂第二节 | D30: 10.9 | E30: 1 | F30: 1 | G30: 1 | H30: 1 | I30: 1 | J30: 1 | K30: 1 | L30: 是 | N30: 是
A31: 捷克 | B31: 史昂 | C31: 四十七课堂第八节 | D31: 10.9 | P31: 流失
A32: 捷克 | B32: 史可 | C32: 二十二课堂第八节 | D32: 10.9 | P32: 流失
A33: 葡萄牙 | B33: 郦锦仪 | C33: 四十六课堂第十节 | D33: 10.1 | N33: 是
A34: 赛尔维亚 | B34: 曾宇菲 | C34: 十课堂第十节 | D34: 10.1
A35: 西班牙 | B35: 张琦嫣 | C35: 四十六课堂第五节 | D35: 10.1 | P35: 流失
A36: 葡萄牙 | B36: 叶诗恬 | C36: 九课堂第一节 | D36: 10.1 | N36: 是
A37: 西班牙 | B37: 孙欣欣 | C37: 三十五课堂第六节 | D37: 10.1 | E37: 1 | F37: 1 | G37: 1 | H37: 1 | I37: 1 | J37: 1 | K37: 1
A38: 法国海外 | B38: 黄涵涵 | C38: Chineseonline L第二节 | D38: 10.1 | N38: 是
A39: 法国海外 | B39: 黄胄雅 | C39: Chineseonline L第三节 | D39: 10.1 | N39: 是
A40: 西班牙 | B40: 季轩宇 | C40: 二十六课堂第十一节 | D40: 10.1 | N40: 是
A41: 意大利 | B41: 胡银伟 | C41: 三十课堂第八节 | D41: 10.1
A42: 希腊 | B42: 郑佳鸿 | C42: 十课堂第十节 | D42: 10.1 | N42: 是
A43: 西班牙 | B43: 张陈浩然 | C43: 二十八课堂7:10 | D43: 10.11 | N43: 是
A44: 西班牙 | B44: 瓦伦 | C44: 二十二课堂第八节 | D44: 10.11 | N44: 是
A46: 西班牙 | B46: 阮子乐 | C46: 九课堂第一节 | D46: 10.14 | E46: 1 | F46: 1 | G46: 1 | H46: 1 | I46: 1 | J46: 1 | K46: 1 | N46: 是
A47: 葡萄牙 | B47: 赵宇诺 | C47: 十三课堂第六节 | D47: 10.14
A48: 葡萄牙 | B48: 尹欣妍 | C48: 一课堂第八节 | D48: 10.14 | E48: 1 | F48: 1 | G48: 1 | H48: 1 | I48: 1 | J48: 1 | K48: 1 | L48: 是 | N48: 是
A49: 意大利 | B49: 胡凯奇 | C49: 二十三课堂第九节 | D49: 10.14 | E49: 1 | F49: 1 | G49: 1 | H49: 1 | I49: 1 | J49: 1 | K49: 1 | N49: 是
A50: 意大利 | B50: 胡美雪 | C50: 十一课堂第七节 | D50: 10.14 | N50: 是
A51: 意大利 | B51: 舒俊杰 | C51: 四十五课堂第九节 | D51: 10.14
A52: 葡萄牙 | B52: 尹芷妍 | C52: 十一课堂第七节 | D52: 10.14 | N52: 是
A53: 意大利 | B53: 姜欣怡 | C53: 四十五课堂第十节 | D53: 10.14 | N53: 是
A54: 奥地利 | B54: 莱欧 | C54: 三十一课堂第四节 | D54: 10.14 | E54: 1 | P54: 流失
A55: 西班牙 | B55: 裘鑫磊 | C55: 四十五课堂第九节 | D55: 10.14 | N55: 是
A56: 意大利 | B56: 姜可莹 | C56: 十一课堂第九节 | D56: 10.15 | N56: 是
A57: 意大利 | B57: 蔡雨烜 | C57: 三十一课堂第九节 | D57: 10.15 | E57: 1 | F57: 1 | G57: 1 | H57: 1 | I57: 1 | J57: 1 | K57: 1
A58: 奥地利 | B58: 陈昆意 | C58: 四十七课堂第九节 | D58: 10.15 | N58: 是
A59: 奥地利 | B59: 陈煜凡 | C59: 三十一课堂第四节 | D59: 10.15 | E59: 1 | F59: 1 | G59: 1 | H59: 1 | I59: 1 | J59: 1 | K59: 1 | N59: 是
A60: 奥地利 | B60: 林伟涛 | C60: 三十一课堂第四节 | D60: 10.15 | E60: 1 | P60: 流失
A61: 意大利 | B61: 郑澈 | C61: 四十三课堂第一节 | D61: 10.15 | E61: 1 | F61: 1 | G61: 1 | H61: 1 | I61: 1 | J61: 1 | K61: 1 | L61: 1 | N61: 是
A62: 葡萄牙 | B62: 潘豪 | C62: 二十七课堂第九节 | D62: 10.15 | N62: 是
A63: 葡萄牙 | B63: 潘均特 | C63: 二十七课堂第十节 | D63: 10.15
A64: 德国 | B64: 吴陈洁 | C64: 三十四课堂第十一节 | D64: 10.15 | E64: 1 | F64: 1 | G64: 1 | H64: 1 | I64: 1 | J64: 1 | K64: 1 | L64: 是 | N64: 是
A65: 比利时 | B65: 吴义明 | C65: 二十二课堂第五节 | D65: 10.15 | E65: 1 | F65: 1 | G65: 1 | H65: 失败
A66: 比利时 | B66: 吴莎霞 | C66: 二十二课堂第六节 | D66: 10.15 | E66: 1 | F66: 1 | G66: 1 | H66: 失败
A67: 葡萄牙 | B67: 封英豪 | C67: 四课堂第十一节 | D67: 10.15 | N67: 是
A68: 西班牙 | B68: 周叶曼妮 | C68: 第四课堂第三节 | D68: 10.15 | N68: 是
A69: 西班牙 | B69: 应烁琦 | C69: 四课堂第十一节 | D69: 10.15 | E69: 1 | F69: 1 | G69: 1 | H69: 1 | I69: 1 | J69: 1 | K69: 1 | L69: 是 | N69: 是
A70: 西班牙 | B70: 李文2、 | C70: 第四课堂第三节 | D70: 10.15 | E70: 1 | F70: 1 | G70: 1 | H70: 1 | I70: 1 | J70: 1 | K70: 1 | L70: 是 | N70: 是
A71: 西班牙 | B71: 李武 | C71: 第四课堂第三节 | D71: 10.16 | E71: 1 | F71: 1 | G71: 1 | H71: 1 | I71: 1 | J71: 1 | K71: 1 | L71: 是 | N71: 是
A72: 西班牙 | B72: 李斌2 | C72: 十课堂第二节 | D72: 10.16 | E72: 1 | F72: 1 | G72: 1 | H72: 1 | I72: 1 | J72: 1 | K72: 1 | N72: 是
A73: 西班牙 | B73: 朴民佑 | C73: 二十六课堂第十一节 | D73: 10.16 | E73: 1 | F73: 1 | G73: 1 | H73: 1 | I73: 1 | J73: 1 | K73: 1
A74: 葡萄牙 | B74: 程卓文 | C74: 四十五课堂第九节 | D74: 10.16 | N74: 是
A75: 意大利 | B75: 胡慧浩 | C75: 二十六课堂第六节 | D75: 10.16 | E75: 1 | F75: 1 | G75: 1 | H75: 1 | I75: 1 | J75: 1 | K75: 1
A76: 意大利 | B76: 胡嘉慧 | C76: 三十三课堂第七节 | D76: 10.16 | E76: 1 | F76: 1 | G76: 1 | H76: 1 | I76: 1 | J76: 1 | K76: 1 | N76: 是
A77: 意大利 | B77: 郑毅 | C77: 二课堂第三节 | D77: 10.16 | E77: 1 | F77: 1 | G77: 1 | H77: 1 | I77: 1 | J77: 1 | K77: 1 | L77: 是 | N77: 是
A78: 意大利 | B78: 范丽莎 | C78: 三十七课堂第一节 | D78: 10.16 | E78: 1 | F78: 1 | G78: 1 | H78: 1 | I78: 1 | J78: 0 | L78: 是 | N78: 是
A79: 西班牙 | B79: 赵俊彦 | C79: 四十三课堂第十节 | D79: 10.16 | E79: 1 | F79: 1 | G79: 1 | H79: 1 | I79: 1 | J79: 1 | K79: 1 | L79: 是 | N79: 是
A80: 捷克 | B80: 蔡沅秀 | C80: 十三课堂第六节 | D80: 10.16 | N80: 是
A81: 巴西 | B81: 周梓琳 | C81: 二十八课堂7:10 | D81: 10.16 | N81: 是
A82: 西班牙 | B82: 曾子航 | C82: 四十五课堂第九节 | D82: 10.16 | N82: 是
A83: 捷克 | B83: 蔡沅秀 | C83: 二十二课堂第五节 | D83: 10.17 | E83: 1 | F83: 1 | G83: 1 | H83: 1 | I83: 1 | J83: 1 | K83: 1 | N83: 是
A84: 西班牙 | B84: 董殷麒 | C84: 四十六课堂第七节 | D84: 10.17 | N84: 是
A85: 西班牙 | B85: 吴欧翔 | C85: 四十五课堂第九节 | D85: 10.17 | N85: 是
A86: 西班牙 | B86: 裘若萱 | C86: 四十一课堂第七节 | D86: 10.17 | N86: 是
A87: 西班牙 | B87: 周晨瑾 | C87: 十七课堂第二节 | D87: 10.17 | E87: 1 | F87: 1 | G87: 1 | H87: 1 | I87: 1 | J87: 1 | K87: 1 | L87: 是 | N87: 是
A88: 意大利 | B88: 蔡佳娴 | C88: 三十一课堂第四节 | D88: 10.17 | N88: 是 | P88: 流失
A89: 西班牙 | B89: 阙立文 | C89: 四课堂第五节 | D89: 10.17 | E89: 1 | F89: 1 | G89: 1 | H89: 1 | I89: 1 | J89: 1 | K89: 1 | L89: 是 | N89: 是
A90: 西班牙 | B90: 夏加楠 | C90: 三十一课堂第六节 | D90: 10.17 | E90: 0 | F90: 1 | G90: 1 | H90: 0 | I90: 1 | J90: 1 | K90: 1 | L90: 是 | N90: 是
A91: 西班牙 | B91: 郭俊涛 | C91: 二十四课堂第七节 | D91: 10.17 | E91: 1 | F91: 1 | G91: 1 | H91: 1 | I91: 1 | J91: 1 | K91: 1 | N91: 是
A92: 西班牙 | B92: 郭静怡1 | C92: 二十六课堂第四节 | D92: 10.17 | E92: 1 | F92: 1 | G92: 1 | H92: 1 | I92: 1 | J92: 1 | K92: 1 | N92: 是
A93: 西班牙 | B93: 王浩宇1 | C93: 四十六课堂第十一节 | D93: 10.17 | N93: 是
A94: 西班牙 | B94: 叶芷旋 | C94: 四十五课堂第九节 | D94: 10.17
A95: 西班牙 | B95: 李羽晨 | C95: 二十六课堂第七节 | D95: 10.17 | E95: 1 | F95: 1 | G95: 请长假 | H95: 试读失败 | L95: 是 | P95: 流失
A96: 西班牙 | B96: 胡诗琪 | C96: 十三课堂第十一节 | D96: 10.17 | E96: 1 | F96: 1 | G96: 1 | H96: 1 | I96: 1 | J96: 1 | K96: 1 | N96: 是
A97: 葡萄牙 | B97: 朱伊娜 | C97: 十三课堂第十一节 | D97: 10.18 | N97: 是
A98: 西班牙 | B98: 胡鑫磊1 | C98: 十三课堂第十一节 | D98: 10.18
A99: 西班牙 | B99: 叶芷涵 | C99: 七课堂第一节. | D99: 10.18 | E99: 1 | F99: 1 | G99: 1 | H99: 1 | I99: 1 | J99: 1 | K99: 1 | N99: 是
A100: 西班牙 | B100: 单亮策 | C100: 三十一课堂第六节 | D100: 10.18 | E100: 1 | F100: 1 | G100: 1 | H100: 1 | I100: 1 | J100: 1 | K100: 1 | N100: 是
A101: 西班牙 | B101: 陈涵1 | C101: 三十七课堂第六节 | D101: 10.18 | E101: 1 | F101: 1 | G101: 1 | H101: 试读失败 | P101: 流失
...
