Workbook

Sheet 《2020年试读名单-启蒙课》
A1: 序号 | B1: 测试时间 | C1: 国家 | D1: 城市 | E1: 时差 | F1: 家长微信名 | G1: 家长微信 | H1: 电话号码 | I1: 学生姓名 | J1: 缴费 | K1: 年龄 | L1: 性别 | M1: 有没有学过拼音 | N1: 是否需要双语老师 | O1: 家长自述程度及学习需求 | P1: 学习课程 | Q1: 测试结果 | R1: 排课安排 | S1: 来源 | T1: 组别 | U1: 业务员 | V1: 试读日期 | W1: 试课安排 | X1: 排课校区 | Y1: 是否在读 | Z1: 是否缴费 | AA1: 失败原因 | AB1: 课程单价 | AC1: 折扣 | AD1: 实收 | AE1: 首次收费时间
B2: 44013 | C2: 澳大利亚 | E2: 2 | F2: joanneys | G2: joanneys | I2: 黄若毅 | J2: =IFERROR(VLOOKUP(I2,Sheet1!A:B,2,FALSE),"zhaobudao") -> 是 | K2: 5 | L2: 男 | M2: 否 | N2: 是 | O2: 可以听得懂 但是不愿意开口说中文 | P2: 启蒙中文 | R2: 张倩 18:30 7.1 | S2: 介绍 | T2: 3 | U2: 翁珊珊 美丽妈妈介绍 | Y2: 1 | Z2: 1 | AA2: 1 | AB2: 116/课 | AC2: 一对一46+2 | AD2: 755.31 | AE2: 7.2日缴费
B3: 44014 | C3: 美国 | D3: 东部 | E3: 12 | H3: 001-7188082035 | I3: 梁彧博 | J3: =IFERROR(VLOOKUP(I3,Sheet1!A:B,2,FALSE),"zhaobudao") -> zhaobudao | K3: 8 | L3: 男 | M3: 否 | N3: 否 | O3: 希望哥哥和妹妹一起学，因为都学过五四快读，识字量差不多 | P3: 启蒙中文 | R3: 林玲玲 6:00 7.2 | S3: 介绍 | T3: 3 | U3: 张文红 | Y3: 1 | Z3: 1 | AA3: 1 | AB3: 116/课 | AC3: 一对一65+3 | AD3: 7540 | AE3: 7.6日缴费
B4: 44014 | C4: 美国 | D4: 东部 | E4: 12 | H4: 001-7188082035 | I4: 梁书婧 | J4: =IFERROR(VLOOKUP(I4,Sheet1!A:B,2,FALSE),"zhaobudao") -> zhaobudao | K4: 5 | L4: 女 | M4: 否 | N4: 否 | O4: 希望哥哥和妹妹一起学，因为都学过五四快读，识字量差不多 | P4: 启蒙中文 | R4: 林玲玲 7:00 7.2 | S4: 介绍 | T4: 3 | U4: 张文红
B5: 44014 | C5: 美国 | D5: 东部 | E5: 12 | F5: felicia | G5: chippiopio | H5: +1 9176671031 | I5: 齊藤鎮彥 | J5: =IFERROR(VLOOKUP(I5,Sheet1!A:B,2,FALSE),"zhaobudao") -> zhaobudao | K5: 5.5 | N5: 是 | P5: 启蒙数学 | R5: 卢爽 21:00 7.2 | S5: 微信 | T5: 3 | U5: 王可
B6: 44015 | C6: 美中 | E6: 13 | G6: Lily | H6: xc420695634 | I6: lexi | J6: =IFERROR(VLOOKUP(I6,Sheet1!A:B,2,FALSE),"zhaobudao") -> zhaobudao | K6: 4.5 | L6: 男 | M6: 否 | N6: 否 | O6: 会中文交流，认识一两百字 | P6: 启蒙 | R6: 童美英 8:00 7.3 | S6: 微信 | T6: 3 | U6: 王可
B7: 44015 | C7: 澳洲 | H7: +61 433603061 | I7: 车伊然 | J7: =IFERROR(VLOOKUP(I7,Sheet1!A:B,2,FALSE),"zhaobudao") -> zhaobudao | K7: 3.5 | M7: 否 | N7: 否 | O7: 可以交流 | P7: 启蒙 | R7: 吴岚 15:00 7.3 | S7: 微信 | T7: 3 | U7: 王可
B8: 44015 | C8: 加拿大 | H8: 无账号 | I8: 陈熙 | J8: =IFERROR(VLOOKUP(I8,Sheet1!A:B,2,FALSE),"zhaobudao") -> zhaobudao | K8: 3 | L8: 男 | M8: 否 | N8: 否 | O8: 零基础，交流可以，孩子很不愿意主动讲话 | P8: 启蒙 | R8: 许杰8:30 7.3 | S8: 微信 | T8: 1 | U8: 何家昌1
B9: 44015 | C9: 美国 | H9: 16504070006 | I9: 吴舒瑶 | J9: =IFERROR(VLOOKUP(I9,Sheet1!A:B,2,FALSE),"zhaobudao") -> 是 | L9: 女 | M9: 否 | N9: 否 | O9: 可以交流 | P9: 启蒙 | R9: 蒋铄 7:20 7.3 | S9: 微信 | T9: 3 | U9: 王可
B10: 44015 | C10: 加拿大 | H10: 17782889773 | I10: Nina | J10: =IFERROR(VLOOKUP(I10,Sheet1!A:B,2,FALSE),"zhaobudao") -> zhaobudao | K10: 4岁 | L10: 女 | M10: 否 | N10: 否 | O10: 会中文交流 零基础 | P10: 启蒙 | R10: 张倩 8:00 7.3 | T10: 白 | U10: 俞酉兰
B11: 44015 | C11: 马来西亚 | H11: 60122236813 | I11: 颜豪庆 | J11: =IFERROR(VLOOKUP(I11,Sheet1!A:B,2,FALSE),"zhaobudao") -> zhaobudao | K11: 3.5 | L11: 男 | M11: 否 | N11: 否 | O11: 会交流，零基础 | P11: 启蒙 | R11: 林玲玲 19:00 7.3 | T11: 白
B12: 44015 | C12: 美西 | E12: 15 | F12: wechunku | G12: klaviergirl91 | I12: Dana Lin | J12: =IFERROR(VLOOKUP(I12,Sheet1!A:B,2,FALSE),"zhaobudao") -> zhaobudao | K12: 6 | L12: 女 | O12: 三位数加法，基本九九乘法 | P12: 启蒙数学 | R12: 解一聪 8:40 7.3 | S12: 微信 | T12: 3 | U12: 程蕾
B13: 44015 | C13: 美国 | F13: Serena | G13: serena138 | H13: 1 5086157686 | I13: 乐乐 | J13: =IFERROR(VLOOKUP(I13,Sheet1!A:B,2,FALSE),"zhaobudao") -> zhaobudao | K13: 5岁 | L13: 女 | M13: 没有 | N13: 否 | O13: 中文一般，认识20个汉字 | P13: 启蒙中文 | R13: 许杰 7:30 7.3 | S13: 微信 | T13: 3 | U13: 毛益丹
B14: 44015 | C14: 美国 | F14: Serena | G14: serena138 | H14: 1 3303895044 | I14: 点点 | J14: =IFERROR(VLOOKUP(I14,Sheet1!A:B,2,FALSE),"zhaobudao") -> zhaobudao | K14: 快5岁 | L14: 女 | M14: 没有 | N14: 否 | O14: 有自己教她认字，进度是四五快读完成了第一册和第二册，平常在家里都说中文，希望后续学拼音 | P14: 启蒙中文 | R14: 许杰 7:30 7.3 | S14: 微信 | T14: 3 | U14: 毛益丹
B15: 44016 | C15: 澳大利亚悉尼 | H15: 416640906 | I15: camille | J15: =IFERROR(VLOOKUP(I15,Sheet1!A:B,2,FALSE),"zhaobudao") -> zhaobudao | K15: 2.5岁 3岁 | L15: 女 | M15: 没有 | N15: 需要 | O15: 小的两岁出头，大宝因为语言发育迟缓，跟小的差不多，中文会基本的沟通，也不是很懂。家长说试试看孩子能不能坐的住 | R15: 国内下午17:30-18:00蒋铄 | U15: 张仁波0
B16: 44016 | C16: 澳大利亚悉尼 | H16: 416640906 | I16: damier | J16: =IFERROR(VLOOKUP(I16,Sheet1!A:B,2,FALSE),"zhaobudao") -> zhaobudao | K16: 2.5岁 3岁 | L16: 女 | M16: 没有 | N16: 需要 | O16: 小的两岁出头，大宝因为语言发育迟缓，跟小的差不多，中文会基本的沟通，也不是很懂。家长说试试看孩子能不能坐的住 | R16: 国内下午17:30-18:00蒋铄 | U16: 张仁波0
B17: 44016 | C17: 加拿大多伦多 | H17: 5147466789 | I17: 王泰博 | J17: =IFERROR(VLOOKUP(I17,Sheet1!A:B,2,FALSE),"zhaobudao") -> zhaobudao | K17: 6岁 | L17: 男 | M17: 没有 | N17: 否 | O17: 认识几个字 喜欢攀岩 听说OK 家里尽力提供中文环境 | R17: 21：00-21:30许杰 | U17: 赵国花2
B18: 44016 | C18: 加拿大温哥华 | H18: 7789286579 | I18: 晨晨 | J18: =IFERROR(VLOOKUP(I18,Sheet1!A:B,2,FALSE),"zhaobudao") -> zhaobudao | K18: 5.5岁 | L18: 男 | M18: 没有 | N18: 否 数学 | O18: 学习数学哦，孩子零基础，没有学习过数学哦。喜欢卡通 | R18: 11：00-11:30解一聪 | U18: 高翱翔2
B19: 44016 | C19: 加拿大温哥华 | H19: 7789286579 | I19: 晨晨 | J19: =IFERROR(VLOOKUP(I19,Sheet1!A:B,2,FALSE),"zhaobudao") -> zhaobudao | K19: 5.5岁 | L19: 男 | M19: 没有 | N19: 否 | O19: 学习中文，孩子平时在家中文交流没有问题，没有学习过拼音什么的喜欢卡通 | R19: 9：00-9:30蒋铄 | U19: 高翱翔2
A20: 二次试读 | B20: 44017 | C20: 美国西海岸 | H20: 1 9192822200 | I20: 米明西 | J20: =IFERROR(VLOOKUP(I20,Sheet1!A:B,2,FALSE),"zhaobudao") -> zhaobudao | K20: 6岁 | L20: 男 | M20: 学过 | N20: 否 | O20: 没有系统学习，不过在看其他学中文的app。拼音基本都会，但是还是有一些不熟练， 而且拼的比较慢，某些字也会拼错， 像“无”字， 他会直接打u，不是wu；建议一年级上册五六单元，孩子话很多，会打断老师聊天，拼音发音二声容易读成四声。因为孩子觉得小学语文枯燥转过来的，孩子喜欢有趣的课程，老师尽量提升宝贝的兴趣 | R20: 国内早上7:00张倩 | U20: 毛益丹3
B21: 44016 | C21: 美国西海岸 | H21: 323 283 7396 | I21: 武雨桐 | J21: =IFERROR(VLOOKUP(I21,Sheet1!A:B,2,FALSE),"zhaobudao") -> zhaobudao | K21: 四岁 | L21: 女 | M21: 否 | N21: 是 | O21: 零基础，一般的对话可以，害羞喜欢画画粉色 大裙子 | R21: 国内早上八点半张倩 | U21: 刘巧芹2 | Y21: 1 | Z21: 1 | AA21: 1 | AB21: 96/课 | AC21: 一对一收一对二44 | AD21: 4224 | AE21: 7.6日缴费
B22: 44016 | C22: 美国西部 | H22: 1 6692566661 | I22: 小宝 | J22: =IFERROR(VLOOKUP(I22,Sheet1!A:B,2,FALSE),"zhaobudao") -> zhaobudao | K22: 快5岁 | M22: 没有 | N22: 否 | O22: 不会写字，会认100个字左右，交流的话中文很好，会很多成语，暂时不学拼音 | R22: 国内早上7:00吴岚 | U22: 毛益丹3
B23: 44016 | C23: 加拿大 | D23: 温哥华 | E23: 15 | F23: Liberty | G23: Liberty_feng | H23: +1 6043387728 | I23: 徐志镐 | J23: =IFERROR(VLOOKUP(I23,Sheet1!A:B,2,FALSE),"zhaobudao") -> zhaobudao | K23: 月底满3岁 | L23: 男 | M23: 否 | N23: 是 | O23: 会说粤语，和一点中文 不会说英文 | P23: 启蒙 | R23: 国内9点张媛媛 | S23: 扫一扫 | T23: 白 | U23: 俞酉兰
A24: 二次试读 | B24: 44017 | F24: 早上7:30张倩 | G24: 美东 | H24: 9176052667 | I24: Darren Ma | J24: =IFERROR(VLOOKUP(I24,Sheet1!A:B,2,FALSE),"zhaobudao") -> zhaobudao | K24: 6 | L24: 男 | M24: 否 | N24: 是 | O24: 孩子零基础，会说一点中文 | P24: 翁珊珊3
B25: 44017 | F25: 国内早上7点钟许杰 | G25: 加拿大 | H25: 17788296089 | I25: Nicole | J25: =IFERROR(VLOOKUP(I25,Sheet1!A:B,2,FALSE),"zhaobudao") -> zhaobudao | K25: 6.5 | L25: 女 | M25: 否 | N25: 是 | O25: 会说中文 不会写 有的时候听不懂 | P25: 启蒙 | T25: 白 | U25: 俞酉兰
B26: 44017 | C26: 美中 | E26: 13 | F26: rina | G26: rina4557715 | I26: Elina | J26: =IFERROR(VLOOKUP(I26,Sheet1!A:B,2,FALSE),"zhaobudao") -> zhaobudao | K26: 6 | L26: 女 | M26: 没有 | N26: 是 | O26: 有时会用中文交流 | P26: 中文 | S26: 微信 | T26: 3 | U26: 翁珊珊
B27: 44018 | C27: 美国 | D27: 西部 | E27: 15 | G27: 13807489455 | I27: 秦可伊 | J27: =IFERROR(VLOOKUP(I27,Sheet1!A:B,2,FALSE),"zhaobudao") -> zhaobudao | K27: 4岁半 | L27: 女 | M27: 否 | N27: 否 | O27: 妈妈在家教了一些字 | P27: 启蒙 | R27: 卢爽8:00 7.6 | T27: 3 | U27: 张霞
B28: 44019 | C28: 美国 | D28: 加利福尼亚 | E28: 15 | H28: 17788583038 | I28: Felicia | J28: =IFERROR(VLOOKUP(I28,Sheet1!A:B,2,FALSE),"zhaobudao") -> zhaobudao | K28: 5.5 | L28: 女 | M28: 否 | N28: 是 | O28: 没学过 一家的 一块上 | P28: 启蒙中文 | R28: 卢爽 7:00 7.7 | T28: 白 | U28: 俞酉兰
B29: 44019 | C29: 美国 | D29: 加利福尼亚 | E29: 15 | H29: 17788583038 | I29: Natasha | J29: =IFERROR(VLOOKUP(I29,Sheet1!A:B,2,FALSE),"zhaobudao") -> zhaobudao | K29: 4 | L29: 女 | M29: 否 | N29: 是 | O29: 没学过 一家的 一块上 | P29: 启蒙中文 | R29: 卢爽 7:00 7.7 | T29: 白 | U29: 俞酉兰
B30: 44019 | C30: 加拿大 | D30: 温哥华 | E30: 15 | H30: 7786808698 | I30: 陆子涵 | J30: =IFERROR(VLOOKUP(I30,Sheet1!A:B,2,FALSE),"zhaobudao") -> 是 | K30: 6 | L30: 女 | M30: 学过 | N30: 否 | O30: 从启蒙开始，20以内的加减法，扳着手指头算 | P30: 启蒙数学 | R30: 卢爽8:15 7.7 | U30: 任宏印
B31: 44019 | C31: 美国 | D31: 西部 | E31: 15 | H31: 13811239849 | I31: 卡卡 | J31: =IFERROR(VLOOKUP(I31,Sheet1!A:B,2,FALSE),"zhaobudao") -> zhaobudao | K31: 5 | L31: 男 | M31: 否 | N31: 否 | O31: 有在网络中文课，还没学拼音，有意向学拼音课 | P31: 启蒙中文 | R31: 卢爽 7:00 7.7 | S31: 微信 | T31: 3 | U31: 毛益丹

Sheet 2020.7
A1: 序号 | B1: 测试时间 | C1: 国家 | D1: 城市 | E1: 时差 | F1: 家长微信名 | G1: 家长微信 | H1: 电话号码 | I1: 学生姓名 | K1: 缴费 | L1: 年龄 | M1: 性别 | N1: 有没有学过拼音 | O1: 是否需要双语老师 | P1: 家长自述程度及学习需求 | Q1: 学习课程 | R1: 测试结果 | S1: 排课安排 | T1: 来源 | U1: 组别 | V1: 业务员 | W1: 试读日期 | X1: 试课安排 | Y1: 排课校区 | Z1: 是否在读 | AA1: 是否缴费 | AB1: 失败原因 | AC1: 课程单价 | AD1: 折扣 | AE1: 实收 | AF1: 首次收费时间
B2: 44013 | C2: 美国 | D2: 美东 | E2: 12 | F2: Yijie Liu | G2: cytotech | I2: 黄善泽 | J2: =TRIM(I2) -> 黄善泽 | K2: =IFERROR(VLOOKUP(J2,Sheet1!A:B,2,FALSE),"zhaobudao") -> zhaobudao | L2: 7 | M2: 男 | N2: 是 | O2: 否 | P2: 孩子之前学习过中文，家长说有二年级的程度，拼音会一点 | Q2: 中文 | R2: 一年级下册，发音不够标准，老师要强调 | S2: 刘钰兰；8:20；7.1 | T2: 微信 | U2: 2 | V2: 高翱翔 | Z2: 0 | AA2: 0
B3: 44013 | C3: 美国 | D3: 西部 | E3: 15 | F3: Jane | G3: zhuangdou2013 | I3: 邵子鑫 | J3: =TRIM(I3) -> 邵子鑫 | K3: =IFERROR(VLOOKUP(J3,Sheet1!A:B,2,FALSE),"zhaobudao") -> zhaobudao | L3: 13岁 | N3: 学过 | O3: 否 | P3: 在美国的中文学校学中文，开学马上升八年级，会拼音 | Q3: 中文 | R3: 三年级上册，一单元，发音标准，难一点的字不认识 | S3: 刘钰兰；9:00；7.1 | T3: 家长介绍 | U3: 3 | V3: 毛益丹
B4: 44013 | C4: 美国 | D4: 西部 | E4: 15 | F4: Jane | G4: zhuangdou2013 | I4: 邵子晗 | J4: =TRIM(I4) -> 邵子晗 | K4: =IFERROR(VLOOKUP(J4,Sheet1!A:B,2,FALSE),"zhaobudao") -> zhaobudao | L4: 11岁 | N4: 学过 | O4: 否 | P4: 在美国的中文学校学中文，开学马上升六年级，会拼音 | Q4: 中文 | R4: 建议从二下一单元开始，发音标准，表达理解可以。 | S4: 张璐；9:40；7.1 | T4: 家长介绍 | U4: 3 | V4: 毛益丹
B5: 44013 | C5: 美西 | E5: 15 | F5: 顽皮鼠 | G5: Wanpishu | I5: 李嘉宝 | J5: =TRIM(I5) -> 李嘉宝 | K5: =IFERROR(VLOOKUP(J5,Sheet1!A:B,2,FALSE),"zhaobudao") -> zhaobudao | L5: 7岁 | M5: 男 | N5: 学过一点 | O5: 否 | P5: 基本的听说没有问题，学过一点拼音 | Q5: 中文 | R5: 一年级上册，四单元秋天开始，拼音全认识，发音标准 | S5: 刘钰兰；9:40；7.1 | T5: 微信 | U5: 3 | V5: 毛益丹
B6: 44013 | C6: 加拿大 | D6: 多伦多 | E6: -12 | F6: 建华 | G6: yoo_hoo76 | I6: 金子鉴 | J6: =TRIM(I6) -> 金子鉴 | K6: =IFERROR(VLOOKUP(J6,Sheet1!A:B,2,FALSE),"zhaobudao") -> zhaobudao | L6: 7岁 | M6: 男 | N6: 有 | O6: 否 | P6: 拼音都学习过读的不标准 大概认识100多个汉字 | Q6: 中文 | R6: 学生发音不是很好，有带国外的口音，词汇量少，不太会组词，建议从一上四单元开始上课 | S6: 周虹 7:40 7-1 | T6: 微信 | U6: 2 | V6: 赵国花
B7: 44013 | C7: 加拿大 | E7: 12 | F7: Yulanda(莹) | G7: yy6479968110 | I7: 乐乐 | J7: =TRIM(I7) -> 乐乐 | K7: =IFERROR(VLOOKUP(J7,Sheet1!A:B,2,FALSE),"zhaobudao") -> zhaobudao | L7: 7 | M7: 女 | N7: 是 | O7: 否 | P7: 在当地有在学习 | Q7: 中文 | R7: 比较害羞，慢热，涉及到复韵母的读音会有点问题，建议从一上五六单元开始上课 | S7: 周虹 8:207-1 | T7: 微信 | U7: 1 | V7: 何家昌
B8: 44013 | C8: 美国 | D8: 中部 | E8: 13 | F8: Chaoying | G8: chaoyingz66 | I8: 陈凯琳 | J8: =TRIM(I8) -> 陈凯琳 | K8: =IFERROR(VLOOKUP(J8,Sheet1!A:B,2,FALSE),"zhaobudao") -> zhaobudao | L8: 10岁 | M8: 女 | N8: 学过 | O8: 否 | P8: 一二年级的水平 | Q8: 中文 | R8: 学生发音标准，朗读流畅，识字量大，建议从二下开始学习 | S8: 周虹 9:00 7-1 | T8: 家长介绍 | U8: 3 | V8: 毛益丹
B9: 44013 | C9: 澳大利亚 | E9: 2 | F9: DI | G9: diyu1065630866 | I9: 陈楚妍 | J9: =TRIM(I9) -> 陈楚妍 | K9: =IFERROR(VLOOKUP(J9,Sheet1!A:B,2,FALSE),"zhaobudao") -> zhaobudao | L9: 11 | M9: 女 | N9: 学过一点 | O9: 否 | P9: 学过一点，中文交流没问题 | Q9: 中文 | R9: 学生发音标准，朗读较流畅，识字量不错，建议从二上三四单元开始学起 | S9: 周虹 9:40 7-1 | T9: 家长介绍 | U9: 3 | V9: 王可 陈彦熹妈妈推荐
B10: 44013 | C10: 美国 | E10: 12 | G10: yinxianglan0521 | I10: 林文慧 | J10: =TRIM(I10) -> 林文慧 | K10: =IFERROR(VLOOKUP(J10,Sheet1!A:B,2,FALSE),"zhaobudao") -> zhaobudao | L10: 6岁半 | M10: 女 | N10: 否 | O10: 是 | P10: 家长说孩子基础很差 | Q10: 中文 | R10: 建议和哥哥一起上拼音课，表达不如哥哥，建议双语老师。 | S10: 张璐 7:40 7.1 | T10: 微信 | U10: 1 | V10: 胡兰
B11: 44013 | C11: 美国 | E11: 12 | G11: yinxianglan0521 | I11: 林文景 | J11: =TRIM(I11) -> 林文景 | K11: =IFERROR(VLOOKUP(J11,Sheet1!A:B,2,FALSE),"zhaobudao") -> zhaobudao | L11: 8岁半 | M11: 男 | N11: 否 | O11: 是 | P11: 中文基础比较差 | Q11: 中文 | R11: 建议从拼音课开始，非常活泼，中文理解表达一般。 | S11: 张璐 7:00 7.1 | T11: 微信 | U11: 1 | V11: 胡东东
B12: 44013 | C12: 美国 | D12: 西部 | E12: 15 | F12: 吴琳 | G12: k2d23p | I12: 小恩 | J12: =TRIM(I12) -> 小恩 | K12: =IFERROR(VLOOKUP(J12,Sheet1!A:B,2,FALSE),"zhaobudao") -> 是 | L12: 7岁 | N12: 没有 | O12: 否 | P12: 学过一册双双教材，认识一些字，不太擅长说句子，家里说中文，孩子听得懂。笔画也学了，想学拼音 | Q12: 中文 | R12: 从拼音课开始，理解表达一般。 | S12: 张璐；9:00；7.1 | T12: 介绍 | U12: 3 | V12: 毛益丹
B13: 44013 | C13: 美国 | D13: 纽约 | E13: 12 | F13: Rebecca | G13: aliceli520 | I13: 林以昊 | J13: =TRIM(I13) -> 林以昊 | K13: =IFERROR(VLOOKUP(J13,Sheet1!A:B,2,FALSE),"zhaobudao") -> zhaobudao | L13: 6 | M13: 男 | N13: 否 | O13: 否 | P13: 零基础，拼音aoe开始学 | Q13: 中文 | T13: 家长介绍 | U13: 2 | V13: 刘巧芹 乐芯妈妈介绍
B14: 44013 | C14: 美国 | D14: 纽约 | E14: 12 | F14: Liang | G14: chenxiaoxi_yu | I14: 陈睿萱 | J14: =TRIM(I14) -> 陈睿萱 | K14: =IFERROR(VLOOKUP(J14,Sheet1!A:B,2,FALSE),"zhaobudao") -> 是 | L14: 6 | M14: 女 | N14: 否 | O14: 是 | P14: 零基础，拼音aoe开始学 | Q14: 中文 | T14: 家长介绍 | U14: 2 | V14: 刘巧芹 乐芯妈妈介绍
B15: 44013 | C15: 美国 | D15: 纽约 | E15: 12 | F15: 晓霞 | G15: li2241984 | I15: 朱紫晴 | J15: =TRIM(I15) -> 朱紫晴 | K15: =IFERROR(VLOOKUP(J15,Sheet1!A:B,2,FALSE),"zhaobudao") -> 是 | L15: 快七岁 | M15: 女 | N15: 否 | O15: 否 | P15: 零基础，拼音aoe开始学 | Q15: 中文 | T15: 家长介绍 | U15: 2 | V15: 刘巧芹 乐芯妈妈介绍
B16: 44013 | C16: 美国 | D16: 纽约 | E16: 12 | F16: MaY。海外购 | G16: candy60701332 | I16: 林卡卡 | J16: =TRIM(I16) -> 林卡卡 | K16: =IFERROR(VLOOKUP(J16,Sheet1!A:B,2,FALSE),"zhaobudao") -> 是 | L16: 8 | M16: 男 | N16: 否 | O16: 否 | P16: 零基础，二月测试过，现在过来上一下正式课，在家中文交流 | Q16: 中文 | T16: 陈珊珊妈妈介绍 | U16: 2 | V16: 高翱翔
B17: 44013 | C17: 美国 | E17: 12 | G17: 冰雨 | I17: 子原 | J17: =TRIM(I17) -> 子原 | K17: =IFERROR(VLOOKUP(J17,Sheet1!A:B,2,FALSE),"zhaobudao") -> zhaobudao | L17: 8岁 | M17: 男 | N17: 学会 | O17: 否 | P17: 孩子学会拼音但是需要巩固。现在二年级 | Q17: 中文 | T17: 微信 | U17: 3 | V17: 张霞
B18: 44014 | C18: 美东 | E18: 12 | F18: Michelle🏘64 | G18: lz1314520 | I18: jia xin | J18: =TRIM(I18) -> jia xin | K18: =IFERROR(VLOOKUP(J18,Sheet1!A:B,2,FALSE),"zhaobudao") -> zhaobudao | L18: 13 | N18: 学过一点 | O18: 否 | P18: 中文交流没问题，以前学过中文 | Q18: 中文 | R18: 朗读不流畅，学过拼音，但是有遗忘，建议从gkh后面复韵母前面开始学 | S18: 周虹 7:40 7-2 | T18: 微信 | U18: 3 | V18: 翁珊珊
B19: 44014 | C19: 美东 | E19: 12 | F19: Michelle🏘65 | G19: lz1314521 | I19: jia ye | J19: =TRIM(I19) -> jia ye | K19: =IFERROR(VLOOKUP(J19,Sheet1!A:B,2,FALSE),"zhaobudao") -> zhaobudao | L19: 11 | N19: 否 | O19: 否 | P19: 中文交流没问题 | Q19: 中文 | R19: 朗读不流畅，学过拼音，但是有遗忘，弟弟的基础比哥哥差，aoe有混淆，四个声调不会读，建议从aoe开始学。 | S19: 周虹 8：20 7-2 | T19: 微信 | U19: 3 | V19: 翁珊珊
B20: 44014 | C20: 美东 | E20: 12 | F20: Michelle🏘66 | G20: lz1314522 | I20: jia yu | J20: =TRIM(I20) -> jia yu | K20: =IFERROR(VLOOKUP(J20,Sheet1!A:B,2,FALSE),"zhaobudao") -> zhaobudao | L20: 10 | N20: 否 | O20: 否 | P20: 中文交流没问题 | Q20: 中文 | R20: 建议从zcs开始，中文理解表达可以，很活泼开朗。 | S20: 张璐 8：20 7.2 | T20: 微信 | U20: 3 | V20: 翁珊珊
B21: 44014 | C21: 澳洲 | E21: 2 | F21: 谢 | G21: angelz2015 | I21: 谢家佑 | J21: =TRIM(I21) -> 谢家佑 | K21: =IFERROR(VLOOKUP(J21,Sheet1!A:B,2,FALSE),"zhaobudao") -> zhaobudao | L21: 8 | M21: 男 | N21: 否 | O21: 否 | P21: 可以交流 | Q21: 中文 | T21: 介绍 | U21: 3 | V21: 张文红
B22: 44014 | C22: 美国 | D22: 西部 | E22: 15 | F22: 兰 | G22: lan9176604297 | I22: 林水 | J22: =TRIM(I22) -> 林水 | K22: =IFERROR(VLOOKUP(J22,Sheet1!A:B,2,FALSE),"zhaobudao") -> 是 | L22: 13岁 | M22: 男 | O22: 否 | P22: 这是12岁的男孩,平常在家说中文,平常可以用中文交流,可是不懂看和写,或者看得不多 | Q22: 中文 | R22: 零基础，完全不会，aoe开始学习，三声发音不准确 | S22: 刘钰兰；7:40；7.2 | T22: 家长介绍 | V22: 任宏印
B23: 44014 | C23: 澳洲 | E23: 2 | F23: Chloe Mi | G23: chloe4671 | I23: 米嘟 | J23: =TRIM(I23) -> 米嘟 | K23: =IFERROR(VLOOKUP(J23,Sheet1!A:B,2,FALSE),"zhaobudao") -> zhaobudao | L23: 8 | M23: 男 | N23: 是 | O23: 否 | P23: 哥哥学过拼音，中文交流 | Q23: 中文 | R23: 建议从iu ui开始，有学过但是忘了一部分，后面的拼音有的会有的不会。或者从一上秋天开始学。理解表达可以，读课文时发音不标准。有点害羞 | S23: 张璐 13:30 7.2 | T23: 微信 | U23: 3 | V23: 杨斌
B24: 44014 | C24: 澳洲 | E24: 2 | F24: Chloe Mi | G24: chloe4671 | I24: 米哒 | J24: =TRIM(I24) -> 米哒 | K24: =IFERROR(VLOOKUP(J24,Sheet1!A:B,2,FALSE),"zhaobudao") -> zhaobudao | L24: 6 | M24: 女 | N24: 否 | O24: 否 | P24: 零基础，中文交流 | Q24: 中文 | R24: 建议从拼音开始学起，识字量大，理解表达表达能力好。比较活泼。 | S24: 张璐 14:10 7.2 | T24: 微信 | U24: 3 | V24: 杨斌
B25: 44014 | C25: 美国 | D25: 加州 | E25: -15 | F25: cathrny | G25: cathrnygao | I25: 赵宏康 | J25: =TRIM(I25) -> 赵宏康 | K25: =IFERROR(VLOOKUP(J25,Sheet1!A:B,2,FALSE),"zhaobudao") -> zhaobudao | L25: 10 | M25: 男 | N25: 否 | O25: 是 | P25: 零基础，最好有双语老师，喜欢数学 | Q25: 中文 | R25: 建议从拼音开始，从aoe或者ie ei开始，理解表达都可以，有一点点害羞。 | S25: 张璐 9:40 7.2 | T25: 家长介绍 | U25: 0 | V25: 王晨 逸凌妈咪介绍
B26: 44014 | C26: 美西 | E26: 15 | F26: 胡俊洛杉矶 | G26: hujun107904875 | I26: Shawn | J26: =TRIM(I26) -> Shawn | K26: =IFERROR(VLOOKUP(J26,Sheet1!A:B,2,FALSE),"zhaobudao") -> zhaobudao | L26: 8 | M26: 男 | N26: 学过 | O26: 否 | P26: 一直在学中文，估计相当于国内一年级的水平 | Q26: 中文 | R26: 建议从一下3 4单元开始学，表达理解都可以，家长想要app可以让学生自己去看作业和课程回顾。 | S26: 张璐 11:00 7.2 | T26: 微信 | U26: 3 | V26: 程蕾
B27: 44014 | C27: 美国 | D27: 东部 | E27: 12 | F27: cuizh | G27: jiangcuizh | I27: 陈净灵 | J27: =TRIM(I27) -> 陈净灵 | K27: =IFERROR(VLOOKUP(J27,Sheet1!A:B,2,FALSE),"zhaobudao") -> 是 | L27: 8 | M27: 女 | N27: 否 | O27: 最好 | P27: 只会一点点，拼音不会，喜欢跳舞 | Q27: 中文 | R27: 孩子每周一节课学过2年中午，有中文基础，会写会认简单的汉字。基础汉语交流都能听懂，可以说简单的词。第一次上课，有一点害羞，后面可以跟上节奏，积极回答老师问题。建议从一年级上册拼音开始学起。 | S27: 刘依琳 21:30 7.2 | T27: 家长介绍 | U27: 2 | V27: 平金军 林宇妈妈介绍 | Z27: 1 | AA27: 1 | AB27: 1 | AC27: 56/课 | AD27: 一对四65 | AE27: 515 | AF27: 7.6日缴费
B28: 44014 | C28: 西班牙 | E28: 6 | F28: 张晶晶Serena | G28: Z139017555 | I28: 潘昊泉 | J28: =TRIM(I28) -> 潘昊泉 | K28: =IFERROR(VLOOKUP(J28,Sheet1!A:B,2,FALSE),"zhaobudao") -> 是 | L28: 8 | M28: 男 | N28: 否 | O28: 否 | P28: 中文字认识300多个 | Q28: 中文 | T28: 微信 | U28: 1 | V28: 何家昌
B29: 44014 | C29: 加拿大 | E29: 15 | F29: 杨柳Willow | G29: Davidestelle | I29: 奕赫 | J29: =TRIM(I29) -> 奕赫 | K29: =IFERROR(VLOOKUP(J29,Sheet1!A:B,2,FALSE),"zhaobudao") -> zhaobudao | L29: 7 | M29: 男 | N29: 有 | O29: 否 | P29: 一年级的课自学完了 | Q29: 中文 | R29: 二上第一单元，发音标准，思路清晰 | S29: 刘钰兰；9:40；7.3 | T29: 家长介绍 | V29: LAWERNCE1妈妈介绍
B30: 44015 | C30: 加拿大 | E30: 15 | F30: Nancy 佳 | G30: nancy-kejia | I30: Nina | J30: =TRIM(I30) -> Nina | K30: =IFERROR(VLOOKUP(J30,Sheet1!A:B,2,FALSE),"zhaobudao") -> zhaobudao | L30: 4 | M30: 女 | N30: 否 | O30: 否 | P30: 零基础 | Q30: 启蒙 | T30: 扫码 | U30: 白 | V30: 俞酉兰
B31: 44015 | C31: 加拿大 | E31: 15 | F31: tingting | G31: wxid_9207ly4bzg2s22 | I31: Lillian | J31: =TRIM(I31) -> Lillian | K31: =IFERROR(VLOOKUP(J31,Sheet1!A:B,2,FALSE),"zhaobudao") -> zhaobudao | L31: 4.7 | M31: 女 | N31: 否 | O31: 是 | P31: 会说广东话和英文，不会说中文 | Q31: 启蒙 | T31: 扫码 | U31: 白 | V31: 俞酉兰
B32: 44015 | C32: 美东 | E32: 12 | F32: Mickey | G32: HUA812985471 | I32: 铭烁 | J32: =TRIM(I32) -> 铭烁 | K32: =IFERROR(VLOOKUP(J32,Sheet1!A:B,2,FALSE),"zhaobudao") -> zhaobudao | L32: 7 | M32: 男 | N32: 否 | O32: 否 | P32: 在国内上幼儿园中班，在家说中文 | Q32: 中文 | R32: 中文沟通流畅，零基础，建议从拼音开始学。 | S32: 周虹 7:40 7.3 | T32: 微信 | U32: 3 | V32: 杨斌
B33: 44015 | C33: 美国 | D33: 纽约 | E33: -12 | F33: 幸福来临 | G33: xiu123m | I33: 陈煾则 | J33: =TRIM(I33) -> 陈煾则 | K33: =IFERROR(VLOOKUP(J33,Sheet1!A:B,2,FALSE),"zhaobudao") -> zhaobudao | L33: 9 | M33: 男 | N33: 一点 | O33: 否 | P33: 会一点拼音 | Q33: 中文 | R33: 中文沟通流畅，零基础，建议从拼音开始学。 | S33: 周虹 8:10 7.3 | T33: 微信 | U33: 0 | V33: 王晨
B34: 44015 | C34: 美东 | E34: 12 | F34: Venus@Compass 917.88 | G34: lemontree859 | I34: 黄梓瑄 | J34: =TRIM(I34) -> 黄梓瑄 | K34: =IFERROR(VLOOKUP(J34,Sheet1!A:B,2,FALSE),"zhaobudao") -> zhaobudao | L34: 12 | N34: 否 | O34: 否 | P34: 中文交流 | Q34: 中文 | R34: 两姐妹程度一般，会拼音，中文能听懂一些，词汇量识字量很少 ，建议从一上四单元开始上课 | S34: 周虹 8:20 7.3 | T34: 微信 | U34: 3 | V34: 翁珊珊 | Z34: 1 | AA34: 1 | AB34: 1 | AC34: 96/课 | AD34: 一对二18 | AE34: 492.8 | AF34: 7.8日缴费
B35: 44015 | C35: 美东 | E35: 12 | F35: Venus@Compass 917.88 | G35: lemontree859 | I35: 黄奕瑄 | J35: =TRIM(I35) -> 黄奕瑄 | K35: =IFERROR(VLOOKUP(J35,Sheet1!A:B,2,FALSE),"zhaobudao") -> zhaobudao | L35: 10 | N35: 否 | O35: 否 | P35: 中文交流 | Q35: 中文 | R35: 两姐妹程度一般，会拼音，中文能听懂一些，词汇量识字量很少 ，建议从一上四单元开始上课 | S35: 周虹 8:20 7.3 | T35: 微信 | U35: 3 | V35: 翁珊珊 | Z35: 1 | AA35: 1 | AB35: 1 | AC35: 96/课 | AD35: 一对二18 | AE35: 492.8 | AF35: 7.8日缴费
B36: 44015 | C36: 美国 | E36: 15 | F36: Helen | G36: wanglin880120 | I36: 王桠楠 | J36: =TRIM(I36) -> 王桠楠 | K36: =IFERROR(VLOOKUP(J36,Sheet1!A:B,2,FALSE),"zhaobudao") -> zhaobudao | L36: 6 | M36: 女 | N36: 无 | O36: 否 | P36: 在家说中文，零基础，没有学过中文，家里给她念过故事书，有点不太理解。 | Q36: 中文 | R36: 比较害羞，不怎么说话，家里都是说中文，能用中文沟通，但是不是很能理解，零基础，建议从拼音开始学起。 | S36: 包海燕 9:20 7.3 | T36: 微信 | U36: 2 | V36: 丁阮琪
B37: 44015 | C37: 美国 | E37: 15 | G37: rich858598 | I37: 蔡昊泽 | J37: =TRIM(I37) -> 蔡昊泽 | K37: =IFERROR(VLOOKUP(J37,Sheet1!A:B,2,FALSE),"zhaobudao") -> zhaobudao | L37: 8 | M37: 男 | N37: 是 | O37: 否 | P37: 上过中文课，有点基础，但是对中文课兴趣不大 | Q37: 中文 | R37: 零基础，十分不配合，上课要妈妈在旁边，不喜欢说，全程不在状态 | S37: 刘钰兰；9:00；7.3 | T37: 家长介绍 | U37: 1 | V37: 邢国栋 锦鹏妈妈介绍
B38: 44015 | C38: 美中 | E38: 13 | F38: bin | G38: binr2005 | I38: Daisy yu | J38: =TRIM(I38) -> Daisy yu | K38: =IFERROR(VLOOKUP(J38,Sheet1!A:B,2,FALSE),"zhaobudao") -> zhaobudao | L38: 6岁 | M38: 女 | N38: 有 | O38: 否 | P38: 一年级的水平，可以交流 | Q38: 中文 | R38: 建议从一上第四单元秋天开始，可以拼读有些慢，理解和表达一般。比较活泼。 | S38: 张璐 7:00 7.3 | T38: 微信 | U38: 3 | V38: 程蕾 | Z38: 1 | AA38: 1 | AB38: 1 | AC38: 53/课 | AD38: 一对四130 | AE38: 6890 | AF38: 7.7日开始每天1000，转一礼拜
B39: 44015 | C39: 美东 | E39: 12 | F39: 碧兰 | G39: wxidtbslgh9xr412 | I39: Jinyi jing | J39: =TRIM(I39) -> Jinyi jing | K39: =IFERROR(VLOOKUP(J39,Sheet1!A:B,2,FALSE),"zhaobudao") -> zhaobudao | L39: 9 | M39: 女 | N39: 学过 | O39: 否 | P39: 当地二年级的水平 | Q39: 中文 | R39: 大姐，二姐，三姐可以一起从一上第四单元开始，弟弟要从拼音开始学起。拼读有点慢，理解和表达一般，认字量一般，很活泼。 | S39: 张璐 8:20 7.3 | T39: 微信 | U39: 3 | V39: 程蕾
B40: 44015 | C40: 美国 | D40: 纽约 | E40: 12 | F40: 建武 | G40: a9176827476 | I40: 高鹏 | J40: =TRIM(I40) -> 高鹏 | K40: =IFERROR(VLOOKUP(J40,Sheet1!A:B,2,FALSE),"zhaobudao") -> zhaobudao | L40: 12 | M40: 男 | N40: 是 | O40: 否 | P40: 家长说孩子学习过拼音，不过知道现在还记不记得，平时在家用中文交流 | Q40: 中文 | R40: 建议从一上第七单元开始，小朋友非常爱学习，自己会从课文里找生字，理解表达一般。 | S40: 张璐 9:00 7.3 | T40: 家长介绍 | U40: 2 | V40: 高翱翔 陈城杰妈妈介绍
B41: 44015 | C41: 加拿大 | E41: 15 | F41: 🇨🇦Cherry S | G41: Cherrysheung18 | I41: Nicole wang | J41: =TRIM(I41) -> Nicole wang | K41: =IFERROR(VLOOKUP(J41,Sheet1!A:B,2,FALSE),"zhaobudao") -> zhaobudao | L41: 6岁半 | M41: 女 | N41: 否 | O41: 是 | P41: 零基础 | Q41: 中文 | R41: 从拼音开始，家长要求双语老师，孩子表达理解都可以，活泼。 | S41: 张璐 10:20 7.3 | T41: 微信 | U41: 1 | V41: 何家昌
A42: 6.3 | B42: 44015 | C42: 美国 | D42: 东部 | E42: 12 | F42: Lu | G42: QQLU0827 | I42: 卢俊灿 | J42: =TRIM(I42) -> 卢俊灿 | K42: =IFERROR(VLOOKUP(J42,Sheet1!A:B,2,FALSE),"zhaobudao") -> 是 | L42: 9 | M42: 男 | N42: 否 | O42: 否 | P42: 学过一点 认识的字不多 | Q42: 中文 | R42: aoe开始，零基础，发音不标准，声调要强调 | S42: 刘钰兰；7:40；7.3 | T42: 家长介绍 | U42: 白 | V42: 张明浩1妈妈介绍 徐晓晓
B43: 44015 | C43: 美国 | D43: 东部 | E43: 12 | F43: Lu | G43: QQLU0827 | I43: 卢俊宏 | J43: =TRIM(I43) -> 卢俊宏 | K43: =IFERROR(VLOOKUP(J43,Sheet1!A:B,2,FALSE),"zhaobudao") -> zhaobudao | L43: 10 | M43: 男 | N43: 否 | O43: 否 | P43: 学过一点 认识的字不多 | Q43: 中文 | R43: aoe开始，零基础，发音不标准，声调要强调 | S43: 刘钰兰；8:20；7.3 | T43: 家长介绍 | U43: 白 | V43: 张明浩1妈妈介绍 徐晓晓
B44: 44015 | C44: 美东 | E44: 12 | F44: Amy欣卉 | G44: amygong | I44: Zion Hu | J44: =TRIM(I44) -> Zion Hu | K44: =IFERROR(VLOOKUP(J44,Sheet1!A:B,2,FALSE),"zhaobudao") -> zhaobudao | L44: 8 | M44: 男 | N44: 学过 | O44: 否 | P44: 学过济南中文一年级课本 | Q44: 中文 | T44: 微信 | U44: 3 | V44: 程蕾
B45: 44015 | C45: 美东 | E45: 12 | F45: Amy欣卉 | G45: amygong | I45: Vivian Hu | J45: =TRIM(I45) -> Vivian Hu | K45: =IFERROR(VLOOKUP(J45,Sheet1!A:B,2,FALSE),"zhaobudao") -> zhaobudao | L45: 6 | M45: 女 | N45: 学过 | O45: 否 | P45: 学过济南中文一年级课本 | Q45: 中文 | T45: 微信 | U45: 3 | V45: 程蕾
B46: 44015 | C46: 意大利 | E46: 6 | F46: 王需要 | G46: fabiomarco | I46: 诸启湖 | J46: =TRIM(I46) -> 诸启湖 | K46: =IFERROR(VLOOKUP(J46,Sheet1!A:B,2,FALSE),"zhaobudao") -> zhaobudao | L46: 15 | M46: 男 | N46: 是 | O46: 否 | P46: 拼音可以，教到小学二年级下册，掌握会快一点，但是忘的也快 | Q46: 中文 | R46: 大的教到小学二年级下册，小的一年级上册。小的有一点学习困难证，会比其他的小孩慢一点，需要跟耐心的老师。大的掌握会快一点，但是忘的也快 | S46: 刘依琳 16:00 7.3 | T46: 微信 | U46: 1 | V46: 何家昌
B47: 44015 | C47: 意大利 | E47: 6 | F47: 王需要 | G47: fabiomarco | I47: 诸启翔 | J47: =TRIM(I47) -> 诸启翔 | K47: =IFERROR(VLOOKUP(J47,Sheet1!A:B,2,FALSE),"zhaobudao") -> zhaobudao | L47: 13 | M47: 男 | N47: 有学过一些 | O47: 否 | P47: 小的一年级上册，拼音一般，声调老教不会，有一点学习困难证，会比其他的小孩慢一点，需要跟耐心的老师 | Q47: 中文 | R47: 大的教到小学二年级下册，小的一年级上册。小的有一点学习困难证，会比其他的小孩慢一点，需要跟耐心的老师。大的掌握会快一点，但是忘的也快 | S47: 刘依琳 16:00 7.3 | T47: 微信 | U47: 1 | V47: 何家昌
B48: 44015 | C48: 意大利 | E48: 6 | F48: 碎格 | G48: HUHAIXlA369 | I48: 周素丽 | J48: =TRIM(I48) -> 周素丽 | K48: =IFERROR(VLOOKUP(J48,Sheet1!A:B,2,FALSE),"zhaobudao") -> 是 | L48: 14 | M48: 女 | N48: 是 | O48: 否 | P48: 过半个学期在中国 | Q48: 中文 | T48: 微信 | U48: 1 | V48: 何家昌
B49: 44015 | C49: 意大利 | E49: 6 | F49: 碎格 | G49: HUHAIXlA369 | I49: 周熠 | J49: =TRIM(I49) -> 周熠 | K49: =IFERROR(VLOOKUP(J49,Sheet1!A:B,2,FALSE),"zhaobudao") -> 是 | L49: 11 | M49: 男 | N49: 否 | O49: 否 | P49: 没上过中文，零基础 | Q49: 中文 | T49: 微信 | U49: 1 | V49: 何家昌
B50: 44015 | C50: 美国 | E50: 12 | F50: 小柔 | G50: xiaorou1979 | I50: 陈懿 | J50: =TRIM(I50) -> 陈懿 | K50: =IFERROR(VLOOKUP(J50,Sheet1!A:B,2,FALSE),"zhaobudao") -> zhaobudao | L50: 6 | M50: 男 | N50: 否 | O50: 否 | P50: 一年级上册数学加减法有点混淆、 | Q50: 数学 | U50: 1 | V50: 李华
B51: 44016 | C51: 美国 | E51: 12 | F51: Renee | G51: yun-90 | I51: 林炜羲 | J51: =TRIM(I51) -> 林炜羲 | K51: =IFERROR(VLOOKUP(J51,Sheet1!A:B,2,FALSE),"zhaobudao") -> 是 | L51: 9 | M51: 男 | N51: 否 | O51: 否 | P51: 没有学过 | Q51: 中文 | T51: 微信 | U51: 3 | V51: 张霞 | Z51: 1 | AA51: 1 | AB51: 1 | AC51: 116/课 | AD51: 一对一65 | AE51: 1067 | AF51: 7.6日缴费
B52: 44016 | C52: 美东 | E52: 12 | F52: tommy | G52: tommyma201 | I52: Darren Ma | J52: =TRIM(I52) -> Darren Ma | K52: =IFERROR(VLOOKUP(J52,Sheet1!A:B,2,FALSE),"zhaobudao") -> zhaobudao | L52: 6 | N52: 没有 | O52: 是 | P52: 家里教了一点中文日常的句子 | Q52: 中文 | R52: 建议YCT（强烈建议）或者认字课开始，零基础，需要双语老师，尽可能带孩子做些游戏让他有兴趣。 | S52: 张璐 8:20 7.4 | T52: 家长介绍 | U52: 3 | V52: 翁珊珊 陈冠燊妈妈推荐
B53: 44016 | C53: 美国 | D53: 西部 | E53: 15 | F53: FB | I53: 张梓谦 | J53: =TRIM(I53) -> 张梓谦 | K53: =IFERROR(VLOOKUP(J53,Sheet1!A:B,2,FALSE),"zhaobudao") -> zhaobudao | L53: 9 | M53: 男 | O53: 是 | R53: 建议从拼音开始，可以听懂部分因为会广东话，普通话不会，表达靠英文需要双语老师，家长要求繁体字。 | S53: 张璐 10:20 7.4 | T53: 微信 | U53: 2 | V53: 赵国花
B54: 44016 | C54: 美国 | D54: 加州 | E54: -15 | F54: cathrny | G54: cathrnygao | I54: Melissa | J54: =TRIM(I54) -> Melissa | K54: =IFERROR(VLOOKUP(J54,Sheet1!A:B,2,FALSE),"zhaobudao") -> zhaobudao | L54: 7 | M54: 女 | N54: 否 | O54: 是 | P54: 零基础，最好有双语老师，喜欢画画 | Q54: 中文 | R54: 建议从拼音课开始，理解表达一般，认字量低，活泼。 | S54: 张璐 9:00 7.4 | T54: 逸凌妈咪介绍 | U54: 0 | V54: 王晨
B55: 44016 | C55: 美国 | D55: 纽约 | E55: 12 | F55: ALisa美国代 | G55: lh16468468 | I55: 胡俊浩 | J55: =TRIM(I55) -> 胡俊浩 | K55: =IFERROR(VLOOKUP(J55,Sheet1!A:B,2,FALSE),"zhaobudao") -> zhaobudao | L55: 12 | M55: 男 | N55: 有 | O55: 否 | P55: 中文基础中等，口语流利，之前学习过拼音 | Q55: 中文 | R55: 建议从一下5单元开始学习，有点害羞，家长想让孩子多写，理解很好表达一般。 | S55: 张璐 7:00 7.4 | T55: 微信 | U55: 2 | V55: 高翱翔
B56: 44016 | C56: 美国 | D56: 西部 | E56: 15 | F56: Huimin | G56: bluedolphinn | I56: 余之悦 | J56: =TRIM(I56) -> 余之悦 | K56: =IFERROR(VLOOKUP(J56,Sheet1!A:B,2,FALSE),"zhaobudao") -> zhaobudao | L56: 10 | M56: 女 | N56: 是 | O56: 否 | P56: 开学五年级 读写估计国内一年级水平 | Q56: 中文 | R56: 一上七八单元，发音标准，沟通没有问题，识字量不多 | S56: 刘钰兰；9:40；7.4 | T56: 家长介绍 | U56: 白 | V56: kayla时妈妈介绍俞酉兰
B57: 44016 | C57: 美国 | D57: 西部 | E57: 15 | F57: Huimin | G57: bluedolphinn | I57: 阎诗云 | J57: =TRIM(I57) -> 阎诗云 | K57: =IFERROR(VLOOKUP(J57,Sheet1!A:B,2,FALSE),"zhaobudao") -> zhaobudao | L57: 8 | M57: 女 | N57: 是 | O57: 是 | P57: 会拼音 一年级水平 有些不能听懂 需要老师在说到不懂的时候英文翻译一下 | Q57: 中文 | R57: 建议从一年级上册第四单元开始，认字量不多，有点害羞，家长不希望有太多作业怕吓到小朋友。 | S57: 张璐 9:40 7.4 | T57: 家长介绍 | U57: 白 | V57: kayla时妈妈介绍俞酉兰
B58: 44016 | C58: 美国 | D58: 西部 | E58: 15 | F58: 双囍妈 | G58: lydiazhang99 | I58: 张飞廉 | J58: =TRIM(I58) -> 张飞廉 | K58: =IFERROR(VLOOKUP(J58,Sheet1!A:B,2,FALSE),"zhaobudao") -> zhaobudao | L58: 10 | M58: 男 | N58: 是 | O58: 否 | P58: 是暨南大学出版社出版四年级语文 | Q58: 中文 | R58: 一下一二单元，发音标准，很主动，识字量比较多，难一点的词语不理解意思 | S58: 刘钰兰；10:20；7.4 | T58: 家长介绍 | U58: 白 | V58: 余之悦妈妈介绍俞酉兰
B59: 44016 | C59: 加拿大 | D59: 温哥华 | E59: 15 | F59: Jessica | G59: pcnnlljj | I59: 张贵恩 | J59: =TRIM(I59) -> 张贵恩 | K59: =IFERROR(VLOOKUP(J59,Sheet1!A:B,2,FALSE),"zhaobudao") -> zhaobudao | L59: 8 | M59: 女 | N59: 是 | O59: 否 | P59: 学完拼音 | Q59: 中文 | R59: 建议从一上第七单元开始，家长想多让孩子表达，理解可以，表达一般，识字量不多。 | S59: 张璐 11：00 7.4 | T59: 扫一扫 | U59: 白 | V59: 俞酉兰
B60: 44016 | C60: 加拿大 | D60: 温哥华 | E60: 15 | F60: Jessica | G60: pcnnlljj | I60: 张婷恩 | J60: =TRIM(I60) -> 张婷恩 | K60: =IFERROR(VLOOKUP(J60,Sheet1!A:B,2,FALSE),"zhaobudao") -> zhaobudao | L60: 6 | M60: 女 | N60: 是 | O60: 否 | P60: 学完拼音 | Q60: 中文 | R60: 一上四单元秋天开始，拼音会，可以沟通，zc要老师强调 | S60: 刘钰兰；11:00；7.4 | T60: 扫一扫 | U60: 白 | V60: 俞酉兰
B61: 44016 | C61: 美东 | E61: 12 | G61: Bella 美国买手 | H61: Ting-duo1314 | I61: 王灿宇 | J61: =TRIM(I61) -> 王灿宇 | K61: =IFERROR(VLOOKUP(J61,Sheet1!A:B,2,FALSE),"zhaobudao") -> zhaobudao | L61: 7 | M61: 男 | N61: 没有 | O61: 否 | P61: 没学过，会说 | Q61: 中文 | R61: aoe开始，零基础，四声发音不标准，可以中文沟通 | S61: 刘钰兰；7:40；7.4 | T61: 微信 | U61: 3 | V61: 王可
B62: 44016 | C62: 美东 | E62: 12 | G62: Bella 美国买手 | H62: Ting-duo1314 | I62: 王凯琳 | J62: =TRIM(I62) -> 王凯琳 | K62: =IFERROR(VLOOKUP(J62,Sheet1!A:B,2,FALSE),"zhaobudao") -> zhaobudao | L62: 5 | M62: 女 | N62: 没有 | O62: 否 | P62: 没学过，会说 | Q62: 中文 | R62: aoe开始，零基础，喜欢画画，时间久专注力不够，可以中文沟通 | S62: 刘钰兰；8:20；7.4 | T62: 微信 | U62: 3 | V62: 王可
B63: 44017 | C63: 美中 | E63: 13 | F63: rina | G63: rina4557715 | I63: Elina | J63: =TRIM(I63) -> Elina | K63: =IFERROR(VLOOKUP(J63,Sheet1!A:B,2,FALSE),"zhaobudao") -> zhaobudao | L63: 6 | M63: 女 | N63: 没有 | O63: 是 | P63: 有时会用中文交流 | Q63: 中文 | T63: 微信 | U63: 3 | V63: 翁珊珊
B64: 44017 | C64: 美西 | E64: 15 | F64: 田宇全 | G64: yuquantian | I64: 田家华 | J64: =TRIM(I64) -> 田家华 | K64: =IFERROR(VLOOKUP(J64,Sheet1!A:B,2,FALSE),"zhaobudao") -> zhaobudao | L64: 9 | M64: 男 | N64: 学过 | O64: 否 | P64: 学过马丽平教材，后来学过新双双，是第四册打酱油的程度，学过拼音 | Q64: 中文 | T64: 微信 | U64: 3 | V64: 翁珊珊
B65: 44018 | C65: 加拿大 | D65: 温哥华 | E65: 15 | F65: 🇨🇦Cherry S | G65: Cherrysheung18 | I65: Nicole | J65: =TRIM(I65) -> Nicole | K65: =IFERROR(VLOOKUP(J65,Sheet1!A:B,2,FALSE),"zhaobudao") -> zhaobudao | L65: 6.5 | M65: 女 | N65: 否 | O65: 是 | P65: 会说不会写 有点不能理解 | Q65: 启蒙 | T65: 扫一扫 | U65: 白 | V65: 俞酉兰
B66: 44018 | C66: 美东 | E66: 12 | F66: 方方土 | G66: daimeng18 | I66: evan | J66: =TRIM(I66) -> evan | K66: =IFERROR(VLOOKUP(J66,Sheet1!A:B,2,FALSE),"zhaobudao") -> zhaobudao | L66: 7 | M66: 男 | N66: 会一点 | O66: 否 | P66: 拼音不熟练，大概认识一两百个字 | Q66: 中文 | R66: 中文听说流畅，拼音以前学过，但是到gkh就不认识了，拼读不够熟练，建议从一上拼音bpmf开始学 | S66: 周虹 7:00 7.6 | T66: 微信 | U66: 3 | V66: 程蕾
B67: 44018 | C67: 美东 | E67: 12 | F67: 方方土 | G67: daimeng18 | I67: yiguo | J67: =TRIM(I67) -> yiguo | K67: =IFERROR(VLOOKUP(J67,Sheet1!A:B,2,FALSE),"zhaobudao") -> zhaobudao | L67: 12 | M67: 男 | N67: 学过 | O67: 否 | P67: 大概小学三年级水平，但是有好几年没学了 | Q67: 中文 | R67: 学生听说没有问题，朗读时第三声容易读错，建议从一下三四单元开始学 | S67: 周虹 8:20 7.6 | T67: 微信 | U67: 3 | V67: 程蕾
B68: 44018 | C68: 加拿大 | E68: 15 | G68: lovebabydou | I68: 小瓜 | J68: =TRIM(I68) -> 小瓜 | K68: =IFERROR(VLOOKUP(J68,Sheet1!A:B,2,FALSE),"zhaobudao") -> zhaobudao | L68: 7 | M68: 男 | N68: 否 | O68: 否 | P68: 零基础 | Q68: 中文 | R68: 零基础，建议从拼音开始学 | S68: 周虹 9:00 7.6 | T68: 微信 | U68: 1 | V68: 何家昌
B69: 44018 | C69: 美西 | E69: 15 | F69: 婧瑗 | G69: Jingly104 | I69: 王姝曼 | J69: =TRIM(I69) -> 王姝曼 | K69: =IFERROR(VLOOKUP(J69,Sheet1!A:B,2,FALSE),"zhaobudao") -> zhaobudao | L69: 8 | M69: 女 | N69: 是 | O69: 否 | P69: 学过拼音但很基础 | Q69: 中文 | R69: 一上册七八单元，发音标准，中文沟通流畅 | S69: 刘钰兰；7:40；7.6 | T69: 微信 | U69: 3 | V69: 翁珊珊 | Z69: 1 | AA69: 1 | AB69: 1 | AC69: 71/课 | AD69: 一对三65+3 | AE69: 两人合交$1315 | AF69: 7.7日缴费
B70: 44018 | C70: 美西 | E70: 15 | F70: 婧瑗 | G70: Jingly104 | I70: 王姝慈 | J70: =TRIM(I70) -> 王姝慈 | K70: =IFERROR(VLOOKUP(J70,Sheet1!A:B,2,FALSE),"zhaobudao") -> zhaobudao | L70: 6 | M70: 女 | N70: 是 | O70: 否 | P70: 学过拼音但很基础 | Q70: 中文 | R70: 拼音aoe开始，不太喜欢说话，认识少量字，不会拼音 | S70: 刘钰兰；8:20；7.6 | T70: 微信 | U70: 3 | V70: 翁珊珊 | Z70: 1 | AA70: 1 | AB70: 1 | AC70: 71/课 | AD70: 一对三65+3 | AE70: 两人合交$1315 | AF70: 7.7日缴费
B71: 44018 | C71: 美西 | E71: 15 | F71: 学萍 | G71: zeng75120 | I71: 曾妮琦 | J71: =TRIM(I71) -> 曾妮琦 | K71: =IFERROR(VLOOKUP(J71,Sheet1!A:B,2,FALSE),"zhaobudao") -> 是 | L71: 8 | M71: 女 | N71: 学过 | O71: 否 | P71: 可能是一年级的水平 | Q71: 中文 | R71: 一上秋天开始，会拼音，零基础，混血，听说比较费力，秋天这种不知道意思，上课不是很积极 | S71: 刘钰兰；9:00；7.6 | T71: 微信 | U71: 3 | V71: 程蕾
B72: 44019 | C72: 美东 | E72: 12 | F72: Julie | G72: wxid_3340483407922 | I72: 朱丽琪 | J72: =TRIM(I72) -> 朱丽琪 | K72: =IFERROR(VLOOKUP(J72,Sheet1!A:B,2,FALSE),"zhaobudao") -> zhaobudao | L72: 11 | M72: 女 | N72: 是 | O72: 否 | P72: 学两三年 会写字拼音 但有时候记得不是很清楚 | Q72: 中文 | R72: 姐姐的程度比弟弟好，识字量也比较大，建议从二下开始上课 | S72: 周虹；7:00；7.7 | T72: 微信 | U72: 3 | V72: 翁珊珊
B73: 44019 | C73: 美东 | E73: 12 | F73: Julie | G73: wxid_3340483407922 | I73: 朱于杰 | J73: =TRIM(I73) -> 朱于杰 | K73: =IFERROR(VLOOKUP(J73,Sheet1!A:B,2,FALSE),"zhaobudao") -> zhaobudao | L73: 10 | M73: 男 | N73: 是 | O73: 否 | P73: 和姐姐一起学的 | Q73: 中文 | R73: 跟姐姐相比，弟弟的朗读和识字量稍弱，建议从二上三四单元开始上课 | S73: 周虹；7:00；7.7 | T73: 微信 | U73: 3 | V73: 翁珊珊
B74: 44019 | C74: 美国 | D74: 纽约 | E74: 12 | F74: 雪宝宝 | G74: wxid_lvoqq6ltd7eh11 | I74: 蔡泽鑫 | J74: =TRIM(I74) -> 蔡泽鑫 | K74: =IFERROR(VLOOKUP(J74,Sheet1!A:B,2,FALSE),"zhaobudao") -> zhaobudao | L74: 11 | M74: 男 | N74: 是 | O74: 否 | P74: 口语流利，会拼音，大概有一年级下册的水平。跟胡俊浩是同学，应该程度差不多 | Q74: 中文 | R74: 一下四单元，沟通没问题，识字量丰富，难点词语不理解 | S74: 刘钰兰；7:40；7.7 | T74: 胡俊浩妈妈介绍 | U74: 2
B75: 44019 | C75: 美国 | E75: 13 | G75: wxid_2g04jkbfrxa622 | I75: tiffany | J75: =TRIM(I75) -> tiffany | K75: =IFERROR(VLOOKUP(J75,Sheet1!A:B,2,FALSE),"zhaobudao") -> zhaobudao | L75: 10 | N75: 否 | O75: 否 | P75: 零基础 | Q75: 中文 | R75: 零基础，aoe开始，声调不太会，没有写过字 | S75: 刘钰兰；9:00；7.7 | T75: 微信 | U75: 1 | V75: 李巧群
B76: 44019 | C76: 美国 | E76: 13 | G76: wxid_2g04jkbfrxa622 | I76: stephanie | J76: =TRIM(I76) -> stephanie | K76: =IFERROR(VLOOKUP(J76,Sheet1!A:B,2,FALSE),"zhaobudao") -> zhaobudao | L76: 7 | N76: 否 | O76: 否 | P76: 零基础 | Q76: 中文 | R76: 零基础，aoe开始，声调不太会，没有写过字 | S76: 刘钰兰；9:40；7.7 | T76: 微信 | U76: 1 | V76: 李巧群
B77: 44019 | C77: 美国 | D77: 西雅图 | E77: 15 | F77: yunfei | G77: A15220440777 | I77: OLIVIA | J77: =TRIM(I77) -> OLIVIA | K77: =IFERROR(VLOOKUP(J77,Sheet1!A:B,2,FALSE),"zhaobudao") -> zhaobudao | L77: 8 | M77: 女 | N77: 学过一点点 | O77: 是 | P77: 学过一点点拼音 会听会讲一点点中文 完全讲听不懂 | Q77: 中文 | R77: 建议从拼音开始学起，中文理解一般，表达弱，需要双语老师。 | S77: 张璐 7:00 7.7 | U77: 2 | V77: 赵国花
B78: 44019 | C78: 加州 | E78: 15 | H78: 17788583038 | I78: Felicia | J78: =TRIM(I78) -> Felicia | K78: =IFERROR(VLOOKUP(J78,Sheet1!A:B,2,FALSE),"zhaobudao") -> zhaobudao | L78: 5.5 | M78: 女 | N78: 否 | O78: 是 | P78: 没学过 一家的 一块上 | Q78: 启蒙 | S78: 卢爽 7:00 7.7 | U78: 白 | V78: 俞酉兰
B79: 44019 | C79: 加州 | E79: 15 | H79: 17788583038 | I79: Natasha | J79: =TRIM(I79) -> Natasha | K79: =IFERROR(VLOOKUP(J79,Sheet1!A:B,2,FALSE),"zhaobudao") -> zhaobudao | L79: 4 | M79: 女 | N79: 否 | O79: 是 | P79: 没学过 一家的 一块上 | Q79: 启蒙 | S79: 卢爽 7:00 7.7 | U79: 白 | V79: 俞酉兰
B80: 44019 | C80: 加拿大 | D80: 温哥华 | E80: 15 | H80: 7786808698 | I80: 陆子涵 | J80: =TRIM(I80) -> 陆子涵 | K80: =IFERROR(VLOOKUP(J80,Sheet1!A:B,2,FALSE),"zhaobudao") -> 是 | L80: 6 | M80: 女 | N80: 学过 | O80: 否 | P80: 从启蒙开始，20以内的加减法，扳着手指头算 | S80: 卢爽8:15 7.7 | V80: 任宏印
B81: 44019 | C81: 美国西部 | E81: 15 | H81: 13811239849 | I81: 卡卡 | J81: =TRIM(I81) -> 卡卡 | K81: =IFERROR(VLOOKUP(J81,Sheet1!A:B,2,FALSE),"zhaobudao") -> zhaobudao | L81: 5 | M81: 男 | N81: 否 | O81: 否 | P81: 有在网络中文课，还没学拼音，有意向学拼音课 | S81: 卢爽 7:00 7.7 | T81: 微信 | U81: 3 | V81: 毛益丹

Sheet Sheet1
A1: 叶文浩1 | B1: 是
A2: 叶鋆睿 | B2: 是
A3: 何子恒 | B3: 是
A4: 吉娜 | B4: 是
A5: 宋崇铭 | B5: 是
A6: 吴楚惟 | B6: 是
A7: 吕泽歆 | B7: 是
A8: 小恩 | B8: 是
A9: 吴炳铨 | B9: 是
A10: 林泽锴1 | B10: 是
A11: 胡昊阳 | B11: 是
A12: 胡昊阳 | B12: 是
... A250: 张皓轩 | B250: 是

Sheet 2020.6
A1: 2020.6月 新生接待试读表 业务员：测+读 老师：试读两次
A2: 序号 | B2: 测试时间 | C2: 国家 | D2: 城市 | E2: 时差 | F2: 家长微信名 | G2: 家长微信 | H2: 电话号码 | I2: 学生姓名 | J2: 年龄 | K2: 性别 | L2: 有没有学过拼音 | M2: 是否需要双语老师 | N2: 家长自述程度及学习需求 | O2: 学习课程 | P2: 测试结果 | Q2: 排课安排 | R2: 来源 电话 微信 报第二门课 学生兄妹 家长介绍（哪个家长写到CC一栏 和你的名字一起） | S2: 组别 | T2: 业务员 | U2: 试读日期 | V2: 试课安排 | W2: 排课校区 | X2: 是否在读 | Y2: 是否缴费 | Z2: 失败原因 | AA2: 课程单价 | AB2: 折扣 | AC2: 实收 | AD2: 首次收费时间
A3: 1 | B3: 6.1 | C3: 美国 | D3: 东部 | E3: 12 | F3: Stella Hang | G3: hualeihang | I3: 蔡乐全 | J3: 13 | K3: 男 | L3: 学过 | M3: 否 | N3: 中文交流，马立平六年级 | O3: 中文 | P3: 学生有学过中文，识字量不错，但是有多遗忘的，建议从一下三四单元开始学习 | Q3: 周虹 7:40 6.1 | R3: 微信 | S3: 3 | T3: 杨斌 | Z3: 家长觉得价格贵，失联
A4: 2 | B4: 6.1 | C4: 美国 | D4: 亚特兰大 | E4: -12 | F4: 涂华 | G4: tuhua_us | I4: 轩辕瀚 | J4: 9 | K4: 女 | L4: 大致 | M4: 否 | N4: 二年级或三年级，500识字量 | O4: 中文 | Q4: 言智02 22:05 6.1 | R4: 家长介绍 | S4: 0 | T4: 王晨 诗瑶妈咪介绍 | V4: 兼 | Z4: 一起参加试课，指名试黄莺老师的课，但是家长希望上课内容是根据当地学习的中文知识帮助孩子加强辅导，在和老师沟通时不是很开心，黄老师也因为时间因素推脱，不愿意接课。
A5: 3 | B5: 6.1 | C5: 美国 | D5: 亚特兰大 | E5: -12 | F5: tracy | G5: tracyyiwenyan | I5: 杨乐乐 | J5: 8 | K5: 女 | L5: 大致 | M5: 否 | N5: 二年级或三年级，识字量100+没有统计计算过 | O5: 中文 | Q5: 言智02 22:05 6.1 | R5: 家长介绍 | S5: 0 | T5: 王晨 诗瑶妈咪介绍 | V5: 兼 | Z5: 一起参加试课，指名试黄莺老师的课，但是家长希望上课内容是根据当地学习的中文知识帮助孩子加强辅导，在和老师沟通时不是很开心，黄老师也因为时间因素推脱，不愿意接课。
A6: 4 | B6: 6.1 | C6: 美国 | D6: 西部 | E6: 15 | F6: Lingo | G6: LingoZheng | I6: 朱天胤 | J6: 7 | K6: 男 | L6: 学过 | M6: 否 | N6: 拼音已经会了初步学了一年级的中文字 | O6: 中文 | P6: 建议一上第四单元《小小的船》开始，测的秋天，生字部分不认识，很好学，跟老师互动很好，主动学习 | Q6: 黄礼云；8:20；6.1 | R6: 家长介绍 | S6: 3 | T6: 杨斌 张晗妈妈介绍 | Z6: 有个夏令营七月份结束到时再排课
A7: 5 | B7: 6.1 | C7: 美国 | D7: 西部 | E7: 15 | F7: G A 李子 | G7: Mara311 | I7: 吕艾黎 | J7: 7 | K7: 女 | L7: 学过 | M7: 否 | N7: 中文交流拼音没问题 | O7: 中文 | P7: 学生正在国外上一下第二单元第四课《四个太阳》，建议接着往下学，学生程度很好，偶尔会记混字，比如块和快，组词造句都很ok，接受能力强 | Q7: 黄礼云；7:40；6.1 | R7: 家长介绍 | S7: 3 | T7: 杨斌 朱天胤妈妈介绍 | Z7: 有个夏令营七月份结束到时再排课
A8: 6 | B8: 6.1 | C8: 新西兰 | D8: 奥克兰 | E8: 4 | F8: iudi | G8: ludizhangatnz | I8: 张之沐 | J8: 8 | K8: 男 | L8: 会 | M8: 否 | N8: 在学国内人教版语文二年级，有点不爱学习 | O8: 中文 | P8: 学生正在上二上第四单元，下一课学《黄山奇石》，建议接着往下上，学生程度还可以，写字笔画不错 | Q8: 黄礼云；13：00；6.1 | R8: 微信 | S8: 2 | T8: 泮攀
A9: 7 | B9: 6.1 | C9: 美国 | D9: 西部 | E9: 15 | F9: Amelia | G9: Amelia130920 | I9: Angela | J9: 5.5 | K9: 女 | L9: 否 | M9: 否 | N9: 中文交流，孩子想学 | O9: 启蒙中文 | Q9: 卢爽7：00 6.1 | R9: 微信 | S9: 3 | T9: 杨斌 | Z9: 家庭矛盾，孩子的学习不归妈妈管向她要爸爸联系方式也不愿意给
A10: 8 | B10: 6.1 | C10: 美国 | D10: 中部 | E10: 13 | F10: 辛运昕 | G10: x117653201 | H10: 6469799899 | I10: 王紫萱 | J10: 6 | K10: 女 | L10: 没有 | M10: 否 | N10: 会说，不怎么会写，会简单的六个韵母 | O10: 启蒙中文 | Q10: 卢爽8:20 6.1 | R10: 微信 | S10: 3 | T10: 程蕾 | Z10: 价格高
A11: 9 | B11: 6.1 | C11: 美国 | D11: 东部 | E11: 12 | F11: 玲 | G11: NJHLing | I11: 黄家睿 | J11: 5 | K11: 女 | L11: 否 | M11: 否 | N11: 在家用中文交流，不识字，家长希望能提高她的听说能力，增大理解，和词汇，之后才识字 | O11: 启蒙中文 | P11: 会说中文，刚开始比较腼腆，孩子活泼可爱，上的是测试ppt，家长说不想让孩子识字，先锻炼她的表达能力和听说能力，建议上启蒙课 | Q11: 卢爽6:00 6.1 | R11: 微信 | S11: 3 | T11: 翁珊珊
A12: 10 | B12: 6.1 | C12: 美西 | D12: 旧金山 | E12: 15 | F12: 夜猫不睡 | G12: lixinglisa | H12: +1 5203018387 | I12: 麦麦 | J12: 4岁半 | K12: 女 | L12: 否 | M12: 否 | N12: 中文口语流利，识字量250-300左右，能读短文。小孩子很不喜欢网课这种形式，完全没接触过拼音，偏旁部首知道一些 | O12: 启蒙中文 | Q12: 卢爽10:30 6.1 | R12: 微信 | S12: 3 | T12: 毛益丹 | Z12: 已经两次试课了，老师没调整好难度，所以教的小孩子都会，家长觉得没必要，和自己在家里教的差不多，并且家长不想学拼音的，所有没办法推小学语文
A13: 11 | B13: 6.1 | C13: 澳洲 | D13: 悉尼 | E13: 2 | F13: Evonne | G13: Evonne912266755 | H13: 610430808878 | I13: 何一依 | J13: 2.5岁 | K13: 女 | L13: 否 | M13: 否 | N13: 交流可以，吐字不清楚 | O13: 启蒙中文 | Q13: 孙恺悦18：30 6.1 | R13: 微信 | S13: 3 | T13: 张文红
A14: 12 | B14: 6.2 | C14: 美西 | D14: 圣何塞 | E14: 15 | F14: Lorraine Lu | G14: wwayway | I14: 陆时安 | J14: 快7岁 | K14: 男 | L14: 学过 | M14: 否 | N14: 学过拼音和一些中文字，和悟空识字一部分 | O14: 中文 | P14: 建议一下二、三单元开始，认字较多，词汇不理解。说话比较慢，会回应老师，不热情。 | Q14: 刘钰兰；7:00；6.2 Chineseonline O 7:00 6.4 | R14: 微信 | S14: 3 | T14: 毛益丹 | V14: 白 | W14: 白 | X14: 1 | Y14: 1 | Z14: 1 | AA14: 56/课 | AB14: 一对四65课时 | AC14: 3640 | AD14: 6.4日缴费
A15: 13 | B15: 6.2 | C15: 美西 | D15: 旧金山 | E15: 15 | F15: miaoyan | G15: yan102713 | I15: 苏智恒 | J15: 快7岁 | L15: 学过 | M15: 否 | N15: 之前在唐人街上了一个学期中文，学过拼音，但不是很会，不反感学拼音 | O15: 中文 | P15: 建议aoe开始，猫狗小动物这些用中文都会讲，在家说粤语，爱说话。 | Q15: 刘钰兰；8:20；6.2 | R15: 微信 | S15: 3 | T15: 毛益丹 | Z15: 去其他机构了，小孩子更喜欢那个机构的课程
A16: 14 | B16: 6.2 | C16: 美国 | D16: 东部 | E16: 12 | F16: annie | G16: g9810104 | I16: 林进轩 | J16: 11 | K16: 男 | L16: 学过差不多忘了 | M16: 否 | N16: 二年级水平，会阅读水浒传三国演义。拼音学过但是差不多都忘了 | O16: 中文 | P16: 建议先学拼音，然后跟着三年级学习，上下册都可以，识字量丰富，认学度高 | Q16: 刘钰兰；9:00；6.2 Chineseonline T10 7:30 6.3 | R16: 微信 | S16: 3 | T16: 展旺 | V16: 兼 | W16: 兼 | X16: 1 | Y16: 1 | Z16: 1 | AA16: 116/课 | AB16: 一对一65课时 | AC16: 7540 | AD16: 6.3日缴费
A17: 15 | B17: 6.2 | C17: 美国 | E17: 12 | G17: Yhmay23 | I17: 黄博腾 | J17: 11岁 | K17: 男 | L17: 会一点 | M17: 否 | N17: 口语会一点简单的能听懂 | O17: 中文 | P17: 基本零基础，很多日常词不太会说，从你我他开始，测试学了天地人，学过拼音，一半记得一半不记得 | Q17: 黄礼云；7:40；6.2 言智16王秋平 6.6 周一周四周六7：50～8：20 | R17: 电话 | S17: 5 | T17: 胡东东 | V17: 兼 | X17: 1 | Y17: 1 | Z17: 1 | AA17: 96/课 | AB17: 一对二65+5课时 | AC17: 6240 | AD17: 6.3日缴费
A18: 16 | B18: 6.2 | C18: 美国 | D18: 纽约 | E18: 2 | F18: Cherie💕美国代购&ABM | G18: jinyun-530 | I18: 吴星桦 | J18: 10 | K18: 男 | L18: 有，不过忘记了 | M18: 否 | N18: 孩子之前学习过拼音，不过应该早就忘记了，认识二百子左右。喜欢画画 | O18: 中文 | P18: 阅读能力很强，识字量大，拼音不是很熟练，要复习一下复韵母和前后鼻韵母，建议从一下二单元开始 | Q18: 黄礼云；8：20；6.2 | R18: 家长介绍 | S18: 2 | T18: 高翱翔 彭梓瑜妈妈介绍 | Z18: 搬家最近没时间，说到低还是嫌弃价格高
A19: 17 | B19: 6.2 | C19: 美国 | D19: 西部 | E19: 15 | F19: bing gao | G19: binggaorw | I19: 高泊宇 | J19: 11 | K19: 男 | L19: 学过 | M19: 否 | N19: 在家讲中文，听说可以，学过一些 | O19: 中文 | P19: 一下第三单元，学生学了五年，但测下来感觉没有五年的程度，声调会搞混 | Q19: 黄礼云；10:20；6.2 Chineseonline H 11:40 6.4 | R19: 微信 | S19: 3 | T19: 王可 | V19: 白 | W19: 白 | X19: 1 | Y19: 1 | Z19: 1 | AA19: 56/课 | AB19: 一对四65课时 | AC19: 3240 | AD19: 6.5日缴费 | AE19: 四人团优惠400
A20: 18 | B20: 6.2 | C20: 美国 | D20: 旧金山 | E20: 15 | G20: helenali999 | I20: 潘笑然 | J20: 12岁 | K20: 女 | L20: 没有 | M20: 否 | N20: 阅读可以看中文小说，写的程度不高。口语可以沟通 | O20: 中文 | P20: 学生喜欢阅读，没有系统学过拼音，声母会读，韵母不会，建议从一上第三单元ai ei ui开始，学完第三单元后，直接跳到四年级下册的班级里，她的认字和听说能力达到了四年级水平，写字可能没那么好，但也还可以 | Q20: 黄礼云；11:30；6.2 | R20: 微信介绍 | S20: 5 | T20: 邢国栋 | X20: 1 | Y20: 1 | Z20: 1 | AA20: 59/课 | AB20: 一对四22+1课时 | AC20: 1298 | AD20: 6.15日缴费
A21: 19 | B21: 6.2 | C21: 美国 | D21: 东部 | E21: 12 | F21: 陈意（纽约人寿） | G21: yvonnechen13 | I21: 陈敏怡 | J21: 9岁 | K21: 女 | L21: 有接触过 | M21: 否 | N21: 口语很好，会写一些字，拼音也有接触过 | O21: 中文 | P21: 拼音学起，比较认真，文静。认字量大。 | Q21: 杨静；7:40；6.2 | R21: 微信 | S21: 3 | T21: 翁珊珊
A22: 20 | B22: 6.2 | C22: 美国 | D22: 西部 | E22: 15 | F22: 然（谭老师 | G22: TR3515 | I22: 储衍 | J22: 9岁 | L22: 学过 | M22: 否 | N22: 学过拼音，但记不住 | O22: 中文 | P22: 建议拼音学起，学生有点大舌头，妈妈说舌头有点问题，老师慢慢讲解可以理解，学生话比较多，过于活泼坐不住。 | Q22: 杨静，9:00；6.2 | R22: 微信 | S22: 3 | T22: 毛益丹 | Y22: 家长和我自己都觉得老师上课效果不好
A23: 21 | B23: 6.2 | C23: 美国 | D23: 西部 | E23: 15 | F23: bing gao | G23: binggaorw | I23: 高泊翔 | J23: 9 | K23: 男 | L23: 学过 | M23: 否 | N23: 在家讲中文，听说可以，比哥哥稍弱一些 | O23: 中文 | P23: 建议一上第六七单元开始学起，学的能力比较好，课文一些词语不理解，不太会造句 | Q23: 杨静；10:20；6.2 Chineseonline H 11:40 6.4 | R23: 微信 | S23: 3 | T23: 王可 | V23: 白 | W23: 白 | X23: 1 | Y23: 1 | Z23: 1 | AA23: 56/课 | AB23: 一对四65课时 | AC23: 3240 | AD23: 6.5日缴费 | AE23: 四人团优惠400
A24: 22 | B24: 6.2 | C24: 美国 | D24: 西部 | E24: 15 | F24: SaSa | G24: SaSa77343 | I24: Abby | J24: 8 | K24: 女 | L24: 学过一点 | M24: 否 | N24: 学过一点拼音，在当地学到一二年级，可以普通话交流 | O24: 中文 | P24: 一下第二三单元开始学起，学生过度害羞不开摄像头，程度很好 | Q24: 杨静；9:40；6.2 | R24: 微信 | S24: 3 | T24: 王可
A25: 23 | B25: 6.2 | C25: 美国 | D25: 东部 | E25: 12 | F25: joy | G25: joyce927956 | I25: 江乃全 | J25: 7 | K25: 男 | L25: 否 | M25: 否 | N25: 识字量50，口语程度只有幼儿园，爱好唱歌 | O25: 中文 | P25: 建议拼音学起，比较认真，不会组词，认字量在50个内 | Q25: 杨静；7;00;6.2 言智38 7：00 6-17 | R25: 推荐 | S25: 2 | T25: 平金军 | U25: 6.17 | V25: 兼 | W25: 兼 | X25: 1 | Y25: 1 | Z25: 1 | AA25: 56/课 | AB25: 一对四65 | AC25: 454 | AD25: 6.11日缴费
A26: 24 | B26: 6.2 | C26: 澳洲 | E26: 2 | F26: 449977992 | G26: 三只小猪 | H26: david449977992 | I26: 潼潼 | J26: 9 | K26: 女 | L26: 普通的会一些 | M26: 否 | N26: 识字两到三百，拼音会一些，喜欢读英文小说，希望严格一点的老师 | O26: 中文 | Q26: 黄礼云；15:00；6.2 | R26: 微信 | S26: 2 | T26: 罗焱
A27: 25 | B27: 6.2 | C27: 加拿大 | D27: 温哥华 | E27: 15 | F27: 钟博 | G27: 17788853261 | H27: +1 7788853261 | I27: 钟宝乐 | J27: 14 | K27: 男 | L27: 是 | M27: 否 | N27: 基础很差，能简单的用中文交流 | O27: 启蒙中文 | Q27: 孙婷婷8:30 6.2 | R27: 微信 | S27: 5 | T27: 赵峰 | Z27: 家长还是有意向让孩子学习中文的，但是对于HSK不是太了解，一节课180元价格嫌贵
A28: 26 | B28: 6.3 | C28: 美国 | H28: +86 18913946146 | I28: 豆宝 | J28: 4.5 | L28: 否 | M28: 否 | N28: 正常沟通 | O28: 启蒙中文 | Q28: 庄雪22:00 6.2 | R28: 微信 | S28: 5 | T28: 李波 | Z28: 去美术宝了 小朋友喜欢那边
A29: 27 | B29: 6.3 | C29: 加拿大 | E29: 12 | G29: Gillian | H29: zhuqu003 | I29: 马榆果 | J29: 4 | K29: 女 | L29: 否 | M29: 否 | N29: 在家家长自己有教过，日常交流没问题 | O29: 启蒙 | Q29: 李晓杰23:00 6.2 | R29: 微信 | S29: 1 | T29: 何家昌 | V29: 兼 | W29: 兼 | X29: 1 | Y29: 1 | Z29: 1 | AA29: 118/课 | AB29: 一对一30课时 | AC29: 3540 | AD29: 6.3日缴费
A30: 28 | B30: 6.3 | C30: 英国 | E30: 7 | F30: 瞌睡 | G30: baobeicz | I30: 常艺霏 | J30: 8岁 | K30: 女 | L30: 是 | M30: 否 | N30: 学过学前班，会一些拼音，有些识字基础，可以日常对话 | O30: 中文 | Q30: 任宏印 ；16:00； 6.2 ChineseonlineA 16:00 6.3 | R30: 家长介绍 | S30: 1 | T30: 何家昌 安纹畅妈妈介绍 | V30: 白 | W30: 白 | X30: 1 | Y30: 1 | Z30: 1 | AA30: 56/课 | AB30: 一对四65课时 | AC30: 3640 | AD30: 6.3日缴费
A31: 29 | B31: 6.3 | C31: 美西 | E31: 15 | F31: SUSU素素 硅谷 VC | G31: SusuLiugo | I31: 冯浩齐 | J31: 7 | K31: 男 | L31: 学过一点 | M31: 是 | O31: 中文 | P31: 一上第八单元开始学起，读没问题，句子不理解，不会组词和造句，孩子比较顽皮坐不住。双语 | Q31: 杨静；7:00；6.3 | R31: 微信 | S31: 3 | T31: 王可 | X31: 1 | Y31: 1 | Z31: 1 | AA31: 56/课 | AB31: 一对四65课时 | AC31: 3640 | AD31: 6.30日缴费
A32: 30 | B32: 6.3 | C32: 美国 | D32: 纽约 | E32: 12 | G32: zhoulipi-9827 | I32: jayden | J32: 8岁 | K32: 男 | L32: 没有 | M32: 否 | N32: 沟通可以但是没有基础 | O32: 中文 | P32: 零基础，学生比较调皮，容易注意力不集中，妈妈说想要报一对一的班级，建议从拼音开始学起。 | Q32: 周虹 7:00 6.3 Chineseonline N 7:40 6.5 | R32: 家长介绍 | S32: 5 | T32: 刘箫 哒哒家长介绍 | W32: 白 | X32: 1 | Y32: 1 | Z32: 1 | AA32: 56/课 | AB32: 一对四65+5课时 | AC32: 3640 | AD32: 6.3日缴费
A33: 31 | B33: 6.3 | C33: 美东 | D33: 东部 | E33: 12 | F33: 三宝麻麻 | G33: 无 | I33: 李圳楠 | J33: 10 | K33: 男 | L33: 学过一点 | M33: 是 | N33: 学过一点，学w | O33: 中文 | P33: 程度非常不错，学生的理解力很好，识字量跟不上，建议从一下开始上课 | Q33: 周虹 8:20 6.3 | R33: 介绍 | S33: 3 | T33: 展旺 | X33: 2 | Y33: 没有 | Z33: 同事竞争
A34: 32 | B34: 6.3 | C34: 美西 | D34: 旧金山 | E34: 15 | F34: Jajane | G34: wxid_e1af73193e12 | I34: 谭煦彤 | J34: 12 | K34: 女 | L34: 学过 | M34: 否 | N34: 当地学了7年了，想着重写作方面 | O34: 中文 | P34: 程度不错，识字量比较少，词汇量较多，组词造句比较好，建议从二上三四单元开开始学习 | Q34: 周虹 9:20 6.3 | R34: 微信 | S34: 3 | T34: 王可 | AB34: 孩子不喜欢
A35: 33 | B35: 6.3 | C35: 美西 | D35: 旧金山 | E35: 15 | F35: 林小欧 | G35: L9175185008 | I35: 谭煦迪 | J35: 8 | K35: 男 | L35: 学过 | M35: 否 | N35: 学了3年了，拼音没问题 | O35: 中文 | P35: 弟弟跟姐姐相对较差，识字量和词汇量都比较少，朗读较为流畅，建议从一上八单元或者一下开始学。 | Q35: 周虹 10:00 6.3 | R35: 微信 | S35: 3 | T35: 王可 | AB35: 孩子不喜欢
A36: 34 | B36: 6.3 | C36: 美国 | D36: 西部 | E36: 15 | F36: 川富 | G36: tang272251187yy | I36: 唐源 | J36: 10 | K36: 女 | L36: 学过 | M36: 否 | N36: 国内学了三年级，刚到美国一年，希望从五年级开始 | O36: 中文 | P36: 建议五上开始，所有生字都认识，文章表层含义理解，深层道理不理解，不会总结 | Q36: 刘钰兰；7:00；6.3 Chineseonline L 9：00 6.4 | R36: 微信 | S36: 3 | T36: 杨斌 | V36: 白 | W36: 白 | X36: 1 | Y36: 1 | Z36: 1 | AA36: 56/课 | AB36: 一对四65课时 | AC36: 3640 | AD36: 6.5日缴费
A37: 35 | B37: 6.3 | C37: 美国 | D37: 中部 | E37: -14 | F37: yoyo高 | G37: gaoqiumei00 | I37: 林尚锴 | J37: 11 | K37: 男 | L37: 有 | M37: 否 | N37: 去年暑假学了2个月中文 ，会看拼音识字，识字量不多 | O37: 中文 | P37: 建议一上四单元开始，拼音会，识字量一般。孩子有些害羞 | Q37: 刘钰兰；8:20；6.3 | R37: 微信 | S37: 0 | T37: 王忆超
A38: 36 | B38: 6.3 | C38: 加拿大 | E38: 15 | F38: tina | G38: tina9972 | I38: 方宝 | J38: 12 | K38: 女 | L38: 有 | M38: 否 | N38: 之前在我们这边学过 后面有3个月没学了，想来从新上课 但是不知道学到哪了 三四年级的程度 | O38: 中文 | P38: 建议四上开始学习，语言表达能力很好，字词有一些不理解意思 | Q38: 刘钰兰；10:20；6.3 Chineseonline F 11:40 6.5 ChineseonlineT10 9:40 6.18 | R38: 微信 | S38: 白 | T38: 俞酉兰 | U38: 6.5 | V38: 白 | W38: 兼 | X38: 1 | Y38: 1 | AA38: 56/课 | AB38: 一对四65课时 | AC38: 3640 | AD38: 6.18缴费
A39: 37 | B39: 6.3 | C39: 美东 | D39: 东部 | E39: 12 | F39: 三宝麻麻 | G39: 无 | I39: 李圳洋 | J39: 9 | K39: 男 | L39: 学过会一点 | M39: 是 | N39: 学过一点，没有老大好 | O39: 中文 | P39: 一上第八单元开始学起，读的能力好，不会组词和造句。 | Q39: 杨静；7:40；6.3 | R39: 介绍 | S39: 3 | T39: 展旺 | Y39: 没有 | Z39: 同事竞争
A40: 38 | B40: 6.3 | C40: 美东 | D40: 纽约 | E40: 12 | F40: 林小欧 | G40: L9175185008 | I40: 王锦文 | J40: 6 | K40: 男 | L40: 没有 | M40: 否 | N40: 会说中文但是没有学过拼音 | O40: 中文 | P40: 建议拼音学起，配合度高很听话。说的能力好很爱表现，认字量50个内。 | Q40: 杨静；9:00；6.3 Chineseonline N 7:40 6.5 | R40: 微信 | S40: 3 | T40: 展旺 | V40: 白 | X40: 1 | Y40: 1 | Z40: 1 | AA40: 56/课 | AB40: 一对四65+2课时 | AC40: 3640 | AD40: 6.4日缴费
A41: 39 | B41: 6.3 | C41: 美国 | D41: 东部 | E41: 12 | F41: jiang ling | G41: wxid_0n3qi2eipjiu11 | I41: 林宇 | J41: 12 | K41: 男 | L41: 否 | M41: 要 | N41: 中文基础0 | O41: 中文 | P41: 建议拼音学起，反映有点慢说中文的能力不太好，要双语老师。 | Q41: 杨静；9:40；6.3 言智07 7:30 6.7 | R41: 家长介绍 | S41: 2 | T41: 平金军 江为翔家长介绍 | V41: 兼 | W41: 兼 | X41: 1 | Y41: 1 | Z41: 1 | AA41: 56/课 | AB41: 一对四65+5课时 | AC41: 3640 | AD41: 6.7日缴费
A42: 40 | B42: 6.3 | C42: 美国 | D42: 佛罗里达 罗德岱堡 | E42: 12 | F42: lin | G42: lin1982103 | I42: 郑安舜 | J42: 13 | K42: 男 | L42: 否 | M42: 是 | N42: 没学过拼音 口语不好就简单的一点点问候 | O42: 中文 | P42: 建议拼音开始学起，哥哥和弟弟一起学起。弟弟能力好一点，哥哥拼音0基础，妈妈希望基础扎实一点一起从头学起拼音。 | Q42: 杨静；10:20；6.3 | R42: 微信 | S42: 1 | T42: 何家昌
A43: 41 | B43: 6.3 | C43: 美国 | D43: 佛罗里达 罗德岱堡 | E43: 12 | F43: lin | G43: lin1982103 | I43: 郑昭航 | J43: 9 | K43: 男 | L43: 否 | M43: 是 | N43: 没学过拼音 口语不好就简单的一点点问候 | O43: 中文 | P43: 建议拼音开始学起，哥哥和弟弟一起学起。弟弟能力好一点，哥哥拼音0基础，妈妈希望基础扎实一点一起从头学起拼音。 | Q43: 杨静；10:20；6.3 | R43: 微信 | S43: 1 | T43: 何家昌
A44: 42 | B44: 6.3 | C44: 美国 | D44: 旧金山 | E44: 15 | G44: helenali999 | I44: 潘凡语 | J44: 7岁 | K44: 女 | L44: 一点 | M44: 否 | N44: 刚开始学，可以正常中文沟通，认识一些字 | O44: 中文 | P44: 建议拼音j;q;x开始学起，认字课的字都认得，学生比较乖巧。 | Q44: 杨静；11:00；6.3 | R44: 微信 | S44: 5 | T44: 邢国栋 | X44: 1 | Y44: 1 | Z44: 1 | AA44: 59/课 | AB44: 一对四22+1 | AC44: 1298 | AD44: 6.15日缴费
A45: 43 | B45: 6.3 | C45: 法国 | E45: 6 | F45: Marjorie Horder | G45: Rhum1979 | I45: Marjorie | K45: 女 | L45: 一点 | M45: 是 | N45: 学过HSK1级，想要考2级，在中国工作，但是工作中多数用英语 | O45: HSK | P45: HSK2级 | Q45: 杨雅晶play east02_x000D_ 18:00 6.3 | R45: 微信 | S45: 白 | T45: 徐晓晓
A46: 44 | B46: 6.3 | C46: 新西兰 | E46: 4 | F46: 向前走！ 别回头 | G46: fyplvshx | I46: 范睿晨 | J46: 6 | K46: 男 | L46: 没有 | M46: 否 | N46: 会说，口语一般，没学过中文，不需要双语老师，喜欢画画跳舞。 | O46: 中文 | P46: 从a;o;e开始学起，爸爸要求基础扎实一点从头学起。测试的程度孩子ai;ei;ui之前的音都学过了。 | Q46: 杨静；13:40；6.3 Chineseonline A 14:50 6.8 | R46: 微信 | S46: 2 | T46: 丁阮琪 | V46: 白 | W46: 白 | X46: 1 | Y46: 1 | Z46: 1 | AA46: 59/课 | AB46: 一对四44+2课时 | AC46: 2596 | AD46: 6.5日缴费
A47: 45 | B47: 6.3 | C47: 美西 | D47: 旧金山 | E47: 15 | F47: SarahLiu | G47: Sarah YuminLiu | H47: +1 4046105886 | I47: 钟天成 | J47: 5岁 | K47: 男 | L47: 否 | M47: 否 | N47: 没有正式学过中文，可以基本中文交流 | O47: 启蒙中文 | Q47: 卢爽 7:30 6.3 | R47: 微信 | S47: 3 | T47: 毛益丹 | Z47: 课程不够适合孩子
A48: 46 | B48: 6.3 | C48: 美国 | D48: 西部 | E48: 12 | F48: 海风 | G48: annie99575 | I48: serena | J48: 8 | K48: 女 | L48: 学过一点点 | N48: 学过一点点 | O48: 启蒙中文 | Q48: 卢爽11:40 6.3 | R48: 微信 | S48: 3 | T48: 展旺 | Z48: 价格高，在别的地方报名了
A49: 47 | B49: 6.3 | C49: 美国 | D49: 西部 | F49: 海风 | G49: annie99575 | I49: tony | J49: 6 | K49: 男 | L49: 学过一点点 | M49: 是 | N49: 学过一点点 | O49: 启蒙中文 | P49: 姐弟一起测试 | Q49: 卢爽11:40 6.3 | R49: 微信 | S49: 3 | T49: 展旺 | Z49: 蹭课的，
A50: 48 | B50: 6.4 | C50: 加拿大 | E50: 12 | G50: happysandy319 | I50: joyce | J50: 4.5 | L50: 否 | M50: 否 | N50: 刚开始学 | O50: 启蒙中文 | Q50: 卢爽22:00 6.3 | R50: 微信 | S50: 5 | T50: 李波 | Z50: 小朋友不喜欢 喜欢线下有交流
A51: 49 | B51: 6.4 | C51: 美国 | E51: 12 | G51: vivimeilin | I51: 陈芷彤 | J51: 5 | L51: 否 | M51: 否 | N51: 只会说 不会写 | O51: 启蒙中文 | Q51: 卢爽22:30 6.3 | R51: 微信 | S51: 5 | T51: 李波 | Z51: 去朋友介绍的学校了
A52: 50 | B52: 6.4 | C52: 美国 | D52: 佛罗里达 奥兰多 | E52: 12 | F52: Grace | G52: yulei868638 | I52: 言慕一 | J52: 5 | K52: 男 | L52: 否 | M52: 否 | N52: 零基础，日常交流没问题 | O52: 启蒙中文 | Q52: 卢爽22:00 6.3 | R52: 微信 | S52: 1 | T52: 何家昌
A53: 51 | B53: 6.4 | C53: 加拿大 | D53: 温哥华 | E53: 15 | F53: Heidy。 | G53: heidy_ll | I53: 嘉轩 | J53: 8岁 | K53: 男 | L53: 否 | M53: 是 | N53: 零基础 会说广东话和英语 | O53: YCT | Q53: play east01 10:00 6.4 | R53: 微信 | S53: 白 | T53: 俞酉兰 | V53: YCT兼 | X53: 0 | Y53: 0 | Z53: 作比对了
A54: 52 | B54: 6.4 | C54: 美国 | D54: 纽约 | E54: 12 | F54: Grace | G54: Grace-Sunshine646 | I54: 张欣晴 | J54: 8 | K54: 女 | L54: 否 | M54: 否 | N54: 中文基础没有，日常的口语听得懂，爱好看书，运动 | O54: 中文 | P54: 零基础，两个小朋友都很认真，弟弟的中文比姐姐差一些，建议从拼音开始学习。 | Q54: 周虹 7:00 6.4 | R54: 电话 | S54: 2 | T54: 罗焱
A55: 53 | B55: 6.4 | C55: 美国 | D55: 纽约 | E55: 12 | F55: Grace | G55: Grace-Sunshine646 | I55: 张羽 | J55: 6 | K55: 男 | L55: 否 | M55: 否 | N55: 中文基础没有，日常的口语听得懂 | O55: 中文 | P55: 零基础，两个小朋友都很认真，弟弟的中文比姐姐差一些，建议从拼音开始学习。 | Q55: 周虹 7:00 6.4 | R55: 电话 | S55: 2 | T55: 罗焱
A56: 54 | B56: 6.4 | C56: 美国 | D56: 纽约 | E56: 12 | F56: April Yu | G56: VickyYu416 | I56: Evangela | J56: 7 | K56: 女 | L56: 学过 | M56: 否 | N56: 7岁 交流没问题 拼音学过了能认识一些汉字 | O56: 中文 | P56: 学生上课很认真，比较活泼，声调第三声有点问题，后面要多练习，建议从一上四五单元开始学习。 | Q56: 周虹 9:00 6.4 ChineseonlineO 7：40 6.6 | R56: 微信 | S56: 3 | T56: 翁珊珊 | V56: 白 | Z56: 觉得一次性付完这么多学费需要考虑
A57: 55 | B57: 6.4 | C57: 加拿大 | D57: 温歌华 | E57: 15 | F57: Jolene | G57: qq649924854 | I57: 黄非凡 | J57: 11岁 | K57: 男 | L57: 是 | M57: 否 | N57: 之前有学过中文，拼音都会，7级加拿大中文水平（不太清楚家长意思） | O57: 中文 | P57: 学生学了2年多的中文了，程度不错，朗读较为流畅，建议从二上四五单元看开始上课 | Q57: 周虹 10:20 6.4 | R57: 电话 | S57: 1 | T57: 李文
A58: 56 | B58: 6.4 | C58: 美国 | E58: 14 | G58: chenhui903330 | I58: 郑瑞霖 | J58: 11岁 | K58: 女 | L58: 否 | M58: 否 | N58: 听得懂 ，但写的少 | O58: 中文 | P58: 建议aoe开始，识字量一般，课文不会读。 | Q58: 刘钰兰；8:20；6.4 言智16 9:10 6.9 | R58: 微信介绍 | S58: 5 | T58: 胡东东 | X58: 1 | Y58: 1 | Z58: 1 | AA58: 118/课 | AB58: 一对一22+4 | AC58: 375 | AD58: 6.5日缴费
A59: 57 | B59: 6.4 | C59: 美国 | E59: 14 | G59: chenhui903330 | I59: 郑天赋 | J59: 9岁 | K59: 男 | L59: 否 | M59: 是 | N59: 少部分听得懂 基础比较弱 | O59: 中文 | P59: 建议识字或拼音学起，接受程度快。零基础要双语 | Q59: 杨静；9：00；6.4 黄老师上课课堂 9:00 6.9 | R59: 微信介绍 | S59: 5 | T59: 胡东东 | X59: 1 | Y59: 1 | Z59: 1 | AA59: 118/课 | AB59: 一对一22+4 | AC59: 375 | AD59: 6.5日缴费
A60: 58 | B60: 6.4 | C60: 美西 | D60: 旧金山 | E60: 15 | F60: 生活小达人 Sasa | G60: wxid_werv4dm33xl222 | I60: 孙梓渝Selina | J60: 13 | K60: 女 | L60: 学过 | M60: 是 | N60: 学过拼音，会讲会听，不会写不会看，可以粤语和英语，普通话不是很好，很有主见，喜欢女老师，不喜欢男老师，记得一定要叫她英文名“Selina ”，不要叫中文名，她不喜欢别人叫她中文名 | O60: 中文 | P60: 建议一上第四单元学起，读的能力好，认字50内，组词和造句比较慢要慢慢等学生。 | Q60: 杨静；10:20；6.4 | R60: 微信 | S60: 3 | T60: 毛益丹 | Z60: 孩子的时间安排不出来
A61: 59 | B61: 6.4 | C61: 加拿大 | D61: 温哥华 | E61: -15 | F61: zhongxiao | G61: mayzhongxiao | I61: 吴钟凯 | J61: 10 | K61: 男 | L61: 否 | M61: 是 | N61: 上过一年中文课 慕一学过拼音 在当地学校不愿意去学习了 基本交流可以 说多了就听不懂了 在家里有要求看书书写 不会笔顺照猫画虎 家人怕打击学习积极性努力维持鼓励教学 | O61: 中文 | P61: 建议一上第四单元开始学起，不太爱说话要引导。 | Q61: 杨静；11:00；6.4 | R61: 微信 | S61: 2 | T61: 赵国花 | Z61: 孩子没有兴趣 上课蔫蔫的有气无力 而且上课自己玩电脑 杜恩加 杜恩理：妈妈觉得费用太贵了学不起 去当地学校了
A62: 60 | B62: 6.4 | C62: 澳大利亚 | D62: 悉尼 | E62: 2 | F62: 婧婧美善品 | G62: Thea88998 | I62: Kimi | J62: 6.5 | K62: 男 | L62: 是 | M62: 否 | N62: 中国小学一年级下册学了一半 | O62: 中文 | P62: 建议一下第六单元开始学起，认字量大。有些词语不太理解。家长视频全程不露脸，语气不太开心。 | Q62: 杨静；13:40；6.4 | R62: 微信 | S62: 3 | T62: 程蕾 | Z62: 线下开课了
A63: 61 | B63: 6.4 | C63: 澳大利亚 | D63: 悉尼 | E63: 2 | F63: 婧婧美善品 | G63: Thea88998 | I63: Elsa | J63: 8 | K63: 女 | L63: 是 | M63: 否 | N63: 中国小学一年级下册学了一半 | O63: 中文 | P63: 建议二年级上册开始，识字量丰富，发音标准 | Q63: 刘钰兰；14:20；6.4 | R63: 微信 | S63: 3 | T63: 程蕾 | Z63: 线下开课了
A64: 62 | B64: 6.4 | C64: 美国 | E64: 13 | F64: Fang | G64: Catfish0315 | I64: 欧阳子芊 | J64: 5岁 | K64: 女 | N64: 三岁的时候上过半年中文学校，主要是听和说 | O64: 启蒙中文 | Q64: 卢爽8:30 6.4 | R64: 微信 | S64: 3 | T64: 张霞 | V64: 兼 | W64: 兼 | X64: 1 | Y64: 1 | Z64: 1 | AA64: 96/课 | AB64: 一对二65课时 | AC64: 877.3 | AD64: 6.6日缴费
A65: 63 | B65: 6.4 | C65: 澳大利亚 | D65: 墨尔本 | E65: 2 | F65: Robert Chen | G65: bobchen_visamaster | I65: 陈笑涵 | J65: 11 | K65: 女 | L65: 学过 | M65: 否 | N65: 学过拼音 | O65: 中文 | P65: 建议一下第六七单元学起，配合上课，喜欢被夸奖。想当朗读家 | Q65: 杨静；15:00；6.4 Chineseonline J 17：10 6.5 | R65: 电话 | S65: 3 | T65: 毛益丹 | V65: 白 | Z65: 没死透，在联系中
A66: 64 | B66: 6.4 | C66: 澳大利亚 | D66: 墨尔本 | E66: 2 | F66: Robert Chen | G66: bobchen_visamaster | I66: 陈石 | J66: 7 | K66: 男 | M66: 否 | O66: 中文 | P66: 一上四单元，配合老师，发音标准，拼音有一些不熟练 | Q66: 刘钰兰；15:30；6.4 | R66: 电话 | S66: 3 | T66: 毛益丹 | Z66: 没死透，在联系中
A67: 65 | B67: 6.4 | C67: 美国 | D67: 宾州 | E67: 12 | F67: Ling | G67: jenny0405 | I67: 张梦颖 | J67: 8 | K67: 女 | L67: 数学 | M67: 是 | N67: 会加减 | O67: 启蒙数学 | Q67: 卢爽8:30 6.4 | R67: 第二门课 | S67: 3 | T67: 展旺 | X67: 1 | Y67: 1 | Z67: 1 | AA67: 53/课 | AB67: 一对四130+8 | AC67: 6240 | AD67: 6.5日缴费 | AE67: 优惠650
A68: 66 | B68: 6.4 | C68: 加拿大 | D68: 温哥华 | E68: 15 | F68: Janey | G68: jingya890859 | I68: Kayla | J68: 5 | K68: 女 | L68: 否 | M68: 否 | N68: 中文交流可以，零基础 | O68: 启蒙 | Q68: 卢爽7:00 6.4 | R68: 扫一扫 | S68: 白 | T68: 俞酉兰 | W68: 兼 | X68: 1 | Y68: 1 | AA68: 118/课 | AB68: 一对一22课时 | AC68: 2596 | AD68: 6.5缴费
A69: 67 | B69: 6.4 | C69: 美国 | D69: 洛杉矶 | E69: 15 | F69: 滕诗雨 | G69: AprilTeng-China | I69: 陈泰祯 | J69: 9 | O69: 启蒙数学 | P69: 未测试，直接试了一节课 | Q69: 俞海娇7:00 6.4 | R69: 第二门课 | S69: 2 | T69: 刘巧芹 | V69: 兼 | W69: 兼 | X69: 1 | Y69: 1 | Z69: 1 | AA69: 93/课 | AB69: 一对一收一对二65课时 | AC69: 两门课一起$1702 | AD69: 6.5日缴费
A70: 68 | B70: 6.5 | C70: 美国 | E70: 12 | G70: lilin697689 | I70: 牟柏恩 | J70: 6 | L70: 否 | M70: 否 | N70: 会简单交流 | O70: 中文 | P70: 零基础，建议一上天地人学起 | Q70: 刘依琳22:00 6.4 | R70: 微信 | S70: 1 | T70: 刘孙丹
A71: 69 | B71: 6.5 | C71: 美国 | D71: 洛杉矶 | E71: 15 | F71: Joye刘 | G71: wxid_ult1i5hykved22 | H71: +1 9094794692 | I71: 唐梓鑫 | J71: 9 | K71: 女 | O71: 启蒙中文 | Q71: 卢爽10:00 6.4 | R71: 微信 | S71: 5 | T71: 赵峰 | V71: 兼 | W71: 兼 | X71: 1 | Y71: 1 | Z71: 1 | AA71: 59/课 | AB71: 一对四22+5课时 | AC71: 1298 | AD71: 6.7日缴费
A72: 70 | B72: 6.5 | C72: 加拿大 | D72: 温歌华 | E72: 15 | F72: Piony 蚊蚊 | G72: love_piony | H72: 01-7788698894 | I72: Vincy | J72: 6岁 | K72: 女 | L72: 否 | M72: 是 | N72: 一直讲粤语，试试中文启蒙课，老师需要双语的 | O72: 启蒙中文 | Q72: 卢爽7:30 6.4 | R72: 微信 | S72: 1 | T72: 赵红艳 | AA72: 中文还行，数学效果不是很好，联系不怎么回复
A73: 71 | B73: 6.5 | C73: 美国 | D73: 纽约 | E73: 12 | F73: KristyGG ෆ⃛ 🤗ෆ | G73: KristyGG0808 | H73: +1 9176889698 | I73: 黄沛琋 | J73: 3 | K73: 女 | L73: 否 | M73: 否 | N73: 中文交流 | O73: 启蒙中文 | Q73: 卢爽22:00 6.4 | R73: 代理介绍 | S73: 3 | T73: 杨斌 | V73: 兼 | W73: 兼 | X73: 1 | Y73: 1 | Z73: 1 | AA73: 99/课 | AB73: 一对一收一对二22课时 | AC73: 2178 | AD73: 6.10日缴费
A74: 72 | B74: 6.5 | C74: 美国 | D74: 纽约 | E74: 12 | H74: +1 9176843288 | I74: Edwin | J74: 6岁 | L74: 没有 | M74: 是 | N74: 零基础 | O74: 启蒙中文 | Q74: 卢爽23:00 6.4 | R74: 微信 | S74: 5 | T74: 刘箫 | Z74: 孩子网课太多，暂时抽不出来时间
A75: 73 | B75: 6.5 | C75: 加拿大 | D75: 温哥华 | E75: 15 | F75: 顺顺 | G75: Lingxi127 | I75: 彤彤 | J75: 7 | K75: 女 | L75: 否 | M75: 否 | N75: 零基础 中文说话流利 | O75: 中文 | P75: 拼音开始学 | Q75: Chineseonline N 7:40 6.5 | R75: 微信 | S75: 白 | T75: 俞酉兰 | V75: 白 | X75: 0 | Y75: 0 | Z75: 孩子不愿意学
A76: 74 | B76: 6.5 | C76: 美国 | D76: 纽约 | E76: 12 | F76: 洋娃娃美国代购 | G76: ww527839616 | H76: 347-542-1126 | I76: 孙浩轩 | J76: 9 | K76: 男 | L76: 否 | M76: 否 | N76: 零基础，没有学习过中文和拼音，日常口语交流没有问题 | O76: 中文 | Q76: Chineseonline N 7:40 6.5 | R76: 家长介绍 | S76: 2 | T76: 高翱翔 彭梓瑜妈妈介绍 | V76: 白 | Z76: 还要在考虑一下，需要时联系，也是嫌弃价格高
A77: 75 | B77: 6.5 | C77: 美国 | D77: 东部 | E77: 12 | F77: 偏偏 | G77: 无 | I77: 张恭旭 | J77: 7 | K77: 男 | L77: 没有 | M77: 否 | N77: 5岁的时候在国内学过两周 | O77: 中文 | P77: 拼音零基础，认识简单的生字，建议学生从拼音开始学习。 | Q77: 周虹 7:40 6.5 | R77: 家长介绍 | S77: 3 | T77: 展旺 张梦颖妈妈介绍 | X77: 1 | Y77: 1 | Z77: 1 | AA77: 56/课 | AB77: 一对四65+3课时 | AC77: 3240 | AD77: 6.5日缴费 | AE77: 优惠400
A78: 76 | B78: 6.5 | C78: 美国 | D78: 纽约 | E78: 12 | F78: kate | G78: xi3479632021 | I78: 林志刚 | J78: 11 | K78: 男 | L78: 学过 | M78: 否 | N78: 学过一点点，中文讲的不好 | O78: 中文 | P78: 学生有一定的基础，上课非常认真，简单的生字都是认识的，但是学过的拼音有很多遗忘了，家长想让孩子打好基础，建议从拼音的aieiui开始学。 | Q78: 周虹 8:20 6.5 Chineseonline Z 8：20 6.6 | R78: 微信 | S78: 3 | T78: 张霞 | V78: 白 | W78: 白 | X78: 1 | Y78: 1 | Z78: 1 | AA78: 53/课 | AB78: 一对四130课时 | AC78: 973.05 | AD78: 6.6日缴费
A79: 77 | B79: 6.5 | C79: 巴西 | D79: 圣保罗 | E79: 12 | G79: guoqiancui | I79: 杨郭乐 | J79: 12 | K79: 男 | L79: 否 | M79: 是 | N79: 有一定中文基础 口语不怎么好 | O79: 中文 | P79: 建议一上第八单元开始学起，声调不会，认字量大。不会组词和造句，句子不理解。孩子英文也不太好说巴西语，妈妈都是在旁边翻译的。 | Q79: 杨静；7:00；6.5 | R79: 微信 | S79: 1 | T79: 李华 | Z79: 价格贵 与他之前在学校的价格相差较大
A80: 78 | B80: 6.5 | C80: 美国 | D80: 旧金山 | E80: 15 | G80: szeyung2000 | I80: Aden 谢 | J80: 8岁 | L80: 没有 | M80: 是 | N80: 零基础 | O80: 中文 | P80: 8岁孩子Aden讨厌中国，只测试了15分钟。零基础，坐不住爸爸强迫孩子坐下了15分钟。建议YCT的课，双语.另外一个孩子没上课 | Q80: 杨静；9:00；6.5 | R80: 电话 | S80: 5 | T80: 赵峰 | Z80: 家长想让孩子学，但是孩子一点兴趣也没有
A81: 79 | B81: 6.5 | C81: 美国 | D81: 旧金山 | E81: -15 | F81: Ariel y | G81: ariel-yeung | I81: 张心桥 | J81: 8.5 | K81: 女 | L81: 否 | M81: 是 | N81: 没有任何基础 也没有怎么学过 在家也是讲广东话 | O81: 中文 | P81: 零基础，建议YCT的课程，学生很认真乖巧。双语 | Q81: 杨静；7:40；6.5 play east02 8:00 6.6 | R81: 家长介绍 | S81: 2 | T81: 赵国花 高崇文妈妈推荐 | V81: yct兼 | W81: yct兼 | X81: 1 | Y81: 1 | Z81: 1 | AA81: 116/课 | AB81: 一对一65课时 | AC81: 1061 | AD81: 6.6日缴费
A82: 80 | B82: 6.5 | C82: 美国 | E82: 12 | G82: liuxiaomin | I82: 王萌萌 | J82: 10岁 | L82: 否 | M82: 否 | N82: 中文学校一年级 | O82: 中文 | P82: 建议一下六七单元学习，孩子上课配合，沟通没有问题，识字量一般 | Q82: 刘钰兰；8:20；6.5 | R82: 微信 | S82: 5 | T82: 李波 | Z82: 小朋友不喜欢 坐不住
A83: 81 | B83: 6.5 | C83: 加拿大 | D83: 温哥华 | E83: 15 | F83: 瞰九天 | H83: 7783225110 | I83: 李艾文 | J83: 7 | L83: 否 | M83: 否 | N83: 零基础，识字量不详，可以口语交流 | O83: 中文 | P83: 孩子配合，建议从基础拼音aoe开始学习 | Q83: 刘钰兰；9:00；6.5 | R83: 电话 | S83: 0 | T83: 张仁波 | X83: 0 | Y83: 0 | Z83: 0
A84: 82 | B84: 6.5 | C84: 美国 | D84: 东部 | E84: 12 | F84: taj | G84: bmtajcheng | I84: 郑丽颍 | J84: 10 | K84: 女 | L84: 学过 | M84: 是 | N84: 学过一点.拼音会拼，但是音标第二声和第四声就分不清楚。 | O84: 中文 | P84: 一上第四单元开始学起，双语。课文能读下来，每个词语都需要英语解释，双语。 | Q84: 杨静；9:40；6.5 双语课堂 8:20 6.6 言智19 7:40 6.8 | R84: 家长介绍 | S84: 3 | T84: 展旺 张梦颖介绍 | V84: 兼 | X84: 1 | Y84: 1 | Z84: 1 | AA84: 56/课 | AB84: 一对四65+3课时 | AC84: 3240 | AD84: 6.5日缴费 | AE84: 优惠400
A85: 83 | B85: 6.5 | C85: 美国 | D85: 洛杉矶 | E85: 15 | F85: 月彤（金湾海参） | G85: dyt6999 | I85: 王俊翔 | J85: 7 | K85: 男 | L85: 否 | M85: 否 | N85: 50字左右，口语还可以的，没有学过拼音 | O85: 中文 | P85: 建议拼音学起，零基础。 | Q85: 杨静；11:00；6.5 | R85: 微信 | S85: 1 | T85: 赵红艳 | AA85: 课程效果不太满意，觉得考拉的课件好，选择了考拉
A86: 84 | B86: 6.5 | C86: 澳大利亚 | E86: 2 | F86: Ashely | G86: baby09142016 | I86: 威廉 | J86: 7 | K86: 男 | L86: 否 | M86: 否 | N86: 中文能沟通，断断续续学过一点中文，识字量不到100个，口语一般，能听懂 | O86: 中文 | P86: 零基础，建议拼音开始，老师讲话要慢一点，不然孩子跟不上。 | Q86: 刘钰兰；15:30；6.5 | R86: 微信 | S86: 2 | T86: 王忆超 | Z86: 跟当地比，价格高的太离谱
A87: 85 | B87: 6.5 | C87: 美国 | E87: 15 | F87: G.G | G87: WXJING20 | I87: 鮑锦鹏 | J87: 8岁 | K87: 男 | L87: 会一些 | M87: 否 | N87: 在美国上过台湾人开的中学学校，简繁一起学的，拼音会一点简单的，声调不会 | O87: 中文 | P87: 建议一上第七八单元开始学起 | Q87: 杨静；10:20；6.5 | R87: 微信 | S87: 5 | T87: 邢国栋 | Z87: 7月份可以
A88: 86 | B88: 6.5 | C88: 美国 | D88: 旧金山 | E88: 15 | G88: bingyu-wang | I88: 王嘉怡 | J88: 5 | K88: 女 | L88: 否 | M88: 否 | N88: 家里教过些简单的字，拼音和识字没有学过。口语能力很好。 | O88: 启蒙中文 | Q88: 卢爽2:00 6.5 | R88: 朋友介绍 | S88: 5 | T88: 李巧群 | V88: 兼 | W88: 兼 | X88: 1 | Y88: 1 | Z88: 1 | AA88: 99/课 | AB88: 一对一收一对二，22+5课时 | AC88: 2178 | AD88: 6.7日缴费
A89: 87 | B89: 6.5 | C89: 美国 | D89: 洛杉矶 | E89: -15 | F89: sunny | G89: sunyingting001 | I89: 李昕娅 | J89: 5 | K89: 女 | L89: 否 | M89: 否 | N89: 零基础，喜欢跳舞画画 | O89: 启蒙中文 | Q89: 卢爽7:00 6.5 | R89: 微信 | S89: 0 | T89: 王晨 | Z89: 家长只上1v1课堂，在悟空中文和我们家做选择，悟空1v1价格40分钟只要80+人民币，比我们家更便宜，所以试读失败。
A90: 88 | B90: 6.5 | C90: 澳大利亚 | E90: 2 | F90: Jeanette | G90: shujeanette | H90: 61451507077 | I90: 麦皓棠 | J90: 3 | K90: 男 | L90: 否 | M90: 是 | N90: 家庭基本口语 | O90: 启蒙中文 | Q90: 卢爽15:00 6.5 | R90: 微信 | S90: 2 | T90: 王忆超 | Z90: 价格太高
A91: 89 | B91: 6.5 | C91: 加拿大 | E91: 12 | G91: xiaozhutou120535 | H91: 17786827737 | I91: 刘曦泽 | J91: 4.5 | K91: 男 | O91: 启蒙中文 | Q91: 卢爽9:00 6.5 | R91: 微信 | S91: 白 | T91: 俞酉兰 | W91: 兼 | X91: 1 | Y91: 1
A92: 90 | B92: 6.5 | C92: 加拿大 | D92: 温歌华 | E92: 15 | F92: Piony 蚊蚊 | G92: love_piony | H92: 01-7788698894 | I92: Vincy | J92: 6岁 | K92: 女 | M92: 是 | N92: 一直讲粤语，之前试了中文启蒙课，老师需要双语的，今天试试启蒙数学课，英语讲孩子才能听懂意思 | O92: 启蒙数学 | Q92: 卢爽9:00 6.5 | R92: 微信 | S92: 1 | T92: 赵红艳 | AA92: 中文还行，数学效果不是很好，联系不怎么回复
A93: 91 | B93: 6.6 | C93: 加拿大 | E93: 13 | F93: zhiyi | G93: zhiyi095522 | I93: Oberyn Chen | J93: 7 | K93: 男 | L93: 否 | M93: 否 | N93: 有基本听说写，拼音无系统学过 | O93: 中文 | P93: 课程顾问的信息不对，学生学过很多生字，拼音会单韵母和大部分的声母，建议从拼音zhchsh或者复韵母开始上课。 | Q93: 周虹 7:00 6.6 | R93: 微信 | S93: 1 | T93: 何家昌
A94: 92 | B94: 6.6 | C94: 美国 | D94: 纽约 | E94: 12 | F94: sisi | G94: wangsisi0416 | I94: 董思扬 | J94: 5 | K94: 女 | L94: 没有 | M94: 否 | N94: 听说没问题，重点加强读和写 | O94: 中文 | P94: 学生上课比较积极，零基础，建议从识字课开始 | Q94: 周虹 8:20 6.6 | R94: 微信 | S94: 3 | T94: 程蕾 | Z94: 坐不住，报了线下
A95: 93 | B95: 6.6 | C95: 美国 | D95: 东部 | E95: 12 | F95: 小林 E Realty&阿胶糕929-523-78 | G95: Callia168 | I95: 史茹萱 | J95: 11 | K95: 女 | L95: 没有 | M95: 否 | N95: 可以中文交流，在当地的周末班上课，学的一般 | O95: 中文 | P95: 学生学过拼音，但是个别读音不是准，生字认识的比较少，建议从一上四单元开始 | Q95: 周虹 9:00 6.6 Chineseonline O 7:40 6.9 | R95: 微信 | S95: 3 | T95: 翁珊珊 | V95: 白 | W95: 白 | X95: 1 | Y95: 1 | Z95: 1 | AA95: 53/课 | AB95: 一对四130+3课时 | AC95: 和兄弟合交$2042.75 | AD95: 6.12日缴费
A96: 94 | B96: 6.6 | C96: 加拿大 | D96: 温哥华 | E96: 15 | F96: Leyna | G96: leyna625 | I96: 舒瀚林 | J96: 9 | K96: 男 | L96: 是 | M96: 否 | N96: 听说流利，可以读带拼音读物和简单故事书，写很勉强， | O96: 中文 | P96: 孩子的程度很好，朗读流畅，识字量也很大，理解能力特别好，建议从三下开始上课。 | Q96: 周虹 9:40 6.6 | R96: 微信 | S96: 1 | T96: 赵红艳 | AA96: 选择了家教，是哥哥跆拳道老师的老婆，可以去老师家里上
A97: 95 | B97: 6.6 | C97: 加拿大 | D97: Calgary | E97: 14 | F97: 朱虹 | G97: liekangma | I97: 罗宇康 | J97: 7 | K97: 男 | L97: 学过 | M97: 否 | N97: 可以中文交流，学过拼音，之前在周末班上课 | O97: 中文 | P97: 学生程度不错，上课配合度很好，朗读流畅，识字量，理解能力都很好，建议从一下三四单元开始上课。 | Q97: 周虹 10：20 6.6 | R97: 微信 | S97: 3 | T97: 翁珊珊 | Z97: 暂时不报名
A98: 96 | B98: 6.6 | C98: 加拿大 | D98: 洛伦多 | E98: -12 | F98: 奥博 | G98: toronto8688 | H98: 6479648688 | I98: 蒲赞天 | J98: 8 | K98: 男 | L98: 是 | M98: 否 | N98: 会拼音，识字量一千多，海外2年级水平 | O98: 中文 | P98: 建议二上第一单元学起，读写能力都很好，很活泼 | Q98: 杨静；7：00；6.6 | R98: 电话 | S98: 0 | T98: 黄帅
A99: 97 | B99: 6.6 | C99: 美国 | D99: 美西 | E99: 15 | F99: rencong | G99: rencong99211555 | I99: 邵德瑞 | J99: 8岁 | K99: 男 | L99: 没有 | M99: 否 | N99: 还没有开始学中文，可以听懂 | O99: 中文 | P99: 建议拼音学起，零基础，学习很认真，不太会表达 | Q99: 杨静；7：40；6.6 | R99: 微信 | S99: 3 | T99: 张霞 | X99: 1 | Y99: 1 | Z99: 1 | AA99: 56/课 | AB99: 一对四65课时 | AC99: 3640 | AD99: 6.9日缴费
A100: 98 | B100: 6.6 | C100: 美国 | D100: 东部 | E100: 12 | F100: 小林 E Realty&阿胶糕929-523-78 | G100: Callia168 | I100: 史紫彬 | J100: 7 | K100: 女 | L100: 没有 | M100: 是 | N100: 能听懂一点中文，孩子不太喜欢学习中文，觉得中文太难，主要要培养中文学习的兴趣 | O100: 中文 | P100: 建议YCT的课，孩子有点排斥学习中文，上课可以玩一下游戏。 | Q100: 杨静；9：00；6.6 play east04 8:20 6.7 | R100: 微信 | S100: 3 | T100: 翁珊珊 | X100: 1 | Y100: 1 | Z100: 1 | AA100: 116/课 | AB100: 一对一65+3课时 | AC100: 和兄弟合交$2042.75 | AD100: 6.12日缴费
...

Sheet 2020.5
A1: 新生接待试读表 业务员：测+读 老师：试读两次
A2: 序号 | B2: 测试时间 | C2: 国家 | D2: 城市 | E2: 时差 | F2: 家长微信名 | G2: 家长微信 | H2: 学生姓名 | I2: 年龄 | J2: 性别 | K2: 有没有学过拼音 | L2: 是否需要双语老师 | M2: 家长自述程度及学习需求 | N2: 学习课程 | O2: 测试结果 | P2: 排课安排 | Q2: 来源 | R2: 组别 | S2: 业务员 | T2: 试读日期 | U2: 试课安排 | V2: 排课校区 | W2: 是否在读 | X2: 是否缴费 | Y2: 失败原因 | Z2: 课程单价 | AA2: 折扣 | AB2: 实收 | AC2: 首次收费时间
A3: 1 | B3: 5.1 | C3: 美国 | E3: 12 | G3: apple | H3: 郭宇镌 | I3: 17 | L3: 是 | M3: 会听说，认识少许字，口语基本都可以 | N3: 中文 | O3: 学生课堂反应能力很好，听力没问题，表达能力一般，明显的英式思维；三声调不准；建议从拼音学起，多练习日常口语 | P3: 刘紫佳7:00 5.1 | Q3: 电话 | R3: 1 | S3: 娄丽华 | Y3: 家长不信任我们学校，不愿意缴费
A4: 2 | B4: 5.1 | C4: 加拿大 | D4: 多伦多 | E4: 12 | F4: Fiona | G4: fionaleeparis | H4: 陆梓朗 | I4: 10 | J4: 男 | K4: 有 | L4: 否 | M4: 孩子零基础 ，之前学习过拼音，很久没有练习了。喜欢 钢琴 足球 basketball | N4: 中文 | O4: 日常交流不行，需要双语老师；拼音学过忘记了，汉字没学过，可以从拼读复习开始学 | P4: 刘依琳 7:40 5.1 | Q4: 家长介绍 | R4: 2 | S4: 高翱翔 陈彦豪妈妈介绍 | W4: 0 | X4: 0 | Y4: 还在谈
A5: 3 | B5: 5.1 | C5: 加拿大 | D5: 多伦多 | E5: 12 | F5: Fiona | G5: fionaleeparis | H5: 陆纪欣 | I5: 12 | J5: 女 | K5: 有 | L5: 否 | M5: 孩子零基础 ，之前学习过拼音，很久没有练习了。喜欢 钢琴 basketball | N5: 中文 | O5: 学生上课表现很好，需要双语老师，听说很困难；建议鼓励孩子张嘴说中文，从零基础开始学习 | P5: 任晓艳 8:20 5.1 | Q5: 家长介绍 | R5: 2 | S5: 高翱翔 陈彦豪妈妈介绍 | W5: 0 | X5: 0 | Y5: 还在谈
A6: 4 | B6: 5.1 | C6: 美国 | E6: 12 | G6: gao8888868 | H6: Leon Gao | I6: 9 | J6: 男 | L6: 否 | M6: 口语流利，会讲不会写 | N6: 中文 | O6: 学生积极性不高，需要上课比较活动调动性强的老师；建议从拼音开始学 | P6: 刘紫佳 9:00 5.1 言智14 单紫薇 22:10 5.17 | Q6: 电话 | R6: 1 | S6: 娄丽华 | T6: 5.2 | U6: 兼 | V6: 兼 | W6: 1 | X6: 1 | Y6: 1 | Z6: 56/课 | AA6: 65课时 | AB6: 3640 | AC6: 5.6日缴费
A7: 5 | B7: 5.2 | C7: 美国 | D7: 西部 | E7: 15 | F7: MaggieRH | G7: Hrmaggie | H7: 杨鼎彬 | I7: 12 | J7: 男 | K7: 学过 | L7: 否 | M7: 一年级 | N7: 中文 | O7: 一上后面部分 | P7: 张文红 5.1 ChineseonlineJ 11:40 5.5 ChineseonlineK1 8：20 5.9 | Q7: 电话 | R7: 3 | S7: 张文红 | U7: 兼 | V7: 白 | W7: 0 | X7: 0 | Y7: 本来就在lingoace在学，家长希望孩子一周五天，但孩子不喜欢
A8: 6 | B8: 5.2 | C8: 美国 | D8: 西部 | E8: 15 | F8: MaggieRH | G8: Hrmaggie | H8: 杨雨涵 | I8: 8 | J8: 女 | K8: 学过 | L8: 否 | M8: 三年级 | N8: 中文 | O8: 上课氛围不错，会回答老师问题，能主动学习，建议从三年级第一课开始学 | P8: 孙水仙 9:00 5.2 ChineseonlineF8:20 5.5 | Q8: 电话 | R8: 3 | S8: 张文红 杨鼎彬妹妹 | T8: 5.11 | U8: 白 | W8: 0 | X8: 0 | Y8: 本来就在lingoace在学，家长希望孩子一周五天，但孩子不喜欢
A9: 7 | B9: 5.2 | C9: 美国 | D9: 纽约 | E9: 12 | F9: irisliu | G9: irisliu32656 | H9: 郭柳钰 | I9: 16 | J9: 女 | K9: 有 | L9: 否 | M9: 3年级程度，会拼音 口语流利 | N9: 中文 | O9: 学生认字很好，写字差一点，测试《在牛肚子里旅行》，建议先学完这课，然后从三年级第一课开始学 | P9: 孙水仙 7:00 5.2 | Q9: 家长介绍 | R9: 2 | S9: 高翱翔 林若惜妈妈介绍 | W9: 0 | X9: 0 | Y9: 时间短，价格高
A10: 8 | B10: 5.2 | C10: 美国 | D10: 纽约 | E10: 12 | F10: irisliu | G10: irisliu32656 | H10: 郭子涵 | I10: 14 | J10: 男 | K10: 有 | L10: 否 | N10: 中文 | O10: 上课很认真，会积极主动提问，学过拼音但掌握程度一般，复韵母有些忘记了，认识简单的汉字，知道笔顺和笔画的概念；建议从复韵母部分开始学 | P10: 赵佳求7:40 5.2 | Q10: 家长介绍 | R10: 2 | S10: 高翱翔 林若惜妈妈介绍 | W10: 0 | X10: 0 | Y10: 时间短，价格高
A11: 9 | B11: 5.2 | C11: 美国 | D11: 纽约 | E11: 12 | F11: irisliu | G11: irisliu32656 | H11: 郭铭钰 | I11: 13 | J11: 女 | K11: 接触过一点 | L11: 否 | M11: 零基础 ，拼音需要重新学习了。 | N11: 中文 | O11: 上课很认真，课堂表现好，听说和理解力都没问题；学过拼音但不扎实，拼读比较困难，建议从声母部分重新学起 | P11: 任晓艳8:20 5.2 | Q11: 家长介绍 | R11: 2 | S11: 高翱翔 林若惜妈妈介绍 | W11: 0 | X11: 0 | Y11: 时间短，价格高
A12: 10 | B12: 5.2 | C12: 澳大利亚 | E12: 2 | F12: Cathy ོQ | G12: Q_Cathy | H12: 天天 | I12: 12 | J12: 男 | K12: 学过一点 | L12: 否 | M12: 简单的学过一点 | N12: 中文 | O12: 哥哥表现力比妹妹弱一些，会一点拼音但是没掌握，建议从一上拼音开始学 | P12: 程晓诺14:20 5.2 | Q12: 微信 | R12: 3 | S12: 杨斌 | W12: 0 | X12: 0 | Y12: 去别的机构试课，之后失联了，被拉黑
A13: 11 | B13: 5.2 | C13: 澳大利亚 | E13: 2 | F13: Cathy ོQ | G13: Q_Cathy | H13: 香香 | I13: 10 | J13: 女 | K13: 学过一点 | L13: 否 | M13: 简单的学过一点 | N13: 中文 | O13: 口语表达有限，会一些拼音但是不熟练，写字能力差，建议从一上拼音开始学 | P13: 程晓诺15:00 5.2 | Q13: 微信 | R13: 3 | S13: 杨斌 | W13: 0 | X13: 0 | Y13: 去别的机构试课，之后失联了，被拉黑
A14: 12 | B14: 5.4 | C14: 美国 | D14: 纽约 | E14: -12 | F14: XiaoZhanG | G14: figtzyx | H14: 马尔若兮 | I14: 7 | J14: 女 | K14: 有 | L14: 否 | M14: 家长说有国内一年级水平 会点拼音 不知道是否忘记 可以正常中文交流 爱好 手工 舞蹈 滑雪 家长要求测一年级下册 | N14: 中文 | O14: 建议一下第三单元开始学起，认字能力不错，词语的理解不懂 | P14: 杨静7:40；5.4 | Q14: 中文 | R14: 2 | S14: 高翱翔 | W14: 0 | X14: 0 | Y14: 老师无法深入孩子的心
A15: 上个月算过人数 | B15: 5.4 | C15: 澳大利亚 | D15: 悉尼 | E15: 2 | F15: Annie Z | G15: AnnieZ510 | H15: 江羿廷 | I15: 5 | J15: 男 | K15: 否 | L15: 否 | M15: 没学过，可以简单的听懂一些，家长希望学会拼读和写字 | N15: 启蒙 | O15: 建议天地人学起，后面拼音学起。中文交流没问题 启蒙课账号 +61 432305700 | P15: 杨静13:00 4.25 Chineseonline A 14:50 4.27 卢爽13:00 5.4 | Q15: 家长介绍 | R15: 3 | S15: 王可 王有衡妈妈推荐 | T15: 5.4 | U15: 兼 | V15: 兼 | W15: 1 | X15: 1 | Y15: 1 | Z15: 116/课 | AA15: 一对一65+3课时 | AB15: 7540 | AC15: 5.9日缴费
A16: 13 | B16: 5.4 | C16: 澳大利亚 | E16: 2 | F16: 小雅Jana | G16: Jana8888 | H16: 王安杰 | I16: 4 | J16: 男 | K16: 否 | L16: 否 | M16: 中文交流，会讲广东话 | N16: 启蒙 | O16: +61 432305700 | P16: 卢爽13:30 5.4 | Q16: 微信 | R16: 3 | S16: 杨斌 | T16: 5.4 | U16: 兼 | V16: 兼 | W16: 1 | X16: 1 | Y16: 1 | Z16: 140/课，一对二价格收费 | AA16: 一对一一小时，前半小时语文后半小数数学，10课时 | AB16: 和数学一起￥1400 | AC16: 5.15日缴费
A17: 14 | B17: 5.4 | C17: 加拿大 | D17: 温哥华 | E17: -15 | F17: 🏡Suki🇨🇦 | G17: suki176156 | H17: 莹莹 | I17: 3.5 | J17: 女 | K17: 否 | L17: 否 | M17: 没学过，识字量50-80 | N17: 启蒙 | P17: 卢爽8:00 5.4 卢爽10:00 5.7 | Q17: 微信 | R17: 白 | S17: 俞酉兰 | T17: 5.7 | U17: 兼 | V17: 兼 | W17: 1 | X17: 1 | Y17: 1 | Z17: 79/课 | AA17: 22课时 | AB17: 1738 | AC17: 5.8日缴费
A18: 15 | B18: 5.5 | C18: 加拿大 | D18: 温哥华 | E18: 15 | G18: ritaluo23 | H18: 张佳美 | I18: 3 | J18: 女 | K18: 否 | L18: 否 | M18: 简单交流在家 | N18: 启蒙 | P18: 卢爽10:30 5.5 | Q18: 微信 | R18: 1 | S18: 赵红艳 | T18: 5.5 | U18: 兼 | V18: 兼 | W18: 1 | X18: 1 | Y18: 1 | Z18: 96/课 | AA18: 一对二，65+5课时 | AB18: 6240 | AC18: 5.18日缴费
A19: 16 | B19: 5.5 | C19: 法国 | E19: 6 | F19: ENMA-D | G19: ENMA-D | H19: 刘咔诺 | I19: 8 | J19: 女 | K19: 是 | L19: 否 | M19: 国外中文学校学到二年级下册，学的一般，脱离拼音有些不认识 | N19: 中文 | O19: 孩子很愿意学，表达很流利，基础不是很扎实，可以从二年级下册开始学 | P19: 程晓茹19:30 5.4 周末班 第二十八课堂1:05 薛万意5.9 | Q19: 家长介绍 | R19: 白 | S19: 欧洲家长推荐 | U19: 夜 | W19: 0 | X19: 0 | Y19: 已经缴费周末班，但是上了一次又要退钱
A20: 17 | B20: 5.5 | C20: 加拿大 | D20: 温哥华 | E20: -15 | F20: Ye | G20: gingeraleye | H20: 童童2 | I20: 10 | J20: 女 | K20: 有 | L20: 否 | M20: 暨南大学第七册 | N20: 中文 | O20: 学过一些中文，但是有遗忘，建议从一下第四、五单元开始上课。 第二次测试，学生程度为一下六单元左右 | P20: 周虹 8:20 5.5 | Q20: 家长介绍 | R20: 白 | S20: 俞酉兰 Ella2妈妈介绍 | W20: 0 | X20: 0 | Y20: 就是想上张娟娟的课，没有课就不报名
A21: 18 | B21: 5.5 | C21: 加拿大 | D21: 温哥华 | E21: -15 | F21: Ye | G21: gingeraleye | H21: 涵涵1 | I21: 8 | J21: 女 | K21: 有 | L21: 否 | M21: 暨南大学第四册 | N21: 中文 | O21: 学过一些中文，从一上七，八单元开始上课 | P21: 周虹 9:00 5.5 Chineseonline C 1张娟娟7:40 5.6 | Q21: 家长介绍 | R21: 白 | S21: 俞酉兰 Ella2妈妈介绍 | T21: 5.5 | U21: 兼 | V21: 兼 | W21: 1 | X21: 1 | Y21: 1 | Z21: 59/课 | AA21: 22课时 | AB21: 1298 | AC21: 5.6缴费
A22: 19 | B22: 5.5 | C22: 美国 | D22: 旧金山 | E22: -15 | F22: Helen GuoGuo | G22: helenguoguoguo | H22: 豆豆 | I22: 3.8岁 | J22: 男 | K22: 否 | L22: 否 | M22: 会说中文，不认识字 | N22: 启蒙 | P22: 卢爽10：00 5.6 | Q22: 家长介绍 | R22: 兼 | S22: 俞酉兰 陈一一妈妈介绍 | T22: 5.6 | U22: 兼 | W22: 0 | X22: 0 | Y22: 孩子喜欢孙悟空，报了悟空中文
A23: 20 | B23: 5.5 | C23: 加拿大 | D23: 温哥华 | E23: -15 | F23: DAISY | G23: saloli | H23: 王子 | I23: 12 | J23: 男 | K23: 是 | L23: 否 | M23: 国内上完三年级 | N23: 中文 | O23: 在国内学完了三年级，从读的情况看，有些简单的生字有遗忘的，建议从四上一单元开始上课。 | P23: 周虹 9:40 5.5 | Q23: 家长介绍 | R23: 白 | S23: Lawrence1妈妈介绍 | W23: 0 | X23: 0 | Y23: 没时间
A24: 21 | B24: 5.5 | C24: 美国 | D24: 东部 | E24: 12 | F24: 与有荣焉 | G24: joy1joy2010 | H24: Quinny | I24: 6 | J24: 女 | K24: 没学过 | L24: 否 | M24: 没学过，可以听说 | N24: 中文 | O24: 年纪偏小坐不住，建议认字2开始学起，测试课已经学完了天地人 | P24: 杨静，7：40；5.5 ChineseonlineA7:40 5.8 | Q24: 微信 | R24: 3 | S24: 王可 | T24: 5.8 | U24: 白 | W24: 0 | X24: 0 | Y24: 喜欢测试老师，其它老师不满意
A25: 22 | B25: 5.5 | C25: 美国 | D25: 东部 | E25: 12 | F25: 与有荣焉 | G25: joy1joy2010 | H25: 妞妞 | I25: 8 | J25: 女 | K25: 没学过 | L25: 否 | M25: 没系统学过，可以交流 | N25: 中文 | O25: 建议拼音i;u学起，接受能力有点慢，建议老师讲课的时候耐心些。字的话认识最简单的，测试课已经学完了a;o;e | P25: 杨静；7：00；5.5 Chineseonline Z 7:00 5.6 | Q25: 微信 | R25: 3 | S25: 王可 | T25: 5.7 | U25: 白 | W25: 0 | X25: 0 | Y25: 喜欢测试老师，其它老师不满意
A26: 23 | B26: 5.5 | C26: 美国 | D26: 洛杉矶 | E26: 15 | F26: 美丰林灵 | G26: forest_bird2012 | H26: henry yang | I26: 10 | J26: 女 | K26: 学过一些 | L26: 要 | M26: 拼音学过一些，二年级水平 | N26: 中文 | O26: 建议拼音ai;ei;ui开始学起，老师讲解要慢一些耐心，学生有点排斥学习。 | P26: 杨静；9：40；5.5 | Q26: 微信 | R26: 2 | S26: 平金军 | W26: 0 | X26: 0 | Y26: 报了别人家，一对一，8月份再来
A27: 24 | B27: 5.5 | C27: 美国 | D27: 东部 | E27: 12 | F27: zeros | G27: jshi112 | H27: 王子文 | I27: 7 | J27: 男 | K27: 学过 | L27: 否 | M27: 拼音学完了，但是还需要巩固 | N27: 中文 | O27: 程度很好，简单的生字都是认识的，拼读不是很熟练，课文读的不够流畅，建议从一上五单元开始上课。 | P27: 周虹 7:00 5.5 Chineseonline W 9:00 5.8 | Q27: 微信 | R27: 3 | S27: 王可 | U27: 排课了没去试读 | W27: 0 | X27: 0 | Y27: 想要一对四的班级，一直没有
A28: 25 | B28: 5.5 | C28: 美国 | D28: 东部 | E28: 12 | F28: Syler | G28: meggy123_ | H28: 凯翌 | I28: 14 | J28: 女 | K28: 学过一点 | L28: 否 | M28: 拼音学过 | N28: 中文 | O28: 程度不错，拼音第四声要注意，建议从一上六单元开始学习。【课程顾问的信息不准确】 | P28: 周虹 7:40 5.5 Chineseonline O 8:20 5.8 | Q28: 介绍 | R28: 3 | S28: 张霞 | T28: 5.8 | U28: 白 | W28: 0 | X28: 0 | Y28: 报名了悟空中文
A29: 26 | B29: 5.5 | C29: 美国 | D29: 西部 | E29: 15 | F29: M | G29: meelion | H29: 焦黎明 | I29: 8 | J29: 男 | K29: 学过 | L29: 否 | M29: 学了三年了 | N29: 中文 | O29: 识字量到一下的程度，但是书写不理想，建议从一上八单元开始上课。 | P29: 周虹 10:20 5.5 Chineseonline H 8:20 5.8 | Q29: 微信 | R29: 3 | S29: 王可 | T29: 5.8 | U29: 白 | V29: 白 | W29: 1 | X29: 1 | Y29: 1 | Z29: 50/课 | AA29: 一对四130+10课时 | AB29: 焦黎明，焦子黎共13000 | AC29: 5.16日缴费
A30: 27 | B30: 5.5 | C30: 美国 | D30: 西部 | E30: 15 | F30: M | G30: meelion | H30: 焦子黎 | I30: 5 | J30: 女 | K30: 没学 | L30: 否 | M30: 还没学过，家长想让学习拼音，说孩子吸收能力不错 | N30: 中文 | O30: 建议拼音i;u;开始学起，接受能力很强，比较活泼，有一定的识字量。测试课简单的学习了a;o;e还需要复习 | P30: 杨静 11:00 5.5 chineseonline Z 7:00 5.9 | Q30: 微信 | R30: 3 | S30: 王可 | T30: 5.8 | U30: 白 | V30: 白 | W30: 1 | X30: 1 | Y30: 1 | Z30: 50/课 | AA30: 一对四130+10课时 | AB30: 焦黎明，焦子黎共13000 | AC30: 5.16日缴费
A31: 28 | B31: 5.5 | C31: 澳大利亚 | D31: 悉尼 | E31: 2 | F31: ［］IVY[] | G31: 无 | H31: 冠聪 | I31: 8 | J31: 男 | K31: 没学 | L31: 否 | M31: 没学过 | N31: 中文 | O31: 零基础，建议认字天地人开始学起，接受能力快，双语 | P31: 杨静；14：20；5.5 | Q31: 微信 | R31: 3 | S31: 展旺 | W31: 0 | X31: 0 | Y31: 蹭课，上课后直接说孩子不敢兴趣
A32: 29 | B32: 5.5 | C32: 美国 | D32: 东部 | E32: 12 | F32: Ella | G32: wangqian52572538 | H32: kelvin | I32: 4 | J32: 男 | K32: 没学过 | L32: 否 | M32: 日常中文交流，但没学过中文 | N32: 启蒙 | O32: 16262259586 | P32: 卢爽7:40 5.5 | Q32: 微信 | R32: 3 | S32: 严杨洁 | U32: 兼
A33: 30 | B33: 5.5 | C33: 加拿大 | D33: 温哥华 | E33: -15 | F33: lena | G33: jinlaxu | H33: 奥利维亚 | I33: 3.8 | J33: 女 | K33: 无 | L33: 否 | M33: 在家中一直坚持说中文 喜欢画画 坐得住 | N33: 启蒙 | O33: 18640554349 | P33: 卢爽9:00 5.5 | Q33: 家长介绍 | R33: 2 | S33: 赵国花 张加翼妈妈介绍 | T33: 5.6 | U33: 兼 | V33: 兼 | W33: 1 | X33: 1 | Y33: 1 | Z33: 76-6/课 | AA33: 35+6课时 | AB33: 和英语一起4550 | AC33: 5.7日缴费
A34: 31 | B34: 5.5 | C34: 美国 | D34: 洛杉矶 | E34: -15 | F34: Irene 加州洛杉矶地产经纪 | G34: Avril3691 | H34: 孙涵泽 | I34: 5 | J34: 男 | K34: 无 | L34: 是 | M34: 零基础，会说一点点中文，喜欢玩，画画。 | N34: 启蒙 | O34: 13904026582 | P34: 卢爽10:00 5.5 | Q34: 微信 | R34: 2 | S34: 丁阮琪 | T34: 5.6 | U34: 兼 | W34: 0 | X34: 0 | Y34: 马上要解禁了，想要去当地看一下 失败原因：孩子离电脑太近，怕孩子近视，且线下快可以报名了，想去看看线下的情况。_x000D_ CC原因：第一次试读时家长兴趣大，第二次试读明显兴趣下降，两次试读之间隔了一天，家长心态有点变化，下次家长要求第二次试读时，尽可能将时间排的紧密。_x000D_ 老师原因：老师其他地方都很好，可以吸引孩子注意力，让孩子集中听课，以后上课提醒孩子不要离电脑更近会更好。_x000D_
A35: 32 | B35: 5.6 | C35: 加拿大 | D35: 温哥华 | E35: -15 | F35: 喵 | G35: kkforever311 | H35: 戴辰熠 | I35: 4.5 | J35: 男 | K35: 否 | L35: 否 | M35: 会说中文，不认识字 | N35: 启蒙 | O35: +1 6043550310 | P35: 卢爽7:30 5.6 | Q35: 家长介绍 | R35: 兼 | S35: 俞酉兰 | T35: 5.6 | U35: 兼 | W35: 0 | X35: 0 | Y35: 0 | Z35: 微信没有回复
A36: 33 | B36: 5.6 | C36: 加拿大 | E36: 12 | G36: xiaoyu648727 | H36: Jayden | I36: 3 | J36: 男 | K36: 否 | L36: 否 | M36: 零基础，小朋友爱动坐不住，001 6479880186 | N36: 启蒙 | O36: 001 6479880186 | P36: 卢爽22:00 5.5 | Q36: 家长介绍 | R36: 1 | S36: 何家昌 aiden妈妈介绍 | T36: 5.5 | U36: 兼 | Y36: 家长觉得孩子不适合线上上课，不打算报名
A37: 34 | B37: 5.6 | C37: 法国 | E37: 6 | G37: paris-xuri | H37: 甘蔡铭 | I37: 7 | K37: 没有 | L37: 否 | M37: 平时中文交流，妈妈自己教的 | N37: 中文 | O37: 从拼音开始学，孩子很配合老师 | P37: 程晓茹 18:30 5.5 言智14 单紫薇 18:45 5.8 | Q37: 电话 | R37: 1 | S37: 赵红艳 | T37: 5.8 | U37: 兼 | Y37: 妈妈想给孩子报当地的，能让孩子交到更多朋友，而且当地可以申请免费都
A38: 35 | B38: 5.6 | C38: 加拿大 | D38: 温哥华 | E38: -15 | F38: light | G38: wxid-1559075596412 | H38: 马潇童 | I38: 6 | J38: 女 | K38: 否 | L38: 否 | M38: 会说会听没有学过 | N38: 中文 | O38: 拼音的复韵母开始（一上第三单元）（爸爸想让孩子上一对一） | P38: 黄礼云10:20 5.6 Chineseonline F 9:40 5.12 | Q38: 扫一扫 | R38: 白 | S38: 俞酉兰 | W38: 0 | X38: 0 | Y38: 想上一对一但是觉得价格贵
A39: 36 | B39: 5.6 | C39: 加拿大 | D39: 温哥华 | E39: -15 | F39: light | G39: wxid-1559075596412 | H39: 马诗蕊 | I39: 8 | J39: 女 | K39: 有 | L39: 否 | M39: 国内上完2年级了 | N39: 中文 | O39: 三上四年级开始（孩子在国内学到二年级，程度不错，爸爸觉得一对多可能效果好一点） | P39: 黄礼云9：40 5.6 | Q39: 扫一扫 | R39: 白 | S39: 俞酉兰 | W39: 0 | X39: 0 | Y39: 想上一对一但是觉得价格贵
A40: 37 | B40: 5.6 | C40: 加拿大 | E40: 加拿大 | F40: Nancy | G40: wxid_qnjid09ucqbf22 | H40: 李曜竹 | I40: 10 | J40: 女 | K40: 是 | L40: 否 | M40: 在中国学习到二年级上学期，忘了很多 | N40: 中文 | O40: 二上四单元开始（程度不错） | P40: 黄礼云9:00 5.6 | Q40: 家长介绍 | R40: 白 | S40: 周禹辰妈妈介绍 | W40: 0 | X40: 0 | Y40: 没课合适
A41: 不计人数 | B41: 5.6 | C41: 加拿大 | E41: 加拿大 | F41: Nancy | G41: wxid_qnjid09ucqbf22 | H41: 李曜竹 | I41: 10 | J41: 女 | K41: 是 | L41: 否 | N41: 书法 | P41: 书法课堂6:10 5.4 | Q41: 家长介绍 | R41: 白 | S41: 周禹辰妈妈介绍 | T41: 5.5 | U41: 兼 | V41: 兼 | W41: 1 | X41: 1 | Y41: 书法活动课，要学毛笔书法，不学钢笔，退费 | AB41: 288 已退费 | AC41: 5.4
A42: 38 | B42: 5.6 | C42: 美国 | D42: 纽约 | E42: -12 | F42: 小惠 | G42: LH3478861338 | H42: 心心 | I42: 10 | J42: 女 | K42: 否 | L42: 是 | M42: 没学过 | N42: 中文 | P42: Chineseonline W 8:20 5.6 | Q42: 群聊添加 | R42: 白 | S42: 俞酉兰 | T42: 5.6 | U42: 白 | W42: 0 | X42: 0 | Y42: 想上一周两节 周末班价格接受不了
A43: 39 | B43: 5.6 | C43: 美国 | D43: 纽约 | E43: -12 | F43: 小惠 | G43: LH3478861338 | H43: 小菱子 | I43: 4.5 | J43: 女 | K43: 否 | L43: 是 | M43: 没学过 | N43: 启蒙 | P43: 卢爽8:00 5.1 | Q43: 群聊添加 | R43: 白 | S43: 俞酉兰 | T43: 5.7 | U43: 兼 | W43: 0 | X43: 0 | Y43: 想上一周两节 周末班价格接受不了
A44: 40 | B44: 5.6 | C44: 美国 | D44: 北加州 | E44: -15 | F44: Panda | G44: wxid_evu8i0hueb0012 | H44: 于昊李 | I44: 8 | J44: 男 | K44: 否 | L44: 是 | M44: 没学过中文 | N44: 中文 | P44: Chineseonline W 8:20 5.6 | Q44: 家长介绍 | R44: 白 | S44: 俞酉兰 | T44: 5.6 | U44: 白 | V44: 白 | W44: 1 | X44: 1 | Y44: 1 | Z44: 56/课 | AA44: 65课时 | AB44: 3640 | AC44: 5.7日缴费
A45: 41 | B45: 5.6 | C45: 美国 | D45: 东部 | E45: 12 | F45: lily | G45: lilyyanjiang80 | H45: 姜宇康 | I45: 7 | J45: 男 | K45: 学过一点 | L45: 否 | M45: 一年级 | N45: 中文 | P45: ChineseonlineZ 7:00 5.6 | Q45: 微信 | R45: 3 | S45: 王可 | W45: 0 | X45: 0 | Y45: 试完觉得很好，想要一家三个一起学，但是后来又说不要了
A46: 42 | B46: 5.6 | C46: 美国 | D46: 东部 | E46: 12 | F46: Midu米多 | G46: midumidu8 | H46: 孔霆曦 | I46: 10 | J46: 男 | K46: 没学过 | L46: 否 | M46: 之前学过一段时间，没学过拼音直接识字了 | N46: 中文 | O46: 识字部分生字基本上都认识，拼音没有学过，建议从拼音开始学起【家长较为严格，希望孩子学习以后能够考级】 | P46: 周虹 7:00 5.6 | Q46: 微信 | R46: 3 | S46: 杨斌 | V46: 0 | W46: 0 | X46: 0 | Y46: 像是已经在其他地方学了，来蹭课
A47: 43 | B47: 5.6 | C47: 美国 | D47: 东部 | E47: 12 | F47: Midu米多 | G47: midumidu8 | H47: 孔霆毅 | I47: 8 | J47: 男 | K47: 没学过 | L47: 否 | M47: 之前学过一段时间，没学过拼音直接识字了 | N47: 中文 | O47: 认识的生字比哥哥少，拼音没有学过，接受程度好，比较害羞，建议从拼音开始学【拼音学了aoe，讲了a的四声】 | P47: 周虹 7:40 5.6 | Q47: 微信 | R47: 3 | S47: 杨斌 | V47: 0 | W47: 0 | X47: 0 | Y47: 像是已经在其他地方学了，来蹭课
A48: 44 | B48: 5.6 | C48: 美国西部 | E48: -15 | F48: 何牙琴 | G48: hesumosuiloveyou | H48: 苏荷 | I48: 6 | J48: 女 | L48: 否 | M48: 零基础，中文口语一般 | N48: 中文 | O48: 上课很积极，配合度很高，简单的生字认识，建议从拼音开始学 | P48: 周虹 8:20 5.6 | Q48: 微信 | R48: 0 | S48: 王晨 | W48: 0 | X48: 0 | Y48: 价格贵
A49: 45 | B49: 5.6 | C49: 美国 | D49: 中部 | E49: 13 | F49: 王碧云 | G49: wang-20080630 | H49: 吴梓旭 | I49: 12 | J49: 男 | K49: 没有 | L49: 否 | M49: 只会说，看和写都不会 | N49: 中文 | O49: 配合度很高，比较活泼，生字和拼音都是零基础，建议从拼音开始学。 | P49: 周虹 9:00 5.6 Chineseonline w 8:20 5.11 言智02 5.18 | Q49: 电话 | R49: 3 | S49: 杨斌 | T49: 5.16 | U49: 白 | V49: 兼 | W49: 1 | X49: 1 | Y49: 1 | Z49: 96/课 | AA49: 一对二，65+4课时 | AB49: 6240 | AC49: 5.16日缴费
A50: 46 | B50: 5.6 | C50: 美国 | D50: 洛杉矶 | E50: -15 | F50: 灵溪 | H50: 范依灵 | I50: 6 | J50: 女 | L50: 否 | M50: 零基础，可以日常中文交流 | N50: 中文 | O50: 零基础的，家长想从识字开始上课，先不学拼音，怕会跟英语混淆，建议从识字开始上课。 | P50: 周虹 9:40 5.6 Chineseonline O1 9:00 | Q50: 微信 | R50: 0 | S50: 王晨 | T50: 5.8 | U50: 白 | W50: 0 | X50: 0 | Y50: 失联了
A51: 47 | B51: 5.6 | C51: 新西兰 | E51: 4 | F51: 樱桃 | G51: anranalto | H51: 安树言 | I51: 7 | J51: 男 | M51: 家里学过一点，没有系统性的学习过，拼音学了一些，但是没有全部学过，大概认识20个单词。 | N51: 中文 | O51: 学过一些拼音，但是基本都忘记了，家长想从拼音开始上课，建议从拼音开始上课 | P51: 周虹 10:20 5.6 陆老师课堂 4：40 5.12 魏老师课堂 5:00 5.23 | Q51: 微信 | R51: 2 | S51: 丁阮琪 | T51: 5.8 | U51: 兼 | V51: 兼 | W51: 1 | X51: 1 | Y51: 1 | Z51: 周末班三个月 | AA51: 26课时 | AB51: 444.43 | AC51: 5.12日缴费
A52: 48 | B52: 5.6 | C52: 加拿大 | D52: 温哥华 | E52: -15 | F52: 海茜 Haixi | G52: xiacecilia | H52: 尼克 | I52: 6 | J52: 男 | L52: 有 | M52: 可以正常交流，口语还是可以的。零基础 会拼音哦 | N52: 中文 | O52: 一上的课本家长已经给他上完了，但是有遗忘，建议从一上六单元开始上课。 | P52: 周虹 11:00 5.6 Chineseonline O 11:00 5.8 | Q52: 家长介绍 | R52: 2 | S52: 高翱翔 杜菲菲妈妈介绍 | T52: 5.8 | U52: 白 | V52: 白 | W52: 1 | X52: 1 | Y52: 1 | Z52: 53/课 | AA52: 65课时，与数学分130 | AB52: 和数学一起￥6890 | AC52: 5.7日缴费
A53: 49 | B53: 5.6 | C53: 加拿大 | E53: 12 | F53: EIisa | G53: EIisa20131 | H53: 杨怡璐 | I53: 10 | N53: 数学 | P53: 夜班3:00 5.1 | Q53: 第二门课 | R53: 3 | S53: 杨斌 | T53: 5.2 | U53: 夜 | V53: 兼 | W53: 1 | X53: 1 | Y53: 1 | Z53: 53/课 | AA53: 130+8课时 | AB53: 6890 | AC53: 5.6日缴费
A54: 50 | B54: 5.6 | C54: 美国 | D54: 东部 | E54: 12 | F54: Syler | G54: meggy123_ | H54: 芸鹤 | I54: 10 | J54: 男 | K54: 学过一点 | L54: 否 | M54: 拼音学过 | N54: 中文 | O54: 一上五单元（声调分不清） | P54: 黄礼云 7:40 5.6 天娃课堂03 7:00 5.8 | Q54: 家长介绍 | R54: 3 | S54: 张霞 | T54: 5.8 | U54: 兼 | W54: 0 | X54: 0 | Y54: 报名了悟空中文
A55: 51 | B55: 5.6 | C55: 美国 | D55: 加州 | E55: 15 | F55: Michelle | G55: lei_michelle_lai | H55: 王若轩 | I55: 11 | J55: 男 | K55: 学过 | L55: 否 | M55: 一直学的马立平教材，现在已经六年级了。想学习写作方面，就是要求语法正确，句式，修辞可以很好的掌握，可能要一对一 | N55: 中文 | O55: 四上开始（妈妈想要孩子侧重学习中文语法，主谓宾，写作等） | P55: 黄礼云 8:20 5.6 作文课 秦琪 | Q55: 微信 | R55: 3 | S55: 王可 | T55: 5.9 | U55: 兼 | W55: 0 | X55: 0 | Y55: 想要写作课，试完觉得课程不合适
A56: 52 | B56: 5.6 | C56: 美国 | D56: 休斯顿 | E56: 13 | F56: 李琪 | G56: vicky2renee | H56: 储蕴霖 | I56: 6.5 | J56: 女 | K56: 没有 | L56: 否 | M56: 学了一点悟空识字，听说没问题，主要想提高读写 | N56: 中文 | O56: 拼音开始学起，认字一单元都会。比较活泼，很爱问问题 | P56: 杨静；9：00；5.6 言智03 7:30 5.9 | Q56: 家长介绍 | R56: 3 | S56: 王可 郑仰珺妈妈推荐 | T56: 5.9 | U56: 兼 | W56: 0 | X56: 0 | Y56: 不太回复
A57: 53 | B57: 5.6 | C57: 美国 | D57: 纽约 | E57: 12 | F57: Kailing | G57: kaychen86 | H57: 王可怡 | I57: 9 | J57: 女 | L57: 无 | M57: 是 | N57: 中文 | O57: 零基础，建议拼音a;o;e学起，双语 | P57: 杨静；7：00；5.6 | Q57: 家长介绍 | R57: 2 | S57: 高翱翔 陈毅涵妈妈介绍 | T57: 5.7 | U57: 兼 | V57: 兼 | W57: 1 | X57: 1 | Y57: 1 | Z57: 50/课 | AA57: 130课时 | AB57: 1834 | AC57: 5.7日缴费
A58: 54 | B58: 5.6 | C58: 美国 | D58: 纽约 | E58: 12 | F58: Kailing | G58: kaychen87 | H58: 王奕轩 | I58: 8 | J58: 男 | L58: 无 | M58: 是 | N58: 中文 | O58: 零基础，建议拼音i;u学起，双语。测试课家长要求体验拼音课a;o;e | P58: 杨静；7:40; 5.6 | Q58: 家长介绍 | R58: 2 | S58: 高翱翔 陈毅涵妈妈介绍 | T58: 5.7 | U58: 兼 | V58: 兼 | W58: 1 | X58: 1 | Y58: 1 | Z58: 50/课 | AA58: 130课时 | AC58: 5.7日缴费
A59: 55 | B59: 5.6 | C59: 加拿大 | D59: 温哥华 | E59: 15 | G59: cyrusz1020 | H59: 张颢焜 | I59: 10 | J59: 男 | K59: 否 | L59: 是 | M59: 听的懂，会说一点，不会写字。上过一年台湾中文 | N59: 中文 | O59: 拼音复韵母不熟悉，建议an;en;in 学起，识字量认得100个字左右。学生有点排斥学习中文，需要老师多引导 | P59: 杨静；9：40；5.6 双语课堂 8：20 5.16” | Q59: 电话 | R59: 5 | S59: 严翔 | T59: 5.16 | U59: 白 | Y59: 家长嫌价格贵，课时多，不报名了
A60: 56 | B60: 5.6 | C60: 加拿大 | D60: 温哥华 | E60: -15 | F60: LEAF | G60: leaf7955 | H60: 李重阳 | I60: 6.5 | J60: 男 | K60: 否 | L60: 无 | M60: 否 | N60: 中文 | O60: 天地人开始学起，小孩不爱说话，，老师要耐心慢慢教，听得懂中文。小孩反应过慢。建议一对一 | P60: 杨静；10：20；5.6 Chineseonline O1 9:00 | Q60: 家长介绍 | R60: 2 | S60: 高翱翔 杜菲菲妈妈介绍 | T60: 5.8 | U60: 白 | V60: 白 | W60: 1 | X60: 1 | Y60: 1 | Z60: 56/课 | AA60: 65课时 | AB60: 3640 | AC60: 5.6日缴费
A61: 57 | B61: 5.6 | C61: 美国西部 | E61: -15 | F61: Helen芬 | H61: 李昭星 | I61: 7 | J61: 男 | K61: 否 | L61: 否 | M61: 是 | N61: 中文 | O61: 建议拼音a;o;e学起，孩子比较活泼，双语 | P61: 杨静；11：00；5.6 言智02 10:20 5.8 | Q61: 微信 | R61: 0 | S61: 王晨 | T61: 5.7 | U61: 兼 | W61: 0 | X61: 0 | Y61: 家长不回复了
A62: 58 | B62: 5.6 | C62: 新西兰 | E62: 4 | F62: 樱桃 | G62: anranalto | H62: 安诗若 | I62: 5 | J62: 女 | K62: 无 | L62: 否 | M62: 家里学过一点，没有系统性的学习过，没有拼音基础。 | N62: 启蒙 | O62: 64211467153 | P62: 卢爽9:30 5.6 | Q62: 微信 | R62: 2 | S62: 丁阮琪 | T62: 5.6 | U62: 兼 | W62: 0 | X62: 0 | Y62: 启蒙价格太贵了 失败原因：因家里有两个孩子，哥哥是小学中文课程，价格和哥哥的课程相差较大，只打算报哥哥的。 CC原因：报价格的时候一开始没有报两个孩子一致的，说不定刚开始报一致的价格，两个都能成。如果接受不了一对二的价格，再报一对三和一对四的价格不迟。 第二个孙婷婷老师孩子很喜欢，第一个蒋晓静老师讲的稍微有点快。 美术课失败原因：去别的机构读了。觉得别的机构更适合。_x000D_ 自身原因：_x000D_ 1. 老师用小窗口画画，孩子看不清老师在画什么，最后发脾气不想画了。后来课程过了一半才换成大窗口，但是那时候孩子和家长已经不满了。_x000D_ 2. 家长觉得老师看不到孩子画画的笔法，孩子笔法错误老师也不知道，这样孩子进步不了。_x000D_ 3. 其他机构在这两方面都做的比我们好，所以选择了其他机构。_x000D_
A63: 59 | B63: 5.6 | C63: 加拿大 | D63: 温哥华 | E63: -15 | F63: lena | G63: jinlaxu | H63: 奥利维亚 | I63: 3.8 | J63: 女 | K63: 无 | L63: 否 | M63: 启蒙课学英文 掌握100多个单词 问句会回答 | N63: 英语启蒙 | O63: 18640554349 | P63: 卢爽8:00 5.6 | Q63: 家长介绍 | R63: 2 | S63: 赵国花 张加翼妈妈介绍 | T63: 5.6 | U63: 兼 | V63: 兼 | W63: 1 | X63: 1 | Y63: 1 | Z63: 76-6/课 | AA63: 30课时 | AB63: 和启蒙一起4550 | AC63: 5.7日缴费
A64: 60 | B64: 5.6 | C64: 加拿大 | D64: 为哥华 | E64: -15 | F64: livia | G64: livia6043568919 | H64: 张加翼 | I64: 3.4 | K64: 无 | L64: 否 | M64: 喜欢车车 很爱学习 坐着描写涂鸦能定一个多小时 在家里中文交流无障碍 | N64: 启蒙 | O64: 16043568619 | P64: 卢爽10:30 5.6 | Q64: 家长介绍 | R64: 2 | S64: 赵国花 熙雅妈妈介绍 | T64: 5.6 | U64: 兼 | V64: 兼 | W64: 1 | X64: 1 | Y64: 1 | Z64: 76-6/课 | AA64: 65+6课时，一对二 | AB64: 4550 | AC64: 5.7日缴费
A65: 61 | B65: 5.6 | C65: 美国西部 | E65: -15 | F65: 何牙琴 | G65: hesumosuiloveyou | H65: 苏茉 | I65: 4 | J65: 女 | K65: 否 | L65: 否 | M65: 零基础，口语一般 | N65: 启蒙 | O65: +1 7024880937 | P65: 卢爽9:00 5.6 | Q65: 微信 | R65: 0 | S65: 王晨 | T65: 5.6 | U65: 兼 | W65: 0 | X65: 0 | Y65: 价格贵
A66: 62 | B66: 5.6 | C66: 加拿大 | D66: 多伦多 | E66: 12 | F66: Sasa | G66: wvsasa | H66: 陆茜雯 | I66: 12 | J66: 女 | K66: 没有 | L66: 是 | M66: 4岁零基础，普通话不标准，需要双语 | N66: 启蒙 | O66: +1 8520205581 | P66: 卢爽7:30 5.6 | Q66: 微信 | R66: 3 | S66: 杨斌 | T66: 5.6 | U66: 兼 | V66: 兼 | W66: 1 | X66: 1 | Y66: 1 | Z66: 56/课 | AA66: 65+6课时 | AB66: 3640 | AC66: 5.17日缴费
A67: 63 | B67: 5.6 | C67: 加拿大 | D67: 温哥华 | E67: -15 | F67: blue | G67: lan-3510560669 | H67: 高梓睿 | I67: 3.1 | J67: 男 | K67: 无 | L67: 否 | M67: 三岁多 能听懂中文 不太会说 语言表达力弱 英文口语也是 混血宝宝 粑粑讲英文 麻麻讲中文 | N67: 启蒙 | O67: 16046001049 | P67: 卢爽9:00 5.6 | Q67: 家长介绍 | R67: 2 | S67: 赵国花 奥利维亚妈妈介绍 | T67: 5.6 | U67: 兼 | W67: 0 | X67: 0 | Y67: 语言天赋不好，在接受心理辅导
A68: 64 | B68: 5.6 | C68: 加拿大 | D68: 温哥华 | E68: 15 | G68: sheonchen | H68: 文文 | I68: 3.5 | K68: 否 | L68: 否 | M68: ma | N68: 启蒙 | O68: 8613660309216 | P68: 卢爽8:00 5.6 | Q68: 微信 | R68: 5 | S68: 严翔 | T68: 5.8 | U68: 兼 | Y68: 家长嫌价格贵，孩子又不喜欢
A69: 65 | B69: 5.6 | C69: 加拿大 | D69: 温哥华 | E69: 15 | G69: sheonchen | H69: 友友 | I69: 5.5 | K69: 否 | L69: 否 | M69: 听得懂会说一点不会写 | N69: 启蒙 | O69: 8613660309216 | P69: 卢爽19:00 5.5 | Q69: 微信 | R69: 5 | S69: 严翔 | T69: 5.8 | U69: 兼 | Y69: 家长嫌价格贵，孩子又不喜欢
A70: 66 | B70: 5.7 | C70: 澳大利亚 | D70: 悉尼 | E70: 2 | F70: fc建筑daniel0403530647 | G70: kathaytex | H70: harper hu | I70: 3 | J70: 女 | K70: 否 | L70: 否 | M70: 中文基础不错，不会拼音，会说中文，不需要双语老师，爱好比较贪玩 | N70: 启蒙 | O70: 15618595052 | P70: 卢爽19:00 5.6 | Q70: 电话 | R70: 2 | S70: 杜玉辉 | T70: 5.5 | U70: 兼 | V70: 兼 | W70: 1 | X70: 0 | Y70: 0 | Z70: 188/5课 | AA70: 启蒙体验课 体验完就不交钱了 | AB70: 188 | AC70: 5.14日缴费
A71: 67 | B71: 5.7 | C71: 美国 | D71: 西部 | E71: 15 | F71: 陆姐 | G71: pper | H71: 张三米 | I71: 5 | J71: 男 | K71: 没有 | L71: 否 | M71: 不认识几个字，交流可以 | N71: 启蒙 | O71: 6506222552 | P71: 卢爽8:00 5.7 | Q71: 微信 | R71: 3 | S71: 展旺 | T71: 5.8 | U71: 兼 | W71: 0 | X71: 0 | Y71: 试课后觉得不喜欢
A72: 68 | B72: 5.7 | F72: libby | G72: libbylin1012 | H72: 林祺越 | I72: 7 | J72: 男 | K72: 没有 | L72: 否 | M72: 零基础 | N72: 中文 | O72: 零基础，年龄较小，很害羞，建议从识字开始上。 | P72: 周虹 7:00 5.7 Chineseonline A 7:40 5.8 | Q72: 微信 | R72: 3 | S72: 翁珊珊 | T72: 5.8 | U72: 白 | W72: 0 | X72: 0 | Y72: 弟弟不喜欢
A73: 69 | B73: 5.7 | F73: libby | G73: libbylin1012 | H73: 林飞瑶 | I73: 10 | J73: 女 | K73: 没有 | L73: 否 | M73: 零基础 | N73: 中文 | O73: 零基础，比弟弟的程度好，建议从识字或者拼音上课都可以【妈妈想让两个孩子分开上课】 | P73: 周虹 7:40 5.7 Chineseonline w 8:20 5.11 | Q73: 微信 | R73: 3 | S73: 翁珊珊 | W73: 0 | X73: 0 | Y73: 姐姐排了课但是课堂号写错了，没上课，后来就不要了
A74: 70 | B74: 5.7 | C74: 美国 | G74: chenamy | H74: 苏烨 | I74: 15 | J74: 男 | K74: 学过一点 | L74: 否 | M74: 会说，没有拼音就不会看，拼音会一点点，在美国学校学习过一点中文 | N74: 中文 | O74: 必须借助拼音拼读，能识字但是有很多不会书写，从一上六单元开始上课。【由于孩子年龄较大，已经建议家长报一对一或者一对二的课程】 | P74: 周虹 8:20 5.7 Chineseonline O 8:20 5.8 言智03 9：20 5.11 | Q74: 介绍 | R74: 3 | S74: 展旺 | T74: 没来试读 | U74: 兼 | W74: 0 | X74: 0 | Y74: 想报少的课程，没让报
A75: 71 | B75: 5.7 | C75: 西班牙 | D75: 马德里 | E75: 6 | G75: wangjinmadrid | H75: 肖迪娜 | I75: 14 | J75: 女 | K75: 有 | L75: 否 | M75: 国内小学毕业，学初一数学 | N75: 数学 | P75: ChineseonlineB11 18:00 5.6 | Q75: 微信 | R75: 5 | S75: 严翔 | T75: 没来试课 | U75: 兼 | Y75: 家长觉得我们数学课课件不好，选择线下学
A76: 72 | B76: 5.7 | C76: 加拿大 | D76: 温哥华 | E76: -15 | F76: 海茜 Haixi | G76: xiacecilia | H76: 尼克 | I76: 6 | J76: 男 | L76: 有 | M76: 可以正常交流，口语还是可以的。零基础 会拼音哦 | N76: 数学 | O76: 一上的课本家长已经给他上完了，但是有遗忘，建议从一上六单元开始上课。 | P76: 周虹 11:00 5.6 言智19 9:40 5.6 | Q76: 家长介绍 | R76: 2 | S76: 高翱翔 杜菲菲妈妈介绍 | T76: 5.7 | U76: 兼 | V76: 兼 | W76: 1 | X76: 1 | Y76: 1 | Z76: 53/课 | AA76: 65课时，与中文分130 | AB76: 和中文一起￥6890 | AC76: 5.7日缴费
A77: 73 | B77: 5.7 | C77: 美国 | D77: 拉斯维加斯 | E77: 15 | G77: lichunjin1111 | H77: 王馨镁 | I77: 12 | J77: 女 | K77: 是 | L77: 否 | M77: 中文5年基础 | N77: 中文 | P77: 二十课堂A 9:00 5.7 | Q77: 电话 | R77: 5 | S77: 倪林行 | U77: 兼 | V77: 兼 | W77: 1 | X77: 1 | Y77: 1 | Z77: 116/课 | AA77: 一周三节，65课时 二四六上课 | AB77: 1070 | AC77: 5.12日缴费
A78: 74 | B78: 5.7 | C78: 加拿大 | D78: 多伦多 | E78: 12 | F78: Joanna车险房险人寿险旅游险商业 | G78: Joanna_jiangna | H78: 陈俊名 | I78: 8 | J78: 男 | K78: 学过 | L78: 是 | M78: 完成了小学二年级，该学三年级了，中文口语程度好 | N78: 中文 | O78: 建议二下第八单元最后一节学起，认字量很多不理解课文，但是不会组词和造句 | P78: 杨静；7：00；5.7 第七课堂5:20 5.13 | Q78: 微信 | R78: 2 | S78: 平金军 | U78: 夜 | W78: 0 | X78: 0 | Y78: 没时间只能上周末班，觉得价格贵
A79: 75 | B79: 5.7 | C79: 加拿大 | D79: 多伦多 | E79: 12 | F79: Joanna车险房险人寿险旅游险商业 | G79: Joanna_jiangna | H79: 陈艾迪 | I79: 6 | J79: 女 | K79: 会一点 | L79: 是 | M79: 学前班，几十个字，中文口语程度好 | N79: 中文 | O79: 建议拼音ai;ei;ui开始学起，认字课都会。 | P79: 杨静；7：40；5.7 第十课堂5:20 5.13 | Q79: 微信 | R79: 2 | S79: 平金军 | U79: 夜 | W79: 0 | X79: 0 | Y79: 没时间只能上周末班，觉得价格贵
A80: 76 | B80: 5.7 | F80: 吉米妈妈 | G80: ilmsjimmy1023 | H80: 陈吉米 | I80: 7 | J80: 男 | K80: 没有 | L80: 是 | M80: 之前没有学过 但是能听懂一点点，发音不标准 | N80: 中文 | O80: 建零基础，建议天地人学起，后期再开始拼音。接收能力很快，双语 | P80: 杨静；9：00；5.7 言智11 9:20 5.9 | Q80: 微信 | R80: 3 | S80: 展旺 | T80: 5.8 | U80: 兼 | V80: 兼 | W80: 1 | X80: 1 | Y80: 1 | Z80: 53/课 | AA80: 一对四130课时 | AB80: 6490 | AC80: 5.12日缴费
A81: 77 | B81: 5.7 | C81: 加拿大 | E81: 12 | F81: Maple | G81: j88cheng | H81: 成绍华 | I81: 9岁 | J81: 男 | K81: 有 | L81: 否 | M81: 有中文基础，口语程度一般,大概一年级水平 | N81: 中文 | O81: 一下二单元开始（学生很配合，中文很好，但是认字可能会混淆） | P81: 黄礼云；7：40；5.7 | Q81: 电话 | R81: 1 | S81: 曹桂菊 | Y81: 家长觉得线下学了，没必要学线上的了
A82: 78 | B82: 5.7 | C82: 加拿大 | E82: 12 | F82: Maple | G82: j88cheng | H82: 成绍天 | I82: 7岁 | J82: 女 | K82: 否 | L82: 否 | M82: 有中文基础，口语程度一般 | N82: 中文 | O82: 一上第五单元开始（乖巧可爱） | P82: 黄礼云；8：20；5.7 | Q82: 电话 | R82: 1 | S82: 曹桂菊 | Y82: 家长觉得线下学了，没必要学线上的了
A83: 79 | B83: 5.7 | C83: 美国 | E83: 12 | G83: ycx-yc | H83: 曹小洋 | I83: 8 | J83: 男 | K83: 否 | L83: 否 | M83: 只会一点点 | N83: 中文 | O83: 拼音zh ch sh学起（aoeiuv测了，学的比较快） | P83: 黄礼云；9：00；5.7 | Q83: 微信 | R83: 1 | S83: 李波 | Y83: 再约第二次试读
A84: 80 | B84: 5.7 | C84: 意大利 | E84: 6 | F84: Jin慧慧 | G84: Baby-Jin001 | H84: durocky | I84: 14 | J84: 男 | K84: 有 | L84: 否 | M84: 可以用中文交流 | N84: 中文 | O84: 一年级水平 | P84: 夜班23:30 5.6 | Q84: 微信 | R84: 3 | S84: 王可 | U84: 夜 | Y84: 孩子大了，但是测出来是一年级水平，孩子不太喜欢
A85: 81 | B85: 5.7 | C85: 意大利 | E85: 6 | F85: Jin慧慧 | G85: Baby-Jin001 | H85: dumixi | I85: 12 | J85: 女 | K85: 没有 | L85: 否 | M85: 可以用中文交流 | N85: 中文 | O85: 一年级水平 | P85: 夜班23:30 5.6 | Q85: 微信 | R85: 3 | S85: 王可 | U85: 夜 | Y85: 孩子大了，但是测出来是一年级水平，孩子不太喜欢
A86: 82 | B86: 5.7 | C86: 法国 | E86: 6 | G86: linbosas | H86: 高振豪 | I86: 7 | J86: 男 | K86: 否 | L86: 否 | M86: 妈妈自己在家教的，没有学过拼音 | N86: 中文 | O86: 从iuv开始（测试学的aoe，孩子有一点认字基础，妈妈在家教的，没学过拼音） | P86: 黄礼云；15：40；5.7 ChineseonlineZ 14:50 5.9 | Q86: 电话 | R86: 1 | S86: 赵红艳 | T86: 5.9 | U86: 白 | V86: 白 | W86: 1 | X86: 1 | Y86: 1 | Z86: 59/课 | AA86: 一对四22课时 | AB86: 1298 | AC86: 5.8日缴费
A87: 83 | B87: 5.7 | C87: 加拿大 | D87: 温哥华 | E87: -15 | F87: 海晴erika | G87: iamabearmom | H87: 梁得意 | I87: 7 | J87: 男 | K87: 无 | L87: 否 | M87: 在家说中文，零基础。喜欢别人叫她小得意 | N87: 中文 | P87: 周虹 10:20 5.7 言智18 10:30 | Q87: 微信 | R87: 2 | S87: 高翱翔 | T87: 5.8 | U87: 兼 | V87: 兼 | W87: 1 | X87: 1 | Y87: 1 | Z87: 116/课 | AA87: 65课时 | AB87: C$1501 | AC87: 5.7日缴费
A88: 84 | B88: 5.7 | C88: 美国 | D88: 都柏林 | E88: -15 | F88: 徐一 | G88: xuyi9621 | H88: Chloe | I88: 3 | J88: 女 | K88: 否 | L88: 是 | M88: 零基础，口语不好 | N88: 启蒙 | O88: +1 9253006680 | P88: 卢爽8:00 5.7 | Q88: 微信 | R88: 0 | S88: 王晨 | U88: 兼 | W88: 0 | X88: 0 | Y88: 只想买很少的课
A89: 85 | B89: 5.7 | C89: 美国 | D89: 纽约 | E89: 12 | G89: xbjennyyang | H89: 翁梓昱 | I89: 3 | J89: 女 | K89: 无 | L89: 是 | M89: 零基础，需要双语 | N89: 启蒙 | O89: 19178658300 | P89: 卢爽7:30 5.7 | Q89: 电话 | R89: 2 | S89: 丁阮琪 | T89: 5.7 | U89: 兼 | W89: 0 | X89: 0 | Y89: 失败原因：本身意向并不是很高，询问价格后，价格太高是一方面，觉得孩子也还小，可以再大些再学。试读体验也不是那么好。_x000D_ 自身原因：开始前一天提醒了启蒙老师创建房间，那时候家长虽然已经报给我电话号码，但还没有注册，因已经拿到帐号，就自然而然的以为家长已经注册了，没有问家长一句注册好没。开始前半小时没有提醒启蒙老师创建房间，导致家长等了几分钟。等创建好房间，家长没等到老师，家长走开了。一来一回去了将近十分钟。老师后面还有排课也没办法延长课堂。上课时长严重不足，导致体验不好。_x000D_
A90: 86 | B90: 5.7 | C90: 澳洲 | D90: 悉尼 | E90: 2 | F90: lioyd | G90: lioyd_001 | H90: Anelia Chiew | I90: 3 | J90: 女 | K90: 无 | L90: 是 | M90: 家里面的人中文不是很好，朋友推荐，就试试课程 | N90: 启蒙 | O90: 61432012291 | P90: 卢爽9:30 5.7 | Q90: 电话 | R90: 2 | S90: 杜玉辉 | T90: 5.9 | U90: 兼 | W90: 0 | X90: 0 | Y90: 0
A91: 87 | B91: 5.7 | C91: 美国 | D91: 新泽西 | E91: 12 | G91: shelly | H91: 林子轩 | I91: 3.5 | J91: 男 | K91: 否 | L91: 否 | M91: 简单沟通 零基础 | N91: 启蒙 | O91: +1 6016222032 | P91: 卢爽9:00 5.7 | Q91: 电话 | R91: 5 | S91: 李波 | T91: 5.7 | U91: 兼 | Y91: 妈妈觉得年纪太小，坐不住
A92: 88 | B92: 5.7 | C92: 美国 | D92: 亚特兰大 | E92: -12 | F92: Maggie | G92: maggielovechen | H92: 付悦珍 | I92: 14 | J92: 女 | K92: 否 | L92: 否 | M92: 可以中文交流，没学过编程 | N92: 编程 | P92: 编程课堂王老师8:30 5.7 | Q92: 微信 | R92: 0 | S92: 王晨 | T92: 5.7 | U92: 兼 | W92: 0 | X92: 0 | Y92: 课程不合适
A93: 89 | B93: 5.7 | C93: 美国 | D93: 丹佛 | E93: -14 | F93: Kiki | G93: pangjing198044 | H93: 李明泽 | I93: 7 | J93: 男 | K93: 否 | L93: 否 | M93: 可以中文交流，没学过编程 | N93: 编程 | P93: 编程课堂王老师9:00 5.7 | Q93: 微信 | R93: 0 | S93: 王晨 | T93: 5.7 | U93: 兼 | W93: 0 | X93: 0 | Y93: 孩子不喜欢
A94: 90 | B94: 5.7 | C94: 美国 | D94: 洛杉矶 | E94: 15 | G94: kiss-mm | H94: 小熊 | I94: 2.5 | M94: 零基础 | N94: 启蒙 | P94: 卢爽1:00 5.7 | Q94: 微信 | R94: 5 | S94: 严翔 | T94: 5.8 | U94: 兼 | Y94: 孩子坐不住，家长打算在大点来学习
A95: 91 | B95: 5.8 | C95: 加拿大 | D95: 温哥华 | E95: -15 | F95: Shirley | G95: maggie476 | H95: 李若华 | I95: 7 | J95: 女 | K95: 是 | L95: 否 | M95: 一年级下册 | N95: 中文 | O95: 一年级下册二单元左右（妈妈希望排到差不多年龄的班级，因为之前上的课年龄差两三岁孩子不爱上课了，需要能调动积极性的，孩子比较活泼 | P95: 黄礼云；10：20；5.8 ChineseonlineH，11：40 5.12 | Q95: 微信 | R95: 白 | S95: 群聊添加 | T95: 5.11 | U95: 白 | Y95: 时间太晚了，要改早一点
A96: 92 | B96: 5.8 | C96: 美国 | D96: 洛杉矶 | E96: -15 | F96: Jimmy's & Jeffy's mommy---Ivy | H96: 伍駿驄（Jimmy） | I96: 5.1 | J96: 男 | K96: 否 | L96: 否 | M96: 自己教过，识字量200个左右 | N96: 启蒙 | P96: 卢爽7:00 5.8 | Q96: 代理 | R96: 白 | S96: 陈静 | T96: 5.13 | U96: 兼 | Y96: 家长觉得老师应该多引导，而不是让孩子重复
A97: 93 | B97: 5.8 | F97: 贤（Julia) | G97: batmanlogo | H97: 欧俊贤 | I97: 9 | J97: 男 | K97: 学过一点 | L97: 否 | M97: 当地学到三年级中文，广东话会多点，普通话也会 | N97: 中文 | O97: 建议二年级下第一单元学起，认字量很大，写字和组词需要加强 | P97: 杨静；7:40,5.8 Chineseonline Q1 7:00 5.11 | Q97: 微信 | R97: 3 | S97: 杨斌 | T97: 5.12 | U97: 兼 | V97: 兼 | Y97: 在谈
A98: 94 | B98: 5.8 | C98: 美国 | D98: 纽约 | E98: 12 | F98: yuan | G98: wxid_0929789297715 | H98: Lucasji | I98: 9 | J98: 男 | K98: 是 | L98: 否 | M98: 能中文交流在学马丽萍四年级，识字量500-1000，读写弱 | N98: 中文 | O98: 三年级上册四单元 | P98: 黄礼云；9：40；5.8 ChineseonlineA 9：40 5.12 | Q98: 微信 | R98: 3 | S98: 张霞 | T98: 5.12 | U98: 白 | W98: 0 | X98: 0 | Y98: 挺喜欢我们的，报名了夏令营，想要美国早上上课，等夏令营结束了再看
A99: 95 | B99: 5.8 | C99: 美国 | D99: 纽约 | E99: 12 | F99: melanie | G99: wxid-59bk2b3s2ydh12 | H99: 蔡可 | I99: 7 | J99: 女 | K99: 否 | L99: 是 | M99: 只会一点点 | N99: 中文 | O99: 拼音学起，双语。小孩不太爱说话。老师要耐心些，慢慢引导。 | P99: 杨静；9:00；5.8 言智02，6：35，5.14 | Q99: 微信 | R99: 3 | S99: 程蕾 | T99: 5.9 | U99: 兼 | V99: 兼 | W99: 1 | X99: 1 | Y99: 1 | Z99: 96/课 | AA99: 一对二65课时 | AB99: 蔡含蔡章蔡可共19120，三人团优惠900 | AC99: 5.13日缴费
A100: 96 | B100: 5.8 | C100: 美国 | D100: 纽约 | E100: 12 | F100: melanie | G100: wxid-59bk2b3s2ydh12 | H100: 蔡含 | I100: 11 | J100: 女 | K100: 是 | L100: 否 | M100: 学过 | N100: 中文 | O100: 复韵母那里复习一下，然后学习课文 | P100: 黄礼云；8：20；5.8 十八课堂C 7:00 5.9 | Q100: 微信 | R100: 3 | S100: 程蕾 | T100: 5.9 | U100: 兼 | V100: 兼 | W100: 1 | X100: 1 | Y100: 1 | Z100: 96/课 | AA100: 一对二65课时 | AC100: 5.13日缴费
...

Sheet 2020.4
A1: 新生接待试读表 业务员：测+读 老师：试读两次
A2: 序号 | B2: 测试时间 | C2: 国家 | D2: 城市 | E2: 时差 | F2: 家长微信名 | G2: 家长微信 | H2: 学生姓名 | I2: 年龄 | J2: 性别 | K2: 有没有学过拼音 | L2: 是否需要双语老师 | M2: 家长自述程度及学习需求 | N2: 学习课程 | O2: 测试结果 | P2: 排课安排 | Q2: 来源 | R2: 组别 | S2: 试读日期 | T2: 业务员 | U2: 排课分组 | V2: 是否在读 | W2: 是否缴费 | X2: 失败原因 | Y2: 课程单价 | Z2: 折扣 | AA2: 实收 | AB2: 首次收费时间 | AG2: =SUM(A2:AF2) -> 0
A3: 1 | B3: 4.1 | C3: 西班牙 | D3: 昆卡 | E3: 6 | F3: cristina | G3: Hhy820905 | H3: 陈芸汐 | I3: 13 | J3: 女 | N3: 数学 | Q3: 报第二门课 | R3: 夜 | T3: 夜 | U3: 兼 | V3: 0 | W3: 0 | X3: 中文课转成数学课，上完就停课
A4: 2 | B4: 4.1 | C4: 澳洲 | E4: 3 | G4: ytt7757942 | H4: 于茗舟 | J4: 男 | K4: 否 | L4: 否 | M4: 1 61403073278 | N4: 启蒙 | P4: 卢爽11:00 4.1 | Q4: 学生兄妹 | R4: 1 | T4: 张文红 | U4: 兼 | V4: 0 | W4: 0 | X4: 杨于葳弟弟，等大一点会来学
A5: 3 | B5: 4.1 | C5: 巴西 | E5: 11 | F5: Lidia Wang | G5: lidia_wang_liqin | H5: 叶雨泽 | I5: 8 | J5: 男 | L5: 否 | M5: 二年级数学 | N5: 数学 | P5: 十一课堂B 仇老师4.1 | Q5: 学生兄妹 | R5: 白 | T5: 叶瑜繁弟弟 | U5: 兼 | V5: 1 | W5: 1 | X5: 和叶瑜繁一起交
A6: 4 | B6: 4.1 | C6: 美国 | D6: 加州 | E6: 15 | F6: Kay 巴菲特地产BROKER | G6: Kaywolf0531 | H6: 乃欧咪Naomi Wolf | I6: 6 | J6: 女 | K6: 有 | L6: 否 | M6: 零基础 学编程 | N6: 编程 | O6: 试过半小时，喜欢 | P6: 编程课堂王老师 9:00 4.1 | Q6: 报第二门课 | R6: 白 | T6: 微信 | U6: 兼 | V6: 1 | W6: 1 | X6: 1 | Y6: 180/课 | Z6: 一周一次 | AA6: ＄100.08 | AB6: 4.1日缴费
A7: 5 | B7: 4.1 | C7: 加拿大 | D7: 多伦多 | E7: 12 | F7: kiki | G7: wxid_3qx4wrt8a5ya21 | H7: 陈婷婷 | I7: 10 | J7: 女 | K7: 无 | L7: 是 | M7: 零基础，不会普通话交流，只会粤语和英语 | N7: 中文 | O7: 需要双语，一上识字开始学 | P7: 徐晓晓8:00 4.1 范老师课堂8:00 4.4 | Q7: 微信 | R7: 2 | T7: 高翱翔 | U7: 兼 | V7: 0 | W7: 0 | X7: 价格贵
A8: 6 | B8: 4.1 | C8: 加拿大 | D8: 多伦多 | E8: 12 | F8: kiki | G8: wxid_3qx4wrt8a5ya21 | H8: 陈镇聪 | I8: 13 | J8: 男 | K8: F | L8: 是 | M8: 会简单交流，非常基础， | N8: 中文 | O8: 不需要，一上识字开始 | P8: 徐晓晓8:00 4.1 范老师课堂8:00 4.4 | Q8: 微信 | R8: 2 | T8: 高翱翔 | U8: 兼 | V8: 0 | W8: 0 | X8: 价格贵
A9: 7 | B9: 4.1 | C9: 加拿大 | D9: 温哥华 | E9: 15 | F9: Winnie 枫情新生活 | G9: audreywinniejohn1009 | H9: 周子欣 | I9: 12 | J9: 女 | K9: 有 | L9: 否 | M9: 拼音学过但是不熟，认识一些常用字，咬字清晰，词汇量一般，写字笔顺很乱不太会写 | N9: 中文 | O9: 不需要双语,建议二上中前期开始 | P9: 胡文君老师 4:00 4.1 | Q9: 电话 | R9: 3 | T9: 杨斌 | U9: 0 | V9: 0 | W9: 0 | X9: 一直没回复
A10: 8 | B10: 4.1 | C10: 澳大利亚 | D10: 布里斯班 | E10: 3 | F10: Daphne千捷 | G10: Daphne_Jie | H10: 岳穆霖 | I10: 4岁半 | J10: 男 | K10: 没学过 | L10: 否 | M10: 认识一百个字左右 想试试学拼音 | N10: 启蒙 | O10: 孩子没有规则意识需要好好引导，建议启蒙或者1对1拼音 | P10: 周虹 7:40 4.1 卢爽 启蒙4.2 | Q10: 微信 | R10: 3 | T10: 翁珊珊 | U10: 兼 | V10: 1 | W10: 1 | X10: 1 | Y10: 96/课 | Z10: 22课时 | AA10: 466澳元 | AB10: 4.10日缴费 | AC10: 岳穆霖，贺羲鸣，Ryan三人一起共￥6240，65+1课时三个人分
A11: 9 | B11: 4.1 | C11: 加拿大 | E11: 12 | G11: F7667C | H11: 陈颖欣 | I11: 10 | J11: 女 | K11: 学一点拼音 | L11: 否 | M11: 学一点拼音 | N11: 中文 | O11: 一上拼音iuv开始 | P11: 周虹 7:40 4.1 卢爽 启蒙4.2 | Q11: 家长介绍 | R11: 1 | T11: 张文红 陈温心妈妈介绍 | U11: 兼 | V11: 1 | W11: 1 | X11: 1 | Y11: 59/课 | Z11: 22课时 | AA11: 1298 | AB11: 4.2日缴费
A12: 10 | B12: 4.1 | C12: 加拿大 | E12: 12 | G12: F7667C | H12: 陈旻泽 | I12: 7 | J12: 男 | K12: 学一点拼音 | L12: 否 | M12: 学一点拼音 | N12: 中文 | O12: 一上拼音iuv开始 | P12: 周虹 7:30 4.1 赵老师课堂 7:00 4.2 | Q12: 家长介绍 | R12: 1 | T12: 张文红 | U12: 兼 | V12: 1 | W12: 1 | X12: 1 | Y12: 59/课 | Z12: 22课时 | AA12: 1298 | AB12: 4.2日缴费
A13: 11 | B13: 4.1 | C13: 加拿大 | E13: 12 | F13: cherry | G13: ch9929926 | H13: 林珍铖 | I13: 11 | J13: 男 | K13: 有 | L13: 否 | M13: 会听中文和基本拼音 书写不行 | N13: 中文 | O13: 一上拼音aoe | P13: 任宏印 8:30 4.1 | Q13: 微信 | R13: 1 | T13: 何家昌 | U13: 0 | V13: 0 | W13: 0 | X13: 孩子不想学
A14: 12 | B14: 4.1 | C14: 加拿大 | E14: 12 | F14: cherry | G14: ch9929926 | H14: 林珍熙 | I14: 6 | J14: 男 | K14: 否 | L14: 否 | M14: 听得差点 不会拼音 不会书写 | N14: 中文 | O14: 一上拼音aoe | P14: 任宏印 8:30 4.1 | Q14: 微信 | R14: 1 | T14: 何家昌 | U14: 0 | V14: 0 | W14: 0 | X14: 孩子不想学
A15: 13 | B15: 4.1 | C15: 澳大利亚 | E15: 3 | F15: Jessica 婕 Z | G15: jie311869 | H15: Annabell Yu（余佳懿） | I15: 7 | J15: 女 | K15: 没学过拼音 | L15: 否 | M15: 国外中文学校二年级 | N15: 中文 | O15: 妈妈问得非常详细，还问了和悟空的对比，孩子口语一般，从拼音或者识字都可以，具体还要顾问跟妈妈在沟通确定 | P15: 任宏印15:30 4.1 赵老师课堂 15:00 4.10 | Q15: 微信 | R15: 3 | T15: 翁珊珊 | U15: 兼 | V15: 0 | W15: 0 | X15: 待定
A16: 14 | B16: 4.1 | C16: 澳大利亚 | E16: 3 | F16: Jessica 婕 Z | G16: jie311869 | H16: Gracelyn Yu（余婧曦） | I16: 9 | J16: 女 | K16: 没学过 | L16: 否 | M16: 国外中文学校四年级，停了两年 | N16: 中文 | O16: 理解力快，学的很好 一上拼音aoe，可以上拼音速成班 | P16: 徐晓晓15:30 4.1 chineseonlineE10 10:50 4.10 | Q16: 微信 | R16: 3 | T16: 翁珊珊 | U16: 兼 | V16: 0 | W16: 0 | X16: 年纪太小坐不住
A17: 15 | B17: 4.1 | C17: 西班牙 | E17: 6 | F17: 婷婷 | G17: tingouyang5 | H17: 翁多豪 | I17: 7 | J17: 男 | K17: 学过一点拼音 | L17: 否 | M17: 1.26日生日 拼音学过一点点，字只学过一到百 | N17: 中文 | O17: 会一点拼音，认识几个简单的字，拼音要拼读重新学 | P17: 徐晓晓17:00 4.1 第十三课堂22:20 | Q17: 微信 | R17: 1 | T17: 俞酉兰 | U17: 夜 | V17: 1 | W17: 1 | X17: 1 | Y17: 660/月 | Z17: 22课时 | AA17: 660 | AB17: 4.8日缴费
A18: 16 | B18: 4.1 | C18: 西班牙 | E18: 6 | F18: 婷婷 | G18: tingouyang5 | H18: 翁佳慧 | I18: 5.5 | J18: 女 | K18: 否 | L18: 否 | M18: 6.4日生日 没学过 | N18: 中文 | O18: 完全零基础，一上识字开始 | P18: 徐晓晓17:00 4.1 | Q18: 微信 | R18: 1 | T18: 俞酉兰 | U18: 0 | V18: 0 | W18: 0 | X18: 不回复了
A19: 17 | B19: 4.1 | C19: 澳大利亚 | D19: 悉尼 | E19: 3 | F19: Annie han | G19: annie9970466 | H19: 黎若诗 | I19: 8 | J19: 女 | K19: 否 | L19: 否 | M19: 当地学过一年，没有学过拼音，认识一些字 | N19: 中文 | O19: 学过一点但是几乎零基础，从一上识字开始 | P19: 徐晓晓17:30 4.1 二十课堂A19:00 4.7 | Q19: 电话 | R19: 3 | T19: 展旺 | U19: 兼 | V19: 0 | W19: 0 | X19: 排课时间隔太久，家长不回复了
A20: 18 | B20: 4.2 | C20: 美国 | D20: 东部 | E20: 12 | F20: 莫颜 | G20: moyanruoxi | H20: 李宇晨 | I20: 6 | J20: 男 | K20: 否 | L20: 是 | M20: 零基础 | N20: 中文 | O20: +1 917 822 7868双语，一上识字开始 | P20: 徐晓晓7:40 4.2 启蒙22:00 4.7 | Q20: 家长介绍 | R20: 3 | T20: 展旺 郑孝颖妈妈介绍 | U20: 兼 | V20: 0 | W20: 0 | X20: 还没完全拒绝，但缴费希望很小
A21: 19 | B21: 4.2 | C21: 加拿大 | D21: 温哥华 | E21: -15 | F21: josie | G21: q247995920 | H21: 李嘉文 | I21: 7 | J21: 女 | K21: 无 | L21: 否 | M21: 个别字会认，会说，有的词不懂意思 | N21: 中文 | O21: 15000787892 孩子程度很好，爱上课很积极，拼音aoe学了a的四个声调 | P21: 任宏印8:00 4.2 三十六课堂张老师 4.7 陆老师课堂陆春美 5：30 5.2 | Q21: 电话 | R21: 2 | T21: 石富贵 | U21: 兼 | V21: 1 | W21: 1 | X21: 1 | Y21: 90/课 | Z21: 22 | AA21: 3960和由由一起 | AB21: 4.2日缴费
A22: 20 | B22: 4.2 | C22: 加拿大 | D22: 温哥华 | E22: 15 | F22: 林丹 | G22: lindan1987217 | H22: Angela2 | I22: 5 | J22: 女 | K22: 是 | L22: 否 | M22: 有学过，但是拼音很差，到现在字母都认不全；想要耐心幽默，赏罚分明的老师 | N22: 中文 | O22: 有拼音基础，先快速复习一下单韵母，再学习复韵母 | P22: 周虹 7:30 4.2 黄莺6:00 4.11 | Q22: 代理 | R22: 白 | T22: 陈静 | U22: 兼 | V22: 1 | W22: 1 | X22: 99团购 | Y22: 99 | Z22: 4.14缴费 | AA22: 后面缴费一对三¥1738 22节课 | AC22: 4.24日缴费，4.30计费
A23: 21 | B23: 4.2 | C23: 加拿大 | D23: 温哥华 | E23: 15 | F23: 林丹 | G23: lindan1987217 | H23: Leo | I23: 7 | J23: 男 | K23: 是 | L23: 否 | M23: 有学过，但是拼音很差，到现在字母都认不全；想要耐心幽默，赏罚分明的老师 | N23: 中文 | O23: 有拼音基础，先快速复习一下单韵母，再学习复韵母 | P23: 周虹 7:30 4.2 第十二课堂5:50钱程 4.7 | Q23: 代理 | R23: 白 | T23: 陈静 | U23: 夜 | V23: 1 | W23: 1 | X23: 99团购 | Y23: 99 | Z23: 4.10缴费 | AA23: 后面缴费一对三¥1738 22节课 | AC23: 4.24缴费
A24: 上个月算过人数 | B24: 4.2 | C24: 美国 | D24: 尔湾 | E24: 15 | F24: 阿康 | G24: akamg789506 | H24: 徐菏阳 | I24: 8 | J24: 女 | K24: 学过 | L24: 否 | M24: 写读比较差 | N24: 中文 | O24: 程度较好，识字量比较大，建议从一上八单元开始学习 | P24: 周虹 8:30 3.26 ChineseOnline E 9：40 | Q24: 家长介绍 | R24: 2 | T24: 平金军 付吉夏家长介绍 | U24: 白 | V24: 1 | W24: 1 | X24: 1 | Y24: 53/课 | Z24: 130 | AA24: 1849 | AB24: 4.13日缴费
A25: 上个月算过人数 | B25: 4.3 | C25: 美国 | D25: 尔湾 | E25: 15 | F25: 阿康 | G25: akamg789506 | H25: 徐沐阳 | I25: 8 | J25: 女 | K25: 学过 | L25: 否 | M25: 写读比较差 | N25: 中文 | O25: 和姐姐一起测的 | P25: 周虹 8:30 3.26 ChineseOnline E 9：40 | Q25: 家长介绍 | R25: 2 | T25: 平金军 | U25: 白 | V25: 1 | W25: 1 | X25: 1 | Y25: 53/课 | Z25: 130 | AB25: 4.13日缴费
A26: 22 | B26: 4.2 | C26: 加拿大 | D26: 温哥华 | E26: 15 | F26: 惠怡 | G26: huiyiq | H26: Emma4 | I26: 4.5 | J26: 女 | K26: 否 | L26: 否 | M26: 在家讲中文，认识一点中文字，不会拼音 | N26: 中文 | O26: 没有基础，一上拼音开始 | P26: 周虹 8:00 4.2 | Q26: 代理 | R26: 白 | T26: 陈静 | U26: 0 | V26: 0 | W26: 0 | X26: 觉得课程一般 推荐一下启蒙课
A27: 23 | B27: 4.2 | C27: 美国 | D27: 加州 | E27: 15 | F27: Natalie | G27: Natalielook | H27: 陈曦琳 | I27: 7.5 | J27: 女 | K27: 无 | L27: 否 | M27: 学了中华字经认字，不会写字，不会拼音，家里讲广东话，课后班讲普通话 | N27: 中文 | O27: 一上拼音开始学【测试课上了aoe】 | P27: 周虹 9:30 4.2 陆老师课堂7:00 4.4 | Q27: 家长介绍 | R27: 2 | T27: 赵国花 刘奕晓麻麻推荐 | U27: 兼 | V27: 0 | W27: 0 | X27: 孩子没有融入，不是很有吸引力
A28: 24 | B28: 4.2 | C28: 加拿大 | D28: 温哥华 | E28: 15 | F28: 元宝儿 | G28: leozhou1343 | H28: 周茹墨加 | I28: 7 | J28: 女 | K28: 无 | L28: 否 | M28: 少量认字，能说能听（希望老师能够带动气氛些） | N28: 中文 | O28: 中文 一上拼音开始学【测试课上了aoe】 | P28: 周虹 10:00 4.2 | Q28: 电话 | R28: 2 | T28: 石富贵 | U28: 0 | X28: 试课老师只露了一点脸，家长觉得很不好
A29: 25 | B29: 4.2 | C29: 美国 | D29: 加州 | E29: 15 | F29: 苏芳Susan | G29: sufang205462 | H29: 曾心怡 | I29: 9 | J29: 女 | K29: 有 | L29: 否 | M29: 2年级/1年级 | N29: 中文 | O29: 一上的五、六单元开始学习。 | P29: 周虹 10.：30 4.2 Chineseonline F 10:20 4.3 | Q29: 微信 | R29: 2 | T29: 王晨 | U29: 白 | V29: 0 | W29: 0 | X29: 价格贵
A30: 26 | B30: 4.2 | C30: 加拿大 | D30: 温哥华 | E30: 15 | F30: josie | G30: q247995920 | H30: 由由 | I30: 5 | J30: 男 | K30: 无 | L30: 否 | M30: 零基础，会说，有的词不懂意思 | N30: 启蒙 | P30: 卢爽8:30 4.2 | Q30: 电话 | R30: 2 | T30: 石富贵 | U30: 兼 | V30: 1 | W30: 1 | X30: 1 | Y30: 90/课 | Z30: 22 | AA30: 和李嘉文一起交 | AB30: 4.2日缴费
A31: 27 | B31: 4.2 | C31: 加拿大 | D31: 温哥华 | E31: 15 | F31: michelle | G31: 13622367933 | H31: 龙龙 | I31: 5.5 | J31: 男 | K31: 无 | L31: 否 | M31: 会听会说，口语流利 | N31: 启蒙 | P31: 卢爽8:00 4.2 | Q31: 电话 | R31: 2 | T31: 石富贵 | U31: 兼 | V31: 1 | W31: 1 | X31: 1 | Y31: 90/课 | Z31: 22 | AA31: 1980 | AB31: 4.2日缴费
A32: 28 | B32: 4.2 | C32: 加拿大 | D32: 温哥华 | E32: 15 | F32: elaine | G32: 13602772434 | H32: 峻峻 | I32: 5 | J32: 男 | K32: 无 | L32: 否 | M32: 零基础，会说，有的词不懂意思 | N32: 启蒙 | P32: 卢爽8:30 4.2 | Q32: 电话 | R32: 2 | T32: 石富贵 | U32: 兼 | V32: 1 | W32: 1 | X32: 1 | Y32: 90/课 | Z32: 22 | AA32: 1980 | AB32: 4.2日缴费
A33: 29 | B33: 4.2 | C33: 新西兰 | E33: 5 | G33: Helenxiaoyi | H33: 蔡尚均 | I33: 6 | J33: 男 | K33: 否 | L33: 否 | M33: 中文交流没问题，词汇量不大，没有学过拼音，可以从aoe开始学 | N33: 中文 | O33: 上课情况良好，需要老师不停的提醒，测试学了aoe中得a以及4个声调 | P33: 任宏印14:30 4.2 赵老师课堂 1:00 4.3 | Q33: 家长介绍 | R33: 1 | T33: 刘巧芹 徐子睿妈妈推荐 | U33: 兼 | V33: 0 | W33: 0 | X33: 孩子太小了，好动
A34: 30 | B34: 4.2 | C34: 美国 | D34: 加州 | E34: 15 | F34: 一个表情 | G34: lunanana1 | H34: 程浩楠 | I34: 3.5 | K34: 无 | L34: 否 | M34: 没有学习过中文，中文交流能力一半一半 | N34: 启蒙 | O34: 不认字，没有学习过中文，中文程度一般 | P34: 卢爽11:20 4.2 | Q34: 微信 | R34: 2 | T34: 高翱翔 | U34: 兼 | V34: 0 | W34: 0 | X34: 妈妈也是老师，来蹭课的
A35: 31 | B35: 4.2 | C35: 加拿大 | D35: 温哥华 | E35: 15 | F35: 元宝儿 | G35: leozhou1343 | H35: 周茹馨羽 | I35: 5 | K35: 无 | L35: 否 | M35: 不识字，能说能听（希望老师能够带动气氛些） | N35: 启蒙 | P35: 卢爽10:30 4.2 | Q35: 电话 | R35: 2 | T35: 石富贵 | U35: 兼 | V35: 0 | W35: 0 | X35: 小的还喜欢的，但是大的不学小的也不学了
A36: 32 | B36: 4.2 | C36: 加拿大 | D36: 温哥华 | E36: 15 | F36: 闵江 | G36: mjmichelle | H36: 何如冰和妹妹 | I36: 5 | N36: 启蒙 | P36: 卢爽10:30 4.2 | Q36: 代理 | R36: 白 | T36: 陈静 | U36: 兼 | V36: 0 | W36: 0 | X36: 不回信息
A37: 33 | B37: 4.2 | C37: 加拿大 | D37: 温哥华 | E37: 15 | F37: Kelly | G37: kellymeng | H37: 张诗淇 | I37: 4 | N37: 启蒙 | P37: 卢爽10:30 4.2 | Q37: 代理 | R37: 白 | T37: 陈静 | U37: 兼 | V37: 0 | W37: 0 | X37: 不喜欢 | Y37: 99团购
A38: 34 | B38: 4.2 | C38: 西班牙 | D38: 巴塞罗那 | E38: 6 | F38: 愿 | G38: violet-isa | H38: 高兴 | I38: 6 | J38: 男 | M38: 老学生试读数学课 | N38: 数学 | P38: 数学课皋老师3.31 4.7 | Q38: 报第二门课 | R38: 3 | T38: 王可 | U38: 兼 | V38: 1 | W38: 1 | X38: 1 | Y38: 56/课 | Z38: 65+3+7 | AA38: 3584 | AB38: 4.1日缴费
A39: 35 | B39: 4.2 | C39: 加拿大 | D39: 温哥华 | E39: 15 | F39: studio.chloey | G39: guluyu | H39: 严顗安 | I39: 4 | N39: 启蒙 | P39: 卢爽10:30 4.2 | Q39: 代理 | R39: 白 | T39: 陈静 | U39: 兼 | V39: 0 | W39: 0 | X39: 试一下其他机构 | Y39: 99团购
A40: 36 | B40: 4.2 | C40: 西班牙 | E40: 6 | F40: 微 | G40: Weiwei28509 | H40: 吴宸宇 | I40: 5 | J40: 男 | K40: 否 | L40: 否 | M40: 没学过中文 | N40: 中文 | O40: 口齿稍微有点不清，但是表达没问题，中文交流可以;一上识字开始或启蒙开始 建议最好上启蒙课，但是不知道能不能接受价格 | P40: 徐晓晓18:30 4.2 二十课堂A19:00 4.7 | Q40: 微信 | R40: 1 | T40: 何家昌 | U40: 兼 | V40: 1 | W40: 1 | X40: 1 | Y40: 56/课 | Z40: 65 | AA40: 3640 | AB40: 4.4日缴费
A41: 37 | B41: 4.2 | C41: 澳大利亚 | D41: 悉尼 | E41: 3 | F41: Amy -G | G41: amy88788 | H41: 杨云隆 | I41: 6 | J41: 男 | K41: 否 | L41: 否 | M41: 在家家长自己教 | N41: 中文 | O41: 孩子非常配合，很乖，一上识字天地人学完 | P41: 陈琪4.2 | Q41: 微信 | R41: 1 | T41: 张文红 | U41: 0 | V41: 0 | W41: 0 | X41: 去悟空学了
A42: 38 | B42: 4.3 | C42: 澳大利亚 | D42: 悉尼 | E42: 3 | F42: Serena | G42: serena_xuxuxu | H42: 沈诗涵 | I42: 4.5岁 | J42: 女 | K42: 没有 | L42: 家长教过一点点，可以简单交流，不是很流利 | M42: 家长教过一点点，认识一些字 | N42: 启蒙 | O42: 61430475688 | P42: 卢爽13:00 4.2 | Q42: 家长介绍 | R42: 3 | T42: 王可 周昕妤妈妈推荐 | U42: 兼 | V42: 0 | W42: 0 | X42: 没回复
A43: 39 | B43: 4.3 | C43: 美国 | D43: 西部 | E43: 15 | F43: Miss W | G43: My jody | H43: Austin | I43: 6 | J43: 男 | K43: 否 | L43: 否 | M43: 会说中文，认识的少 | N43: 中文 | O43: 孩子非常配合，很乖，一上识字天地人学完 | P43: ChineseonlineF11:00 4.9 | Q43: 微信 | R43: 3 | T43: 王可 | U43: 兼 | V43: 0 | W43: 0 | X43: 待定
A44: 40 | B44: 4.3 | C44: 美国 | D44: 加利福尼亚 | E44: 15 | F44: cindy | G44: cindyliu95035 | H44: 朴piáo石 | I44: 4.5岁 | J44: 男 | K44: 没学过 | L44: 否 | M44: 认识基本的大小多少 | N44: 中文 | O44: 孩子较活跃 ，需要专心抓住孩子的注意力一上天地人 | P44: 任宏印4.3 启蒙4.4 | Q44: 电话 | R44: 3 | T44: 杨斌 | U44: 兼 | V44: 0 | W44: 0 | X44: 启蒙课爸爸喜欢要交钱，但是妈妈觉得贵
A45: 41 | B45: 4.3 | C45: 澳大利亚 | D45: 悉尼 | E45: 3 | F45: 彬彬 | G45: qq 158676748 | H45: 蔡以森 | I45: 10岁 | J45: 男 | K45: 是 | L45: 否 | M45: 有学过一些 | N45: 中文 | O45: 识字量200左右，一下开始学 | P45: 徐晓晓11:30 4.3 | Q45: 电话 | R45: 3 | T45: 李波 | U45: 0 | V45: 0 | W45: 0 | X45: 嫌价格贵，对学校师资表示怀疑
A46: 42 | B46: 4.3 | C46: 澳大利亚 | D46: 悉尼 | E46: 3 | F46: 彬彬 | G46: qq158676748 | H46: 蔡以来 | I46: 6岁 | J46: 男 | K46: 是 | L46: 否 | M46: 零基础 | N46: 中文 | O46: 不需要双语，可以中文交流，拼读可以，一上课文开始、 | P46: 徐晓晓11:00 4.3 | Q46: 电话 | R46: 3 | T46: 李波 | U46: 0 | V46: 0 | W46: 0 | X46: 嫌价格贵，对学校师资表示怀疑
A47: 43 | B47: 4.3 | C47: 美国 | D47: 中部 | E47: -13 | F47: 陈语璇 | G47: yu503804306 | H47: 冯炜 | I47: 10 | K47: 无 | L47: 否 | M47: 会听会说，写一些字 | N47: 中文 | O47: 中文 一上拼音开始学【测试课上了aoe】 | P47: 周虹 7:00 4.3 陆老师课堂陆春香7:00 4.4 | Q47: 家长介绍 | R47: 2 | T47: 王晨 陈嘉炜妈妈介绍 | U47: 兼 | V47: 1 | W47: 1 | X47: 1 | Y47: 59/课 | Z47: 22 | AA47: 和冯沁一起2596 | AB47: 4.6日缴费 | AC47: 二四六上课
A48: 44 | B48: 4.3 | C48: 美国 | D48: 中部 | E48: -13 | F48: 陈语璇 | G48: yu503804306 | H48: 冯沁 | I48: 8 | K48: 无 | L48: 否 | M48: 会听会说，不会写 | N48: 中文 | O48: 中文 一上拼音开始学【测试课上了aoe】 | P48: 周虹 7:30 4.3 陆老师课堂陆春香7:00 4.4 | Q48: 家长介绍 | R48: 2 | T48: 王晨 陈嘉炜妈妈介绍 | U48: 兼 | V48: 1 | W48: 1 | X48: 1 | Y48: 59/课 | Z48: 22 | AA48: 和冯炜一起2596 | AB48: 4.6日缴费 | AC48: 二四六上课
A49: 45 | B49: 4.3 | C49: 美国 | D49: 洛杉矶 | E49: 15 | G49: WANGXIN20081231 | H49: Jason | I49: 11 | J49: 男 | K49: 有 | L49: 否 | M49: 一上基础 | N49: 中文 | O49: 一上七单元开始 | P49: 周虹 8:00 4.3 | Q49: 微信 | R49: 1 | T49: 张文红 | U49: 0 | V49: 0 | W49: 0 | X49: 平时课程多，排不出课
A50: 46 | B50: 4.3 | C50: 美国 | D50: 洛杉矶 | E50: 15 | G50: WANGXIN20081231 | H50: Ariel | I50: 8 | J50: 女 | K50: 有 | L50: 否 | M50: 一上基础 | N50: 中文 | O50: 一上四单元《秋天》开始 | P50: 周虹8:30 4.3 | Q50: 微信 | R50: 1 | T50: 张文红 | U50: 0 | V50: 0 | W50: 0 | X50: 平时课程多，排不出课
A51: 47 | B51: 4.3 | C51: 美国 | D51: 纽约 | E51: 12 | F51: 云 | G51: linyanyun634903 | H51: 刘昕宜 | I51: 14 | J51: 女 | K51: 学过 | L51: 否 | M51: 国内学过，拼音很好，读完国内二年级来美国，期间没怎么读中文，书写都忘了 | N51: 中文 | O51: 三上中后段或者三下开始 | P51: 周虹 9:30 4.3 ChineseonlineL7:00 4.7 | Q51: 家长介绍 | R51: 3 | T51: 展旺 林雨晴妈妈介绍 | U51: 白 | V51: 1 | W51: 1 | X51: 1 | Y51: 56/课 | Z51: 65+3 | AA51: 3640 | AB51: 4.3日缴费
A52: 48 | B52: 4.3 | C52: 美国 | D52: 加州 | E52: 15 | F52: Liza | G52: wxid_cvg7h91kzwqf51 | H52: 陈宇翰 | I52: 11 | J52: 男 | K52: 是 | L52: 否 | M52: 美洲华语教材刚开始学第三册。拼音学过了，学得还不错，认识一些简单的字。中文可以说，就是不爱说 | N52: 中文 | P52: 周虹 10:00 4.3 ChineseononlineG 08:20 4.28 言智30 7:00 5.27 | Q52: 微信 | R52: 白 | T52: 微信 | U52: 白 | V52: 1 | W52: 1 | Y52: 99/课 | AA52: 2180 | AB52: 5.26缴费
A53: 不计人数 | B53: 43690 | C53: 加拿大 | D53: 蒙特利尔 | E53: 12 | F53: Jing | G53: msjane | H53: 刘思辰 | I53: 4.5 | J53: 女 | K53: 是 | L53: 否 | N53: 中文 | O53: 拼音拼读弱，复习复韵母开始 | P53: Chineseonline I 7:40 8.13 8.14 8.15 8.16 8.17 8.20 8.21 8.22 8.23 8.26 8.27 8.28 8.29 8.30 | Q53: 微信 | R53: 1 | T53: 何家昌 | U53: 白 | V53: 1 | W53: 1 | X53: 1 | Y53: 1100/月 | Z53: 260 | AA53: 11000 | AB53: 4.3日缴费
A54: 49 | B54: 4.3 | C54: 美国 | D54: 洛杉矶 | E54: 15 | F54: 阳光柠檬 | G54: yuanyuanusa001 | H54: 李明哲 | I54: 7 | J54: 男 | K54: 有 | L54: 否 | M54: 二年级上册数学课 | N54: 数学 | O54: 一下和二上都试了，愿意学二上 | P54: 第十一课堂第十节课4.3日成功 | Q54: 报第二门课 | R54: 白 | T54: 微信 | U54: 夜 | V54: 1
A55: 50 | B55: 4.3 | C55: 澳大利亚 | D55: 墨尔本 | E55: 3 | G55: JaneWang4428 | H55: 杨念慈 | I55: 14 | J55: 女 | K55: 是 | L55: 否 | M55: 中文交流没问题，在国外学习到二到三年级了 | N55: 中文 | P55: 宋老师课堂宋培培14:00 4.6 | Q55: 电话 | R55: 1 | T55: 刘巧芹 | U55: 兼 | V55: 1 | W55: 1 | X55: 1 | Y55: 56/课 | Z55: 65 | AA55: 和杨大伟一起￥6890 | AB55: 4.7日缴费
A56: 51 | B56: 4.3 | C56: 澳大利亚 | D56: 墨尔本 | E56: 3 | G56: GraceLimSH | H56: 林启恒 ShawnLam | I56: 11 | J56: 男 | K56: 否 | L56: 否 | M56: 不会说中文需要双语词汇量不大 | N56: 中文 | O56: 不需要双语，拼读基本过关，识字量很少，从一上课文开始 | P56: 徐晓晓13:00 4.3 | Q56: 电话 | R56: 1 | T56: 刘巧芹 | U56: 0 | V56: 0 | W56: 0 | X56: 当天测完很喜欢，但是说和爸爸商量时间就没回复了
A57: 52 | B57: 4.3 | C57: 澳大利亚 | D57: 墨尔本 | E57: 3 | G57: GraceLimSH | H57: 林启真 AlethiaLam | I57: 9 | J57: 女 | K57: 否 | L57: 否 | M57: 不会说中文需要双语词汇量不大 | N57: 中文 | O57: 不需要双语，拼读不过关，需要复韵母开始 | P57: 徐晓晓13:00 4.3 | Q57: 电话 | R57: 1 | T57: 刘巧芹 | U57: 0 | V57: 0 | W57: 0 | X57: 当天测完很喜欢，但是说和爸爸商量时间就没回复了
A58: 53 | B58: 4.3 | C58: 加拿大 | D58: 温哥华 | E58: -15 | F58: coffee | G58: 17787239828 | H58: 唐于焱 | I58: 5 | J58: 男 | K58: 无 | L58: 否 | M58: 没有拼音基础，中文口语流利 | N58: 启蒙 | O58: 17787239828 | P58: 卢爽11:00 4.3 | Q58: 家长介绍 | R58: 2 | T58: 石富贵 李嘉文妈妈介绍 | U58: 兼 | V58: 1 | W58: 1 | X58: 1 | Y58: 90/课 | Z58: 22 | AA58: 1980 | AB58: 4.3日缴费
A59: 54 | B59: 4.3 | C59: 加拿大 | D59: 温哥华 | E59: -15 | F59: josie | G59: q247995920 | H59: 李嘉文 | I59: 7 | J59: 女 | K59: 否 | L59: 否 | M59: 会加减，乘法 | N59: 数学 | O59: 86 15000787892 | P59: 卢爽9:00 4.3 六课堂 4:20 4.10 | Q59: 电话 | R59: 2 | T59: 石富贵 | U59: 兼 | V59: 1 | W59: 1 | X59: 1 | Y59: 56/课 | Z59: 33 | AA59: 3640和由由一起 | AB59: 4.10日缴费
A60: 55 | B60: 4.3 | C60: 加拿大 | D60: 温哥华 | E60: -15 | F60: josie | G60: q247995920 | H60: 由由 | I60: 5 | J60: 男 | K60: 否 | L60: 否 | M60: 会一定的加减法 | N60: 数学 | O60: +1 7786685090 | P60: 卢爽9:30 4.3 | Q60: 电话 | R60: 2 | T60: 石富贵 | U60: 兼 | V60: 1 | W60: 1 | X60: 1 | Y60: 56/课 | Z60: 33 | AA60: 和李嘉文一起交 | AB60: 4.10日缴费
A61: 56 | B61: 4.3 | C61: 加拿大 | D61: 温哥华 | E61: -15 | F61: michelle | G61: 13622367933 | H61: 龙龙 | I61: 5.5 | J61: 男 | K61: 否 | L61: 否 | M61: 会一些百以内的加减法。家长明确表示不要那种类似启蒙中文课的，要教算术的，希望孩子能和国内孩子一样， | N61: 数学 | O61: 13622367933 | P61: 卢爽10:30 4.3 卢爽 8:00 4.24 | Q61: 家长介绍 | R61: 2 | T61: 石富贵 李嘉文妈妈介绍 | U61: 兼 | V61: 1 | W61: 1 | X61: 1 | Y61: 56/课 | Z61: 35课时 | AA61: 1960 | AB61: 4.24日缴费
A62: 57 | B62: 4.3 | C62: 加拿大 | D62: 温哥华 | E62: -15 | F62: elaine | G62: 86+13602772434 | H62: 峻峻 | I62: 5 | J62: 男 | K62: 否 | L62: 否 | M62: 会一定的加减法 | N62: 数学 | O62: 86+13602772434 | P62: 卢爽11:00 4.3 | Q62: 家长介绍 | R62: 2 | T62: 石富贵 李嘉文妈妈介绍 | U62: 兼 | V62: 0 | W62: 0 | X62: 觉得老师不行
A63: 58 | B63: 4.3 | C63: 澳大利亚 | D63: 墨尔本 | E63: 3 | G63: JaneWang4428 | H63: 杨大伟 | I63: 8 | J63: 男 | K63: 否 | L63: 是 | M63: 需要双语老师 词汇量不大 可以从拼音学起 | N63: 中文 | O63: 零基础，不怎么需要双语 | P63: 赵老师课堂15:00 4.3 Chineseinline G 17：00 5.27 | Q63: 电话 | R63: 1 | T63: 刘巧芹 | U63: 白 | V63: 1 | W63: 1 | X63: 1 | Y63: 56/课 | Z63: 65 | AA63: 和杨念慈一起 | AB63: 4.7日缴费
A64: 59 | B64: 4.3 | C64: 澳大利亚 | D64: 墨尔本 | E64: 3 | G64: JangWang4428 | H64: Leon | I64: 6 | J64: 男 | K64: 否 | L64: 是 | M64: 混血零基础需要双语 | N64: 中文 | O64: 零基础，需要双语 | P64: 徐晓晓15:00 4.3 赵佳求赵老师课堂15:00 4.6 | Q64: 电话 | R64: 1 | T64: 刘巧芹 | U64: 兼 | V64: 0 | W64: 0 | X64: 跟不上
A65: 60 | B65: 4.3 | C65: 澳大利亚 | D65: 悉尼 | E65: 3 | F65: AO lina | G65: linal-piggy | H65: 赵小燕 | I65: 11 | J65: 女 | K65: 学过 | L65: 否 | M65: 学到当地6年级 拼音学过一点 | N65: 中文 | O65: 孩子程度不错，妈妈希望一年级上开始，个人建议一上10课左右 | P65: 任宏印 14:00 4.3 ChineseonlineL13:00 4.7 | Q65: 电话 | R65: 3 | T65: 李波 | U65: 白 | V65: 0 | W65: 0 | X65: 嫌价格贵，不打算学
A66: 61 | B66: 4.3 | C66: 新西兰 | E66: 5 | F66: 郝儒君 | G66: hao31707113 | H66: 郝瑞 | I66: 11 | K66: 有 | L66: 否 | M66: 中文交流没有问题，学习过拼音，生字可以用拼音读出来，但是不会写字，不知道字词的大意 | N66: 中文 | O66: 一上的五、六单元开始学习。 | P66: 周虹 14:00 4.3 | Q66: 微信 | R66: 2 | T66: 高翱翔 | U66: 0 | V66: 0 | W66: 0 | X66: 不回复
A67: 62 | B67: 4.3 | C67: 加拿大 | D67: 温哥华 | E67: 15 | F67: Jenny li | G67: zhanzhanyaoyao | H67: 瑶瑶1 | I67: 7 | J67: 女 | K67: 是 | L67: 否 | M67: 拼音好，中文表达好 | N67: 中文 | O67: 一上中后断 | P67: 徐晓晓8:30 4.3 | Q67: 代理 | R67: 白 | T67: 陈静 | U67: 0 | V67: 0 | W67: 0 | X67: 学校开网课了，先上学校的课
A68: 63 | B68: 4.3 | C68: 加拿大 | D68: 温哥华 | E68: 15 | H68: 赵天娇 | I68: 5 | J68: 女 | K68: 是 | L68: 否 | M68: 拼音基础过关，识字量少 | N68: 中文 | O68: 一上刚开始 | P68: 徐晓晓8:30 4.3 Chineseonline(H10)4.9 | Q68: 代理 | R68: 白 | T68: 陈静 | U68: 兼 | V68: 0 | W68: 0 | X68: 太难了 重新排一周三天的
A69: 64 | B69: 4.3 | C69: 加拿大 | D69: 温哥华 | E69: 15 | F69: Na | G69: wxid_gmvsl5p2j5wi12 | H69: 李小卫 | I69: 7 | J69: 男 | K69: 是 | L69: 否 | M69: 混血，发音好，中文理解力稍弱 | N69: 中文 | O69: 一上中后断 | P69: 徐晓晓8:30 4.3 | Q69: 代理 | R69: 白 | T69: 陈静 | U69: 0 | V69: 0 | X69: 学校开网课了，先上学校的课
A70: 65 | B70: 4.3 | C70: 加拿大 | D70: 温哥华 | E70: 15 | F70: 卉 | G70: z6042639688 | H70: 曾子欢 | I70: 12 | J70: 男 | K70: 有 | L70: 否 | M70: 有学过拼音 | N70: 中文 | O70: 一下程度 | P70: 周虹9:00 4.3 赵老师课堂二四六 赵佳求8:20 4.9 周虹9:00 4.3 ChineseonlineT108:20 4.9 | Q70: 代理 | R70: 白 | T70: 陈静 | U70: 兼 | V70: 1 | W70: 1 | X70: 99团购 | Y70: 99
A71: 66 | B71: 4.3 | C71: 加拿大 | D71: 温哥华 | E71: 15 | F71: Charlene liu - 劉卓瑩 | G71: liuzhuoying916 | H71: 李尚謙 | I71: 7 | J71: 男 | K71: 是 | L71: 否 | M71: 拼音可以。認字不多，有拼音的時候依賴拼音 | N71: 中文 | O71: 一上秋天，孩子非常活泼，上课教了一个秋字，写得是比较差 | P71: 任宏印11:30 4.3 要学成语故事 | Q71: 代理 | R71: 白 | T71: Yuki | U71: 要学成语故事
A72: 67 | B72: 4.3 | C72: 加拿大 | D72: 温哥华 | E72: 15 | F72: lvee | G72: lvee11 | H72: 齐霁 | I72: 5 | K72: 无 | L72: 否 | M72: 交流无障碍 没有特意学过 | N72: 启蒙 | O72: 17782238611 | P72: 卢爽10:30 4.3 | Q72: 微信 | R72: 2 | T72: 赵国花 | U72: 兼 | V72: 0 | W72: 0 | X72: 妈妈觉得我们课程太幼稚
A73: 68 | B73: 4.3 | C73: 美国 | D73: 洛杉矶 | E73: 15 | G73: Htang_04 | H73: Emma萧 | I73: 3 | J73: 女 | M73: 在家里说广东话零基础 | N73: 启蒙 | O73: 16262024484 | P73: 卢爽9:00 4.3 | Q73: 家长介绍 | R73: 1 | T73: 刘巧芹 陈泰祯妈妈介绍 | U73: 兼 | V73: 1 | W73: 1 | X73: 1 | Y73: 119/课 | Z73: 一对一30课时 | AA73: 499.24 | AB73: 4.4日缴费
A74: 69 | B74: 4.4 | C74: 加拿大 | D74: 温哥华 | E74: 15 | F74: Ammy | G74: lovelyammy | H74: 霍欣 | I74: 12 | J74: 女 | K74: 否 | L74: 否 | M74: 基本看不懂，但能讲 | N74: 中文 | O74: 拼读没问题，识字量二年级，可以从二下开始学 | P74: 徐晓晓7:00 4.4 赵老师课堂二四六 赵佳求8:20 4.9 | Q74: 代理 | R74: 白 | T74: 陈静 | U74: 兼 | V74: 1 | W74: 1 | X74: 99团购 | Z74: 99团购
A75: 70 | B75: 4.4 | C75: 加拿大 | D75: 温哥华 | E75: 15 | F75: Ammy | G75: lovelyammy | H75: 霍正贤 | I75: 14 | J75: 男 | K75: 是 | L75: 否 | M75: 中文简单能读，不能写 | N75: 中文 | O75: 拼读较弱，识字量少，需要从一上课文开始 | P75: 徐晓晓7:00 4.4 ChineseonlineF10:20 4.8 | Q75: 代理 | R75: 白 | T75: 陈静 | U75: 兼 | V75: 1 | W75: 1 | X75: 99团购 | Z75: 99团购
A76: 71 | B76: 4.4 | C76: 美国 | D76: 纽约 | E76: -12 | F76: 女人衣柜 | G76: abc5467011abc | H76: 邓梓琪 | I76: 10 | J76: 女 | L76: 是 | M76: 英语D级，可阅读一些简单的句子，学校教的老师说的都听不懂 | N76: 英文 | O76: 英语五年级开始 | P76: 言智英语01杨诗怡 4.4 | Q76: 微信 | R76: 2 | T76: 王晨 | U76: 兼 | V76: 0 | W76: 0 | X76: 最近网课太多了，要过段时间再确定
A77: 72 | B77: 4.4 | C77: 澳大利亚 | D77: 布里斯班 | E77: 2 | F77: 🌙玥儿🌝🌙AU | G77: htymoon | H77: 梓涵 | I77: 3 | J77: 男 | K77: 没学过 | L77: 否 | M77: 中文有些发音不标准 | N77: 启蒙课 | O77: 61416430658 | P77: 卢爽8:10 4.4 | Q77: 微信 | R77: 3 | T77: 翁珊珊 | U77: 兼 | V77: 0 | W77: 0 | X77: 太小了坐不住
A78: 73 | B78: 4.5 | C78: 美国 | D78: 纽约 | E78: 12 | G78: kay927685 | H78: 王芯晨 | I78: 6 | J78: 女 | K78: 否 | L78: 否 | M78: 词汇量不大 可以中文交流 没有学过拼音 | N78: 中文 | O78: 从拼音aoe开始学 有一点识字量 在美国中文学校学习一周一次 注重听说 希望孩子以后可以自主阅读 不重视写 拼音调值不准 家长也不准 重视一下纠音 比较开朗 | P78: 刘紫佳7:30 4.5 | Q78: 电话 | R78: 1 | T78: 刘巧芹 | U78: 0 | V78: 0 | W78: 0 | X78: 价格贵
A79: 74 | B79: 4.5 | C79: 加拿大 | D79: 温哥华 | E79: -15 | F79: 囡囡 | G79: nannanyymm | H79: 康铭珈（琪琪） | I79: 5 | J79: 女 | K79: 未学全 | L79: 否 | M79: 拼音未学全学到了jqx | N79: 中文 | O79: 从复韵母开始 只认识单个拼音 上课活泼 互动较好 | P79: 刘紫佳10:00 4.5 言智02黄莺10:00 4.21 数学 言智19阮洪慧 4.28 | Q79: 微信 | R79: 2 | T79: 赵辉 | U79: 兼职 | V79: 1 | W79: 1 | X79: 1 | Y79: 118/课 | Z79: 12 | AA79: 两人一起1416 | AB79: 4.18日缴费 | AC79: 一对一 周二周三
A80: 75 | B80: 4.5 | C80: 加拿大 | D80: 温哥华 | E80: -15 | F80: 囡囡 | G80: nannanyymm | H80: 康铭玥 | I80: 11 | J80: 女 | K80: 有 | L80: 否 | M80: 小学五年级下册语文水平 | N80: 中文 | O80: 一年级下中段开始 拼读较好 有一定的识字量和中文储备 | P80: 刘紫佳10:20 4.5 ChineseonlineQ1 11:00 4.21 数学 言智19阮洪慧 4.28 | Q80: 微信 | R80: 2 | T80: 赵辉 | U80: 兼 | V80: 1 | W80: 1 | X80: 1 | Y80: 59/课 | Z80: 6 | AB80: 4.18日缴费 | AC80: 一周三天
A81: 76 | B81: 4.5 | C81: 美国 | D81: 西部 | E81: 15 | F81: fleur | G81: fleurfleurtang | H81: 钟心洛 | I81: 5 | J81: 女 | K81: 没学过 | L81: 否 | M81: 听说没问题，读写不行 | N81: 中文 | O81: 从天地人开始 学生比较活泼 零基础 | P81: 刘紫佳11:00 4.5 ChineseonlineF11:00 4.9 | Q81: 家长介绍 | R81: 3 | T81: 王可 叶阳阳妈妈推荐 | U81: 白 | V81: 0 | W81: 0 | X81: 待定
A82: 77 | B82: 4.5 | C82: 西班牙 | E82: 6 | G82: ghy9958 | H82: 徐向祖 | I82: 24 | J82: 男 | K82: 否 | L82: 是 | M82: 学过一点点拼音，简单的中文交流沟通可以，需要双语老师 | N82: 中文 | O82: 双语 | P82: 天娃课堂03杨启21:00 4.5 | Q82: 微信 | R82: 1 | T82: 刘敏 | U82: 兼 | V82: 0 | W82: 0 | X82: 不想学了，大学毕业有工作顾不上
A83: 78 | B83: 4.5 | C83: 美国 | D83: 纽约 | E83: 12 | F83: rongfu | G83: rongfu1002 | H83: Olivia Gu | I83: 7 | J83: 女 | K83: 否 | L83: 否 | M83: 只会简单交流，没学过中文 | N83: 中文 | O83: 从拼音aoe开始学 孩子在学校学音标 担心会混 家长注重听说 表达能力 学生发音不标准 四发不清晰 | P83: 刘紫佳7:00 4.5 ChineseonlineI7:40 4.9 | Q83: 微信 | R83: 1 | T83: 刘敏 | U83: 白 | V83: 0 | W83: 0 | X83: 网课太多，不想再学了
A84: 79 | B84: 4.5 | C84: 美国 | D84: 纽约 | E84: 12 | F84: 卢霞 | G84: janicelovebin | H84: 陈琳 | I84: 9 | J84: 女 | L84: 否 | M84: 能用中文交流 | N84: 中文 | O84: 从天地人开始学习 没有识字量 还是担心拼音和音标会混 发音不标准 有点不自信 | P84: 刘紫佳8:30 4.5 53/节8：50 4.7 | Q84: 家长介绍 | R84: 3 | T84: 展旺 张梦颖妈妈介绍 | U84: 兼职 | V84: 1 | W84: 1 | X84: 1 | Y84: 53/课 | Z84: 130+8 | AA84: 978 | AB84: 4.8日缴费
A85: 80 | B85: 4.6 | C85: 澳大利亚 | D85: 悉尼 | E85: 2 | F85: Anton | G85: antoniawang001 | H85: 王英杰 | I85: 6 | J85: 男 | K85: 没学过 | L85: 否 | M85: 说得很好 | N85: 中文 | O85: 很爱说，逻辑很缜密，学习能力强，接受度高；从一上识字开始 | P85: 徐晓晓8:00 4.6 蒋老师课堂8：50 4.7 | Q85: 微信 | R85: 3 | T85: 王可 | U85: 兼 | V85: 0 | W85: 0 | X85: 上课效率不高，性价比不高
A86: 81 | B86: 4.6 | C86: 美国 | D86: 圣何塞 | E86: 15 | F86: Suzanne | G86: suzanneh13 | H86: 陈子琦 | I86: 10 | J86: 女 | K86: 学过 | L86: 否 | M86: 在当地学了很久 | N86: 中文 | O86: 拼读可以，识字量一上水平，表达能力弱，需要加强表达，可以从一下开始学 | P86: 徐晓晓8：30 4.6 ChineseonlineG 8:20 | Q86: 家长介绍 | R86: 3 | T86: 王可 贾宇涵爸爸推荐 | U86: 白 | V86: 0 | W86: 0 | X86: 测完就没上课，就说不合适自己
A87: 82 | B87: 4.6 | C87: 澳大利亚 | D87: 悉尼 | E87: 2 | F87: 凌乱 | G87: llua5118 | H87: 冯晓怡（丫丫） | I87: 6 | J87: 女 | K87: 还没 | L87: 否 | M87: 在当地学了一年马力平教材 | N87: 中文 | O87: 一上识字开始，很爱笑，很好学 | P87: 徐晓晓9：30 4.6 | Q87: 家长介绍 | R87: 3 | T87: 王可 陈彦熹妈妈推荐 | U87: 0 | V87: 0 | W87: 0 | X87: 时间没定
A88: 83 | B88: 4.6 | C88: 澳大利亚 | D88: 悉尼 | E88: 2 | F88: 西兰花海 | G88: Candy6491027 | H88: 褚思成 | I88: 6 | J88: 男 | K88: 没学过 | L88: 否 | M88: 听说没有问题 | N88: 中文 | O88: 一上拼音测试了aoe可以继续往下学习 声调发音标准 上课活泼互动较好 | P88: 徐晓晓12:30 4.6 赵老师课堂15:00 4.8 | Q88: 家长介绍 | R88: 3 | T88: 王可 陈彦熹妈妈推荐 | U88: 兼 | V88: 0 | W88: 0 | X88: 拓展太少
A89: 84 | B89: 4.6 | C89: 澳大利亚 | D89: 悉尼 | E89: 2 | F89: 怀德维宁 | G89: weiningsydney | H89: 张维宁 | I89: 9 | J89: 女 | K89: 拼音学完了 | L89: 否 | M89: 听说没有问题 读写不行 | O89: 一上课文 秋天开始 | P89: 徐晓晓 17:00 4.6 Chineseonline L 13:00 4.8 | Q89: 家长介绍 | R89: 3 | T89: 王可 陈彦熹妈妈推荐 | U89: 白 | V89: 1 | W89: 1 | X89: 1 | Y89: 56/课 | Z89: 65 | AA89: 3640 | AB89: 4.9日缴费
A90: 85 | B90: 4.6 | C90: 新西兰 | E90: 4 | F90: Yuan | G90: wxid_c80734247cka22 | H90: 黄浩鸣 | I90: 6 | J90: 男 | K90: 无 | L90: 否 | M90: 零基础 | N90: 中文 | O90: 零基础 声调调值不准 需要着重抓一下 学生上课配合较高 | P90: 徐晓晓15:00 4.6 | Q90: 微信 | R90: 2 | T90: 高翱翔 | U90: 0 | V90: 0 | W90: 0 | X90: 报其他家了
A91: 86 | B91: 4.6 | C91: 美国 | E91: 15 | G91: iris20101231123baoer | H91: 孙宝儿 | I91: 9 | J91: 女 | K91: 有 | L91: 否 | M91: 之前断断续续学过2年中文 | N91: 中文 | P91: 徐晓晓 11：00 4.6 | Q91: 家长介绍 | R91: 1 | T91: 俞酉兰 王涵雨妈妈介绍 | U91: 0 | V91: 0 | W91: 0 | X91: 没回复
A92: 87 | B92: 4.6 | C92: 澳大利亚 | D92: 墨尔本 | E92: 3 | F92: Sam税务会计师 贷款经纪 | G92: samsongphotography | H92: sylas song | I92: 4 | K92: 没学过 | M92: 听说很棒 | N92: 启蒙 | O92: 430111607 | P92: 卢爽16:30 4.3 | Q92: 电话 | R92: 3 | T92: 张霞 | U92: 兼 | V92: 0 | W92: 0 | X92: 家长不回复了
A93: 88 | B93: 4.6 | C93: 美国 | E93: 12 | G93: wxid_ce3ub0b2o6y71 | H93: Maxum | I93: 4.5 | J93: 男 | K93: 否 | L93: 是 | M93: +1-3182543933 会交流 有时候可能孩子不清楚的，需要英文表达，没有中文名 | N93: 启蒙 | P93: 卢爽22:30 4.3 | Q93: 家长介绍 | R93: 1 | T93: 张文红 am介绍 | U93: 兼 | V93: 1 | W93: 1 | X93: 1 | Y93: 76/课 | Z93: 65 | AA93: 697 | AB93: 4.7日缴费
A94: 89 | B94: 4.7 | C94: 美国 | D94: 纽约 | E94: 12 | F94: Michelle77 | G94: michellelinshuzhen | H94: 索非亚 | I94: 10 | J94: 女 | M94: 三位数以内的加减法都可以，乘法三位数乘以两位数，三位数乘以一位数都没问题，除法三位数除以两位数，三位数除以一位数都没问题，难度再高一点就不会了。 | N94: 数学 | P94: ChineseonlineB11 王亚光数学21:00 4.6 | Q94: 微信 | R94: 1 | T94: 刘敏 | U94: 兼 | V94: 0 | W94: 0 | X94: 价格贵
A95: 90 | B95: 4.7 | C95: 美国 | D95: 宾州 | E95: 12 | F95: Ling | G95: jenny0405 | H95: 张梦颖 | I95: 8 | J95: 女 | N95: 数学 | O95: 三年级左右程度 | P95: ChineseonlineB11 王亚光数学7:00 4.7 | Q95: 报第二门课 | R95: 3 | T95: 展旺 | U95: 兼 | V95: 0 | W95: 0 | X95: 觉得不是很专业，不太喜欢
A96: 91 | B96: 4.7 | C96: 加拿大 | D96: 温哥华 | E96: 15 | G96: wxid_h88wx3orbye711 | H96: 刘熙雅（天天） | I96: 7 | J96: 女 | N96: 数学 | P96: 黄老师课堂 黄超丽9:00 4.7 | Q96: 报第二门课 | R96: 2 | T96: 赵国花 | U96: 兼 | V96: 0 | W96: 0 | X96: 孩子不喜欢
A97: 92 | B97: 4.7 | C97: 美国 | D97: 纽约 | E97: -12 | F97: kethy zhang | G97: kethyyezhang | H97: 张路杰 | I97: 5 | J97: 男 | K97: 无 | L97: 是 | M97: 识字80 | N97: 启蒙 | O97: 1-5163981160 | P97: 卢爽20:30 4.6 | Q97: 微信 | R97: 2 | T97: 王晨 | U97: 兼 | V97: 1 | W97: 1 | X97: 1 | Y97: 116/课 | Z97: 65+1课时，每人33 | AA97: $200+$870 | AB97: 4.10日缴费,4.29日缴费
A98: 93 | B98: 4.7 | C98: 美国 | D98: 纽约 | E98: -12 | F98: kethy zhang | G98: kethyyezhang | H98: 张炜奇 | I98: 8 | J98: 男 | K98: 无 | L98: 否 | M98: 认识200字 | N98: 中文 | O98: 不需要双语，识字都学过但是基本忘记了，可以从一上拼读开始学 | P98: 徐晓晓21：00 4.6 陈莹老师教室 周三晚8:30，周六晚9点 4.10 | Q98: 微信 | R98: 2 | T98: 王晨 | U98: 兼 | V98: 1 | W98: 1 | X98: 1 | Y98: 116/课 | AB98: 4.10日缴费,4.29日缴费
A99: 94 | B99: 4.7 | C99: 美国 | D99: 纽约 | E99: -12 | F99: 从心开始 | H99: 林嘉轩 | I99: 12 | J99: 男 | K99: 有 | L99: 否 | M99: 会拼音，开始在学简单的笔画 | N99: 中文 | O99: 拼读较差，建议从拼音的双韵母部分开始再复习一下拼读。【意向不大，家长说现在有空，他们自己可以教授】 | P99: 周虹 9:00 4.7 | Q99: 微信 | R99: 2 | T99: 王晨 | U99: 0 | V99: 0 | W99: 0 | X99: 家长自己教
A100: 95 | B100: 4.7 | C100: 美国 | D100: 纽约 | E100: 12 | G100: d29599183 | H100: 张妮可 | I100: 10 | J100: 女 | K100: 否 | L100: 否 | M100: 零基础没有学过拼音 可以流利说中文 | N100: 中文 | O100: 接受能力较强，从拼音学起 | P100: 周虹 7:30 4.7 | Q100: 电话 | R100: 1 | T100: 刘巧芹 | U100: 0 | V100: 0 | W100: 0 | X100: 挺满意但是在纠结价格，网课太费钱了
...

Sheet 2020.3
A2: 序号 | B2: 测试时间 | C2: 国家 | D2: 城市 | E2: 时差 | F2: 家长微信名 | G2: 家长微信 | H2: 学生姓名 | I2: 年龄 | J2: 性别 | K2: 有没有学过拼音 | L2: 是否需要双语老师 | M2: 家长自述程度及学习需求 | N2: 学习课程 | O2: 测试结果 | P2: 排课安排 | Q2: 来源 | R2: 组别 | S2: 业务员 | T2: 排课分组 | U2: 是否在读 | V2: 是否缴费 | W2: 失败原因 | X2: 课程单价 | Y2: 折扣 | Z2: 实收 | AA2: 首次收费时间
A3: 1 | B3: 3.1 | C3: 美国 | D3: 特拉华州 | E3: 13 | F3: Tina免税玩购·美欧店 | G3: gracesong2012 | H3: Andy Wu | I3: 10 | J3: 男 | K3: 有 | L3: 否 | M3: 数学国内三下到四上之间水平 | N3: 数学 | O3: 数学课 | P3: 数学课04 9:00 3.1 | Q3: 微信 | R3: 3 | S3: 王可 | T3: 兼 | U3: 1 | V3: 1 | W3: 1 | X3: 53/课 130课 | Z3: 6890 | AA3: 2.29日缴费
A4: 2 | B4: 3.1 | C4: 美国 | D4: 东部 | E4: 13 | F4: Sophie | G4: huakaifugui2020 | H4: 孙一文 | I4: 13 | M4: 理解能力强，读字速度慢，一下到二上之间 | N4: 中文 | O4: 周末班 | P4: 滕柳星 9:00 3.1 | Q4: 微信 | R4: 3 | S4: 王可 | T4: 0 | U4: 0 | V4: 0 | W4: 时间定不好
A5: 3 | B5: 3.1 | C5: 加拿大 | D5: 多伦多 | E5: 13 | F5: 秦窗窗 | G5: qinchuanger | H5: 姜子欣 | I5: 11 | M5: 2008.7.15 中文普通话交流无障碍，读写困难 | N5: 中文 | O5: 会拼音，中文词汇表达会有点困难，词汇量两百左右，建议从一上中后段开始学 | P5: 徐晓晓8:00 3.2 ChineseonlineH8:00 3.5 ChineseonlineE8:00 3.10 chineseonlineH8:20 3.19 | Q5: 家长介绍 | R5: 2 | S5: 赵国花 王梓珂妈妈介绍 | T5: 白 | U5: 1 | V5: 1 | W5: 1 | X5: 59/课 | Z5: 1298 | AA5: 3.19日缴费
A6: 4 | B6: 3.3 | C6: 西班牙 | E6: 7 | F6: caili sun | G6: X690569006 | H6: 詹欣怡 | M6: 一上中间，拼音不错 | N6: 中文 | O6: 数学课 | P6: 第一课堂第五节课 | Q6: 报第二门课 | R6: 1 | S6: 何家昌 | T6: 夜3组 | U6: 1 | V6: 1 | W6: 1 | X6: 650/月 | Z6: €1018 | AA6: 3.3日缴费
A7: 5 | B7: 3.3 | C7: 西班牙 | E7: 7 | F7: caili sun | G7: X690569006 | H7: 詹可怡 | M7: 一上中间，拼音不错 | N7: 中文 | O7: 数学课 | P7: 第二十一课堂第三节课 | Q7: 报第二门课 | R7: 1 | S7: 何家昌 | T7: 夜3组 | U7: 1 | V7: 1 | W7: 1 | X7: 650/月 | AA7: 3.3日缴费
A8: 6 | B8: 3.3 | C8: 美国 | D8: 东部 | E8: 13 | F8: Serena | G8: serenajian | H8: 简斯若 | I8: 6 | M8: 中文流利，不会拼音 | N8: 中文 | P8: 滕柳星8:00 3.3 天娃课堂01 8:00 3.7 | Q8: 家长介绍 | R8: 2 | S8: 敖雪家长介绍王晨 | T8: 兼 | U8: 0 | V8: 0 | W8: 没时间，一周三节排不了
A9: 7 | B9: 3.3 | C9: 澳大利亚 | E9: 3 | F9: Amy是曦妈 | G9: z531002025 | H9: 郑乐曦 | I9: 4.5 | M9: 启蒙课 | N9: 启蒙 | P9: 卢老师启蒙课17:00 2.29 3.1 | Q9: 家长介绍 | R9: 1 | S9: 张文红 李乐轩妈妈介绍 | T9: 兼 | U9: 1 | V9: 1 | W9: 1 | X9: 79/课 | Z9: 1738 | AA9: 3.3日缴费 | AB9: 3.2-4.20日 一周三次
A10: 8 | B10: 3.3 | C10: 美国 | D10: 西部 | E10: 16 | F10: 高大高 | G10: gao42464801 | H10: 邓若琳 | I10: 9 | M10: 学了2.5年了，拼音不错，很多字是会读不会写 | N10: 中文 | O10: 二上后到二下前水平 | P10: 滕柳星 10:30 3.3 ChineseonlineQ10:00 3.4 | Q10: 微信 | R10: 3 | S10: 王可 | T10: 白 | U10: 1 | V10: 1 | W10: 1 | X10: 65课时，中文24＋数学41 | Z10: 3640 | AA10: 3.10日缴费 | AB10: 一周三次
A11: 9 | B11: 3.4 | C11: 美国 | D11: 纽约 | F11: Anita Fang | G11: anita_fzx | H11: Andrew Zeng | I11: 7 | M11: 男 | N11: yct | O11: 中文学校学了拼音，学得不认真，没办法中文口语交流，建议学Yct | P11: 滕柳星8:00 3.4 ChineseonlineT 8:40 3.5 | Q11: 电话 | R11: 1 | S11: 刘敏 | T11: 兼 | U11: 0 | V11: 0 | W11: 很晚下班，没人陪上课
A12: 10 | B12: 3.4 | C12: 加拿大 | D12: 万锦 | F12: uiolet | G12: uioletlao | H12: 陈逸帆 | I12: 10 | M12: 之前学过一点点，后来没学了 | N12: yct | O12: 听得懂广东话，不会普通话，零基础，建议先学拼音再YCT | P12: 滕柳星9:00 3.4 二十课堂8:40 3.6 | Q12: 微信 | R12: 1 | S12: 何家昌 | T12: 兼 | U12: 0 | V12: 0 | W12: 怕弟弟妹妹太吵影响其他同学，等弟弟妹妹长大些再报名
A13: 11 | B13: 3.4 | C13: 中国 | D13: 福建 | F13: 陈孔燕 | G13: chenky2 | H13: 邬骐骏 | I13: 6 | J13: 男 | K13: 否 | L13: 否 | M13: 学过一点 会读不会写 现在是大班，9月份上小学，想给他过渡好幼小衔接 | N13: 中文 | O13: 非常聪明，识字量巨大 | P13: 滕柳星11:00 3.4 | Q13: 微信 | R13: 3 | S13: 王可 | T13: 0 | U13: 0 | V13: 0 | W13: 价格太贵
A14: 12 | B14: 3.4 | C14: 澳大利亚 | D14: 悉尼 | E14: 3 | F14: Ellie W | G14: sisley0011 | H14: 邱新童（lsabella） | I14: 7 | M14: 学校有学 ，听说没问题 | N14: 中文 | O14: 中文词汇量一般，有一些不会表达；拼音不会，需要从头开始 | P14: 徐晓晓14:00 3.4 ChineseonlineG16:30 3.6 | Q14: 微信 | R14: 3 | S14: 王可 | T14: 白 | U14: 0 | V14: 0 | W14: 最近有点忙，想过段时间学
A15: 13 | B15: 3.4 | C15: 新西兰 | D15: 奥克兰 | E15: 3 | F15: 瑜 | G15: zhaoyu150531 | H15: 王泓尧 | I15: 7 | M15: 家长说拼音已经学习完，认识几个字，没有怎么系统的学习过，在家中文交流 | N15: 中文 | O15: 一上江南左右程度 | P15: 滕柳星14:30 3.4 ChineseonlineC14:00 3.5 | Q15: 微信 | R15: 2 | S15: 高翱翔 | T15: 兼 | U15: 1 | V15: 1 | W15: 1 | X15: 56/课 65课时 | Z15: 3640 | AA15: 3.7日缴费
A16: 14 | B16: 3.5 | C16: 意大利 | F16: 汉 | G16: bohan718538 | H16: 蔡如意 | I16: 9岁 | M16: 暑假学了两个月，沟通没问题；拼读没问题，读拼音个别不流畅，认字和书写没问题 | N16: 中文 | P16: 三十一课堂00:40 3.5 | Q16: 微信 | R16: 1 | S16: 何家昌 | T16: 夜3组 | U16: 1 | V16: 1 | W16: 1 | X16: 660/月 | Z16: 660 | AA16: 3.12日缴费
A17: 15 | B17: 3.5 | C17: 澳大利亚 | D17: 新南威尔士 | E17: 2 | F17: Frieda | G17: frieda | H17: 诸葛羽靓 | I17: 6 | J17: 男 | K17: 有 | L17: 否 | M17: 小名 骄骄 | N17: 中文 | O17: 识字量大，声母学过不熟，不太会拼，四声不熟练，jqx左右都可 | P17: 滕柳星13:30 3.5 | Q17: 家长介绍 | R17: 3 | S17: 王可 王希捷妈妈介绍 | T17: 0 | U17: 0 | V17: 0 | W17: 没定时间
A18: 16 | B18: 3.5 | C18: 澳大利亚 | D18: 悉尼 | E18: 3 | F18: Ashley | G18: Ashleybabygirl | H18: 陈双如 | I18: 5 | M18: 学过国内一年级上册 | N18: 中文 | O18: 中文表达一般，但是交流没问题，稍微有点害羞 | P18: 徐晓晓13:30 3.5 ChineseonlineI 12:40 3.6 | Q18: 家长介绍 | R18: 3 | S18: 王可 王希捷妈妈介绍 | T18: 白 | U18: 0 | V18: 0 | W18: 当地有免费网络公开课
A19: 17 | B19: 3.5 | C19: 新西兰 | D19: 奥克兰 | E19: 5 | F19: 杨玉环jade释然 | G19: yyh102298 | H19: 李阳01 | I19: 5 | M19: 自己在家教， | N19: 中文 | O19: 妈妈在家自己教，dtnl左右开始可以 中国11:00 | P19: 滕柳星11:00 3.5 ChineseonlineJ | Q19: 微信 | R19: 1 | S19: 何家昌 | T19: 白 | U19: 0 | V19: 0 | W19: 不读了
A20: 18 | B20: 3.6 | C20: 美国 | D20: 旧金山 | E20: 16 | F20: 茜美代纯手工阿胶糕 | G20: sissipeterannaamy | H20: 何敏慧Anna | I20: 10 | M20: 只会说，中文类词汇储备不多 | N20: 中文 | O20: 拼音基本没问题，可以从课文刚开始，不会识字 | P20: 徐晓晓9:00 3.6 | Q20: 微信 | R20: 3 | S20: 展旺 | T20: 0 | U20: 0 | V20: 0 | W20: 老爸不愿意给他们学，觉得压力太大了
A21: 19 | B21: 3.6 | C21: 美国 | D21: 旧金山 | E21: 16 | F21: 茜美代纯手工阿胶糕 | G21: sissipeterannaamy | H21: 何晓雯Amy | I21: 7.5 | M21: 只会说，中文类词汇储备不多 | N21: 中文 | O21: 拼读要复韵母复习 | P21: 徐晓晓9:00 3.6 | Q21: 微信 | R21: 3 | S21: 展旺 | T21: 0 | U21: 0 | V21: 0 | W21: 老爸不愿意给他们学，觉得压力太大了
A22: 20 | B22: 3.6 | C22: 澳大利亚 | D22: 悉尼 | E22: 3 | F22: Ashley | G22: Ashleybabygirl | H22: 陈沐芸 | I22: 7 | M22: 中国学了一个月，把一本快学完了， | N22: 中文 | O22: 但是掌握不佳，拼读不流畅，复韵母程度复习 | P22: 滕柳星13:30 3.6 ChineseonlineL14:00 3.6 | Q22: 家长介绍 | R22: 3 | S22: 王可 王希捷妈妈介绍 | T22: 白 | U22: 0 | V22: 0 | W22: 当地有免费网络公开课
A23: 21 | B23: 3.6 | C23: 西班牙 | D23: 马德里 | E23: 7 | F23: 品芬 | G23: 605486655 | H23: 叶浩 | I23: 13 | N23: 中文 | O23: 一上拼音 | P23: 第三十六课堂A第一节课 3.6 | Q23: 微信 | R23: 1 | S23: 张文红 | T23: 夜1组 | U23: 0 | V23: 0 | W23: 人太多，孩子向，不好意思交流，不计入老师数据
A24: 22 | B24: 3.6 | C24: 西班牙 | D24: 马德里 | E24: 7 | F24: 品芬 | G24: 605486655 | H24: 叶怡 | I24: 15 | N24: 中文 | O24: 一下 | P24: 第八课堂A第二节课 3.6 | Q24: 微信 | R24: 1 | S24: 张文红 | T24: 夜2组 | U24: 0 | V24: 0 | W24: 不喜欢老师，不计入老师数据
A25: 23 | B25: 3.6 | C25: 西班牙 | D25: 马德里 | E25: 7 | F25: 品芬 | G25: 605486655 | H25: 郑怡 | I25: 14 | N25: 中文 | O25: 一下 | P25: 第八课堂A第四节课 3.6 | Q25: 微信 | R25: 1 | S25: 张文红 | T25: 夜2组 | U25: 0 | V25: 0 | W25: 不喜欢老师，不计入老师数据
A26: 24 | B26: 3.7 | C26: 加拿大 | D26: 汉密尔顿 | E26: 13 | F26: 7Ester7 | G26: ecjy2000 | H26: 陈以灵 | I26: 8 | M26: 拼音掌握了点，在当地中文学校学习的；在用讲英语，中文只会一点点 | N26: 中文 | O26: 需要活泼开朗的双语老师教学 | P26: 魏霞00:00 3.6 | Q26: 微信 | R26: 2 | S26: 高翱翔 | T26: 0 | U26: 0 | V26: 0 | W26: 如果疫情不严重家人没时间可以考虑我们；现在主要姐姐教，在当地学
A27: 25 | B27: 3.7 | C27: 美国 | E27: 13 | F27: OYH | G27: ouyangweng520 | H27: 翁俊翔 | I27: 8 | M27: 没有学习过拼音之前当地中文学校学的是暨南大学的教材会写几个字 可以听懂但不会说的那种 | N27: 中文 | O27: 中文词汇较少，但是普通交流没问题；生字量50左右，拼音没学过，中国一二三早上8:00 | P27: 徐晓晓8:00 3.7 十八课堂C 8:00覃琦 | Q27: 微信 | R27: 2 | S27: 高翱翔 | T27: 兼 | U27: 0 | V27: 0 | W27: 当地中文学校也开网课了
A28: 26 | B28: 3.7 | C28: 澳大利亚 | E28: -2 | F28: Daniel 庞 | G28: danielpang_melbourne | H28: William pang 小宇 | I28: 7 | M28: 7岁 有上过中文课，拼音不太好，认字一般，笔顺不对 | N28: 中文 | O28: 可以从复韵母阶段开始学 | P28: 滕柳星11:00 3.7 | Q28: 电话 | R28: 3 | S28: 王可 | T28: 0 | U28: 0 | V28: 0 | W28: 没定好时间
A29: 27 | B29: 3.7 | C29: 澳大利亚 | D29: 悉尼 | E29: 3 | F29: Fay | G29: Fay_xiaofei | H29: Adaline | I29: 5 | M29: 可以交流 识字量不到200 写字不行 | N29: 中文 | O29: 家里教过一些，不过相当于零基础；明年开始学英语拼读，可以现在学拼音 | P29: 徐晓晓11:00 3.7 ChineseonlineC周六日 16:00半小时3.8 | Q29: 家长介绍 | R29: 3 | S29: 王可 王希捷妈妈介绍 | T29: 兼 | U29: 1 | V29: 1 | W29: 1 | Y29: 一对一 65课 | Z29: 7540 | AA29: 3.10日缴费
A30: 28 | B30: 3.8 | C30: 美国 | D30: 夏威夷 | E30: 17 | F30: my | G30: my86861 | H30: 陈裕轩 | I30: 9 | M30: 国内一年级中文学校一学期会拼音但是很久没学 | N30: 中文 | O30: 有一些识字量，但是拼音需要从拼读开始复习 | P30: 徐晓晓12:00 3.8 | Q30: 微信 | R30: 2 | S30: 王晨 | T30: 0 | U30: 0 | V30: 0 | W30: 觉得价格太贵
A31: 29 | B31: 3.8 | C31: 美国 | D31: 夏威夷 | E31: 17 | F31: my | G31: my86861 | H31: 陈裕蒴shuò | I31: 6 | M31: 中文学校学习，拼音不太会 | N31: 中文 | O31: 零基础，很活跃，需要老师能控场 | P31: 徐晓晓12:30 3.8 | Q31: 微信 | R31: 2 | S31: 王晨 | T31: 0 | U31: 0 | V31: 0 | W31: 觉得价格太贵
A32: 30 | B32: 3.8 | C32: 新西兰 | D32: 奥克兰 | E32: 5 | F32: sophia wang | G32: elaine_kids_fashion | H32: 林筠欣 | I32: 8 | M32: 零基础，表达和理解都很好，学习能力也强，建议从一年级的拼音开始学习 | N32: 中文 | O32: 早上7点或者11点 国内时间姐姐的表达和理解都很好，学习能力也强，建议从一年级的拼音开始学习 | P32: 徐晓晓14:30 3.8 天娃课堂01 7:00 3.11 ChineseonlineE15:30 3.16 三十八课堂 7:40 3.18 | Q32: 微信 | R32: 1 | S32: 何家昌 | T32: 夜2组 | U32: 1 | V32: 1 | W32: 1 | Y32: 56/课 | Z32: 3640 | AA32: 3.16日缴费
A33: 31 | B33: 3.8 | C33: 新西兰 | D33: 奥克兰 | E33: 5 | F33: sophia wang | G33: elaine_kids_fashion | H33: 林家逸 | I33: 5 | M33: 零基础，接受程度会慢一些，建议从启蒙课程开始学习，主要以表达、识字为主 | N33: 中文 | O33: 弟弟不愿意学 姐姐先学 | P33: 徐晓晓14:30 3.8 | Q33: 微信 | R33: 1 | S33: 何家昌 | T33: 0 | U33: 0 | V33: 0 | W33: 不愿意学
A34: 32 | B34: 3.10 | C34: 加拿大 | D34: 温哥华 | E34: 15 | F34: 张仪 | G34: L427521l | H34: 李福田 | I34: 9 | M34: 7783258812 男，2011年12月3日；7岁半拼音和识字都认识一点 | N34: 中文 | O34: 9月份试读，3月份重新上课 | P34: ChineseonlineJ 13:40 3.10 | Q34: 微信 | R34: 白 | S34: Emma介绍 | T34: 白 | U34: 1 | V34: 1 | W34: 1 | Y34: 650/月 半年送两周 | Z34: 3900 | AA34: 3.9日缴费
A35: 33 | B35: 3.10 | C35: 加拿大 | D35: 温哥华 | E35: 15 | F35: 张仪 | G35: L427521l | H35: 李佳茜 | I35: 7 | N35: 中文 | P35: ChineseonlineB10 10:00 3.10 Chineseonline F 14:00 3.25 | Q35: 微信 | R35: 白 | S35: Emma介绍 | T35: 兼 | U35: 1 | V35: 1 | W35: 1 | Y35: 650/月 半年送两周 | Z35: 3900 | AA35: 3.9日缴费
A36: 34 | B36: 3.10 | C36: 加拿大 | D36: 多伦多 | E36: 12 | F36: 林氏地产团队林敏 | G36: reinario | H36: 何嘉豪 | I36: 8 | M36: 不怎么懂中文，之前学习过一点点，不理想，需要双语教学，生日3月8日 | N36: 双语 | O36: 零基础，需要双语 | P36: 徐晓晓8:00 3.10 十八课堂C覃琦 8:00 3.12 | Q36: 家长介绍 | R36: 2 | S36: 高翱翔 sami妈妈介绍 | T36: 兼 | U36: 1 | V36: 1 | W36: 1 | Y36: 44课时 | Z36: 2600 | AA36: 3.18日缴费
A37: 35 | B37: 3.10 | C37: 美国 | D37: 东部 | E37: 12 | F37: 透明果冻 | G37: elaine12Wang | H37: 魏文熙 | I37: 6 | M37: 没学过听得懂 | N37: 中文 | O37: 零基础 要8:20上课 | P37: 滕柳星8:30 3.10 天娃课堂01 7:00 3.11 | Q37: 电话 | R37: 3 | S37: 杨斌 | T37: 兼 | U37: 0 | V37: 0 | W37: 当地比较恐慌，学校还没停学，暂时不学
A38: 36 | B38: 3.10 | C38: 美国 | D38: 西部 | E38: 15 | F38: 高大高 | G38: gao42464801 | H38: 邓若琳 | I38: 9 | N38: 数学 | O38: 二上后到二下前水平 | P38: 第十一课堂6:55 3.8 | Q38: 微信 | R38: 3 | S38: 王可 | T38: 白 | U38: 1 | V38: 1 | W38: 1 | X38: 和中文一起缴，41课时 | AA38: 3.10日缴费 | AB38: 一周五次
A39: 37 | B39: 3.10 | C39: 美国 | D39: 旧金山 | F39: 李珊珊 | G39: Sackife | H39: 王希加亚 | I39: 4.5 | M39: 有个表弟路易4岁 | N39: 中文 | O39: 零基础 | P39: 滕柳星 10:30 3.10 | Q39: 微信 | R39: 3 | S39: 展旺 | T39: 0 | U39: 0 | V39: 0 | W39: 家长觉得贵，孩子表现也不是很喜欢
B40: 2019.12月客户 | C40: 澳大利亚 | D40: 悉尼 | E40: 3 | F40: 杨静钰Gracy Yang | G40: richardjxu1972 | H40: Addison徐思源 | I40: 8 | M40: 一上中间 | N40: 中文 | O40: 一周一天，周六下午 中国16:00-17:00 | P40: 滕柳星 14:30 12.31 ChineseonlineL 16:30 1.17 ChineseonlineH16:50 3.5 天娃课堂03 15:40 3.14 | Q40: 电话 | R40: 3 | S40: 展旺 | T40: 兼 | U40: 1 | V40: 1 | W40: 1 | X40: 1100/月 | Y40: 周末班一小时，十节课，九折 | Z40: 1215 | AA40: 3.10日缴费
A41: 38 | B41: 3.10 | C41: 美国 | D41: 东部 | E41: 12 | F41: Yanny | G41: yanny0303 | H41: 郑孝莹 | I41: 5 | M41: 不会说中文，零基础，比较内向 | N41: 启蒙 | O41: 双语 | P41: 任宏印8:00 3.10 十八课堂C 8:00 3.12 | Q41: 微信 | R41: 3 | S41: 展旺 | T41: 兼 | U41: 1 | V41: 1 | W41: 1 | X41: 76/课 | Y41: 一对二付一对三 | Z41: 705 | AA41: 3.17日缴费
A42: 39 | B42: 3.11 | C42: 美国 | D42: 纽约 | E42: 12 | F42: 瑶 | G42: Woainibaobaohang | H42: 乐杭 | I42: 7 | M42: 男 | N42: 中文 | O42: 学过单韵母，有点忘记了。iuv左右学纽约时间晚上7点到9点都可以 | P42: 滕柳星 8:30 3.11 天娃课堂01 7:00 3.12 | Q42: 微信 | R42: 1 | S42: 刘敏 | T42: 兼 | U42: 0 | V42: 0 | W42: 想要一对二，但觉得价格太贵
A43: 40 | B43: 3.11 | C43: 德国 | D43: 德国 | E43: 6 | F43: 平平 | G43: wxid_eljz740xk4ne11 | H43: 嘟嘟1 | I43: 7 | M43: 在家和妈妈学，没有系统的教过，他听得懂中文，但说的不行 | N43: 中文 | P43: 第五十六课堂第一节课 3.11 | Q43: 微信 | R43: 白 | S43: 马婧介绍 | T43: 夜4组
A44: 41 | B44: 3.11 | C44: 加拿大 | D44: 温哥华 | E44: 15 | F44: May | G44: huangmei636412 | H44: Evan huang | I44: 6 | M44: 零基础，会说 | N44: 中文 | O44: 零基础 | P44: 滕柳星10:00 3.11 ChineseonlineR 10:20 3.13 | Q44: 家长介绍 | R44: 1 | S44: 何家昌 林鸿博妈妈介绍 | T44: 白 | U44: 1 | V44: 1 | W44: 1 | X44: 59/课 | Y44: 22课时 | Z44: 1298 | AA44: 3.15日缴费
A45: 42 | B45: 3.11 | C45: 新西兰 | D45: 哈密尔顿 | E45: 5 | F45: 伊铭宝宝 | G45: erin_huang88 | H45: 黄景杨 | I45: 8 | M45: 学过拼音，四声略不熟 | N45: 中文 | O45: 拼音基本掌握，声调略不熟需要复习，一上中水平，中国中午11点上课 | P45: 滕柳星11:30 3.11 ChineseonlineN 11:00 3.16 | Q45: 微信 | R45: 1 | S45: 何家昌 | T45: 白 | U45: 0 | V45: 0 | W45: 报了当地的中文学校
A46: 43 | B46: 3.11 | C46: 新西兰 | D46: 哈密尔顿 | E46: 5 | F46: 伊铭宝宝 | G46: erin_huang88 | H46: 黄琬仟 | I46: 6 | M46: 中文学过一点，但是不会说中文，几乎零基础，听得懂粤语 | N46: 中文 | O46: 零基础，只会粤语英语，需要双语课或启蒙，中国中午11点上课 | P46: 滕柳星11:30 3.11 第十八课堂C16:00 3.17 | Q46: 微信 | R46: 1 | S46: 何家昌 | T46: 兼 | U46: 0 | V46: 0 | W46: 报了当地的中文学校
A47: 44 | B47: 3.11 | C47: 美国 | D47: 西部 | E47: 15 | F47: Jean欧阳Realtor | G47: Jean-oy | H47: Enna O’Young（用户名Ennajoy）欧阳凯恩 | I47: 10 | M47: 刚学完西游记，中文不是很好 | N47: 中文 | O47: 基本交流无障碍，拼音熟练，有时会有点表达不出自己的意思，二上后或二下前程度 | P47: 滕柳星12:00 3.11 ChineseonlineG1 11:40 3.16 ChineseonlineL 9:00 3.19 Chineseonline N 8:20 3.20 | Q47: 微信 | R47: 3 | S47: 展旺 | T47: 白 | U47: 0 | V47: 0 | W47: 孩子不喜欢
A48: 45 | B48: 3.7 | C48: 美国 | E48: 12 | F48: Anita Fang | G48: anita_fzx | H48: 曾嘉琳 | N48: 启蒙 | P48: 卢老师3.7 | Q48: 微信 | R48: 1 | S48: 刘敏 | T48: 兼 | U48: 0 | V48: 0 | W48: 妈妈和爸爸沟通说没时间陪读 爷爷奶奶又不会普通话不放心 想先报线下中文课
A49: 46 | B49: 3.11 | C49: 新西兰 | D49: 奥克兰 | E49: 5 | F49: RXY | G49: rxy0829 | H49: 关丞洋 | I49: 5 | M49: 可以听懂中文，但是自己发音不标准 | N49: 启蒙 | P49: 陈琪3.11 3.12 | Q49: 微信 | R49: 2 | S49: 高翱翔 | T49: 兼 | U49: 0 | V49: 0 | W49: 也没问价，在悟空试过课，说大一点再上
A50: 47 | B50: 3.12 | C50: 西班牙 | D50: 萨拉戈萨 | E50: 6 | G50: jianjing675852139 | H50: 李哲文 | I50: 6 | M50: 只去过几天，太远了 | N50: 中文 | O50: 零基础，可以交流 | P50: 徐晓晓17:00 3.11 第五十五课堂第四节课 3.12 五十六课堂第一节3.13 | Q50: 微信 | R50: 1 | S50: 俞酉兰 | T50: 夜4组 | U50: 1 | V50: 1 | W50: 1 | X50: 660/月 | Y50: 一对六 | Z50: 660 | AA50: 3.17日缴费
A51: 48 | B51: 3.12 | C51: 美国 | D51: 西部 | E51: 15 | F51: zoe | G51: h13502821084 | H51: 杜映霖 | I51: 8 | M51: 二年级，有一定的中文基础，但是程度很低了 | N51: 中文 | O51: 拼读有些不准，识字量100左右，可以从一上课文部分学 | P51: 徐晓晓7:00 3.12 chineseonlineG8:20 3.16 chineseonlineL 8：20 3.20 | Q51: 微信 | R51: 1 | S51: 刘巧芹 | T51: 白 | U51: 0 | V51: 0 | W51: 孩子不喜欢
A52: 49 | B52: 3.12 | C52: 美国 | D52: 纽约 | E52: 12 | F52: 禧燕堂~印尼燕窝（ Christy） | G52: ping031582 | H52: 董秋荷 | I52: 9 | M52: 星期天有去中文学校 一年级 | N52: 中文 | O52: 学生程度一年级程度偏差 不会中文拼音的拼读方法，有一定的基础，简单的字认识一些，可以从一上课文部分开始。周末班。 | P52: 任宏印7；00 3.12 第五课堂 6:00 3.13 ChineseonlineB10 23:00 周末班 | Q52: 家长介绍 | R52: 1 | S52: 刘巧芹何思迦爸爸介绍 | T52: 兼 | U52: 0 | V52: 0 | W52: 不喜欢
A53: 50 | B53: 3.12 | C53: 加拿大 | D53: 最东部 | E53: 11 | F53: 思琪 依玲Elaine | G53: elainezong2012 | H53: 宗子宜Emily（粽子） | I53: 10 | M53: 国内学完三年级，目前自学四年级 | N53: 中文 | O53: 可以从四上接着学，基础很扎实 | P53: 徐晓晓7:40 3.12 | Q53: 微信 | R53: 1 | S53: 何家昌 | T53: 0 | U53: 0 | V53: 0 | W53: 在线下学校报名了
A54: 51 | B54: 3.12 | C54: 美国 | D54: 东部 | E54: 12 | F54: Rachel | G54: huaxiang73 | H54: 温光晴 | I54: 8 | M54: 听得懂一些中文，平时都讲粤语，中文口语一般 | N54: 中文 | O54: 拼音会一些，声调不准，需要复习；识字量50左右，可以从课文刚开始学 | P54: 徐晓晓8:30 3.12 ChineseonlineL8:20 3.13 | Q54: 家长介绍 | R54: 2 | S54: 王晨敖雪妈妈介绍 | T54: 白 | U54: 1 | V54: 1 | W54: 1 | X54: 59/课 | Y54: 一对四 | Z54: 1298 | AA54: 3.14日缴费
A55: 52 | B55: 3.12 | C55: 加拿大 | D55: 多伦多 | E55: 12 | G55: joanneshenwenhua | H55: James3 | I55: 14 | M55: 有学过一点 听说有障碍，要双语老师 | N55: 中文 | O55: 会说中文，不需双语，零基础，一对二，中国早上八点二四五 | P55: 滕柳星8:00 3.12 天娃课堂01徐晓晓8:00 3.13 ChineseonlineM孙水仙7:40 3.18 | Q55: 家长介绍 | R55: 2 | S55: 赵国花姜子欣妈妈推荐 | T55: 兼 | U55: 1 | V55: 1 | W55: 1 | X55: 99/课 | Y55: 一对一 | Z55: 2178 | AA55: 3.14日缴费 | AB55: 美国一三四上课 一对二
A56: 53 | B56: 3.12 | C56: 加拿大 | D56: 多伦多 | E56: 12 | G56: joanneshenwenhua | H56: Joyce2叶婧安 | I56: 12 | M56: 会说一点也完全是外国人口音，要双语老师 | N56: 中文 | O56: 可以不用双语，基本能交流，从拼音开始学；学习态度很好 | P56: 滕柳星8:00 3.12 天娃课堂01徐晓晓8:00 3.13 ChineseonlineM孙水仙7:40 3.18 | Q56: 家长介绍 | R56: 2 | S56: 赵国花姜子欣妈妈推荐 | T56: 兼 | U56: 1 | V56: 1 | W56: 1 | X56: 99/课 | Y56: 一对一 | Z56: 2178 | AA56: 3.14日缴费 | AB56: 美国一三四上课 一对二
A57: 54 | B57: 3.12 | C57: 澳大利亚 | D57: 悉尼 | E57: 3 | F57: Vien | G57: wxid_xq31upbcpl7522 | H57: 蔡宗勳 | I57: 8 | M57: 断断续续学过一年 交流没问题 | N57: 中文 | O57: 一上中程度 | P57: 滕柳星9:00 3.12 ChineseonlineC1 15:00 3.13 | Q57: 家长介绍 | R57: 3 | S57: 王可 王有衡妈妈推荐 | T57: 兼 | U57: 0 | V57: 0 | W57: 家长说要过一段时间
A58: 55 | B58: 3.12 | C58: 美国 | D58: 圣何塞 | E58: 15 | F58: Yoyo | G58: yoyowong66 | H58: 郑子谦 | I58: 11 | M58: 国内一年级水平。可以听懂中文 | N58: 中文 | O58: 一下中后，要周末班 | P58: 滕柳星10:30 3.12 二十课堂 12:30 3.16 | Q58: 家长介绍 | R58: 3 | S58: 展旺 汪星彤妈妈介绍 | T58: 兼 | U58: 1 | V58: 1 | W58: 1 | X58: 56/课 65课时，两人团-200 | Y58: 6880 | Z58: 3.21日缴费
A59: 56 | B59: 3.12 | C59: 加拿大 | D59: 温哥华 | E59: 15 | G59: wxid_h88wx3orbye711 | H59: 刘熙雅（天天） | I59: 7 | M59: 学过拼音 中英文交流都OK 认识汉字 书写有困难 | N59: 中文 | O59: 拼读基本会，需要复习一下，读得比较慢，识字量50以下；可以从一上课文刚开始学 | P59: 徐晓晓10:30 3.12 ChineseonlineM 11:00 3.13 | Q59: 家长介绍 | R59: 2 | S59: 赵国花张亦森爸爸推荐 | T59: 兼 | U59: 1 | V59: 1 | W59: 1 | X59: 59/课 | Y59: 1298 | Z59: 3.17日缴费
A60: 57 | B60: 3.12 | C60: 美国 | D60: 圣何塞 | E60: 15 | F60: Yoyo | G60: yoyowong66 | H60: LukeZheng | I60: 5 | M60: 是自己在家教的没上过中文学校 | N60: 中文 | P60: 陈琪11:30 3.12 ChineseonlineR10：20 3.17 | Q60: 家长介绍 | R60: 3 | S60: 展旺 汪星彤妈妈介绍 | T60: 兼 | U60: 0 | V60: 0 | W60: 觉得启蒙课价格太贵
A61: 58 | B61: 3.12 | C61: 美国 | E61: 15 | F61: 净悟 | G61: USAmail0815 | H61: 王烨1 | I61: 11 | M61: 国内一年级学完出国，自学到三年级 | N61: 中文 | P61: 徐晓晓11:00 3.12 中文课堂11:40 3.13 | Q61: 家长介绍 | R61: 2 | S61: 高翱翔 李思蓓妈妈介绍 | T61: 兼 | U61: 1 | V61: 1 | W61: 1 | X61: 53/课 四人团130课时-650 | Y61: 6240 | Z61: 3.14日缴费
A62: 59 | B62: 3.12 | C62: 美国 | D62: 圣何塞 | E62: 15 | F62: Yoyo | G62: yoyowong66 | H62: 郑亦涵 | I62: 8 | M62: 程度一般，上课比较积极，零基础 | N62: 中文 | O62: 从识字开始学，没学过拼音 | P62: 任宏印11:00 3.12 ChineseonlineR 3.19 | Q62: 家长介绍 | R62: 3 | S62: 展旺 汪星彤妈妈介绍 | T62: 白 | U62: 1 | V62: 1 | W62: 1 | X62: 56/课 65课时，两人团-200 | Y62: 和郑子谦一起交 | Z62: 3.21日缴费
A63: 60 | B63: 3.12 | C63: 澳大利亚 | D63: 新南威尔士 | F63: Jing Wan | G63: jennywan86 | H63: 黄豆豆1 | I63: 7 | M63: 普通话说得很好 | N63: 中文 | O63: 复韵母开始 | P63: 滕柳星 13:30 3.12 ChineseonlineL 13:00 3.13 | Q63: 家长介绍 | R63: 3 | S63: 王可 希捷妈妈推荐 | T63: 白 | U63: 0 | V63: 0 | W63: 没回复
A64: 61 | B64: 11.3没算过试读 | C64: 塞尔维亚 | E64: 7 | F64: 笑忘书 | G64: wzx92801280 | H64: 何温雅 | I64: 4 | M64: 会听中文，说不太好，当地说匈牙利语，希望能用中文交流 | N64: 中文 | P64: ChineseonlineT隋老师20:00 3.1 | Q64: 微信 | R64: 2 | S64: 王晨 | T64: 兼 | U64: 1 | V64: 已经算过 | W64: 1 | X64: 一周三次 | Y64: 1100 | Z64: 11.30日缴费
B65: 1.22 | C65: 美国 | D65: 西部 | E65: 16 | F65: Emily | G65: emilysanjose | H65: ethan3 chen | I65: 10 | M65: 阅读能力好二上课文阅读没问题，但是一下生字需要巩固。建议一下课文开始 | N65: 中文 | P65: 杨启1.21 ChineseonlineG12:00 2.26 ChineseonlineJ 11：00 3.10 | Q65: 微信 | R65: 3 | S65: 王可 | T65: 白 | U65: 1 | V65: 1 | W65: 1 | X65: 41课时，一三五 | Y65: 523 | Z65: 3.12日缴费
B66: 1.22 | C66: 美国 | D66: 西部 | E66: 16 | F66: Emily | G66: emilysanjose | H66: elaine2 shen | I66: 6 | M66: 认识一点生字，但是拼音不会，建议拼音开始，慢热 | N66: 中文 | P66: 3 | Q66: 微信 | R66: 3 | S66: 王可 | T66: 兼 | U66: 1 | V66: 1 | W66: 1 | X66: 24课时 一三五 | Z66: 3.12日缴费
A67: 62 | B67: 3.13 | C67: 美国 | D67: 纽约 | E67: 12 | F67: li cheng | G67: musiclicn | H67: Derek1 | I67: 6 | M67: 男孩 当地有报中文周末班中文能听懂 | N67: 中文 | O67: 拼音熟练，一上《影子》左右。中国周四、周日早上7:30。一对一 | P67: 滕柳星7:20 3.13 | Q67: 微信 | R67: 1 | S67: 刘敏 | T67: 兼 | U67: 1 | V67: 1 | W67: 1 | X67: 118/课 一周两次 一对一 | Y67: 944 | Z67: 3.15日缴费
A68: 63 | B68: 3.13 | C68: 美国 | D68: 西部 | E68: 15 | F68: 张莉 | G68: lilyzhang0823 | H68: 邝雨欣 | I68: 6 | M68: 下个月6岁了，之前在唐人街的中文学校读中文的 | N68: 中文 | O68: 比较内向，有一点基础，但是程度不好，反应不够快，举手不积极，零基础 | P68: 魏霞7:40 3.13 ChineseonlineN9:00 3.14 | Q68: 家长介绍 | R68: 3 | S68: 展旺林道博妈妈介绍 | T68: 白 | U68: 0 | V68: 0 | W68: 报了其他家
A69: 64 | B69: 3.13 | C69: 美国 | D69: 西部 | E69: 15 | F69: 张莉 | G69: lilyzhang0823 | H69: 邝雨檬 | I69: 6 | M69: 下个月6岁了，之前在唐人街的中文学校读中文的 | N69: 中文 | O69: 妹妹更活泼，知道的比较多，积极回答问题，aoe学过，但是不会辨认声调 | P69: 魏霞7:40 3.13 ChineseonlineN9:00 3.14 | Q69: 家长介绍 | R69: 3 | S69: 展旺林道博妈妈介绍 | T69: 白 | U69: 0 | V69: 0 | W69: 报了其他家
A70: 65 | B70: 3.13 | C70: 美国 | D70: 波士顿 | E70: 12 | F70: Katrina | G70: Katrina-niena | H70: 陈炫佑 | I70: 12 | M70: 会说不会写，拼音也不会 | N70: 中文 | O70: 可以正常交流，0识字量，aoe学会了，接下来iuv | P70: 滕柳星9:00 3.13 | Q70: 电话 | R70: 3 | S70: 展旺 | T70: 0 | U70: 0 | V70: 0 | W70: 一直没回复
A71: 66 | B71: 3.13 | C71: 加拿大 | D71: 温哥华 | E71: 15 | F71: Sarah孙烨 | G71: sunyeSarah | H71: Eden | I71: 4.5 | M71: 7786803233 | N71: 启蒙 | P71: 陈琪8:30 3.13 classin8:00 3.16 | Q71: 微信 | R71: 1 | S71: 何家昌 刘怡暄妈妈拉的群 | T71: 兼 | U71: 1 | V71: 1 | W71: 1 | X71: 76/课 一对二 | Y71: 65课时 | Z71: 4940 | AA71: 3.17日缴费
A72: 67 | B72: 3.13 | C72: 英国 | D72: 伦敦 | E72: 7 | F72: 野螃蟹 | G72: wildcrabuk | H72: 刘睿旎（馒头） | I72: 7 | M72: 可以听懂 但是不太会说和写 周末9点~10点，中国时间16:00~17:00，一上零基础，需要会一点英语的老师 | N72: 中文 | P72: 陈琪16:00 3.13 | Q72: 家长介绍 | R72: 3 | S72: 王可黄以诺妈妈推荐 | T72: 0 | U72: 0 | V72: 0 | W72: 家长说不读了，原因没说
A73: 68 | B73: 3.13 | C73: 英国 | D73: 伦敦 | E73: 7 | F73: 野螃蟹 | G73: wildcrabuk | H73: 刘睿恩（肉肉） | I73: 5 | M73: 可以听懂 但是不太会说和写 周末9点~10点，中国时间16:00~17:00，一上零基础，需要会一点英语的老师 | N73: 中文 | P73: 陈琪16:00 3.13 | Q73: 家长介绍 | R73: 3 | S73: 王可黄以诺妈妈推荐 | T73: 0 | U73: 0 | V73: 0 | W73: 家长说不读了，原因没说
A74: 69 | B74: 3.14 | C74: 新西兰 | D74: 奥克兰 | E74: 5 | F74: sophia wang | G74: elaine_kids_fashion | H74: 林筠欣（美术） | I74: 8 | M74: 零基础，表达和理解都很好，学习能力也强，建议从一年级的拼音开始学习 | N74: 美术 | P74: 美术课堂14:30 3.14 | Q74: 微信 | R74: 1 | S74: 何家昌 | T74: 兼 | U74: 0 | V74: 0 | W74: 觉得老师上课语速太快，报了另外一家
A75: 70 | B75: 3.14 | C75: 意大利 | E75: 7 | F75: luca（hong wang） | G75: hngwng82 | H75: 洪凯文 | I75: 12 | M75: 中文学校学到一年级 | N75: 中文 | P75: 第四十五课堂第二节课3.12 | Q75: 微信群 | R75: 白 | S75: 直播推广 | T75: 夜4组 | U75: 1 | V75: 1 | W75: 1 | X75: 650/月 | Y75: 1300 | Z75: 3.19日缴费
A76: 71 | B76: 3.14 | C76: 意大利 | E76: 7 | F76: luca（hong wang） | G76: hngwng82 | H76: 洪杰森 | I76: 8 | M76: 只会一点拼音 | N76: 中文 | P76: 第五十五课堂第五节课3.12 | Q76: 微信群 | R76: 白 | S76: 直播推广 | T76: 夜3组 | U76: 1 | V76: 1 | W76: 1 | X76: 650/月 | Z76: 3.19日缴费
A77: 72 | B77: 3.14 | C77: 澳大利亚 | D77: 悉尼 | E77: 3 | F77: 恋汐 | G77: missy6121 | H77: 王翔3 | I77: 6 | M77: 之前有会点中文，对拼音没概念，没学过 | N77: 中文 | O77: 有一点基础 口语符合教学程度，从识字课开始，妈妈准备让他和他同学一起报班 然后一起上课 | P77: 任宏印7:30 3.14 | Q77: 微信 | R77: 2 | S77: 平金军 | T77: 0 | U77: 0 | V77: 0 | W77: 说过段时间再排课，一直没回
A78: 73 | B78: 3.14 | C78: 西班牙 | E78: 7 | F78: ml love you | G78: yml_1015 | H78: 王梓涵 | I78: 7 | M78: 学过一点 | N78: 中文 | O78: 拼音复习班，要中国17:00上课 | P78: 陈琪16:00 3.13 ChineseonlineG 17:30 3.17 | Q78: 微信 | R78: 1 | S78: 何家昌 | T78: 白 | U78: 1 | V78: 1 | W78: 1 | X78: 59/课 | Y78: 351.4 | Z78: 3.21日缴费
A79: 74 | B79: 3.14 | C79: 西班牙 | E79: 7 | F79: ml love you | G79: yml_1015 | H79: 王梓宸 | I79: 5 | M79: 学过一点 | N79: 中文 | O79: 从头开始，零基础，要中国17:00上课 | P79: 陈琪16:00 3.13 ChineseonlineI17:35 3.19 | Q79: 微信 | R79: 1 | S79: 何家昌 | T79: 白 | U79: 1 | V79: 1 | W79: 1 | X79: 59/课 | Z79: 3.21日缴费
A80: 75 | B80: 3.14 | C80: 美国 | D80: 纽约 | E80: 12 | F80: wu x | G80: wxid_459wmmmclrcb22 | H80: Amanda liu | I80: 6 | M80: 济南大学写的教材学了两年了，刚开始学拼音；请家教在家学了一段时间 | N80: 中文 | O80: 拼音从拼读开始复习，识字量50以下 | P80: 徐晓晓8:00 3.14 ChineseonlineG | Q80: 家长介绍 | R80: 3 | S80: 王可 冯爱文妈妈介绍 | T80: 白 | U80: 1 | V80: 1 | W80: 1 | X80: 190/课 一小时，一对一 50节课，送2节课 | Y80: 9500 | Z80: 3.17日缴费
A81: 76 | B81: 3.14 | C81: 美国 | D81: 西部 | E81: 15 | F81: sara | G81: sara009 | H81: EricYang1（多多） | I81: 7 | M81: 口语不错，在家说 | N81: 中文 | O81: 笔画都掌握了，iuv开始 | P81: 滕柳星8:30 3.14 | Q81: 微信 | R81: 3 | S81: 王可 | T81: 0 | U81: 0 | V81: 0 | W81: 没回复
A82: 77 | B82: 3.14 | C82: 加拿大 | D82: 多伦多 | E82: 12 | F82: Gloria | G82: liuruoyi1231 | H82: 马毓彤 | I82: 9 | M82: 家长说孩子有国内4年级的水平 | N82: 中文 | O82: 老师建议三上 | P82: 任宏印8:30 3.14 ChineseonlineS 王秀玉 | Q82: 微信 | R82: 2 | S82: 高翱翔 | T82: 兼 | U82: 1 | V82: 1 | W82: 1 | X82: 118/次 一小时一次 22课时 | Y82: 2596 | Z82: 3.20日缴费
A83: 78 | B83: 3.14 | C83: 美国 | D83: 加州 | E83: 15 | F83: Yue | G83: wangyuebeida | H83: 黄小圆 | I83: 10 | J83: 女 | K83: 有 | L83: 否 | M83: 学过一些，拼音也学过，忘了很多 | N83: 中文 | O83: 零基础，从aoe学起 | P83: 任宏印11：00 3.14 黄老师课堂 周二11:00.周三到周六9 3.20 | Q83: 家长介绍 | R83: 3 | S83: 王可柏恩妈妈推荐 | T83: 兼 | U83: 1 | V83: 1 | W83: 1 | X83: 116/课 65课时 | Y83: +3节课 | Z83: 7540 | AA83: 3.25日缴费
A84: 79 | B84: 3.14 | C84: 加拿大 | D84: 多伦多 | E84: 12 | F84: Ching_Ching | H84: 林墨 | I84: 4 | J84: 男 | K84: 否 | L84: 否 | M84: 零基础 | N84: 启蒙 | Q84: 微信 | R84: 2 | S84: 平金军 | T84: 兼 | U84: 0 | V84: 0 | W84: 不喜欢
A85: 80 | B85: 3.14 | C85: 澳大利亚 | E85: 3 | F85: suki代购 | G85: sukiwang0723 | H85: 虞安妮 | I85: 7.5 | M85: 在当地中文学校学 | N85: 中文 | O85: jqx左右 | P85: 滕柳星 15:30 3.14 | Q85: 家长介绍 | R85: 3 | S85: 王可 王有衡妈妈介绍 | U85: 0 | V85: 0 | W85: 测试时效果不好，不太喜欢，需要重新安排
A86: 81 | B86: 3.15 | C86: 美国 | D86: 西部 | E86: 15 | F86: 心锁歌瑞森无钢圈內衣 | G86: zeng131230 | H86: 李朝晟 | I86: 6 | M86: 零基础双语老师 | N86: 中文 | O86: 中文基础很差，配合一般，需要积极引导，要双语零基础 | P86: 徐晓晓7:00 3.15 二十课堂 7:00 3.17 | Q86: 微信 | R86: 2 | S86: 王晨 | T86: 兼 | U86: 0 | V86: 0 | W86: 觉得价格贵
A87: 82 | B87: 3.15 | C87: 美国 | D87: 旧金山 | E87: 15 | F87: Sam哥 | G87: samxsxiao | H87: 萧语彤 | I87: 6 | M87: 数学零基础 | N87: 数学 | O87: 中国早上9:00上课 | P87: 数学课堂05 9:00 3.15 | Q87: 微信 | R87: 2 | S87: 赵国花陈童麻麻推荐 | T87: 兼 | U87: 0 | V87: 0 | W87: 一周只想上两次，觉得单独安排太贵
A88: 83 | B88: 3.15 | C88: 澳大利亚 | E88: 3 | F88: Jia lin | G88: a35260723 | H88: 小笳 | I88: 7 | M88: 家里讲中文，没学过 识字量不到100 | N88: 中文 | O88: 拼音基本掌握《秋天》开始 | P88: 滕柳星 7:00 3.15 | Q88: 家长介绍 | R88: 3 | S88: 王可 邱新童妈妈介绍 | T88: 0 | U88: 0 | V88: 0 | W88: 觉得澳元汇率太低，价格太贵
A89: 84 | B89: 3.15 | C89: 澳大利亚 | E89: 3 | F89: Jia lin | G89: a35260723 | H89: 小小 | I89: 5 | M89: 家里讲中文，没学过 识字量不到100 | N89: 中文 | O89: 复韵母需要复习 | P89: 滕柳星 7:00 3.15 | Q89: 家长介绍 | R89: 3 | S89: 王可 邱新童妈妈介绍 | T89: 0 | U89: 0 | V89: 0 | W89: 觉得澳元汇率太低，价格太贵
A90: 85 | B90: 3.15 | C90: 加拿大 | D90: 多伦多 | E90: 12 | F90: Sophia | G90: sophiafyd | H90: 胡爱娜 | I90: 5 | M90: 不太会说，能听懂50% | N90: 中文 | O90: 很害羞，不爱说话，很难引导出讲话 不过会听老师讲；建议试一下启蒙 | P90: 徐晓晓7:30 3.15 建议试一下启蒙 | Q90: 微信 | R90: 2 | S90: 王晨 | T90: 兼 | U90: 0 | V90: 0 | W90: 没回复
A91: 86 | B91: 3.15 | C91: 美国 | D91: 西部 | E91: 15 | F91: 豆芽妈 Tammy | G91: tammy_usa | H91: 钟胜杰 | I91: 6 | M91: 会说，零基础 | N91: 中文 | O91: 零基础 | P91: 滕柳星8:30 3.15 ChineseonlineE(10）宋8:00 3.10 天娃01 陆7:00 3.24 | Q91: 微信 | R91: 2 | S91: 王晨 | T91: 兼 | U91: 0 | V91: 0 | W91: 妈妈说最近比较忙，有时间再说
A92: 87 | B92: 3.15 | C92: 加拿大 | D92: 多伦多 | E92: 12 | G92: Katina_xjh | H92: 黄晞琳 | I92: 12 | M92: 混血，听懂一点点对话 有学过一点会说会讲粤语 | N92: 中文 | O92: 听没问题，说会一点点，声母拼读开始学 | P92: 张文红8:00 3.15 | Q92: 家长介绍 | R92: 2 | S92: 赵国花 Joyce妈妈介绍 | T92: 0 | U92: 0 | V92: 0 | W92: 测试效果不好，家长不回复了
A93: 88 | B93: 3.15 | C93: 美国 | D93: 圣迭戈 | E93: 15 | F93: suzhen爱笑的川妹子 | G93: suzhen89 | H93: 朱帅宇 | I93: 5 | M93: 混血，听和说可以，零基础 8587171625 | N93: 中文 | O93: 可以交流，不过反应比较慢，可以试一下零基础的拼音 | P93: 徐晓晓8:30 3.15 ChineseonlineE(10）宋8:00 3.17 | Q93: 微信 | R93: 2 | S93: 王晨 | T93: 兼 | U93: 1 | V93: 1 | W93: 1 | X93: 59/课 | Y93: 1298 | Z93: 3.17日缴费
A94: 89 | B94: 3.15 | C94: 美国 | D94: 盖恩斯维尔 | E94: 13 | F94: Steve | G94: qingyao1981a | H94: 寿湘宁 | I94: 8 | M94: 在中文学校学了一年，没学拼音 | N94: 中文 | O94: 口语流利，零基础，反应很快 | P94: 滕柳星 9:30 3.15 Chineseonline N 9:00 3.17 | Q94: 微信 | R94: 1 | S94: 俞酉兰 | T94: 白 | U94: 0 | V94: 0 | W94: 觉得价格贵
A95: 90 | B95: 3.15 | C95: 美国 | D95: 盖恩斯维尔 | E95: 13 | F95: Steve | G95: qingyao1981a | H95: 寿一凡 | I95: 6 | M95: 在中文学校学了一年，没学拼音 | N95: 中文 | O95: 口语流利，零基础 | P95: 滕柳星 9:30 3.15 Chineseonline N 9:00 3.17 | Q95: 微信 | R95: 1 | S95: 俞酉兰 | T95: 白 | U95: 0 | V95: 0 | W95: 觉得价格贵
A96: 91 | B96: 3.15 | C96: 加拿大 | D96: 多伦多 | E96: 12 | G96: Katina_xjh | H96: 黄卓晞 | I96: 7 | M96: 混血，中文零基础，需要提供双语老师 | N96: 双语中文 | O96: 很积极，很热情；懂一点点，认识几个简单的生字，可以上双语的小学语文，零基础开始 | P96: 徐晓晓9:30 3.15 | Q96: 家长介绍 | R96: 2 | S96: 赵国花 Joyce妈妈介绍 | T96: 0 | U96: 0 | V96: 0 | W96: 测试效果不好，家长不回复了
A97: 92 | B97: 3.15 | C97: 加拿大 | D97: 多伦多 | E97: 12 | G97: Katina_xjh | H97: 黄敬晞 | I97: 6 | M97: 混血，中文零基础，需要提供双语老师 | N97: 双语中文 | O97: 很积极，很热情；一点都不会说，可以上双语的小学语文，零基础开始 | P97: 徐晓晓9:30 3.15 | Q97: 家长介绍 | R97: 2 | S97: 赵国花 Joyce妈妈介绍 | T97: 0 | U97: 0 | V97: 0 | W97: 测试效果不好，家长不回复了
A98: 93 | B98: 3.15 | C98: 美国 | D98: 圣何塞 | E98: 15 | F98: yulin Pan | G98: ypins j | H98: 陈宇暄 | I98: 10 | M98: 四年级，刚开始学四五快读，后来用的王双双中文教材，学完了第五册 | N98: 中文 | O98: 不能脱离拼音，建议二上前中 | P98: 滕柳星10:00 3.15 chineseonlieG 10:20 3.17 | Q98: 家长介绍 | R98: 3 | S98: 王可 柏恩妈妈介绍 | T98: 白 | U98: 0 | V98: 0 | W98: 没回复
A99: 94 | B99: 3.15 | C99: 美国 | D99: 圣何塞 | E99: 15 | F99: yulin Pan | G99: ypins j | H99: 陈宇昕 | I99: 5 | M99: 没学过，稍微认识几个字 | N99: 中文 | O99: 零基础或启蒙课 | P99: 滕柳星 10:30 3.15 | Q99: 家长介绍 | R99: 3 | S99: 王可 柏恩妈妈介绍 | T99: 0 | U99: 0 | V99: 0 | W99: 没回复
A100: 95 | B100: 3.15 | C100: 加拿大 | D100: 魁北克省 | E100: 12 | F100: elina | G100: wxid_2j4mkonk14qp12 | H100: 王欢欢 | I100: 10 | M100: 二年级的课文和生字都没问题，三年级课文阅读没问题，但是阅读理解一般 | N100: 中文 | O100: 建议二下 | P100: 张文红9:30 3.15 | Q100: 家长介绍 | R100: 1 | S100: 张文红 林妙滢介绍 | T100: 0 | U100: 0 | V100: 0 | W100: 没回复
A101: 96 | B101: 3.15 | C101: 加拿大 | D101: 魁北克省 | E101: 12 | F101: elina | G101: wxid_2j4mkonk14qp12 | H101: 王飞飞 | I101: 7 | M101: 单韵母学过，简单的字认识，从拼读开始学 | N101: 中文 | O101: 建议拼读 | P101: 张文红9:30 3.15 | Q101: 家长介绍 | R101: 1 | S101: 张文红 林妙滢介绍 | T101: 0 | U101: 0 | V101: 0 | W101: 没回复
...

Sheet 2020.2
A1: 新生接待试读表 业务员：测+读 老师：试读两次
A2: 序号 | B2: 上课时间 | C2: 国家 | D2: 城市 | E2: 家长微信名 | F2: 家长微信 | G2: 学生姓名 | H2: 年龄 | I2: 程度 | J2: 时差 | K2: 接待需求/情况 | L2: 排课安排 | M2: 来源 | N2: 组别 | O2: 业务员 | P2: 就读分组 | Q2: 试读 | R2: 在读 | S2: 失败原因 | T2: 失败原因分类 | U2: 折扣 | V2: 实收
A3: 1 | B3: 2.3 | C3: 美国 | D3: 宾州 | E3: Ling | F3: jenny0405 | G3: 张梦颖 | H3: 8 | I3: 零基础 听声音像台湾人 | J3: 12 | K3: 表达一般，但是词汇量挺丰富的，比较慢热； | L3: 徐晓晓9:00 2.3 三十八8:40 3.3 | M3: 微信 | N3: 3 | O3: 展望 | P3: 兼 | Q3: 1 | R3: 1 | S3: 1 | T3: 美国周四不上课，一周四天 | U3: 65课时+5课时 | V3: 525 | W3: 3.7日缴费
A4: 2 | B4: 2.3 | C4: 加拿大 | D4: 多伦多 | E4: 薇 | F4: wxid_lwodds1dzmj712 | G4: 管邦岳 | H4: 12 | I4: 国外中文学校上到五年级 | J4: 13 | K4: 中文认字一上的水平，理解力一般，也是一年级的水平，词汇量积累较少，建议从一下或者二上开始学习 | L4: 徐晓晓8:30 2.3 ChineseonlineD 8:40 2.11 | M4: 微信 | N4: 3 | O4: 王可 | P4: 白 | Q4: 1 | R4: 0 | S4: 先不上了，他们想每天都上，但是没时间，家长说等那边活动结束之后再来报，四月底
A5: 3 | B5: 2.3 | C5: 美国 | D5: 史丹顿岛 | E5: Jessica 霞 | F5: linchen10250203 | G5: 林晨曦1 | H5: 7 | I5: 零基础 中文跟可以听懂一点 需要双语老师不太会中文表达，老师要听得懂英语一点 | J5: 13 | K5: 拼音开始中国8:00 | L5: 滕柳星8:00 2.3 | M5: 家长介绍 | N5: 2 | O5: 高翱翔 董鸿杰妈妈介绍 | P5: 0 | Q5: 1 | R5: 0 | S5: 爸爸自己教
A6: 4 | B6: 2.3 | C6: 加拿大 | D6: 温哥华 | E6: Nancy丽艳 | F6: Apmill | G6: James | H6: 10 | I6: 会说和听中文，字认的不多，不会写；拼音学过，不过现在都忘了 | J6: 16 | K6: 拼音开始学。中国下午两点上课。 | L6: 滕柳星8:30 2.3 ChineseonlineL14:00 2.11 | M6: 代理 | N6: 白 | O6: 陈静 | P6: 白 | Q6: 1 | R6: 1 | S6: 1 | U6: 65课时，从2.20日开始算 | V6: 3640 | W6: 2.27日缴费
A7: 5 | B7: 2.3 | C7: 澳大利亚 | E7: 文瑾 | F7: wenjinwan | G7: 黄简 | H7: 6 | I7: 可以用中文简单交流，认识少量中文字 澳洲小朋友 | J7: 3 | K7: 拼音学过但是忘记了，需要复习；词汇量有100左右，可以简单的读写，可以从拼读或者是复韵母开始学习 | L7: 徐晓晓10:30 2.3 ChineseonlineT10 11:20 2.11 | M7: 家长介绍 | N7: 3 | O7: 王可 王希捷妈妈介绍 | P7: 兼 | Q7: 1 | R7: 1 | S7: 1 | U7: 130课时 | V7: 6890 | W7: 2.12日缴费
A8: 6 | B8: 2.3 | C8: 中国 | D8: 福建 | E8: Yan | F8: onlylqy | G8: 王梓萱 | H8: 6 | I8: 人在国内，拼音学的不好，就想要快速有效率的学好拼音 | J8: 0 | K8: 大班学过拼音，但是复韵母不会，拼读有点不熟悉，可以拼读复习部分； | L8: 徐晓晓11:00 2.3 ChineseonlineT10 11:20 2.11 | M8: 家长介绍 | N8: 3 | O8: 王可 王晟睿妈妈介绍 | P8: 兼 | Q8: 1 | R8: 0 | S8: 嫌贵
A9: 7 | B9: 2.3 | C9: 日本 | G9: 杨旭 | H9: 12 | I9: 在日本上过国学课，声调没有完全掌握 识字量很多 | J9: 1 | K9: 认字挺多的，但是词汇量并不丰富，受国学影响，白话的句子表达很弱，可以从二上开始学习 | L9: 徐晓晓15:00 2.3 ChineseonlineC19:10 2.11 | M9: 家长介绍 | N9: 2 | O9: 王晨 陈诗涵妈妈介绍 | P9: 兼 | Q9: 1 | R9: 0 | S9: 觉得内容太浅
A10: 8 | B10: 2.3 | C10: 中国 | E10: 清风 | F10: you15903114350 | G10: 刘灿1 | H10: 20 | I10: 试读美术课 | J10: 0 | L10: 张乙格14:00 2.3 | M10: 微信 | N10: 2 | O10: 高翱翔 | P10: 兼 | Q10: 1 | R10: 0 | S10: 觉得贵
A11: 9 | B11: 2.4 | C11: 韩国 | D11: 首尔 | E11: 지아^^智雅 有所作为🏅🏅🏅 | F11: rry-2008 | G11: 金道研 | H11: 11 | I11: 拼音学过，不是很熟练， | J11: 1 | K11: 复韵母左右，中国19:30上课，一周三四节课 | L11: 滕柳星19:30 2.3 | M11: 家长介绍 | N11: 白 | O11: 李银舒妈妈介绍 | P11: 0 | Q11: 1 | R11: 1 | S11: 用收费老师的微信询问
A12: 10 | B12: 2.4 | C12: 西班牙 | E12: 开心七月 | F12: juliofeliz | G12: 叶雨婷 | H12: 11 | I12: 书写很棒，认识的字多，理解也快，语法不过关 | J12: 7 | K12: 建议上二下 | L12: 魏霞00:00 2.4 第三课堂第一节课2.10 | M12: 微信 | N12: 1 | O12: 何家昌 | P12: 一 | Q12: 1 | R12: 1 | S12: 1 | U12: 欧洲客户 | V12: 640 | W12: 2.15日缴费
A13: 11 | B13: 2.4 | C13: 西班牙 | E13: 演艺15998838888 | F13: h15604005288 | G13: Alina | H13: 13 | I13: 英语程度很好，要上大学英语，周末一对一 | J13: 7 | L13: 魏霞1:30 2.4 | M13: 微信 | N13: 1 | O13: 何家昌 | P13: 0 | Q13: 1 | R13: 0 | S13: 要学雅思，我们的老师教不了
A14: 12 | B14: 2.4 | C14: 美国 | D14: 纽约 | E14: 🍒ʚɞღMęñdÿღʚɞ🍒 | F14: Mendy5581- | G14: 陈立信 | H14: 10 | I14: 会听一点中文，但是表达很弱，没有学过 | J14: 13 | K14: 双语上课更好，但是也能听懂一点中文 | L14: 徐晓晓20:30 2.3 | M14: 电话 | N14: 3 | O14: 樊爱玉 | P14: 0 | Q14: 1 | R14: 0 | S14: 试课的时候网络很卡，体验不好，不想继续试课
A15: 13 | B15: 2.4 | C15: 美国 | D15: 纽约 | E15: 🍒ʚɞღMęñdÿღʚɞ🍒 | F15: Mendy5581- | G15: 陈立仁 | H15: 9 | I15: 没有学习过，但是会说一点中文，需要双语老师 | J15: 13 | L15: 徐晓晓6:30 2.4 | M15: 电话 | N15: 3 | O15: 樊爱玉 | P15: 0 | Q15: 1 | R15: 0 | S15: 试课的时候网络很卡，体验不好，不想继续试课
A16: 14 | B16: 2.4 | C16: 加拿大 | D16: 温哥华 | E16: Cindyzhou | F16: haitangxi | G16: 周千墨 | H16: 6 | I16: 会说中文，认得一些非常基础简单的汉字，不能自主阅读，理解力很好；自学过拼音 | J16: 16 | K16: 周三 16:30-18:30有课；周四 周五15:15-16:00有课 一周可以学三次；可以从拼读复习开始学 | L16: 徐晓晓7:30 2.4 ChineseonlineK 9:20 2.18 | M16: 代理 | N16: 白 | O16: 陈静 | P16: 白 | Q16: 1 | R16: 0 | S16: 网课冲突，孩子纪律散漫，自己教
A17: 15 | B17: 2.4 | C17: 美国 | D17: 东部 | E17: Tom cui | F17: cuizhengfeng | G17: 崔熙儿 | H17: 9 | I17: 学习英文 在美国生活了一段时间，后面回国了，现在又去美国了 英文基础不好，需要学习英文，几乎零基础 | J17: 13 | K17: 中国凌晨4:30之后都可以，希望用自然拼读法学英语，高利闪可以上 | L17: 滕柳星7:00 2.4 | M17: 微信 | N17: 3 | O17: 樊爱玉 | P17: 0 | Q17: 1 | R17: 0 | S17: 国内出去的要隔离；当地学校还没找好时间不确定；孩子最近玩得太野了不想上课
A18: 16 | B18: 2.4 | C18: 加拿大 | D18: 温哥华 | E18: Jessica Chou 家儀 | F18: jess1116 | G18: Ari Chang | H18: 6 | I18: 認字一些些 但是目前是看繁體 但是打算開始教他拼音 | J18: 16 | K18: 拼音开始希望中国早上9:20或10:00开始上课，试课可以8:00，中国周四周六不能上课 | L18: 滕柳星10:00 2.4 天娃课堂03 8:00 2.8 | M18: 代理 | N18: 白 | O18: 陈静 | P18: 兼 | Q18: 1 | R18: 0 | S18: 要和先生讨论一下是不是长期跟我们学习
A19: 17 | B19: 2.4 | C19: 美国 | D19: 东部 | E19: 燕云 | F19: yanyun326 | G19: 张耀中 | H19: 12 | I19: 学过拼音 一上中后段水平 | J19: 13 | L19: 滕柳星8:30 2.4 ChineseonlineL8:40 2.11 | M19: 微信 | N19: 2 | O19: 王晨 | P19: 白 | Q19: 1 | R19: 1 | S19: 1 | U19: 年交，送20课时 | V19: 26000 | W19: 2.11日缴费
A20: 18 | B20: 2.4 | C20: 美国 | D20: 东部 | E20: 燕云 | F20: yanyun326 | G20: 张耀杰 | H20: 8 | I20: 没学过拼音会基本笔画，零基础 | J20: 13 | K20: 拼音开始中国8:00 | L20: 滕柳星8:30 2.4 天娃课堂03 8:00 2.8 ChineseonlineZ 7:00 5.29 | M20: 微信 | N20: 2 | O20: 王晨 | P20: 白 | Q20: 1 | R20: 1 | S20: 1 | U20: 年交，送20课时 | W20: 2.11日缴费
A21: 19 | B21: 2.4 | C21: 加拿大 | E21: Lucy | F21: ygj777888 | G21: 1 | H21: 7 | I21: 声母基本掌握，拼读和复韵母不熟练 | J21: 16 | K21: 拼音前中段学习。希望中国11:20上课 | L21: 滕柳星11:30 2.4 ChineseonlineT10 11:20 2.11 | M21: 微信 | N21: 1 | O21: 何家昌 | P21: 兼 | Q21: 1 | R21: 0 | S21: 交了数学，中文先不上
A22: 20 | B22: 2.5 | C22: 澳大利亚 | D22: 新南威尔士 | E22: A婷 | F22: A11020508 | G22: 张琰希 | H22: 10 | I22: 当地学了三年中文，阅读感觉像一年级一样， | J22: 3 | K22: 一下水平 | L22: 滕柳星9:00 2.5 ChineseonlineE 17:00 2.10 | M22: 家长介绍 | N22: 1 | O22: 张文红 陈梦婷妈妈介绍 | P22: 白 | Q22: 1 | R22: 1 | S22: 1 | U22: 半年交，送5课时，介绍弟弟（合起来年交的价格） | V22: 6500 | W22: 2.14日缴费
A23: 21 | B23: 2.5 | C23: 澳大利亚 | E23: Vincent | F23: wingwei2006 | G23: 胡涵哲 | H23: 7.5 | I23: 中文交流OK，拼音学过一些，拼读会一点 | J23: 3 | K23: iuv左右开始 | L23: 滕柳星 13:30 2.5 ChineseonlineL14:00 2.11 | M23: 家长介绍 | N23: 1 | O23: 张文红 李乐涵妈妈介绍 | P23: 白 | Q23: 1 | R23: 0 | S23: 觉得价格高
A24: 22 | B24: 2.6 | C24: 加拿大 | D24: 多伦多 | E24: 燕平 | F24: wxid_ws6bnsa4el5j22 | G24: 廖弘易 | H24: 8 | I24: 妈妈教完人教版一年级上下 | J24: 13 | K24: 二上前中水平 | L24: 滕柳星8:00 2.6 ChineseonlineD 8:40 2.11 | M24: 家长介绍 | N24: 2 | O24: 高翱翔 卓安娜妈妈介绍 | P24: 白 | Q24: 1 | R24: 0 | S24: 觉得贵，卓安娜只收620
A25: 23 | B25: 2.6 | C25: 巴西 | D25: 圣保罗 | E25: �Isabella | F25: felizdade | G25: 萧楚橦 | H25: 6 | I25: 在中国上过一年的中班 | J25: 11 | K25: 要巴西晚上9:30 中国8:30，会基本笔画，拼音学起 | L25: 滕柳星9:00 2.6 天娃课堂03 8:00 2.8 | M25: 家长介绍 | N25: 白 | O25: 廖铭晔妈妈介绍 | P25: 兼 | Q25: 想要巴西晚上九点半试读数学，2.17开始 | S25: 收费老师微信
A26: 24 | B26: 2.6 | C26: 加拿大 | D26: 多伦多 | E26: 踏实 | F26: annie_1969 | G26: 吴淋欣 | H26: 13 | I26: 曾自己教过 自己也有自学 拼音有点会，最好先学拼音 | J26: 13 | K26: 复习拼音声母gkh左右不分，然后可到一上后段，希望中国时间10:40上课 | L26: 滕柳星9:30 2.6 ChineseonlineK9:20 2.12 | M26: 家长介绍 | N26: 2 | O26: 奚肯恩妈妈推荐 平金军 | P26: 白 | Q26: 1 | R26: 0 | S26: 试读了一次，后来没回复，语音也不接
A27: 25 | B27: 2.6 | C27: 加拿大 | E27: 明天的明 | F27: catherinexuesk | G27: 常启铭 | H27: 7 | I27: 交流基本没问题，拼音会，不识字一点 | J27: 14 | K27: 拼读不是很熟练，但是基本不用再学，可以从《秋天》开始学习 | L27: 徐晓晓9:30 2.6 ChineseonlineR9:20 2.27 | M27: 家长介绍 | N27: 白 | O27: 翟俊宇妈妈介绍 | P27: 白 | Q27: 1 | R27: 0 | S27: 感觉网上效果有限，我们给他找了线下的一对一中文老师了
A28: 26 | B28: 2.6 | C28: 加拿大 | D28: 东部 | E28: yo麻轻奢代购 | F28: shenzihang865625_zx | G28: 周奕杉 | H28: 5.5 | I28: 学过一点中文，交流基本没问题 | J28: 13 | K28: 声母部分学过了，复韵母要开始学习，拼读能力很强，学习能力不错；识字量有100左右 | L28: 徐晓晓9:00 2.6 ChineseonlineB10 2.14 | M28: 微信 | N28: 3 | O28: 王可 | P28: 兼 | Q28: 1 | R28: 0 | S28: 没回复
A29: 27 | B29: 2.6 | C29: 美国 | D29: 尔湾 | E29: Renee | F29: xinyao0724 | G29: 高一笑 | H29: 7 | I29: 女孩在家会说中文，没学过拼音 | J29: 16 | K29: 声母单独认识，拼读一般，可以复韵母开始，希望中国11:00上课 | L29: 滕柳星11:00 2.6 ChineseonlineT10 11:20 2.11 | M29: 微信 | N29: 2 | O29: 平金军 | P29: 兼 | Q29: 1 | R29: 0 | S29: 孩子太小，家长在和孩子沟通
A30: 28 | B30: 2.6 | C30: 美国 | D30: 尔湾 | E30: Renee | F30: xinyao0724 | G30: 高一鸣1 | H30: 5 | I30: 男孩会说中文，没学过拼音 | J30: 16 | K30: 零基础，希望中国11:00上课 | L30: 滕柳星11:00 2.6 | M30: 微信 | N30: 2 | O30: 平金军 | P30: 0 | Q30: 1 | R30: 0 | S30: 孩子太小，家长在和孩子沟通
A31: 29 | B31: 2.9 | C31: 加拿大 | D31: 温哥华 | E31: Phoebe | F31: chacha3003 | G31: 胡沐恩 | H31: 6 | I31: 听说没问题，读写零基础 | J31: 16 | K31: 交流很活跃，有点容易走神，从拼音开始学 | L31: 徐晓晓8:30 2.9 三十八课堂A8:40 2.18 | M31: 代理 | N31: 白 | O31: 陈静 | P31: 兼 | Q31: 1 | R31: 1 | S31: 只能周末上课
A32: 30 | B32: 2.10 | C32: 澳大利亚 | D32: 墨尔本 | E32: 自渡 | F32: que8343 | G32: 王嘉薇 | H32: 5.5 | I32: 中文交流无障碍，没学过 | J32: 3 | K32: 会基本笔画，拼音学起，中国下午三点钟之后 | L32: 滕柳星10:00 2.10 ChineseonlineL14:00 2.11 | M32: 电话 | N32: 1 | O32: 刘敏 | P32: 白 | Q32: 1 | R32: 0 | S32: 孩子太小了，接受太慢，想要报线下面对面
A33: 31 | B33: 2.10 | C33: 美国 | D33: 旧金山 | E33: Ming Jia | F33: jiam03 | G33: 贾宇涵 | H33: 10 | I33: 一直在学中文 | J33: 16 | K33: 二下前中段水平，一三五 我们6~9点 | L33: 滕柳星8:00 2.10 Chineseonline I 9:00 3.18 | M33: 微信 | N33: 3 | O33: 王可 | P33: 白 | Q33: 1 | R33: 1 | S33: 1 | U33: 56/课 | V33: 3640 | W33: 3.26日缴费
A34: 32 | B34: 2.11 | C34: 加拿大 | E34: Lucy | F34: ygj777888 | G34: 刘怡睻 | H34: 7 | I34: 试数学 | J34: 16 | K34: 10以内加减法 | L34: 天娃课堂01 12：00 2.11 | M34: 微信 | N34: 1 | O34: 何家昌 | P34: 兼 | Q34: 1 | R34: 1 | S34: 1 | T34: 数学课 | U34: 59/课 | V34: 1298 | W34: 美国
A35: 33 | B35: 2.12 | C35: 新西兰 | D35: 奥克兰 | E35: Angela | F35: wxid_9780807809412 | G35: 贾雨鑫 | H35: 4 | I35: 零基础，可以基本交流，需要女老师 | J35: 5 | K35: 兴趣为主，上启蒙课程；很健谈，互动性很好 | L35: 徐晓晓14:30 2.12 启蒙二级14:30 2.18 | M35: 微信 | N35: 2 | O35: 高翱翔 | P35: 启 | Q35: 1 | R35: 0 | S35: 两个平台都不喜欢，各种理由
A36: 34 | B36: 2.13 | C36: 芬兰 | E36: Rachel | F36: rachel0518babe | G36: 傅妮娅 | H36: 6 | I36: 零基础，在家说中文，不会写，妈妈自己教了一些拼音 | J36: 6 | K36: 单韵母学过，声母还没开始学；很健谈，很外向 | L36: 徐晓晓20:30 12.12 要芬兰下午三点半 一三五 ChineseonlineT10 21:30 | M36: 微信 | N36: 2 | O36: 高翱翔 | P36: 兼 | Q36: 1 | R36: 0 | S36: 一直在纠结要不要上
A37: 35 | B37: 2.13 | C37: 美国 | D37: 特拉华州 | E37: Tina免税玩购·美欧店 | F37: gracesong2012 | G37: Andy Wu | H37: 10 | I37: 在国内夏令营学过拼音，之后暑假也学过一上 | J37: 13 | K37: 拼音掌握基本没问题，识字量只有100左右，一上需要重新学 | L37: 徐晓晓6:30 2.13 ChineseonlineJ8:00 2.14 四十四课堂6:00 2.18 | M37: 微信 | N37: 3 | O37: 王可 | P37: 二 | Q37: 1 | R37: 1 | S37: 1 | T37: 中文课 | U37: 53/课 130+5 | V37: 6890 | W37: 2.18日缴费
A38: 36 | B38: 2.13 | C38: 加拿大 | D38: 温哥华 | E38: rinoa | F38: rinoa766 | G38: Flynn，李嘉泽 | H38: 8 | I38: 男生8岁，国内一年级水平，听说没问题 | J38: 15 | K38: 识字量100左右；拼音有学一点点，学起来很快，但是要重新学，预计排到T课堂8:40 | L38: 徐晓晓9:00 2.13 ChineseonlineT8:40 2.18 | M38: 代理 | N38: 白 | O38: 陈静 | P38: 兼 | Q38: 1 | R38: 0 | S38: 学生不喜欢，就是不愿意上
A39: 37 | B39: 2.14 | C39: 美国 | D39: 西部 | E39: 庄慧珍 | F39: zhuangyan7057 | G39: 庄大漠 | H39: 7 | I39: 男两个孩子都是零基础，能听懂一些简单的中文 | J39: 16 | K39: 零基础，口语没问题，想一周上三天，时间待确定 | L39: 滕柳星7:30 2.14 兼职一对一 | M39: 家长介绍 | N39: 3 | O39: 王可石易泉妈妈介绍 | P39: 兼 | Q39: 1 | R39: 1 | S39: 1 | U39: 一对一 116/节 | V39: 1076 | W39: 2.28日缴费
A40: 38 | B40: 2.14 | C40: 美国 | D40: 西部 | E40: 庄慧珍 | F40: zhuangyan7057 | G40: 庄波荻 | H40: 5 | I40: 男两个孩子都是零基础，能听懂一些简单的中文 | J40: 16 | K40: 零基础，口语没问题，想一周上三天，时间待确定 | L40: 滕柳星7:30 2.14 | M40: 家长介绍 | N40: 3 | O40: 王可石易泉妈妈介绍 | P40: 0 | Q40: 1 | R40: 0 | S40: 哥哥先学
A41: 39 | B41: 2.14 | C41: 澳大利亚 | D41: 新南威尔士 | E41: 戈楷雯 | F41: sherry584407 | G41: 戈楷雯 | H41: 9.5 | I41: 男生，拼音会一半，需要再巩固，识字十个，会中文沟通 | J41: 3 | K41: 掌握基本笔画拼音单韵母，声母部分学起，希望中国下午3:30上课，每周二踢球上不了 | L41: 滕柳星 15:30 2.14 ChineseonlineC 15:30 2.17 | M41: 家长介绍 | N41: 1 | O41: 李乐轩妈妈介绍 张文红 | P41: 兼 | Q41: 1 | R41: 0 | S41: 马上考OC了，没时间
A42: 40 | B42: 2.15 | C42: 西班牙 | G42: 杨汶娜 | H42: 7 | I42: 零基础，挺有礼貌的 | J42: 7 | L42: 魏霞00:00 2.15 | M42: 微信 | N42: 1 | O42: 何家昌 | P42: 0 | Q42: 1 | R42: 0 | S42: 软件下不了，小程序上课内容不全
A43: 41 | B43: 2.15 | C43: 加拿大 | D43: 多伦多 | F43: yqydk_ | G43: 千訸hé | H43: 6 | I43: 有学过一点拼音 家里中文交流 | J43: 13 | K43: 非常聪明乖巧，在国内上过小学一上半学期，拼音只记得单韵母，声母学起。时间待确定 | L43: 滕柳星7:30 2.15 | M43: 微信 | N43: 2 | O43: 高翱翔 薛晨亮妈妈介绍 | P43: 0 | Q43: 1 | R43: 0 | S43: 最近定不了时间
A44: 42 | B44: 2.15 | C44: 美国 | D44: 纽约 | E44: 幸运昕 | F44: x117653201 | G44: 王銳泽 | H44: 7 | I44: 零基础 中文沟通没问题 | J44: 13 | K44: 学过拼音但是大部分忘了，iuv左右开始，中国8:00-10:00都可以上课 | L44: 滕柳星8:30 2.15 天娃课堂03 8:00 2.18 | M44: 微信 | N44: 1 | O44: 刘敏 | P44: 兼 | Q44: 1 | R44: 0 | S44: 小朋友时间排不开
A45: 43 | B45: 2.15 | C45: 美国 | D45: 纽约 | E45: 幸运昕 | F45: x117653201 | G45: 王紫萱1 | H45: 5 | I45: 零基础 中文沟通没问题 | J45: 13 | K45: 2019.9月开始在双语班学中文，识字量有50左右，拼音还没学过，中国8:00-10:00都可以上课 | L45: 徐晓晓8:30 2.15 三十八A 8:40 2.18 | M45: 微信 | N45: 1 | O45: 刘敏 | P45: 兼 | Q45: 1 | R45: 0 | S45: 小朋友时间排不开
A46: 44 | B46: 2.15 | C46: 澳大利亚 | D46: 悉尼 | E46: nikihe | F46: Mavis | G46: 郭瑜 | H46: 9 | I46: 女孩，快十岁，拼音节本掌握，一上后段或一下前段课文 | J46: 3 | K46: 只能一周上3天，周二，周三，周六，也是澳洲4:30，就是国内13:30。预计排到N课堂钱家瑞一起 | L46: 滕柳星10:00 2.15 ChineseonlineN 13:30 周二三六 2.18 | M46: 家长介绍 | N46: 2 | O46: 平金军余恩哲妈妈介绍 | P46: 白 | Q46: 1 | R46: 0 | S46: 孩子不喜欢视频上课，家长觉得对视力不好
A47: 45 | B47: 2.15 | C47: 澳大利亚 | D47: 悉尼 | E47: nikihe | F47: Mavis | G47: 郭泽 | H47: 7 | I47: 男孩，快八岁，识字量较大，拼音只会单韵母 | J47: 3 | K47: 只能一周上3天，周二，周三，周六，也是澳洲4:30，就是国内13:30 | L47: 滕柳星10:30 2.15 ChineseonlineA 13:30周一二三 2.17 | M47: 家长介绍 | N47: 2 | O47: 平金军余恩哲妈妈介绍 | P47: 白 | Q47: 1 | R47: 0 | S47: 孩子不喜欢视频上课，家长觉得对视力不好
A48: 46 | B48: 2.15 | C48: 美国 | D48: 纽约 | E48: 道 | F48: benben160 | G48: 卢佩淇 | H48: 9 | I48: 零基础不会中文 | J48: 13 | K48: 学习对外汉语，一周只能上两天，12:00 | L48: 滕柳星12:00 2.15 ChineseonlineT10 12:00 2.16 | M48: 电话 | N48: 1 | O48: 刘巧芹 | P48: 兼 | Q48: 1 | R48: 1 | S48: 1 | U48: 56/课 | V48: 519.05 | W48: 2.26日缴费
A49: 47 | B49: 2.16 | C49: 澳大利亚 | D49: 悉尼 | G49: 岳恩瑞 | H49: 10 | I49: 零基础 | J49: 3 | K49: 学过拼音但是忘记了，从拼读开始复习；识字在50个以下 | L49: 徐晓晓17:30 2.15 ChineseonlineG 17:30 2.20 | M49: 微信 | N49: 3 | O49: 展旺 | P49: 白 | Q49: 1 | R49: 0 | S49: 从没上过课，进课堂就退出了
A50: 48 | B50: 2.16 | C50: 澳大利亚 | D50: 悉尼 | G50: 岳恩雅 | H50: 5 | I50: 零基础 | J50: 3 | K50: 零基础开始 | L50: 徐晓晓17:30 2.15 ChineseonlineG 17:30 2.20 | M50: 微信 | N50: 3 | O50: 展旺 | P50: 白 | Q50: 1 | R50: 0 | S50: 从没上过课，进课堂就退出了
A51: 49 | B51: 2.16 | C51: 德国 | E51: 李朝起 | F51: jklli77 | G51: 李晶逸 | H51: 16 | I51: 小时侯上两年中文学校，每周六一次，现在读写基本不会，说会 | J51: 7 | K51: 拼读基本没问题，识字量200左右，可以一下开始学 | L51: 徐晓晓20:30 2.15 第二十六课堂第三节课 | M51: 微信 | N51: 1 | O51: 何家昌 | P51: 夜 | Q51: 1 | R51: 0 | S51: 排了课但是没去
A52: 50 | B52: 2.16 | C52: 德国 | E52: 李朝起 | F52: jklli77 | G52: 李景达 | H52: 13 | I52: 小时侯上两年中文学校，每周六一次，现在读写基本不会，说会 | J52: 7 | K52: 拼读需要复习，声调不准，识字量可以忽略不计 | L52: 徐晓晓20:30 2.15 | M52: 微信 | N52: 1 | O52: 何家昌 | P52: 0 | Q52: 1 | R52: 0 | S52: 弟弟不想学
A53: 51 | B53: 2.16 | C53: 美国 | D53: 佛罗里达州 | E53: Katy | F53: ks2233 | G53: 陈秦梢 Hughchen | H53: 14 | I53: 男，一半英语一半家乡话，零基础 | J53: 13 | K53: 不需要双语，沟通基本没问题，零基础，希望国内9:00上课 | L53: 徐晓晓22:00 2.15 三十八A8:40 2.18 | M53: 家长介绍 | N53: 1 | O53: 林嘉敏妈妈介绍 刘巧芹 | P53: 兼 | Q53: 1 | R53: 1 | S53: 1 | U53: 118/课 一对一 | V53: 2596 | W53: 3.4日缴费
A54: 52 | B54: 2.16 | C54: 美国 | D54: 匹兹堡 | E54: Andy Dong | F54: dong7461252 | G54: 董明轩 | H54: 8 | I54: 8岁零基础，不需要双语，可以听懂大部分口语，拼音学过但是读不饱满准确，略微的有点英文提示即可 | J54: 13 | K54: 希望美国五点上课 | L54: 滕柳星7:00 2.16 第五课堂6:00 2.18 | M54: 电话 | N54: 1 | O54: 刘巧芹 | P54: 夜 | Q54: 1 | R54: 0 | S54: 家长是电脑盲，搞不定软件
A55: 53 | B55: 2.16 | C55: 加拿大 | D55: 素里市 | E55: Hope | F55: wxid_p468gv48m8s122 | G55: 许葆瑄 | H55: 13 | I55: 妈妈自己教的，小学阶段学完了，阅读不够，写作没有结构和思路，用词不准确；初中回国上过一年初一 | J55: 16 | K55: 试课上的六上《故宫博物院》水平相当，想先考hsk4级，再考6级，家长对上课形式比较满意，和孩子再商量一下，可以先学课本内容，后期备考专项训练提高 | L55: 滕柳星8:00 2.16 | M55: 家长介绍 | N55: 白 | O55: 微信 | P55: 0 | Q55: 1 | R55: 0 | S55: 不喜欢网课，一直都是面对面的授课，家长已经删除我们微信
A56: 54 | B56: 2.16 | C56: 美国 | D56: 洛杉矶 | E56: 碧海蓝天 | F56: wxid_jzfleruihmya12 | G56: 杨晨3（晨晨） | H56: 6 | I56: 6岁，学过中文，拼音不会 | J56: 16 | K56: 比较皮，坐不住，家长没回复，孩子调皮有点不想学 | L56: 滕柳星9:30 2.16 ChineseonlineF11:00 4.9 | M56: 微信 | N56: 2 | O56: 平金军 | P56: 白 | Q56: 1 | R56: 0 | S56: 孩子太调皮了，很活跃
A57: 55 | B57: 2.16 | C57: 加拿大 | D57: 多伦多 | E57: 动力 | F57: s8184849 | G57: 林妙莹1Nicole | H57: 11 | I57: 回国的时候一对一学过拼音，大部分会，中文可以交流，汉字不会认和写 | J57: 13 | K57: 2019.4.8日试读过，课程满意但是没时间，拼音拼读基本没有问题，有时候第二声和第四声会混淆，一年级上册课文拼音拼读基本没问题，但是没有拼音基本不太会读，认识的字不是很多，可以从一上课文学 | L57: 张文红9:00 2.16 ChineseonlineR 9:20 2.18 | M57: 电话 | N57: 1 | O57: 张文红 | P57: 白 | Q57: 1 | R57: 1 | S57: 1 | U57: 65课时；56/课 | V57: 3640 | W57: 2.27日缴费
A58: 56 | B58: 2.16 | C58: 加拿大 | D58: 多伦多 | E58: 动力 | F58: s8184849 | G58: 林金城Richard | H58: 13 | I58: 回国的时候一对一学过拼音，大部分会，中文可以交流，汉字不会认和写 | J58: 13 | K58: 2019.4.8日试读过，课程满意但是没时间，拼音拼读基本没有问题，有时候第二声和第四声会混淆，一年级上册课文拼音拼读基本没问题，但是没有拼音基本不太会读，认识的字不是很多，可以从一上课文学 | L58: 张文红9:00 2.16 ChineseonlineR 9:20 2.18 | M58: 电话 | N58: 1 | O58: 张文红 | P58: 白 | Q58: 1 | R58: 0 | S58: 等妹妹学好了再报名
A59: 57 | B59: 2.16 | C59: 美国 | D59: 纽约 | E59: jenny | F59: jenny960516733 | G59: 家振 | H59: 12 | I59: 在家说中文，没有在学校学过，不会写 | J59: 13 | K59: 会说中文，识字量50左右，没系统学过 | L59: 滕柳星9:30 2.16 三十八A8:40 2.20 十八B7:40 2.26 | M59: 家长介绍 | N59: 白 | O59: 微信陈浩锟妈妈推荐 | P59: 白 | Q59: 1 | R59: 1 | S59: 1 | U59: 59/课 | V59: 1300 | W59: 2.26日缴费
A60: 58 | B60: 2.16 | C60: 加拿大 | D60: 温哥华 | E60: Susan | F60: wxid_f7el4ba7uzry22 | G60: 成博帆 | H60: 12 | I60: 拼音基本问题不大，识字量200左右，但是不看拼音读课文不行 | J60: 15 | K60: 可以从一上后半段学起 | L60: 徐晓晓9:30 2.16 | M60: 代理 | N60: 白 | O60: 陈静 | P60: 0 | Q60: 1 | R60: 0 | S60: 没有回复了
A61: 59 | B61: 2.16 | C61: 澳大利亚 | D61: 悉尼 | E61: Ariana | F61: arianawu | G61: 王有衡 | H61: 6 | I61: 学过拼音，正在认字，中文会说，有日常抄写，没有默写，识字很少 | J61: 3 | K61: 拼读可以，认字50左右，很活泼好动，可以从一上课文刚开始学，要中国时间下午四五点 | L61: 徐晓晓11:00 2.16 ChineseonlineA 15:30 2.19 | M61: 家长介绍 | N61: 3 | O61: 王可 王希捷妈妈介绍 | P61: 白 | Q61: 1 | R61: 1 | S61: 1 | U61: 65课时 | V61: 澳币800 | W61: 2.29日缴费
A62: 60 | B62: 2.18 | C62: 加拿大 | D62: 温哥华 | E62: LuLu | F62: lulurocks | G62: Luke xu徐立赫 | H62: 5 | I62: 五岁 没有学过拼音，刚出国，口语交流没问题 | J62: 16 | K62: 不想学拼音，怕和英语混起来 | L62: ChineseonlineN8:40 2.18 ChineseonlineO10:20 4.22 | M62: 家长介绍 | N62: 白 | O62: 微信 Lawrence妈妈介绍 | P62: 白 | Q62: 1 | R62: 0 | S62: 身体不好，等好一点安排
A63: 61 | B63: 2.18 | C63: 美国 | D63: 史丹顿岛 | E63: 一米阳光 | F63: huangbiyan366808 | G63: 陈珊珊 | H63: 11 | I63: 零基础，在家用中文交流，口语没问题 | J63: 13 | L63: 滕柳星9:30 2.18 三十八课堂 8:40 2.19 | M63: 家长介绍 | N63: 2 | O63: 陈绮琳妈妈介绍 高翱翔 | P63: 兼 | Q63: 1 | R63: 1 | S63: 1 | U63: 1100/月 | V63: 3300 | W63: 2.20日缴费
A64: 62 | B64: 2.18 | C64: 美国 | D64: 洛杉矶 | E64: Liuying | F64: lylinda1122 | G64: 樊启航 | H64: 6 | I64: 会说中文，一上学完了 | J64: 13 | L64: ChineseonlineA 10:00 | M64: 家长介绍 | N64: 白 | O64: 唐晶吴弥一妈妈推荐 | P64: 白 | Q64: 1 | R64: 1 | S64: 1 | U64: 59/课 | V64: 1298 | W64: 2.17日缴费
A65: 63 | B65: 2.18 | C65: 西班牙 | E65: 厉伟芬 | F65: weifenli8 | G65: 夏慧慧 | H65: 17 | I65: 拼音都会的 但是很多不标准 一上课文没有拼音就不会读 一上的生字只认识3个（中、在、花） 还有弟弟妹妹 性格挺好的 听写听不来 字还行 | J65: 7 | L65: 三十一课堂A第六节课郭老师 2.18 | M65: 微信 | N65: 1 | O65: 何家昌 | P65: 三 | Q65: 1 | R65: 1 | S65: 1 | T65: 30课时 | V65: €119
A66: 64 | B66: 2.18 | C66: 西班牙 | D66: 奥伦塞 | E66: 杨晓微 | F66: yangxiaowei258 | G66: 智博 | H66: 6 | I66: 很腼腆不爱讲话 很难沟通 能沟通了就还好 发音很准 | J66: 7 | L66: 第二十七课堂A楼老师第七节课 2.18 | M66: 微信 | N66: 1 | O66: 何家昌 | P66: 四 | Q66: 1 | R66: 0 | S66: 大一些再来
A67: 65 | B67: 2.18 | C67: 西班牙 | E67: 燕 | F67: linchunyan625066588 | G67: 陈旻泽 | H67: 7 | I67: 口语不错，认识很多东西，书写超级棒，就是笔画错误 | J67: 7 | L67: 第三十八课堂A黄老师 第七节课 2.18 | M67: 微信 | N67: 1 | O67: 何家昌 | P67: 二 | Q67: 1 | R67: 1 | S67: 1 | U67: 660/月 | V67: 660 | W67: 2.25日缴费
B68: 12.20 | C68: 美国 | D68: 纽约 | E68: 沫沫 | F68: joylin123456789a | G68: 卢卡斯 | H68: 9 | I68: 9岁，会说和听 | J68: 13 | K68: 学过一点拼音，但是只会认不会拼读，拼读要重新学；生字认识基础的； 词汇量丰富 | L68: 徐晓晓8:00 12.20 ChineseonlineT8:10 12.21 ChineseonlineG 8:00 2.19 | M68: 家长介绍 | N68: 1 | O68: 刘巧芹 | P68: 白 | Q68: 1 | R68: 1 | S68: 1 | T68: 12月试读，2月缴费 | U68: 59/课 | V68: 1298 | W68: 2.18日缴费
A69: 66 | B69: 2.19 | C69: 美国 | D69: 西部 | E69: Yan Gao | F69: heathDIY | G69: 伊诺 | H69: 11 | I69: 能说一些，但是读写不行；美国上五年级 | J69: 16 | K69: 二上 中前段程度 | L69: 范乃琪8:00 2.19 美国下周四，周五上午8:00-8:30 第二十五课堂00:00 2.27 | M69: 家长介绍 | N69: 白 | O69: 毋诗林妈妈介绍 | P69: 二 | Q69: 1 | R69: 1 | S69: 1 | T69: 56/课 | U69: 65课时 | V69: 3640 | W69: 3.26日缴费
A70: 67 | B70: 2.19 | C70: 美国 | D70: 西部 | E70: Yan Gao | F70: heathDIY | G70: 熙悦 | H70: 8 | I70: 学过拼音，但是识字量不多，不能自主阅读；美国上二年级 | J70: 16 | K70: 一上后段或者一下刚开始 | L70: 滕柳星7:20 2.19 美国下周周三、周四晚上20:40-21:10 ChineseonlineE12:40 2.27 | M70: 家长介绍 | N70: 白 | O70: 毋诗林妈妈介绍 | P70: 白 | Q70: 1 | R70: 1 | S70: 1 | T70: 56/课 | W70: 3.26日缴费
A71: 68 | B71: 2.19 | C71: 美国 | D71: 西部 | E71: Janice纯手工阿胶糕 | F71: qin951412 | G71: 陈淑明 | H71: 12 | I71: 没学过在家说中文 | J71: 16 | K71: 零基础 | L71: 滕柳星 11:00 2.19 ChineseonlineJ 9:40 | M71: 家长介绍 | N71: 2 | O71: 王晨陈诗涵妈妈推荐 | P71: 白 | Q71: 1 | R71: 1 | S71: 1 | U71: 130课时 | V71: ¥7793.46+$600 | W71: 2.29日缴费
A72: 69 | B72: 2.19 | C72: 美国 | D72: 西部 | E72: Janice纯手工阿胶糕 | F72: qin951412 | G72: 陈丽明 | H72: 5 | I72: 没学过在家说中文 | J72: 16 | K72: 零基础 | L72: 滕柳星 11:00 2.19 ChineseonlineJ 9:40 | M72: 家长介绍 | N72: 2 | O72: 王晨陈诗涵妈妈推荐 | P72: 白 | Q72: 1 | R72: 1 | S72: 1 | U72: 130课时 | W72: 2.29日缴费
A73: 70 | B73: 2.19 | C73: 德国 | E73: 春天 | F73: hcl004915779551321 | G73: 何欣茹 | H73: 15 | I73: 德语英文有点像 会一点拼音 很多东西认识但是不能用中文表达 音调第二声第三声有点不是很分得清 很配合 很文静的女孩子 拼读会一点，但是意思不懂 | J73: 6 | L73: 第六课堂A第四节课 2.19 | M73: 微信 | N73: 1 | O73: 何家昌 | P73: 四 | Q73: 1 | R73: 1 | S73: 1 | U73: 22课时 660/月 | V73: 660 | W73: 3.2日缴费
A74: 71 | B74: 2.2 | C74: 奥地利 | E74: 丫头 | F74: mei-0125 | G74: 李索菲 | H74: 8 | I74: 零基础，会说不会写 | J74: 7 | K74: 零基础 | L74: 魏霞2.19 第五十六课堂第八节课2.20 | M74: 微信 | N74: 白 | O74: 微信 | P74: 四 | Q74: 1 | R74: 1 | S74: 1 | U74: 季交，650/月 | V74: 1950 | W74: 2.25日缴费
A75: 72 | B75: 2.25 | C75: 奥地利 | E75: 丫头 | F75: mei-0125 | G75: 李西蒙 | I75: 零基础，会说不会写 | J75: 7 | K75: 零基础 | L75: 魏霞2.19 第五十六课堂第八节课2.20 | M75: 微信 | N75: 白 | O75: 微信 | P75: 四 | Q75: 1 | R75: 1 | S75: 1 | U75: 季交，650/月 | V75: 1950 | W75: 2.25日缴费
A76: 73 | B76: 2.2 | C76: 中国 | E76: 刘双锋（趁年轻） | F76: daozu--feng | G76: 刘双锋 | H76: 36 | I76: 学英语口语 | J76: 0 | L76: 英语课堂20:00 2.20 | M76: 微信 | N76: 白 | O76: 微信 | P76: 0 | Q76: 1 | R76: 0 | S76: 价格太贵了
A77: 74 | B77: 2.21 | C77: 加拿大 | D77: 多伦多 | E77: Selina&月 | F77: selina599878 | G77: 陈俊文 | H77: 8 | I77: 在家中文交流 之前在当地学习过一点点中文，只学了几个汉字，没有学习过拼音。 | J77: 13 | K77: 零基础 | L77: 滕柳星 8:20 2.21 三十八课堂 刘朵朵 8:40 2.22 ChineseonlineT10 10:00 3.3 | M77: 家长介绍 | N77: 2 | O77: 高翱翔sam妈妈介绍 | P77: 兼 | Q77: 1 | R77: 0 | S77: 许老师不上课了他就不报名了
A78: 75 | B78: 2.21 | C78: 美国 | D78: 纽约 | E78: MaY。海外购 | F78: candy60701332 | G78: 林卡卡 | H78: 7 | I78: 没有学习过中文，拼音什么的 ，零基础。在家中文交流；很乖，学习能力挺强 | J78: 13 | K78: 零基础 | L78: 徐晓晓8:30 2.21 三十八课堂 刘朵朵 8:40 2.22 | M78: 家长介绍 | N78: 2 | O78: 高翱翔陈珊珊妈妈介绍 | P78: 兼 | Q78: 1 | R78: 0 | S78: 孩子不愿意学
A79: 76 | B79: 2.21 | C79: 美国 | D79: 中部 | E79: Linna Shang | F79: Linna201010 | G79: 李逍遥 | H79: 8 | I79: 在家里面的话都是中文。但是他们在学校还有其他的环境，都是英文。两个人都可以说中文，男生呢，他已经学过拼音，会拼音或声调。然后看着平时可以念出那个字来的。只是识字方面比较差 | J79: 14 | K79: 《秋天》左右开始零基础 | L79: 滕柳星10:00 2.21 第五课堂6:00 3.11 | M79: 微信 | N79: 3 | O79: 王可 | P79: 一 | Q79: 1 | R79: 1 | S79: 1 | U79: 65课时 | V79: 948 | W79: 3.4日缴费
A80: 77 | B80: 2.21 | C80: 美国 | D80: 中部 | E80: Linna Shang | F80: Linna201010 | G80: 李灵儿 | H80: 5 | I80: 在家里面的话都是中文。但是他们在学校还有其他的环境，都是英文。两个人都可以说中文。女孩子呢，也会使一些字，但是没有学过拼音。 | J80: 14 | K80: 零基础 | L80: 滕柳星9:30 2.21 天娃课堂02 9:20 3.11 | M80: 微信 | N80: 3 | O80: 王可 | P80: 兼 | Q80: 1 | R80: 1 | S80: 1 | U80: 65课时 | W80: 3.4日缴费
A81: 78 | B81: 2.21 | C81: 澳大利亚 | E81: coco | F81: cocochen0915 | G81: 陈祉诺 | H81: 6 | I81: 6岁 会说，但是没学过 | J81: 3 | K81: 零基础 9月份试读过，现在正式上课 | L81: ChineseonlineG 16:30 2.21 | M81: 家长介绍 | N81: 2 | O81: 平金军 余恩哲妈妈介绍 | P81: 白 | Q81: 1 | R81: 1 | S81: 1 | U81: 65课时，送5课时 | V81: 3640 | W81: 2.27日缴费
A82: 79 | B82: 2.22 | C82: 美国 | D82: 纽约 | E82: stay with me | F82: RenStaywithMe | G82: 李睿鑫 | H82: 6 | I82: 男学过拼音，但是忘得差不多了，可以bpmf开始 | J82: 13 | L82: 滕柳星9:00 2.22 | M82: 微信 | N82: 1 | O82: 刘敏 | P82: 0 | Q82: 1 | R82: 0 | S82: 学生时间排满了
A83: 80 | B83: 2.25 | C83: 加拿大 | D83: 温哥华 | E83: jing | F83: wxid_nycuofw0husx11 | G83: Vivian2嘉萱 | H83: 8 | I83: 中文学校学到二年级，认识几十个字，拼音学过 简单点的能拼 | J83: 16 | K83: 一下水平,有点难了 | L83: 滕柳星10::00 2.25 ChineseonlineN10:40 2.26 | M83: 代理 | N83: 白 | O83: 陈静 | P83: 白 | Q83: 1 | R83: 0 | S83: 怎么说呢 感觉这种不太适合我们家孩子 还有相比这边的中文学校课时费有点小贵 虽说进度会快很多 但是这边的孩子接触中文机会少 只要一停下来就全都忘了 不过老师都是很棒的 很有耐心 也能照顾到每个小朋友
A84: 81 | B84: 2.25 | C84: 加拿大 | D84: 温哥华 | E84: coco | F84: bing5829 | G84: Rico1 | H84: 5.5 | I84: 中文会写五十个字，拼音没接触过，可以从拼音学起 | J84: 16 | K84: 零基础拼音 | L84: 滕柳星 12:30 2.25 | M84: 代理 | N84: 白 | O84: 陈静 | P84: 0 | Q84: 1 | R84: 0 | S84: 先不上了，以后再联系我们
A85: 82 | B85: 2.25 | C85: 加拿大 | D85: 温哥华 | E85: Alice chen | F85: bemay001 | G85: 黄奕鸣 | H85: 4 | I85: 只会一点日常交流，有些需要英语来解释；完全没有学过中文 | J85: 16 | K85: 需要双语老师 | L85: 陈琪12:30 2.25 启蒙课堂2 11:30卢老师 2.26 启蒙课堂1 10:30 陈耀3.11 十八课堂B 10:30 3.17 | M85: 代理 | N85: 白 | O85: 陈静 | P85: 兼 | Q85: 1 | R85: 1 | S85: 要试一下滕老师
A86: 83 | B86: 2.26 | C86: 加拿大 | D86: 温哥华 | E86: 柒小璐_Chelsea | F86: lukuci | G86: 李孟诚 | H86: 5.5 | I86: 中国待了五年半，中文完全没问题，目前只认识几十个字；刚到加拿大四个半月，刚开始学英语，不学拼音 | J86: 16 | L86: 中文课堂3隋博 11:00 2.26 | M86: 代理 | N86: 白 | O86: 陈静 | P86: 兼 | Q86: 1 | R86: 0 | S86: 觉得课程对孩子没什么用
A87: 84 | B87: 2.26 | C87: 美国 | D87: 西部 | E87: wxid_iibyq0zt8ajx12 | F87: jie | G87: Brian01 | H87: 10 | I87: 零基础在家说粤语，需要双语老师 | J87: 16 | K87: 排双语课 | L87: 徐晓晓11:30 2.26 | M87: 家长介绍 | N87: 2 | O87: 王晨 淑明丽明妈妈介绍 | P87: 0 | Q87: 1 | R87: 0 | S87: 孩子兴趣不大
A88: 85 | B88: 2.26 | C88: 加拿大 | D88: 温哥华 | E88: Amy | F88: Amyzou1865 | G88: 邓钧诚 | H88: 7 | I88: 中文几乎零基础，中文交流有点问题，最好有双语老师 | J88: 16 | K88: 零基础，双语课 | L88: 范乃琪11:30 2.26 第二十课堂A高老师10:20 3.11 | M88: 代理 | N88: 白 | O88: 陈静 | P88: 兼 | Q88: 1 | R88: 1 | S88: 1 | U88: 56/课 四人团-400 | V88: 457.08 | W88: 3.24日缴费
A89: 86 | B89: 2.27 | C89: 美国 | D89: 洛杉矶 | E89: Ruby | F89: ruby-he1215 | G89: 王懿宸 | H89: 12 | I89: 幼儿园学过，基本忘得差不多了 | J89: 16 | K89: 每天洛杉矶时间下午6:30-9:00 一上中，中国12点 | L89: 滕柳星11:00 2.27 ChineseonlineN 12:00 2.28 | M89: 家长介绍 | N89: 1 | O89: 俞酉兰 王涵雨妈妈介绍 | P89: 白 | Q89: 1 | R89: 1 | S89: 1 | U89: 56/课 | V89: 3640 | W89: 3.3日缴费
A90: 87 | B90: 2.27 | C90: 加拿大 | D90: 温哥华 | E90: jacquelinecheang | F90: jackiechristie | G90: 潘匡沁 | H90: 7 | I90: 拼音学过一点，阅读也可以一点点，但中文比较差，主要说英文 | J90: 16 | K90: 声母复习或复韵母开始 | L90: 滕柳星11:30 2.27 ChineseonlineB1011:20 3.3 3.5 | M90: 代理 | N90: 白 | O90: 陈静 | P90: 兼 | Q90: 1 | R90: 1 | S90: 1 | T90: 加拿大一三五 | U90: 59/课 22课时 | V90: 186.71 | W90: 3.7日缴费
A91: 88 | B91: 2.27 | C91: 美国 | E91: Amy yuansfer | F91: amy1980liu | G91: 王涵雨 | H91: 14 | I91: 没有学过，字认识但不会写，不会拼音 | J91: 16 | K91: 拼音开始，学完笔顺后可以直接跳级到三年级，识字量至少三年级程度，。涵雨二四六的中午12点时间 要一次一个小时的课 | L91: 范乃琪12:00 2.27 天娃课堂03 二四六12:00 2.29 | M91: 微信 | N91: 1 | O91: 俞酉兰 | P91: 兼 | Q91: 1 | R91: 1 | S91: 1 | U91: 22课时，一对一 100/课 | V91: 2200 | W91: 3.10日缴费
A92: 89 | B92: 2.27 | C92: 美国 | D92: 圣何塞 | E92: Irene | F92: irenechihuili | G92: 邢宇承 | H92: 12 | I92: 中文大概二年级程度 | J92: 16 | K92: 网上学习过，拼音有学过，不过有点忘记了，复习一下更好；识字量200左右；可以一上课文部分，中前段都可以 | L92: 徐晓晓13:00 2.27 ChineseonlineN 13:30 2.28 | M92: 家长介绍 | N92: 2 | O92: 赵国花 Emma介绍 | P92: 白 | Q92: 1 | R92: 1 | S92: 1 | U92: 59/课 | V92: 185.64 | W92: 3.1日缴费
A93: 90 | B93: 2.27 | C93: 美国 | D93: 加利福尼亚 旧金山 | E93: Monna | F93: monnamengconnor | G93: 孟凯伦 | H93: 11 | I93: 六年级，中文水平五年级，能写作文，能读文章，中文五年级的水平，在当地有一直学中文的 | J93: 16 | L93: 滕柳星12:00 2.27 | M93: 电话 | N93: 1 | O93: 张文红 | P93: 0 | Q93: 1 | R93: 0 | S93: 孩子不喜欢
A94: 91 | B94: 2.27 | C94: 韩国 | E94: 鱼 | F94: victorhou1223 | G94: David3 | H94: 6 | I94: 韩国的和锦辰是一家的，不会说中文 | J94: 1 | K94: 认识不少字，拼音也会，但是坐不住 | L94: 滕柳星14:00 2.27 | M94: 微信 | N94: 1 | O94: 俞酉兰 | P94: 0 | Q94: 1 | R94: 0 | S94: 孩子坐不住
A95: 92 | B95: 2.27 | C95: 马来西亚 | E95: 鱼 | F95: victorhou1223 | G95: 锦辰 | H95: 6 | I95: 在家教过，会说中文零基础 | J95: 0 | L95: 滕柳星14:00 2.27 | M95: 微信 | N95: 1 | O95: 俞酉兰 | P95: 0 | Q95: 1 | R95: 0 | S95: 孩子太小坐不住
A96: 93 | B96: 2.27 | C96: 澳大利亚 | D96: 悉尼 | E96: A.艺蓊旎 | F96: yvonne982232 | G96: 郭爱林1 | H96: 6.5 | I96: 没学过，会说，交流没问题 | J96: 3 | L96: 滕柳星15:30 2.27 chineseonlineJ16:00 3.6 | M96: 微信 | N96: 3 | O96: 王可 | P96: 白 | Q96: 1 | R96: 1 | S96: 1 | U96: 65课，送5课时，3.10日开始 | V96: 3640 | W96: 3.12日缴费
A97: 94 | B97: 2.28 | C97: 美国 | E97: Sarah vermette | F97: luoshaowen080503 | G97: Sarah2 | H97: 成人 | J97: 16 | L97: 美术课堂 12:00 2.28 | M97: 家长介绍 | N97: 1 | O97: 张文红林妙莹妈妈推荐 | P97: 兼 | Q97: 1 | R97: 0 | S97: 等四月份再报
A98: 95 | B98: 2.28 | C98: 美国 | D98: 圣何塞 | E98: Karen | F98: karenxinguan | G98: 黄以诺 | H98: 10 | I98: 10岁 学到马丽萍四年级 | J98: 15 | K98: 8月份试过，当时设备有问题 | L98: 滕柳星7:00 2.28 二十三课堂7:30 3.3 | M98: 家长介绍 | N98: 3 | O98: 王可 | P98: 二 | Q98: 1 | R98: 1 | S98: 1 | U98: 65课时 3.5日开始计费 | V98: 3640 | W98: 3.5日缴费
A99: 96 | B99: 2.28 | C99: 巴西 | D99: 圣保罗 | E99: 东晓 | F99: DONGXIAO0902 | G99: 陈凯龙 | H99: 9 | J99: 11 | K99: 一上中后 | L99: 滕柳星8:00 2.28 ChineseonlineJ 7:00 3.11 | M99: 家长介绍 | N99: 白 | O99: 陈嘉玫妈妈推荐 | P99: 白 | Q99: 1 | R99: 1 | S99: 500/月
A100: 97 | B100: 2.28 | C100: 美国 | D100: 西部 | E100: GXF | F100: duo_lafeng | G100: 李加诺(Noah) | H100: 5 | I100: 没学过，听说可以，写不行 | J100: 16 | K100: 零基础 | L100: 滕柳星10:30 2.28 | M100: 微信 | N100: 3 | O100: 王可 | P100: 0 | Q100: 1 | R100: 0 | S100: 孩子不喜欢
...

Sheet 2020.1
A1: 新生接待试读表
A2: 序号 | B2: 上课时间 | C2: 国家 | D2: 城市 | E2: 家长微信名 | F2: 家长微信 | G2: 学生姓名 | H2: 年龄 | I2: 程度 | J2: 时差 | K2: 接待需求/情况 | L2: 排课安排 | M2: 来源 | N2: 组别 | O2: 业务员 | P2: 就读分组 | Q2: 试读 | R2: 在读 | S2: 失败原因 | T2: 失败原因分类 | U2: 折扣 | V2: 实收
A3: 1 | B3: 1.01 | C3: 西班牙 | D3: 萨拉戈萨 | E3: 晓妙 | F3: sun261589857 | G3: 季昕怡 | H3: 9 | I3: 9岁，学到复韵母 | J3: 7 | L3: 范乃琪21:45 12.31 第四十三课堂第八节课1.01 | M3: 微信 | N3: 1 | O3: 俞酉兰 | P3: 三 | Q3: 1 | R3: 1 | S3: 1 | U3: 半年先付448欧，一个月后再付半年 | V3: 美元480 | W3: 1.02日缴费 | X3: 7000/年
A4: 2 | B4: 1.01 | C4: 澳大利亚 | D4: 悉尼 | E4: Karman | F4: Karman-Ho | G4: 王晟睿 | H4: 8 | I4: 8岁4个月，在国内学过一年级，二年级跟龙凤汉语学了六十几节课； | J4: 3 | K4: 识字量有二年级，但是写字只有一上的水平；可以从二年级开始学，从二下第一课开始学 | L4: 徐晓晓8:20 1.1 ChineseonlineI10任宏印8:30 1.3 | M4: 家长介绍 | N4: 3 | O4: 王可希捷妈妈推荐 | P4: 白 | Q4: 1 | R4: 1 | S4: 1 | T4: 一对一 | U4: 65课，116元/课 | V4: 7540 | W4: 1.1日缴费
A5: 3 | B5: 1.01 | C5: 美国 | E5: jessica | F5: wxid3175811758611 | G5: 李雨桐 | H5: 7 | I5: 7岁自己读过一年级的课本 | J5: 13 | L5: 滕柳星 12:30 1.1 | M5: 家长介绍 | N5: 3 | O5: 樊爱玉 周密妈妈介绍 | P5: 0 | Q5: 1 | R5: 0 | S5: 学生时间还没协调好，学生兴致也不高
A6: 4 | B6: 1.01 | C6: 美国 | D6: 西部 | E6: Lei | F6: seesealei | G6: 方立鹏 | I6: 方恬韵弟弟。19年1月份试读过，时间不合适，再次试读 | J6: 16 | K6: 很喜欢温老师。1月底来 | L6: ChineseonlineH 12:00 1.1 | M6: 学生兄妹 | N6: 白 | O6: 微信 | P6: 白 | Q6: 1 | R6: 1 | S6: 1月底再来
A7: 5 | B7: 1.02 | C7: 法国 | E7: 军 | F7: wxid_6pxh7kyiaga311 | G7: 吴米娜 | H7: 11 | I7: 11岁，识字量达到一下程度，但是家长希望让孩子复习一下拼音 | J7: 7 | L7: 范乃琪5:00 12.31 第四课堂第九节课1.02 | M7: 家长介绍 | N7: 夜 | O7: 微信 | P7: 一 | Q7: 1 | R7: 1 | S7: 1 | U7: 季交 620/月 | V7: 1860 | W7: 1.10日缴费
A8: 6 | B8: 1.02 | C8: 美国 | D8: 新泽西 | E8: 巧克力 | F8: rocio-v | G8: 邓童（小蜜蜂） | H8: 7 | I8: 7岁女孩，一直在中文学校有学习 | J8: 13 | K8: 拼读复韵母不是很熟，但是可以读课文；一年级的可以80%脱离拼音，识字量500左右；可以一下开始学习 | L8: 徐晓晓8:20 1.2 ChineseonlineA8:00 1.3 | M8: 微信 | N8: 3 | O8: 王可 | P8: 白 | Q8: 1 | R8: 0 | S8: 说是找到更适合的学习方式了
A9: 7 | B9: 1.02 | C9: 美国 | D9: 纽约 | E9: Rose elsa | F9: f634124629 | G9: 郑珍蕊 | H9: 9 | I9: 快9岁了，有学中文，每周六早上9:00-12；00有上了一年了 | J9: 13 | K9: 建议从复韵母开始复习拼音 | L9: 杨启 9:00 12.31 ChineseonlineQ 9:20 1.2 | M9: 微信 | N9: 3 | O9: 樊爱玉 | P9: 白 | Q9: 1 | R9: 0 | S9: 暂时先不考虑，线下还有课，五月份才结束
A10: 8 | B10: 1.02 | C10: 美国 | D10: 西部 | E10: 陈文芳 | F10: CWF712 | G10: 陈奕迅 | H10: 7 | I10: 7岁，零基础，听说流利，很聪明 | J10: 16 | L10: 滕柳星7:00 1.2 ChineseonlineK 9:20 1.3 | M10: 学生兄妹 | N10: 2 | O10: 王晨 陈诗涵弟弟 | P10: 白 | Q10: 1 | R10: 1 | S10: 1 | U10: 130课时 一周五节 | V10: 932.5 | W10: 1.5日缴费
A11: 9 | B11: 1.02 | C11: 美国 | D11: 休斯顿 | E11: Xiaoyan | F11: xiaoyanz96 | G11: 董忆辰 | H11: 7 | I11: 今年七岁了我在家自己教过一阵，后来一直在中文学校学习中文，有一定基础，中文学校学了五册了，国内一下中后水平 | J11: 14 | K11: 一周五天时间排不太出来，另外约 | L11: 滕柳星8:00 1.2 | M11: 微信 | N11: 3 | O11: 王可 | P11: 0 | Q11: 1 | R11: 0 | S11: 孩子不喜欢，妈妈还在做思想工作
A12: 10 | B12: 1.03 | C12: 美国 | D12: 东部 | E12: Xuanxue | F12: xuanxue_ao | G12: 敖雪 | H12: 8 | I12: 8岁，想从三上开始学 | J12: 13 | L12: 魏霞 23:00 12.31 四十四课堂 22:40 1.1 1.2 ChineseonlineI 10:00 1.3 | M12: 微信 | N12: 2 | O12: 王晨 | P12: 白 | Q12: 1 | R12: 1 | S12: 1 | U12: 130课时，送10课时 二四五上课 | V12: 6890 | W12: 1.7日缴费
A13: 11 | B13: 1.03 | C13: 美国 | D13: 东部 | E13: 常俊霞 | F13: Janeklein | G13: 常丹泥 | H13: 7 | I13: 7岁 不会说中文，在中文学校学习了两年，学了对外汉语，中国时间八点半左右， | J13: 13 | K13: 测试不算上课 中国周二 周四8:30 联系可以上对外汉语的老师 | L13: 滕柳星8:00 1.3 二十课堂高利闪8:30 1.7 | M13: 家长介绍 | N13: 2 | O13: 王晨 常盛妈妈 介绍 | P13: 兼 | Q13: 1 | R13: 1 | S13: 1 | U13: 一对一 22课时 中国二 四8:30 | V13: 375 | W13: 1.14日缴费
A14: 12 | B14: 1.03 | C14: 美国 | D14: 宾夕法尼亚州 | E14: Sara | F14: bella2672260924 | G14: Isabella | H14: 11 | I14: 11岁，零基础，需要双语老师，偏爱说粤语 | J14: 13 | L14: 张文红 10:00 1.3 ChineseonlineK 10:00 1.4 | M14: 微信 | N14: 4 | O14: 张文红 | P14: 白 | Q14: 1 | R14: 1 | S14: 1 | U14: Isabella、Emma和姜安霓一起凑一年的价格 | V14: 3250 | W14: 1.11日缴费
A15: 13 | B15: 1.03 | C15: 美国 | D15: 费城 | E15: 果 | F15: guo721520 | G15: Aimeehuang 黄文美 | H15: 5 | I15: 5岁零基础 | J15: 13 | L15: 滕柳星10:30 1.3 ChineseonlineB9:00 陈琪 1.4 | M15: 微信 | N15: 4 | O15: 张文红 | P15: 启 | Q15: 1 | R15: 0 | S15: 妈妈回家就很晚了，小孩要睡了，没时间陪上课
A16: 14 | B16: 1.03 | C16: 美国 | D16: 费城 | E16: 果 | F16: guo721520 | G16: Evahuang黄文嘉 | H16: 3 | I16: 3岁零基础 | J16: 13 | L16: 滕柳星10:30 1.3 ChineseonlineB9:00 陈琪 1.4 | M16: 微信 | N16: 4 | O16: 张文红 | P16: 启 | Q16: 1 | R16: 0 | S16: 妈妈回家就很晚了，小孩要睡了，没时间陪上课
A17: 15 | B17: 1.03 | C17: 美国 | E17: 永恒的承诺 | F17: bin21793 | G17: 陈惠玲 | H17: 12 | J17: 13 | K17: 一上课文 | L17: 范老师 12:10 1.3 ChineseonlineH课堂8:00 1.6 | M17: 微信 | N17: 2 | O17: 马永楠 | P17: 白 | Q17: 1 | R17: 1 | S17: 1 | U17: 22课时 | V17: 1298 | W17: 1.14日缴费
A18: 16 | B18: 1.03 | C18: 美国 | E18: 永恒的承诺 | F18: bin21793 | G18: 陈俊伟 | H18: 10 | J18: 13 | K18: 一上拼音 | L18: 范老师 12:10 1.3 ChineseonlineC课堂8:40 1.6 | M18: 微信 | N18: 2 | O18: 马永楠 | P18: 兼 | Q18: 1 | R18: 0 | S18: 先报姐姐
A19: 17 | B19: 1.03 | C19: 中国 | D19: 深圳 | E19: MILIYA米莉亚礼服郭晴 | F19: sunnykwok8 | G19: 可可1 | H19: 5 | I19: 四周岁半,妈妈是做国外代购的非常忙基础:零.妈妈的期望:学好英语 从娃娃抓起 | J19: 0 | L19: 范老师 12:10 1.3 ChineseonlineC课堂8:40 1.6 | M19: 微信 | N19: 2 | O19: 赵国花 | P19: 兼 | Q19: 1 | R19: 0 | S19: 就上了一次课，太小了坐不住
A20: 18 | B20: 1.04 | C20: 法国 | E20: 叶光宗 | F20: yeguangzong62710 | G20: 叶芷欣 | H20: 8 | I20: 8岁，零基础 | J20: 7 | L20: 范乃琪8:00 1.4 第五十六课堂第九节课1.6 | M20: 家长介绍 | N20: 白 | O20: 刘俊宇妈妈介绍 | P20: 四 | Q20: 1 | R20: 1 | S20: 1 | U20: 620/月，季交 | V20: 1860 | W20: 1.16日缴费
A21: 19 | B21: 1.04 | C21: 美国 | E21: star💫 | F21: wangying19891125 | G21: 陈馨淣 | H21: 7 | I21: 7岁，拼音班中后段 | J21: 13 | L21: 范乃琪10:10 1.4 第四十二课堂7:10 1.6 1.7 第八课堂7：30 1.8 | M21: 电话 | N21: 1 | O21: 俞酉兰 | P21: 三 | Q21: 1 | R21: 0 | S21: 上课状态挺好的，但是试读结束妈妈没回复，希望不大
A22: 20 | B22: 1.04 | C22: 加拿大 | D22: 温哥华 | E22: ʚBeiBeiɞ | F22: Ydlj519 | G22: Eason2 辰辰 | H22: 7 | I22: 7岁半 拼音差不多都会，字写的不太好；必须带拼音阅读 | J22: 16 | K22: 一上课文部分开始；程度不错，上课也很乖 | L22: 任宏印9:15 1.4 ChineseonlineC10:40 1.17 | M22: 家长介绍 | N22: 白 | O22: Janice妈妈介绍 | P22: 兼 | Q22: 1 | R22: 1
A23: 21 | B23: 1.04 | C23: 加拿大 | D23: 温哥华 | E23: charlotte Li（婷） | F23: cresent_full | G23: 匡家豪 | H23: 11 | I23: 11岁，可以看不太复杂的故事，认字应该在1000个里面 | J23: 16 | K23: 可以从二年级开始测试，识字水平有二上，写字水平只有一年级，可以从一下开始 | L23: 徐晓晓11:30 1.4 ChineseonlineQ12:00 1.6 | M23: 代理 | N23: 白 | O23: 陈静 | P23: 白 | Q23: 1 | R23: 1 | S23: 1 | U23: 130课时，送8课时，满6000-260 | V23: 6630 | W23: 2.12日缴费
A24: 22 | B24: 1.04 | C24: 美国 | D24: 西部 | E24: 秀丽 | F24: wid96m7 ntxqpro31 | G24: 彭博1 | H24: 9 | I24: 9岁断断续续学过 | J24: 16 | K24: 一上后段程度，家长表示无法一周五天，时间后定 | L24: 滕柳星 10:30 1.4 | M24: 家长介绍 | N24: 3 | O24: 樊爱玉刘璧伟妈妈介绍 | P24: 0 | Q24: 1 | R24: 0 | S24: 觉得价格有点贵
A25: 23 | B25: 1.04 | C25: 美国 | D25: 西部 | E25: 秀丽 | F25: wid96m7 ntxqpro31 | G25: 彭蓓 | H25: 5 | I25: 5岁没学过 | J25: 16 | K25: 零基础，家长表示无法一周五天，时间后定 | L25: 滕柳星 11:00 1.4 | M25: 家长介绍 | N25: 3 | O25: 樊爱玉刘璧伟妈妈介绍 | P25: 0 | Q25: 1 | R25: 0 | S25: 觉得价格有点贵
A26: 24 | B26: 1.05 | C26: 西班牙 | E26: 妍 | F26: XIAORU0521 | G26: Ryan2 | H26: 5 | I26: 5岁 学美术 | J26: 7 | K26: 目前在中国，想学美术 | L26: 第九课堂张乙格15:00 1.5 | M26: 报第二门课 | N26: 3 | O26: 王可 | P26: 兼 | Q26: 1 | R26: 1 | S26: 1 | U26: 39/课 260课时 | V26: 10140 | W26: 3.11日缴费
A27: 25 | B27: 1.05 | C27: 美国 | D27: 西部 | E27: Jianxia | F27: jianxianing | G27: 黄安宁 | H27: 3.5 | I27: 三岁半，可以正常的中文交流 | J27: 16 | K27: 词汇量丰富，平时是个小话痨，交流没问题；上level1 认字困难，互动没问题 | L27: 徐晓晓 11:30 1.5 陈琪1.6 | M27: 微信 | N27: 2 | O27: 高翱翔 | P27: 启 | Q27: 1 | R27: 1 | S27: 1 | U27: 79元/节 一周三节 65课时 | V27: 719 | W27: 1.8日缴费
A28: 26 | B28: 1.05 | C28: 美国 | D28: 纽约 | E28: an liang | F28: aliang292743580 | G28: 朱梓轩 | H28: 9.5 | I28: 9岁半，基本沟通没问题，拼音需要强化。认识很多字但是写不太好 | J28: 13 | K28: 周末班 | L28: 范乃琪9:30 1.5 ChineseonlineB 23:00 1.5 | M28: 微信 | N28: 3 | O28: 樊爱玉 | P28: 兼 | Q28: 1 | R28: 1 | S28: 1 | U28: 周末班32+2课时 一小时一次 | V28: 3640 | W28: 1.14日缴费
A29: 27 | B29: 1.05 | C29: 澳大利亚 | D29: 悉尼 | E29: 达润法律事务所 | F29: guan0433699918 | G29: Ryan3 关润晨（音） | H29: 8 | I29: 8岁 在当地中文学校有学习，拼音没有学，但能靠英语自然拼读语感念个七七八八，识字量在一上后段，写字公整，比较慢热，可以学拼音，也可学一上课文后段 | J29: 3 | K29: 等家长确认上课时间 | L29: 滕柳星9:30 1.5 | M29: 电话 | N29: 3 | O29: 樊爱玉 | P29: 0 | Q29: 1 | R29: 0 | S29: 周末才能联系上
A30: 28 | B30: 1.05 | C30: 美国 | D30: 圣何塞 | E30: Nancy | F30: liuwei19831982 | G30: 吕思想 | H30: 11 | I30: 11岁，国内上完二年级出国，三年没有学中文了，程度二下或三上 | J30: 16 | K30: 三上程度开始 | L30: 范乃琪11:00 1.5 ChineseonlineB 12:40 1.16 | M30: 微信 | N30: 3 | O30: 王可 | P30: 兼 | Q30: 1 | R30: 1 | S30: 1 | U30: 65课时 | V30: 3640 | W30: 1.21日缴费
A31: 29 | B31: 1.06 | C31: 加拿大 | D31: 温哥华 | E31: 网上商城Grace张 | F31: grace8834 | G31: Eileen 蔡 | H31: 12 | I31: 12 听得懂点中文，没有学习过中文 | J31: 16 | K31: 中国周一到周五，12:00，零基础 | L31: 唐晶 1.6 ChineseonlineD12:00 1.7 1.8 ChineseonlineT 8:40 1.10 ChineseonlineA 13:30 | M31: 家长介绍 | N31: 2 | O31: 高翱翔 张涵溪爸爸介绍 | P31: 白 | Q31: 1 | R31: 1 | S31: 1 | U31: 一二五 半年交 | V31: 6600 | W31: 1.14日缴费 | X31: 2020.1.17-2021.1.22
A32: 30 | B32: 1.06 | C32: 德国 | E32: 艳 | F32: Wxid_1zlzbg4gw51j12 | G32: 李凯萱 | H32: 18 | I32: 18岁，学了几年中文，沟通没问题 | J32: 7 | L32: 魏霞 1.7 第二课堂1:20 1.8 | M32: 家长介绍 | N32: 2 | O32: 王晨 伊雅琳妈妈介绍 | P32: 四 | Q32: 1 | R32: 1 | S32: 1 | U32: 一周四次，65课时，1.20日开始缴费 | V32: 3234 | W32: 1.9日缴费
A33: 31 | B33: 1.07 | C33: 美国 | D33: 加州 | E33: raina美甲 | F33: Raina-zou | G33: Lorianna Liu姗姗 | H33: 10 | I33: 10岁，当地一周一节课上过，听说没问题，拼音不太熟悉 | J33: 16 | K33: 学拼音是插班的，不扎实，需要重头开始重新学；中文交流没问题，但是表达一般，词汇量不多；妈妈怕孩子太累，不想要安排太紧，想等七月份打完比赛再安排 | L33: 徐晓晓10:00 1.7 ChineseonlineB10 11:20 1.10 ChineseonlineR 11:20 1.11 | M33: 微信 | N33: 2 | O33: 王晨 | P33: 白 | Q33: 1 | R33: 0 | S33: 要六月再报名
A34: 32 | B34: 1.07 | C34: 美国 | D34: 加州 | E34: Lily senior loan officer | F34: Dawn4083964081 | G34: 何青晏 | H34: 8 | I34: 8岁，识字量达到一下程度，但是拼音还不行，马上回国读书，家长希望孩子先把拼音学好 | J34: 16 | L34: 范乃琪10:45 1.7 ChineseonlineK 9:20 1.8 | M34: 微信 | N34: 3 | O34: 王可 | P34: 白 | Q34: 1 | R34: 1 | S34: 1 | U34: 65课时+3节课 1.10日开始计费 | V34: 3640 | W34: 1.8日缴费
A35: 33 | B35: 1.07 | C35: 美国 | D35: 加州 | E35: lilly 林 | F35: whocareme25 | G35: 林龙 | H35: 11 | I35: 11岁，会拼音，能听懂不太会说，识字量低，建议一上《画》左右开始 | J35: 16 | K35: 等家长确认上课时间 | L35: 滕柳星11:00 1.7 | M35: 家长介绍 | N35: 2 | O35: 高翱翔李思蓓妈妈介绍 | P35: 0 | Q35: 1 | R35: 0 | S35: 没时间上课
A36: 34 | B36: 1.07 | C36: 美国 | D36: 加州 | E36: lilly 林 | F36: whocareme25 | G36: 林锦 | H36: 9 | I36: 9岁，会拼音，能听懂不太会说，识字量低，建议一上《画》左右开始 | J36: 16 | K36: 等家长确认上课时间 | L36: 滕柳星11:00 1.7 | M36: 家长介绍 | N36: 2 | O36: 高翱翔李思蓓妈妈介绍 | P36: 0 | Q36: 1 | R36: 0 | S36: 没时间上课
A37: 35 | B37: 1.07 | C37: 美国 | D37: 西雅图 | E37: Sophia | F37: liuqiaosong120 | G37: 高子萱 | H37: 10 | I37: 10岁，中国上了二年级，在家自学中文，阅读量大，识字量小学六年级，家长觉得一天半小时上课时间太短 | J37: 16 | K37: 北京时间周二11:00上课上一个小时 | L37: 滕柳星 8:30 1.7 作文课堂张连喜 11:00 1.14 | M37: 微信 | N37: 2 | O37: 马永楠 | P37: 0 | Q37: 1 | R37: 0 | S37: 一周一小时
A38: 36 | B38: 1.08 | C38: 美国 | D38: 纽约 | E38: Anna | F38: dan870822 | G38: 阮俊轩 | H38: 7 | I38: 7岁，可以简单的听的懂一点点中文，在家平时用广东话和英语交流，之前上过三个多月时间网课，说会看一点点拼音，应该是零基础开始学习，需要双语老师 | J38: 13 | K38: 拼音先复习拼读 | L38: 徐晓晓9：00 1.8 ChineseonlineC8:40 1.13 | M38: 家长介绍 | N38: 2 | O38: 高翱翔邓俊杰妈妈介绍 | P38: 兼 | Q38: 1 | R38: 0 | S38: 最近没时间，过段时间再说
A39: 37 | B39: 1.08 | C39: 美国 | D39: 东部 | E39: May | F39: chenqinmei2780 | G39: 王杰登 | H39: 7 | I39: 7岁 性别：男 之前在lingoAce试过课 | J39: 13 | K39: 知识扎实，阅读一般，性格比较骄傲；可以从一下开始上 | L39: 杨启8:30 1.8 ChineseonlineJ9:20 1.9 1.10 ChineseonlineG 9:20 | M39: 家长介绍 | N39: 3 | O39: 樊爱玉冯爱文妈妈介绍 | P39: 白 | Q39: 1 | R39: 0 | S39: 课程觉得一般，吸引力不是很大
A40: 38 | B40: 1.08 | C40: 美国 | D40: 纽约 | E40: Sophia | F40: linxiuzhen409594 | G40: 陈嘉怡 | H40: 8 | I40: 八岁零基础需要双语 | J40: 13 | K40: 中文交流没问题，零基础，中国六点半 | L40: 滕柳星9:30 1.8 第三课堂7:00 1.9 | M40: 家长介绍 | N40: 4 | O40: 刘巧芹林皓晨妈妈推荐 | P40: 一 | Q40: 1 | R40: 1 | S40: 1 | U40: 22课时 | V40: 187 | W40: 1.8日缴费
A41: 39 | B41: 1.08 | C41: 美国 | D41: 亨廷顿海滩 | E41: E.Z莜语 | F41: zs_tracy | G41: 姜安霓 | H41: 10 | I41: 10岁，只会简单的中文交流，中英结合着讲话福建，日常交流没有问题，没在学校学过，零基础，学得快 | J41: 16 | K41: 抽不出来一周五天，上课时间商量 | L41: 滕柳星11:00 1.8 ChineseonlineB10 11:20 1.9 ChineseonlineR 11：20 1.11 | M41: 家长介绍 | N41: 4 | O41: 张文红Isabella介绍 | P41: 白 | Q41: 1 | R41: 0 | S41: 想要一周三天的，现在妈妈自己教
A42: 40 | B42: 1.08 | C42: 美国 | D42: 加州 | E42: liya | F42: liyazhu0624 | G42: 张天俊 | H42: 5 | I42: 5岁，听说没问题，在APP上学过一点 | J42: 16 | K42: 学过一点 | L42: 徐晓晓11:00 1.8 ChineseonlineB10 11:20 1.9 ChineseonlineL 11:20 1.16 | M42: 微信 | N42: 4 | O42: 刘巧芹 | P42: 白 | Q42: 1 | R42: 1 | S42: 1 | U42: 65课时，一周四天 满3000-100 | V42: 3540 | W42: 1.15日缴费
A43: 41 | B43: 1.08 | C43: 美国 | D43: 旧金山 | E43: 谭娉SAC | F43: tanping2009 | G43: 黄家丰 | H43: 10 | I43: 10岁需要双语零基础 | J43: 16 | K43: 需要双语课 零基础 | L43: 徐晓晓11:45 1.8 ChineseonlineT 8:40 1.9 ChineseonlineD 12:00 1.15 | M43: 微信 | N43: 2 | O43: 王晨 | P43: 白 | Q43: 1 | R43: 1 | S43: 1 | U43: 22课时 | V43: 1298 | W43: 1.16日缴费
A44: 42 | B44: 1.08 | C44: 美国 | D44: 洛杉矶 | E44: david | F44: DAVIDDAIUSA | G44: William | H44: 10 | I44: 10岁，一上中后段 | J44: 16 | L44: 范乃琪11:00 1.8 ChineseonlineH 11:20 1.9 换到D课堂 双语 | M44: 电话 | N44: 4 | O44: 王谢霞 | P44: 白 | Q44: 1 | R44: 1 | S44: 1 | U44: 22课时 | V44: 1298 | W44: 1.11日缴费
A45: 43 | B45: 1.08 | C45: 美国 | D45: 洛杉矶 | E45: david | F45: DAVIDDAIUSA | G45: Natalie | H45: 12 | I45: 12岁，一下程度 | J45: 16 | K45: 学过八年中文 | L45: 范乃琪11:30 1.8 ChineseonlineQ 12:00 1.9 ChineseonlineA 11:20 | M45: 电话 | N45: 4 | O45: 王谢霞 | P45: 白 | Q45: 1 | R45: 0 | S45: 姐姐没时间上课了
A46: 44 | B46: 1.08 | C46: 加拿大 | D46: 萨斯卡通 | E46: Ling | F46: lingguo57557 | G46: 翟俊宇 | H46: 7 | I46: 7岁 国内一年级，识字还行，就是写的少；拼音学过但是忘得差不多了 | J46: 14 | K46: 拼音基本没问题，一上的课文识字都不错，写字比较弱，可以从一上后半段开始学；互动性很强，词汇量丰富，理解力也很好 | L46: 徐晓晓9:00 1.1 ChineseonlineG 1.2 1.3 | M46: 代理 | N46: 白 | O46: 陈静 | P46: 白 | Q46: 1 | R46: 1 | S46: 1 | U46: 65课时 50/课 一周四节，周六不来 | V46: 3250 | W46: 1.15日缴费
A47: 45 | B47: 1.09 | C47: 德国 | E47: jh | F47: ziyan140752 | G47: 王浩然2 | H47: 13 | I47: 13岁，二上中间程度 | J47: 7 | L47: 魏霞23:40 1.9 第二十二课堂第二节课1.10 | M47: 华嘉仪妈妈介绍 | N47: 白 | O47: 微信 | P47: 一 | Q47: 1 | R47: 0 | S47: 嫌贵
A48: 46 | B48: 1.09 | C48: 德国 | E48: jh | F48: ziyan140752 | G48: 王浩文 | H48: 12 | I48: 12岁，二上中间程度 | J48: 7 | L48: 魏霞23:40 1.9 第五课堂第二节课1.10 | M48: 华嘉仪妈妈介绍 | N48: 白 | O48: 微信 | P48: 一 | Q48: 1 | R48: 0 | S48: 嫌贵
A49: 47 | B49: 1.09 | C49: 美国 | D49: 亚特兰大 | E49: Qu薛姐 | F49: veraququququququ | G49: 孙文一 | H49: 8 | I49: 8岁， | J49: 13 | K49: 孩子拼音不错，识字量也很好，但是写字水平非常低，建议一上开始，老师上课难的字，尽量写拼音，别写字，孩子会跟着抄 | L49: 任宏印8:40 1.9 ChineseonlineK8:00 | M49: 学生兄妹 | N49: 3 | O49: 樊爱玉 孙文周哥哥 | P49: 白 | Q49: 1 | R49: 1 | S49: 还没试完
A50: 48 | B50: 1.09 | C50: 美国 | D50: 东部 | E50: 晓艳 | F50: xiaoyangao888 | G50: 郑欧莱 | H50: 12 | I50: 12岁男，只能说一点中文，上过中文课，拼音会一点儿 | J50: 13 | K50: 需要双语辅助，可以从复韵母开始复习，不用双语 | L50: 徐晓晓8:00 1.9 ChineseonlineQ 9:20 1.10 | M50: 电话 | N50: 4 | O50: 刘敏 | P50: 白 | Q50: 1 | R50: 1 | S50: 1 | U50: 一对一，一周一次一小时 188/课 | V50: 4512 | W50: 1.16日缴费
A51: 49 | B51: 1.09 | C51: 美国 | D51: 纽约 | E51: Fiona | F51: wxid zas4ot96k1ybz12 | G51: 窦子涵 | H51: 7 | I51: 七岁 刚去美国两年，听说没问题 | J51: 13 | K51: 虽然说学过一点但是几乎零基础；比较腼腆不爱说话，理解力不错的； | L51: 徐晓晓8:45 1.9 ChineseonlineT 8:40 1.15 | M51: 微信 | N51: 3 | O51: 王可 | P51: 白 | Q51: 1 | R51: 0
A52: 50 | B52: 1.09 | C52: 美国 | E52: Shirley | F52: shirleygao1985 | G52: 郑子荣 | H52: 9 | I52: 9岁男孩零基础愿意学接受能力强 | J52: 13 | K52: 想要中国的9:00-9:30上课 | L52: 滕柳星 8:30 1.9 ChineseonlineT 8:40 1.10 | M52: 微信 | N52: 3 | O52: 展旺 | P52: 白 | Q52: 1 | R52: 0 | S52: 一家三口只交一人
A53: 51 | B53: 1.09 | C53: 美国 | E53: Shirley | F53: shirleygao1985 | G53: 郑芷鑫 | H53: 11 | I53: 11岁女孩零基础愿意学接受能力强 | J53: 13 | K53: 想要中国的9:00-9:30上课 | L53: 滕柳星 8:30 1.9 ChineseonlineT 8:40 1.10 | M53: 微信 | N53: 3 | O53: 展旺 | P53: 白 | Q53: 1 | R53: 1 | S53: 1 | U53: 65课时 | V53: 3640 | W53: 1.14日缴费
A54: 52 | B54: 1.09 | C54: 美国 | E54: Shirley | F54: shirleygao1985 | G54: 陈孔培 | H54: 10 | I54: 10岁男孩零基础愿意学接受能力强 | J54: 13 | K54: 想要中国的9:00-9:30上课 | L54: 滕柳星 8:30 1.9 ChineseonlineT 8:40 1.10 | M54: 微信 | N54: 3 | O54: 展旺 | P54: 白 | Q54: 1 | R54: 0 | S54: 一家三口只交一人
A55: 53 | B55: 1.09 | C55: 美国 | D55: 纽约 | E55: Hot Y.Y.私房烘焙 正常接单！ | F55: trista2011999 | G55: 陈唐 | H55: 11 | I55: 11岁，识字量一上，拼音需要重新复习，复韵母阶段 | J55: 13 | L55: 范乃琪9:00 1.9 ChineseonlineL 9:20 1.11 | M55: 微信 | N55: 2 | O55: 王晨 | P55: 白 | Q55: 1 | R55: 1 | S55: 太简单了要重新安排时间
A56: 54 | B56: 1.09 | C56: 美国 | D56: 纽约 | E56: Hot Y.Y.私房烘焙 正常接单！ | F56: trista2011999 | G56: 陈汉 | H56: 7 | I56: 7岁，识字量无法学课文，拼音从声母阶段复习 | J56: 13 | L56: 范乃琪9:30 1.9 ChineseonlineK 9:20 1.11 | M56: 微信 | N56: 2 | O56: 王晨 | P56: 白 | Q56: 1 | R56: 1 | S56: 太简单了要重新安排时间
A57: 55 | B57: 1.09 | C57: 加拿大 | D57: 温哥华 | E57: Jun Zi（訾军7783233789 | F57: junzirealty | G57: 訾泓为 | H57: 10 | I57: 10岁，学过一些，会说中文，但有时候表达的不是很清楚 | J57: 16 | K57: 拼读可以，但是声调会不准，需要多练习；识字量100左右，可以从一上中后段开始学习；学习不是很积极，不过也会配合老师 | L57: 徐晓晓12:30 1.9 | M57: 电话 | N57: 4 | O57: 刘巧芹 | P57: 0 | Q57: 1 | R57: 0 | S57: 测完课之后一直没回复了
A58: 56 | B58: 1.09 | C58: 美国 | D58: 尔湾 | E58: Ray | F58: Ray9819126 | G58: 周暄德 | H58: 6 | I58: 6岁零基础 | J58: 16 | K58: 零基础中国二四六 | L58: 滕柳星10:30 1.9 ChineseonlineB10 9:20 1.11 | M58: 微信 | N58: 2 | O58: 平金军 | P58: 兼 | Q58: 1 | R58: 0 | S58: 要一周三天，不想上小班课
A59: 57 | B59: 1.09 | C59: 美国 | D59: 尔湾 | E59: Ray | F59: Ray9819126 | G59: 周暄棣 | H59: 13 | I59: 哥哥国内二上中后水平 | J59: 16 | K59: 五年级 | L59: 滕柳星11:00 1.9 ChineseonlineB10 10:00 1.15 | M59: 微信 | N59: 2 | O59: 平金军 | P59: 兼 | Q59: 1 | R59: 0 | S59: 一周两天
A60: 58 | B60: 1.09 | C60: 美国 | D60: 美西 | E60: 辣妈美国月子中心会所 | F60: lxm9493949126 | G60: 韩雨霏 | H60: 7 | I60: 双胞胎7岁听说OK拼音到jqx，不太会拼 | J60: 16 | K60: 需要11:00-12:00上课一周五天可以新开班11:20，和周子媛班级试读的其他同学一起 | L60: 滕柳星12:00 1.9 ChineseonlineB10 11:20 | M60: 微信 | N60: 2 | O60: 王晨 | P60: 兼 | Q60: 1 | R60: 1 | S60: 要交费的
A61: 59 | B61: 1.09 | C61: 美国 | D61: 美西 | E61: 辣妈美国月子中心会所 | F61: lxm9493949126 | G61: 韩雨融 | H61: 7 | I61: 双胞胎7岁听说OK拼音到jqx，不太会拼 | J61: 16 | K61: 需要11:00-12:00上课 | L61: 滕柳星12:00 1.9 ChineseonlineB10 11:20 | M61: 微信 | N61: 2 | O61: 王晨 | P61: 兼 | Q61: 1 | R61: 1 | S61: 要交费的
A62: 60 | B62: 1.09 | C62: 美国 | D62: 芝加哥 | E62: 雪 | F62: sandyzou8899 | G62: 邹晓雪 | H62: 28 | I62: 28岁，A2水平，能理解大部份日常生活中常用的句子和表达。法在单纯的例行性事务中能够有效沟通，针对熟悉的例行性事务进行简单直接的信息交换。能简单描述个人背景、周遭环境及切身需求之事物。想学英语 | J62: 14 | L62: 滕柳星12:30 1.9 英语课堂 12:30 1.10 | M62: 家长介绍 | N62: 3 | O62: 王可 郑佳欣妈妈介绍 | P62: 兼 | Q62: 1 | R62: 0 | S62: 价格接受不了
